Workbook

Sheet About
A1: CpUDSC Cost per Unit Distributed Solar Capacity
A3: Sources: | B3: Price Trajectory
B4: NREL
B5: 2020, 2022
B6: Annual Technology Baseline 2020, Annual Technology Baseline 2022
B7: https://atb.nrel.gov/
B8: "Solar - PV Dist. Res" tab
B9: "Solar - PV Dist. Comm" tab
B11: Solar DC to AC Derate Value
B12: Jens Schoene, EnerNex
B13: 2015
B14: Production Levels of Utility-Scale and Residential-Scale PV Systems
B15: http://brattle.com/system/publications/pdfs/000/005/188/original/Comparative_Generation_Costs_of_Utility-Scale_and_Residential-Scale_PV_in_Xcel_Energy_Colorado's_Service_Area.pdf?1436797265
B16: This document is included as Appendix B of a report by Brattle Group. It is on Page 10 of the EnerNex report, which is Page 70 of the PDF
B18: Share of Costs that are Soft Costs
B19: NREL
B20: 2018
B21: U.S. Solar Photovoltaic System Cost Benchmark: Q1 2018
B22: https://www.nrel.gov/docs/fy17osti/68925.pdf
B23: Page viii, Figure ES-2
A25: Notes
A26: We use the ATB "Moderate" case
A28: "Soft costs" (non-hardware costs, such as the cost of installation)
A29: are a subset of the total costs. Soft costs are not subject to
A30: reductions from endogenous learning.
A32: 2019 to 2012 | B32: 0.89805482
A33: 2020 to 2012 | B33: 0.88711067

Sheet DC to AC
A1: Watts DC are lower than Watts AC, but AC is needed to either sell to the grid or to power devices in homes.
A2: Therefore, we convert to the cost per Watt AC using a derate factor:
A3: 0.859 | B3: DC to AC derate factor

Sheet Solar - PV Dist. Comm 2021
A1: TEST | L1: https://atb.nrel.gov/electricity/2021/commercial_pv
T3: Inputs
J4: Take me to: | T4: Calculated
B7: X | G7: Assumptions
H9: Technology | J9: Basis Year: | L9: 2019
J10: All values are given in 2019 U.S. dollars, using the Consumer Price Index (BLS, 2020) for dollar year conversions. Projections use an inflation assumption of 2.5% per year.
J11: Commercial Solar Photovoltaic
J14: Representative Dist. Commercial system is fixed-tilt roof mounted with capacity of 300 kW
J15: Overnight Capital Cost, Capacity Factor, Fixed O&M, and Variable O&M costs
J16: represent $/kW DC; however LCOE reflects $/MWh AC.
J17: Capacity factors chosen here to reflect range across the continental U.S. using NREL PVWATTS
N20: Available | O20: Available
N21: Capacity | O21: Generation
N22: (GW) | O22: (GWh)
N23: 386 | O23: 506000
L26: ATB values reflect annual average capacity factor over life of plant including estimated degradation, starting at 0.7% per year, reducing to 0.2%, 0.5%, and 0.5% annual degradation by 2050 for the advanced, moderate, and conservative scenarios, respectively. Capacity factors also assume an energy yield gain at the module of 10%, 5%, and 2.5% for advanced, moderate, and conservatives scenarios.
H32: Finance | J32: Financial Assumptions:
J33: Inflation Rate | N33: =L63 -> 0.025
J34: Capital Recovery Period (Years) | N34: =S34 -> 30 | S34: 30
J35: Interest Rate Nominal - Moderate | N35: =L65 -> 0.04
J36: Calculated Interest Rate Real - Moderate | N36: =L68 -> 0.014634146
J37: Interest During Construction - Nominal | N37: =L70 -> 0.035
J38: Rate of Return on Equity Nominal - Moderate | N38: =L72 -> 0.088
J39: Calculated Rate of Return on Equity Real - Moderate | N39: =L75 -> 0.061463415
J40: Debt Fraction - Moderate | N40: =L78 -> 0.759
J41: Tax Rate (Federal and State) | N41: =L80 -> 0.2574
J42: WACC Nominal - Moderate | N42: =L82 -> 0.043753336
J43: WACC Real - Moderate | N43: =L85 -> 0.018295938
J44: Depreciation Period | N44: 5
J45: Construction Finance Factor | N45: =SUMPRODUCT(K57:K59,L57:L59,M57:M59)+SUMPRODUCT(K57:K59,O57:O59,N57:N59) -> 1.0244028
J46: Present Value of Depreciation | N46: =SUMPRODUCT(R56:W56,R58:W58) -> 0.88881179
J47: Project Finance Factor | N47: =(1 - N41 * N46) / (1 - N41) -> 1.0385401
J48: Capital Recovery Factor (CRF) Nominal - Moderate | N48: =L88 -> 0.060494177
J49: Capital Recovery Factor (CRF) Real - Moderate | N49: =L91 -> 0.043610542
J50: Equity Premium During Construction | N50: 0.02
J51: Cost of equity during construction | N51: =N38+N50 -> 0.108
J52: Construction Duration yrs | L52: 1
J53: Year | K53: Capital | L53: Accumulated | M53: Percent of Leverage During Construction | N53: Percent of Equity During Construction | O53: Accumulated Equity Cost
J54: Index | K54: Fraction | L54: Interest
Q55: MACRS yr | R55: 1 | S55: 2 | T55: 3 | U55: 4 | V55: 5 | W55: 6
Q56: Depreciation | R56: 0.2 | S56: 0.32 | T56: 0.192 | U56: 0.1152 | V56: 0.1152 | W56: 0.0576
J57: 0 | K57: 1 | L57: =1+((1+N37)^(J57+0.5)-1) -> 1.0173495 | M57: 0.8 | N57: =1-M57 -> 0.2 | O57: =1+((1+$N$51)^(J57+0.5)-1) -> 1.0526158 | Q57: Fraction
J58: 1 | K58: 0 | L58: =1+((1+N37)^(J58+0.5)-1) -> 1.0529567 | M58: 0.8 | N58: =1-M58 -> 0.2 | O58: =1+((1+$N$51)^(J58+0.5)-1) -> 1.1662983 | Q58: Depreciation | R58: =1/((1+$N$43)*(1+$N$33))^R55 -> 0.95808077 | S58: =1/((1+$N$43)*(1+$N$33))^S55 -> 0.91791876 | T58: =1/((1+$N$43)*(1+$N$33))^T55 -> 0.87944031 | U58: =1/((1+$N$43)*(1+$N$33))^U55 -> 0.84257485 | V58: =1/((1+$N$43)*(1+$N$33))^V55 -> 0.80725476 | W58: =1/((1+$N$43)*(1+$N$33))^W55 -> 0.77341527
J59: 2 | K59: 0 | L59: =1+((1+N37)^(J59+0.5)-1) -> 1.0898102 | M59: 0.8 | N59: =1-M59 -> 0.2 | O59: =1+((1+$N$51)^(J59+0.5)-1) -> 1.2922585 | Q59: Factor
L61: Base Year
L62: 2019 | M62: 2020 | N62: 2021 | O62: 2022 | P62: 2023 | Q62: 2024 | R62: 2025 | S62: 2026 | T62: 2027 | U62: 2028 | V62: 2029 | W62: 2030 | X62: 2031 | Y62: 2032 | Z62: 2033 | AA62: 2034 | AB62: 2035 | AC62: 2036 | AD62: 2037 | AE62: 2038 | AF62: 2039 | AG62: 2040 | AH62: 2041 | AI62: 2042 | AJ62: 2043 | AK62: 2044 | AL62: 2045 | AM62: 2046 | AN62: 2047 | AO62: 2048 | AP62: 2049 | AQ62: 2050
J63: Assumptions | K63: Inflation Rate | L63: ='[1]WACC Calc'!F420 -> 0.025 | M63: ='[1]WACC Calc'!G420 -> 0.025 | N63: ='[1]WACC Calc'!H420 -> 0.025 | O63: ='[1]WACC Calc'!I420 -> 0.025 | P63: ='[1]WACC Calc'!J420 -> 0.025 | Q63: ='[1]WACC Calc'!K420 -> 0.025 | R63: ='[1]WACC Calc'!L420 -> 0.025 | S63: ='[1]WACC Calc'!M420 -> 0.025 | ... AQ63: ='[1]WACC Calc'!AK420 -> 0.025
K64: Interest Rate Nominal - Advanced | L64: ='[1]WACC Calc'!F421 -> 0.04 | M64: ='[1]WACC Calc'!G421 -> 0.04 | N64: ='[1]WACC Calc'!H421 -> 0.04 | O64: ='[1]WACC Calc'!I421 -> 0.04 | P64: ='[1]WACC Calc'!J421 -> 0.04 | Q64: ='[1]WACC Calc'!K421 -> 0.04 | R64: ='[1]WACC Calc'!L421 -> 0.04 | S64: ='[1]WACC Calc'!M421 -> 0.04 | ... AQ64: ='[1]WACC Calc'!AK421 -> 0.04
K65: Interest Rate Nominal - Moderate | L65: ='[1]WACC Calc'!F422 -> 0.04 | M65: ='[1]WACC Calc'!G422 -> 0.04 | N65: ='[1]WACC Calc'!H422 -> 0.04 | O65: ='[1]WACC Calc'!I422 -> 0.04 | P65: ='[1]WACC Calc'!J422 -> 0.04 | Q65: ='[1]WACC Calc'!K422 -> 0.04 | R65: ='[1]WACC Calc'!L422 -> 0.04 | S65: ='[1]WACC Calc'!M422 -> 0.04 | ... AQ65: ='[1]WACC Calc'!AK422 -> 0.04
K66: Interest Rate Nominal - Conservative | L66: ='[1]WACC Calc'!F423 -> 0.04 | M66: ='[1]WACC Calc'!G423 -> 0.04 | N66: ='[1]WACC Calc'!H423 -> 0.04 | O66: ='[1]WACC Calc'!I423 -> 0.04 | P66: ='[1]WACC Calc'!J423 -> 0.04 | Q66: ='[1]WACC Calc'!K423 -> 0.04 | R66: ='[1]WACC Calc'!L423 -> 0.04 | S66: ='[1]WACC Calc'!M423 -> 0.04 | ... AQ66: ='[1]WACC Calc'!AK423 -> 0.04
K67: Calculated Interest Rate Real - Advanced | L67: ='[1]WACC Calc'!F424 -> 0.014634146 | M67: ='[1]WACC Calc'!G424 -> 0.014634146 | N67: ='[1]WACC Calc'!H424 -> 0.014634146 | O67: ='[1]WACC Calc'!I424 -> 0.014634146 | P67: ='[1]WACC Calc'!J424 -> 0.014634146 | Q67: ='[1]WACC Calc'!K424 -> 0.014634146 | R67: ='[1]WACC Calc'!L424 -> 0.014634146 | S67: ='[1]WACC Calc'!M424 -> 0.014634146 | ... AQ67: ='[1]WACC Calc'!AK424 -> 0.014634146
K68: Calculated Interest Rate Real - Moderate | L68: ='[1]WACC Calc'!F425 -> 0.014634146 | M68: ='[1]WACC Calc'!G425 -> 0.014634146 | N68: ='[1]WACC Calc'!H425 -> 0.014634146 | O68: ='[1]WACC Calc'!I425 -> 0.014634146 | P68: ='[1]WACC Calc'!J425 -> 0.014634146 | Q68: ='[1]WACC Calc'!K425 -> 0.014634146 | R68: ='[1]WACC Calc'!L425 -> 0.014634146 | S68: ='[1]WACC Calc'!M425 -> 0.014634146 | ... AQ68: ='[1]WACC Calc'!AK425 -> 0.014634146
K69: Calculated Interest Rate Real - Conservative | L69: ='[1]WACC Calc'!F426 -> 0.014634146 | M69: ='[1]WACC Calc'!G426 -> 0.014634146 | N69: ='[1]WACC Calc'!H426 -> 0.014634146 | O69: ='[1]WACC Calc'!I426 -> 0.014634146 | P69: ='[1]WACC Calc'!J426 -> 0.014634146 | Q69: ='[1]WACC Calc'!K426 -> 0.014634146 | R69: ='[1]WACC Calc'!L426 -> 0.014634146 | S69: ='[1]WACC Calc'!M426 -> 0.014634146 | ... AQ69: ='[1]WACC Calc'!AK426 -> 0.014634146
K70: Interest During Construction - Nominal | L70: ='[1]WACC Calc'!F427 -> 0.035 | M70: ='[1]WACC Calc'!G427 -> 0.035 | N70: ='[1]WACC Calc'!H427 -> 0.035 | O70: ='[1]WACC Calc'!I427 -> 0.035 | P70: ='[1]WACC Calc'!J427 -> 0.035 | Q70: ='[1]WACC Calc'!K427 -> 0.035 | R70: ='[1]WACC Calc'!L427 -> 0.035 | S70: ='[1]WACC Calc'!M427 -> 0.035 | ... AQ70: ='[1]WACC Calc'!AK427 -> 0.035
K71: Rate of Return on Equity Nominal - Advanced | L71: ='[1]WACC Calc'!F428 -> 0.088 | M71: ='[1]WACC Calc'!G428 -> 0.088 | N71: ='[1]WACC Calc'!H428 -> 0.088 | O71: ='[1]WACC Calc'!I428 -> 0.088 | P71: ='[1]WACC Calc'!J428 -> 0.088 | Q71: ='[1]WACC Calc'!K428 -> 0.088 | R71: ='[1]WACC Calc'!L428 -> 0.088 | S71: ='[1]WACC Calc'!M428 -> 0.088 | ... AQ71: ='[1]WACC Calc'!AK428 -> 0.088
K72: Rate of Return on Equity Nominal - Moderate | L72: ='[1]WACC Calc'!F429 -> 0.088 | M72: ='[1]WACC Calc'!G429 -> 0.088 | N72: ='[1]WACC Calc'!H429 -> 0.088 | O72: ='[1]WACC Calc'!I429 -> 0.088 | P72: ='[1]WACC Calc'!J429 -> 0.088 | Q72: ='[1]WACC Calc'!K429 -> 0.088 | R72: ='[1]WACC Calc'!L429 -> 0.088 | S72: ='[1]WACC Calc'!M429 -> 0.088 | ... AQ72: ='[1]WACC Calc'!AK429 -> 0.088
K73: Rate of Return on Equity Nominal - Conservative | L73: ='[1]WACC Calc'!F430 -> 0.088 | M73: ='[1]WACC Calc'!G430 -> 0.088 | N73: ='[1]WACC Calc'!H430 -> 0.088 | O73: ='[1]WACC Calc'!I430 -> 0.088 | P73: ='[1]WACC Calc'!J430 -> 0.088 | Q73: ='[1]WACC Calc'!K430 -> 0.088 | R73: ='[1]WACC Calc'!L430 -> 0.088 | S73: ='[1]WACC Calc'!M430 -> 0.088 | ... AQ73: ='[1]WACC Calc'!AK430 -> 0.088
K74: Calculated Rate of Return on Equity Real - Advanced | L74: ='[1]WACC Calc'!F431 -> 0.061463415 | M74: ='[1]WACC Calc'!G431 -> 0.061463415 | N74: ='[1]WACC Calc'!H431 -> 0.061463415 | O74: ='[1]WACC Calc'!I431 -> 0.061463415 | P74: ='[1]WACC Calc'!J431 -> 0.061463415 | Q74: ='[1]WACC Calc'!K431 -> 0.061463415 | R74: ='[1]WACC Calc'!L431 -> 0.061463415 | S74: ='[1]WACC Calc'!M431 -> 0.061463415 | ... AQ74: ='[1]WACC Calc'!AK431 -> 0.061463415
K75: Calculated Rate of Return on Equity Real - Moderate | L75: ='[1]WACC Calc'!F432 -> 0.061463415 | M75: ='[1]WACC Calc'!G432 -> 0.061463415 | N75: ='[1]WACC Calc'!H432 -> 0.061463415 | O75: ='[1]WACC Calc'!I432 -> 0.061463415 | P75: ='[1]WACC Calc'!J432 -> 0.061463415 | Q75: ='[1]WACC Calc'!K432 -> 0.061463415 | R75: ='[1]WACC Calc'!L432 -> 0.061463415 | S75: ='[1]WACC Calc'!M432 -> 0.061463415 | ... AQ75: ='[1]WACC Calc'!AK432 -> 0.061463415
... K86: WACC Real - Conservative | L86: ='[1]WACC Calc'!F443 -> 0.018295938 | M86: ='[1]WACC Calc'!G443 -> 0.018295938 | N86: ='[1]WACC Calc'!H443 -> 0.018295938 | O86: ='[1]WACC Calc'!I443 -> 0.018295938 | P86: ='[1]WACC Calc'!J443 -> 0.018295938 | Q86: ='[1]WACC Calc'!K443 -> 0.018295938 | R86: ='[1]WACC Calc'!L443 -> 0.018295938 | S86: ='[1]WACC Calc'!M443 -> 0.018295938 | ... AQ86: ='[1]WACC Calc'!AK443 -> 0.018295938
K87: Capital Recovery Factor (CRF) Nominal - Advanced | L87: =L81 / (1 - (1 / (1 + L81)^$N$34)) -> 0.060494177 | M87: =M81 / (1 - (1 / (1 + M81)^$N$34)) -> 0.060494177 | N87: =N81 / (1 - (1 / (1 + N81)^$N$34)) -> 0.060494177 | O87: =O81 / (1 - (1 / (1 + O81)^$N$34)) -> 0.060494177 | P87: =P81 / (1 - (1 / (1 + P81)^$N$34)) -> 0.060494177 | Q87: =Q81 / (1 - (1 / (1 + Q81)^$N$34)) -> 0.060494177 | R87: =R81 / (1 - (1 / (1 + R81)^$N$34)) -> 0.060494177 | S87: =S81 / (1 - (1 / (1 + S81)^$N$34)) -> 0.060494177 | ... AQ87: =AQ81 / (1 - (1 / (1 + AQ81)^$N$34)) -> 0.060494177
K88: Capital Recovery Factor (CRF) Nominal - Moderate | L88: =L82 / (1 - (1 / (1 + L82)^$N$34)) -> 0.060494177 | M88: =M82 / (1 - (1 / (1 + M82)^$N$34)) -> 0.060494177 | N88: =N82 / (1 - (1 / (1 + N82)^$N$34)) -> 0.060494177 | O88: =O82 / (1 - (1 / (1 + O82)^$N$34)) -> 0.060494177 | P88: =P82 / (1 - (1 / (1 + P82)^$N$34)) -> 0.060494177 | Q88: =Q82 / (1 - (1 / (1 + Q82)^$N$34)) -> 0.060494177 | R88: =R82 / (1 - (1 / (1 + R82)^$N$34)) -> 0.060494177 | S88: =S82 / (1 - (1 / (1 + S82)^$N$34)) -> 0.060494177 | ... AQ88: =AQ82 / (1 - (1 / (1 + AQ82)^$N$34)) -> 0.060494177
K89: Capital Recovery Factor (CRF) Nominal - Conservative | L89: =L83 / (1 - (1 / (1 + L83)^$N$34)) -> 0.060494177 | M89: =M83 / (1 - (1 / (1 + M83)^$N$34)) -> 0.060494177 | N89: =N83 / (1 - (1 / (1 + N83)^$N$34)) -> 0.060494177 | O89: =O83 / (1 - (1 / (1 + O83)^$N$34)) -> 0.060494177 | P89: =P83 / (1 - (1 / (1 + P83)^$N$34)) -> 0.060494177 | Q89: =Q83 / (1 - (1 / (1 + Q83)^$N$34)) -> 0.060494177 | R89: =R83 / (1 - (1 / (1 + R83)^$N$34)) -> 0.060494177 | S89: =S83 / (1 - (1 / (1 + S83)^$N$34)) -> 0.060494177 | ... AQ89: =AQ83 / (1 - (1 / (1 + AQ83)^$N$34)) -> 0.060494177
K90: Capital Recovery Factor (CRF) Real - Advanced | L90: =L84 / (1 - (1 / (1 + L84)^$N$34)) -> 0.043610542 | M90: =M84 / (1 - (1 / (1 + M84)^$N$34)) -> 0.043610542 | N90: =N84 / (1 - (1 / (1 + N84)^$N$34)) -> 0.043610542 | O90: =O84 / (1 - (1 / (1 + O84)^$N$34)) -> 0.043610542 | P90: =P84 / (1 - (1 / (1 + P84)^$N$34)) -> 0.043610542 | Q90: =Q84 / (1 - (1 / (1 + Q84)^$N$34)) -> 0.043610542 | R90: =R84 / (1 - (1 / (1 + R84)^$N$34)) -> 0.043610542 | S90: =S84 / (1 - (1 / (1 + S84)^$N$34)) -> 0.043610542 | ... AQ90: =AQ84 / (1 - (1 / (1 + AQ84)^$N$34)) -> 0.043610542
K91: Capital Recovery Factor (CRF) Real - Moderate | L91: =L85 / (1 - (1 / (1 + L85)^$N$34)) -> 0.043610542 | M91: =M85 / (1 - (1 / (1 + M85)^$N$34)) -> 0.043610542 | N91: =N85 / (1 - (1 / (1 + N85)^$N$34)) -> 0.043610542 | O91: =O85 / (1 - (1 / (1 + O85)^$N$34)) -> 0.043610542 | P91: =P85 / (1 - (1 / (1 + P85)^$N$34)) -> 0.043610542 | Q91: =Q85 / (1 - (1 / (1 + Q85)^$N$34)) -> 0.043610542 | R91: =R85 / (1 - (1 / (1 + R85)^$N$34)) -> 0.043610542 | S91: =S85 / (1 - (1 / (1 + S85)^$N$34)) -> 0.043610542 | ... AQ91: =AQ85 / (1 - (1 / (1 + AQ85)^$N$34)) -> 0.043610542
K92: Capital Recovery Factor (CRF) Real - Conservative | L92: =L86 / (1 - (1 / (1 + L86)^$N$34)) -> 0.043610542 | M92: =M86 / (1 - (1 / (1 + M86)^$N$34)) -> 0.043610542 | N92: =N86 / (1 - (1 / (1 + N86)^$N$34)) -> 0.043610542 | O92: =O86 / (1 - (1 / (1 + O86)^$N$34)) -> 0.043610542 | P92: =P86 / (1 - (1 / (1 + P86)^$N$34)) -> 0.043610542 | Q92: =Q86 / (1 - (1 / (1 + Q86)^$N$34)) -> 0.043610542 | R92: =R86 / (1 - (1 / (1 + R86)^$N$34)) -> 0.043610542 | S92: =S86 / (1 - (1 / (1 + S86)^$N$34)) -> 0.043610542 | ... AQ92: =AQ86 / (1 - (1 / (1 + AQ86)^$N$34)) -> 0.043610542
D97: X | G97: Future Projections
L98: Basis Year
L99: 2019 | M99: 2020 | N99: 2021 | O99: 2022 | P99: 2023 | Q99: 2024 | R99: 2025 | S99: 2026 | T99: 2027 | U99: 2028 | V99: 2029 | W99: 2030 | X99: 2031 | Y99: 2032 | Z99: 2033 | AA99: 2034 | AB99: 2035 | AC99: 2036 | AD99: 2037 | AE99: 2038 | AF99: 2039 | AG99: 2040 | AH99: 2041 | AI99: 2042 | AJ99: 2043 | AK99: 2044 | AL99: 2045 | AM99: 2046 | AN99: 2047 | AO99: 2048 | AP99: 2049 | AQ99: 2050
H100: Techno-Economic Cost and Performance Parameters | J100: Net Capacity Factor (%) | K100: Commercial PV - Class 10 - Advanced | L100: 0.11974505 | M100: 0.12191978 | N100: 0.12409451 | O100: 0.12626924 | P100: 0.12844397 | Q100: 0.1306187 | R100: 0.13279343 | S100: 0.13496816 | T100: 0.1371429 | U100: 0.13931763 | V100: 0.14149236 | W100: 0.14366709 | X100: 0.14397941 | Y100: 0.14429173 | Z100: 0.14460405 | AA100: 0.14491637 | AB100: 0.14522869 | AC100: 0.14554101 | AD100: 0.14585333 | AE100: 0.14616565 | AF100: 0.14647797 | AG100: 0.14679029 | AH100: 0.1471026 | AI100: 0.14741492 | AJ100: 0.14772724 | AK100: 0.14803956 | AL100: 0.14835188 | AM100: 0.1486642 | AN100: 0.14897652 | AO100: 0.14928884 | AP100: 0.14960116 | AQ100: 0.14991348
K101: Commercial PV - Class 10 - Moderate | L101: 0.11974505 | M101: 0.12103743 | N101: 0.12232982 | O101: 0.1236222 | P101: 0.12491459 | Q101: 0.12620697 | R101: 0.12749935 | S101: 0.12879174 | T101: 0.13008412 | U101: 0.13137651 | V101: 0.13266889 | W101: 0.13396127 | X101: 0.13444656 | Y101: 0.13493186 | Z101: 0.13541715 | AA101: 0.13590244 | AB101: 0.13638773 | AC101: 0.13687302 | AD101: 0.13735831 | AE101: 0.1378436 | AF101: 0.13832889 | AG101: 0.13881418 | AH101: 0.13929947 | AI101: 0.13978476 | AJ101: 0.14027005 | AK101: 0.14075534 | AL101: 0.14124063 | AM101: 0.14172592 | AN101: 0.14221122 | AO101: 0.14269651 | AP101: 0.1431818 | AQ101: 0.14366709
K102: Commercial PV - Class 10 - Conservative | L102: 0.11974505 | M102: 0.11974505 | N102: 0.11974505 | O102: 0.11974505 | P102: 0.11974505 | Q102: 0.11974505 | R102: 0.11974505 | S102: 0.11974505 | T102: 0.11974505 | U102: 0.11974505 | V102: 0.11974505 | W102: 0.11974505 | X102: 0.12045586 | Y102: 0.12116667 | Z102: 0.12187748 | AA102: 0.12258829 | AB102: 0.12329911 | AC102: 0.12400992 | AD102: 0.12472073 | AE102: 0.12543154 | AF102: 0.12614235 | AG102: 0.12685316 | AH102: 0.12756397 | AI102: 0.12827478 | AJ102: 0.1289856 | AK102: 0.12969641 | AL102: 0.13040722 | AM102: 0.13111803 | AN102: 0.13182884 | AO102: 0.13253965 | AP102: 0.13325046 | AQ102: 0.13396127
K103: Commercial PV - Class 9 - Advanced | L103: 0.13163862 | M103: 0.13402935 | N103: 0.13642009 | O103: 0.13881082 | P103: 0.14120156 | Q103: 0.14359229 | R103: 0.14598302 | S103: 0.14837376 | T103: 0.15076449 | U103: 0.15315523 | V103: 0.15554596 | W103: 0.15793669 | X103: 0.15828004 | Y103: 0.15862338 | Z103: 0.15896672 | AA103: 0.15931006 | AB103: 0.1596534 | AC103: 0.15999674 | AD103: 0.16034008 | AE103: 0.16068342 | AF103: 0.16102676 | AG103: 0.1613701 | AH103: 0.16171344 | AI103: 0.16205678 | AJ103: 0.16240012 | AK103: 0.16274346 | AL103: 0.1630868 | AM103: 0.16343014 | AN103: 0.16377349 | AO103: 0.16411683 | AP103: 0.16446017 | AQ103: 0.16480351
K104: Commercial PV - Class 9 - Moderate | L104: 0.13163862 | M104: 0.13305937 | N104: 0.13448012 | O104: 0.13590087 | P104: 0.13732162 | Q104: 0.13874237 | R104: 0.14016311 | S104: 0.14158386 | T104: 0.14300461 | U104: 0.14442536 | V104: 0.14584611 | W104: 0.14726686 | X104: 0.14780035 | Y104: 0.14833384 | Z104: 0.14886733 | AA104: 0.14940083 | AB104: 0.14993432 | AC104: 0.15046781 | AD104: 0.1510013 | AE104: 0.15153479 | AF104: 0.15206829 | AG104: 0.15260178 | AH104: 0.15313527 | AI104: 0.15366876 | AJ104: 0.15420225 | AK104: 0.15473574 | AL104: 0.15526924 | AM104: 0.15580273 | AN104: 0.15633622 | AO104: 0.15686971 | AP104: 0.1574032 | AQ104: 0.15793669
K105: Commercial PV - Class 9 - Conservative | L105: 0.13163862 | M105: 0.13163862 | N105: 0.13163862 | O105: 0.13163862 | P105: 0.13163862 | Q105: 0.13163862 | R105: 0.13163862 | S105: 0.13163862 | T105: 0.13163862 | U105: 0.13163862 | V105: 0.13163862 | W105: 0.13163862 | X105: 0.13242003 | Y105: 0.13320144 | Z105: 0.13398286 | AA105: 0.13476427 | AB105: 0.13554568 | AC105: 0.13632709 | AD105: 0.1371085 | AE105: 0.13788992 | AF105: 0.13867133 | AG105: 0.13945274 | AH105: 0.14023415 | AI105: 0.14101556 | AJ105: 0.14179698 | AK105: 0.14257839 | AL105: 0.1433598 | AM105: 0.14414121 | AN105: 0.14492262 | AO105: 0.14570404 | AP105: 0.14648545 | AQ105: 0.14726686
K106: Commercial PV - Class 8 - Advanced | L106: 0.13713922 | M106: 0.13962985 | N106: 0.14212049 | O106: 0.14461112 | P106: 0.14710175 | Q106: 0.14959238 | R106: 0.15208302 | S106: 0.15457365 | T106: 0.15706428 | U106: 0.15955491 | V106: 0.16204555 | W106: 0.16453618 | X106: 0.16489386 | Y106: 0.16525155 | Z106: 0.16560924 | AA106: 0.16596693 | AB106: 0.16632461 | AC106: 0.1666823 | AD106: 0.16703999 | AE106: 0.16739768 | AF106: 0.16775536 | AG106: 0.16811305 | AH106: 0.16847074 | AI106: 0.16882843 | AJ106: 0.16918611 | AK106: 0.1695438 | AL106: 0.16990149 | AM106: 0.17025917 | AN106: 0.17061686 | AO106: 0.17097455 | AP106: 0.17133224 | AQ106: 0.17168992
K107: Commercial PV - Class 8 - Moderate | L107: 0.13713922 | M107: 0.13861934 | N107: 0.14009945 | O107: 0.14157957 | P107: 0.14305969 | Q107: 0.1445398 | R107: 0.14601992 | S107: 0.14750003 | T107: 0.14898015 | U107: 0.15046027 | V107: 0.15194038 | W107: 0.1534205 | X107: 0.15397628 | Y107: 0.15453206 | Z107: 0.15508785 | AA107: 0.15564363 | AB107: 0.15619942 | AC107: 0.1567552 | AD107: 0.15731099 | AE107: 0.15786677 | AF107: 0.15842255 | AG107: 0.15897834 | AH107: 0.15953412 | AI107: 0.16008991 | AJ107: 0.16064569 | AK107: 0.16120147 | AL107: 0.16175726 | AM107: 0.16231304 | AN107: 0.16286883 | AO107: 0.16342461 | AP107: 0.16398039 | AQ107: 0.16453618
K108: Commercial PV - Class 8 - Conservative | L108: 0.13713922 | M108: 0.13713922 | N108: 0.13713922 | O108: 0.13713922 | P108: 0.13713922 | Q108: 0.13713922 | R108: 0.13713922 | S108: 0.13713922 | T108: 0.13713922 | U108: 0.13713922 | V108: 0.13713922 | W108: 0.13713922 | X108: 0.13795329 | Y108: 0.13876735 | Z108: 0.13958141 | AA108: 0.14039548 | AB108: 0.14120954 | AC108: 0.1420236 | AD108: 0.14283767 | AE108: 0.14365173 | AF108: 0.1444658 | AG108: 0.14527986 | AH108: 0.14609392 | AI108: 0.14690799 | AJ108: 0.14772205 | AK108: 0.14853611 | AL108: 0.14935018 | AM108: 0.15016424 | AN108: 0.15097831 | AO108: 0.15179237 | AP108: 0.15260643 | AQ108: 0.1534205
K109: Commercial PV - Class 7 - Advanced | L109: 0.14439783 | M109: 0.14702029 | N109: 0.14964274 | O109: 0.1522652 | P109: 0.15488766 | Q109: 0.15751012 | R109: 0.16013258 | S109: 0.16275504 | T109: 0.16537749 | U109: 0.16799995 | V109: 0.17062241 | W109: 0.17324487 | X109: 0.17362149 | Y109: 0.17399811 | Z109: 0.17437473 | AA109: 0.17475135 | AB109: 0.17512797 | AC109: 0.17550458 | AD109: 0.1758812 | AE109: 0.17625782 | AF109: 0.17663444 | AG109: 0.17701106 | AH109: 0.17738768 | AI109: 0.1777643 | AJ109: 0.17814092 | AK109: 0.17851754 | AL109: 0.17889416 | AM109: 0.17927078 | AN109: 0.1796474 | AO109: 0.18002402 | AP109: 0.18040064 | AQ109: 0.18077725
K110: Commercial PV - Class 7 - Moderate | L110: 0.14439783 | M110: 0.14595628 | N110: 0.14751474 | O110: 0.1490732 | P110: 0.15063165 | Q110: 0.15219011 | R110: 0.15374857 | S110: 0.15530702 | T110: 0.15686548 | U110: 0.15842394 | V110: 0.15998239 | W110: 0.16154085 | X110: 0.16212605 | Y110: 0.16271125 | Z110: 0.16329645 | AA110: 0.16388165 | AB110: 0.16446685 | AC110: 0.16505206 | AD110: 0.16563726 | AE110: 0.16622246 | AF110: 0.16680766 | AG110: 0.16739286 | AH110: 0.16797806 | AI110: 0.16856326 | AJ110: 0.16914846 | AK110: 0.16973366 | AL110: 0.17031886 | AM110: 0.17090407 | AN110: 0.17148927 | AO110: 0.17207447 | AP110: 0.17265967 | AQ110: 0.17324487
K111: Commercial PV - Class 7 - Conservative | L111: 0.14439783 | M111: 0.14439783 | N111: 0.14439783 | O111: 0.14439783 | P111: 0.14439783 | Q111: 0.14439783 | R111: 0.14439783 | S111: 0.14439783 | T111: 0.14439783 | U111: 0.14439783 | V111: 0.14439783 | W111: 0.14439783 | X111: 0.14525498 | Y111: 0.14611213 | Z111: 0.14696928 | AA111: 0.14782643 | AB111: 0.14868358 | AC111: 0.14954073 | AD111: 0.15039789 | AE111: 0.15125504 | AF111: 0.15211219 | AG111: 0.15296934 | AH111: 0.15382649 | AI111: 0.15468364 | AJ111: 0.15554079 | AK111: 0.15639794 | AL111: 0.15725509 | AM111: 0.15811225 | AN111: 0.1589694 | AO111: 0.15982655 | AP111: 0.1606837 | AQ111: 0.16154085
K112: Commercial PV - Class 6 - Advanced | L112: 0.15155103 | M112: 0.1543034 | N112: 0.15705577 | O112: 0.15980814 | P112: 0.16256051 | Q112: 0.16531288 | R112: 0.16806525 | S112: 0.17081762 | T112: 0.17356999 | U112: 0.17632236 | V112: 0.17907473 | W112: 0.1818271 | X112: 0.18222237 | Y112: 0.18261765 | Z112: 0.18301292 | AA112: 0.1834082 | AB112: 0.18380348 | AC112: 0.18419875 | AD112: 0.18459403 | AE112: 0.18498931 | AF112: 0.18538458 | AG112: 0.18577986 | AH112: 0.18617514 | AI112: 0.18657041 | AJ112: 0.18696569 | AK112: 0.18736096 | AL112: 0.18775624 | AM112: 0.18815152 | AN112: 0.18854679 | AO112: 0.18894207 | AP112: 0.18933735 | AQ112: 0.18973262
... K129: Commercial PV - Class 1 - Conservative | L129: 0.18626187 | M129: 0.18626187 | N129: 0.18626187 | O129: 0.18626187 | P129: 0.18626187 | Q129: 0.18626187 | R129: 0.18626187 | S129: 0.18626187 | T129: 0.18626187 | U129: 0.18626187 | V129: 0.18626187 | W129: 0.18626187 | X129: 0.18736753 | Y129: 0.18847319 | Z129: 0.18957885 | AA129: 0.19068451 | AB129: 0.19179016 | AC129: 0.19289582 | AD129: 0.19400148 | AE129: 0.19510714 | AF129: 0.19621279 | AG129: 0.19731845 | AH129: 0.19842411 | AI129: 0.19952977 | AJ129: 0.20063542 | AK129: 0.20174108 | AL129: 0.20284674 | AM129: 0.2039524 | AN129: 0.20505805 | AO129: 0.20616371 | AP129: 0.20726937 | AQ129: 0.20837503
L131: 2019 | M131: 2020 | N131: 2021 | O131: 2022 | P131: 2023 | Q131: 2024 | R131: 2025 | S131: 2026 | T131: 2027 | U131: 2028 | V131: 2029 | W131: 2030 | X131: 2031 | Y131: 2032 | Z131: 2033 | AA131: 2034 | AB131: 2035 | AC131: 2036 | AD131: 2037 | AE131: 2038 | AF131: 2039 | AG131: 2040 | AH131: 2041 | AI131: 2042 | AJ131: 2043 | AK131: 2044 | AL131: 2045 | AM131: 2046 | AN131: 2047 | AO131: 2048 | AP131: 2049 | AQ131: 2050
J132: Annual Energy Production (kWh/kW) | K132: Commercial PV - Class 10 - Advanced | L132: =L100*8760 -> 1048.9666 | M132: =M100*8760 -> 1068.0173 | N132: =N100*8760 -> 1087.0679 | O132: =O100*8760 -> 1106.1186 | P132: =P100*8760 -> 1125.1692 | Q132: =Q100*8760 -> 1144.2198 | R132: =R100*8760 -> 1163.2705 | S132: =S100*8760 -> 1182.3211 | ... AQ132: =AQ100*8760 -> 1313.2421
K133: Commercial PV - Class 10 - Moderate | L133: =L101*8760 -> 1048.9666 | M133: =M101*8760 -> 1060.2879 | N133: =N101*8760 -> 1071.6092 | O133: =O101*8760 -> 1082.9305 | P133: =P101*8760 -> 1094.2518 | Q133: =Q101*8760 -> 1105.5731 | R133: =R101*8760 -> 1116.8943 | S133: =S101*8760 -> 1128.2156 | ... AQ133: =AQ101*8760 -> 1258.5237
K134: Commercial PV - Class 10 - Conservative | L134: =L102*8760 -> 1048.9666 | M134: =M102*8760 -> 1048.9666 | N134: =N102*8760 -> 1048.9666 | O134: =O102*8760 -> 1048.9666 | P134: =P102*8760 -> 1048.9666 | Q134: =Q102*8760 -> 1048.9666 | R134: =R102*8760 -> 1048.9666 | S134: =S102*8760 -> 1048.9666 | ... AQ134: =AQ102*8760 -> 1173.5008
K135: Commercial PV - Class 9 - Advanced | L135: =L103*8760 -> 1153.1543 | M135: =M103*8760 -> 1174.0971 | N135: =N103*8760 -> 1195.04 | O135: =O103*8760 -> 1215.9828 | P135: =P103*8760 -> 1236.9256 | Q135: =Q103*8760 -> 1257.8685 | R135: =R103*8760 -> 1278.8113 | S135: =S103*8760 -> 1299.7541 | ... AQ135: =AQ103*8760 -> 1443.6787
K136: Commercial PV - Class 9 - Moderate | L136: =L104*8760 -> 1153.1543 | M136: =M104*8760 -> 1165.6001 | N136: =N104*8760 -> 1178.0458 | O136: =O104*8760 -> 1190.4916 | P136: =P104*8760 -> 1202.9374 | Q136: =Q104*8760 -> 1215.3831 | R136: =R104*8760 -> 1227.8289 | S136: =S104*8760 -> 1240.2746 | ... AQ136: =AQ104*8760 -> 1383.5254
K137: Commercial PV - Class 9 - Conservative | L137: =L105*8760 -> 1153.1543 | M137: =M105*8760 -> 1153.1543 | N137: =N105*8760 -> 1153.1543 | O137: =O105*8760 -> 1153.1543 | P137: =P105*8760 -> 1153.1543 | Q137: =Q105*8760 -> 1153.1543 | R137: =R105*8760 -> 1153.1543 | S137: =S105*8760 -> 1153.1543 | ... AQ137: =AQ105*8760 -> 1290.0577
K138: Commercial PV - Class 8 - Advanced | L138: =L106*8760 -> 1201.3396 | M138: =M106*8760 -> 1223.1575 | N138: =N106*8760 -> 1244.9755 | O138: =O106*8760 -> 1266.7934 | P138: =P106*8760 -> 1288.6113 | Q138: =Q106*8760 -> 1310.4293 | R138: =R106*8760 -> 1332.2472 | S138: =S106*8760 -> 1354.0652 | ... AQ138: =AQ106*8760 -> 1504.0037
K139: Commercial PV - Class 8 - Moderate | L139: =L107*8760 -> 1201.3396 | M139: =M107*8760 -> 1214.3054 | N139: =N107*8760 -> 1227.2712 | O139: =O107*8760 -> 1240.237 | P139: =P107*8760 -> 1253.2028 | Q139: =Q107*8760 -> 1266.1687 | R139: =R107*8760 -> 1279.1345 | S139: =S107*8760 -> 1292.1003 | ... AQ139: =AQ107*8760 -> 1441.3369
K140: Commercial PV - Class 8 - Conservative | L140: =L108*8760 -> 1201.3396 | M140: =M108*8760 -> 1201.3396 | N140: =N108*8760 -> 1201.3396 | O140: =O108*8760 -> 1201.3396 | P140: =P108*8760 -> 1201.3396 | Q140: =Q108*8760 -> 1201.3396 | R140: =R108*8760 -> 1201.3396 | S140: =S108*8760 -> 1201.3396 | ... AQ140: =AQ108*8760 -> 1343.9636
K141: Commercial PV - Class 7 - Advanced | L141: =L109*8760 -> 1264.925 | M141: =M109*8760 -> 1287.8977 | N141: =N109*8760 -> 1310.8704 | O141: =O109*8760 -> 1333.8432 | P141: =P109*8760 -> 1356.8159 | Q141: =Q109*8760 -> 1379.7886 | R141: =R109*8760 -> 1402.7614 | S141: =S109*8760 -> 1425.7341 | ... AQ141: =AQ109*8760 -> 1583.6087
K142: Commercial PV - Class 7 - Moderate | L142: =L110*8760 -> 1264.925 | M142: =M110*8760 -> 1278.5771 | N142: =N110*8760 -> 1292.2291 | O142: =O110*8760 -> 1305.8812 | P142: =P110*8760 -> 1319.5333 | Q142: =Q110*8760 -> 1333.1854 | R142: =R110*8760 -> 1346.8374 | S142: =S110*8760 -> 1360.4895 | ... AQ142: =AQ110*8760 -> 1517.6251
K143: Commercial PV - Class 7 - Conservative | L143: =L111*8760 -> 1264.925 | M143: =M111*8760 -> 1264.925 | N143: =N111*8760 -> 1264.925 | O143: =O111*8760 -> 1264.925 | P143: =P111*8760 -> 1264.925 | Q143: =Q111*8760 -> 1264.925 | R143: =R111*8760 -> 1264.925 | S143: =S111*8760 -> 1264.925 | ... AQ143: =AQ111*8760 -> 1415.0978
K144: Commercial PV - Class 6 - Advanced | L144: =L112*8760 -> 1327.587 | M144: =M112*8760 -> 1351.6978 | N144: =N112*8760 -> 1375.8085 | O144: =O112*8760 -> 1399.9193 | P144: =P112*8760 -> 1424.03 | Q144: =Q112*8760 -> 1448.1408 | R144: =R112*8760 -> 1472.2516 | S144: =S112*8760 -> 1496.3623 | ... AQ144: =AQ112*8760 -> 1662.0578
... K161: Commercial PV - Class 1 - Conservative | L161: =L129*8760 -> 1631.654 | M161: =M129*8760 -> 1631.654 | N161: =N129*8760 -> 1631.654 | O161: =O129*8760 -> 1631.654 | P161: =P129*8760 -> 1631.654 | Q161: =Q129*8760 -> 1631.654 | R161: =R129*8760 -> 1631.654 | S161: =S129*8760 -> 1631.654 | ... AQ161: =AQ129*8760 -> 1825.3652
L163: 2019 | M163: 2020 | N163: 2021 | O163: 2022 | P163: 2023 | Q163: 2024 | R163: 2025 | S163: 2026 | T163: 2027 | U163: 2028 | V163: 2029 | W163: 2030 | X163: 2031 | Y163: 2032 | Z163: 2033 | AA163: 2034 | AB163: 2035 | AC163: 2036 | AD163: 2037 | AE163: 2038 | AF163: 2039 | AG163: 2040 | AH163: 2041 | AI163: 2042 | AJ163: 2043 | AK163: 2044 | AL163: 2045 | AM163: 2046 | AN163: 2047 | AO163: 2048 | AP163: 2049 | AQ163: 2050 | AR163: =AQ163+1 -> 2051 | AS163: =AR163+1 -> 2052 | AT163: =AS163+1 -> 2053 | AU163: =AT163+1 -> 2054 | AV163: =AU163+1 -> 2055 | AW163: =AV163+1 -> 2056 | AX163: =AW163+1 -> 2057 | AY163: =AX163+1 -> 2058 | ... BK163: =BJ163+1 -> 2070
J164: CAPEX ($/kW) | K164: Commercial PV - Class 10 - Advanced | L164: =$N$45*(L196+L325) -> 1806.4626 | M164: =$N$45*(M196+M325) -> 1762.4296 | N164: =$N$45*(N196+N325) -> 1656.2193 | O164: =$N$45*(O196+O325) -> 1550.009 | P164: =$N$45*(P196+P325) -> 1443.7988 | Q164: =$N$45*(Q196+Q325) -> 1337.5885 | R164: =$N$45*(R196+R325) -> 1231.3782 | S164: =$N$45*(S196+S325) -> 1125.1679 | ... AQ164: =$N$45*(AQ196+AQ325) -> 519.80177
...

Sheet Solar - PV Dist. Comm 2022
A1: Solar Distributed Commercial PV | M1: https://atb.nrel.gov/electricity/2022/commercial_pv
U2: Inputs
U3: Calculated
U4: Input from other tab
B7: X | G7: Assumptions
H9: Technology | J9: Base Year: | M9: 2020
J10: All values are given in 2020 U.S. dollars, using the Consumer Price Index (BLS, 2021) for dollar year conversions where source dollar years don't match 2020.
J11: Commercial Solar Photovoltaic
J14: Representative Dist. Commercial system is fixed-tilt roof mounted with capacity of 200 kW
J15: Overnight Capital Cost, Capacity Factor, Fixed O&M, and Variable O&M costs
J16: represent $/kW DC; however LCOE reflects $/MWh AC.
J17: Capacity factors chosen here to reflect range across the continental U.S. using NREL PVWATTS.
O20: Available | P20: Available
O21: Capacity | P21: Generation
O22: (GW) | P22: (GWh)
O23: 386 | P23: 506000
M26: ATB values reflect annual average capacity factor over life of plant including estimated degradation, starting at 0.7% per year, reducing to 0.2%, 0.5%, and 0.5% annual degradation by 2050 for the advanced, moderate, and conservative scenarios, respectively. Capacity factors also assume an energy yield gain at the module of 10%, 5%, and 2.5% for advanced, moderate, and conservatives scenarios.
H32: Finance | J32: Financial Assumptions:
J33: Capital Recovery Period (Years) | O33: =S34 -> 30 | Q33: Financial Case | S33: ='[2]Financial and CRP Inputs'!$B$5 -> Market
J34: Depreciation Period | O34: 5 | Q34: Capital Recovery Period | S34: =IF('[2]Financial and CRP Inputs'!$E$5="Custom",'[2]Financial and CRP Inputs'!$J$9,IF('[2]Financial and CRP Inputs'!$E$5="TechLife",'[2]Financial and CRP Inputs'!$I$9,'[2]Financial and CRP Inputs'!$E$5)) -> 30
J35: Equity Premium During Construction | O35: 0.02
J36: Construction Duration yrs | O36: 1
J37: Year | K37: Capital | L37: Percent of Leverage During Construction | M37: Percent of Equity During Construction
J38: Index | K38: Fraction
J41: 0 | K41: 1 | L41: 0.8 | M41: =1-L41 -> 0.2
J42: 1 | K42: 0 | L42: 0.8 | M42: =1-L42 -> 0.2
J43: 2 | K43: 0 | L43: 0.8 | M43: =1-L43 -> 0.2
M45: Base Year
M46: 2020 | N46: 2021 | O46: 2022 | P46: 2023 | Q46: 2024 | R46: 2025 | S46: 2026 | T46: 2027 | U46: 2028 | V46: 2029 | W46: 2030 | X46: 2031 | Y46: 2032 | Z46: 2033 | AA46: 2034 | AB46: 2035 | AC46: 2036 | AD46: 2037 | AE46: 2038 | AF46: 2039 | AG46: 2040 | AH46: 2041 | AI46: 2042 | AJ46: 2043 | AK46: 2044 | AL46: 2045 | AM46: 2046 | AN46: 2047 | AO46: 2048 | AP46: 2049 | AQ46: 2050
J47: Assumptions | K47: Inflation Rate | L47: * | M47: =IF($S$33="Market",'[2]WACC Calc'!F159,'[2]WACC Calc'!F524) -> 0.025 | N47: =IF($S$33="Market",'[2]WACC Calc'!G159,'[2]WACC Calc'!G524) -> 0.025 | O47: =IF($S$33="Market",'[2]WACC Calc'!H159,'[2]WACC Calc'!H524) -> 0.025 | P47: =IF($S$33="Market",'[2]WACC Calc'!I159,'[2]WACC Calc'!I524) -> 0.025 | Q47: =IF($S$33="Market",'[2]WACC Calc'!J159,'[2]WACC Calc'!J524) -> 0.025 | R47: =IF($S$33="Market",'[2]WACC Calc'!K159,'[2]WACC Calc'!K524) -> 0.025 | S47: =IF($S$33="Market",'[2]WACC Calc'!L159,'[2]WACC Calc'!L524) -> 0.025 | T47: =IF($S$33="Market",'[2]WACC Calc'!M159,'[2]WACC Calc'!M524) -> 0.025 | ... AQ47: =IF($S$33="Market",'[2]WACC Calc'!AJ159,'[2]WACC Calc'!AJ524) -> 0.025
K48: Interest Rate Nominal | L48: Advanced | M48: =IF($S$33="Market",'[2]WACC Calc'!F160,'[2]WACC Calc'!F525) -> 0.04 | N48: =IF($S$33="Market",'[2]WACC Calc'!G160,'[2]WACC Calc'!G525) -> 0.04 | O48: =IF($S$33="Market",'[2]WACC Calc'!H160,'[2]WACC Calc'!H525) -> 0.04 | P48: =IF($S$33="Market",'[2]WACC Calc'!I160,'[2]WACC Calc'!I525) -> 0.04 | Q48: =IF($S$33="Market",'[2]WACC Calc'!J160,'[2]WACC Calc'!J525) -> 0.04 | R48: =IF($S$33="Market",'[2]WACC Calc'!K160,'[2]WACC Calc'!K525) -> 0.04 | S48: =IF($S$33="Market",'[2]WACC Calc'!L160,'[2]WACC Calc'!L525) -> 0.042 | T48: =IF($S$33="Market",'[2]WACC Calc'!M160,'[2]WACC Calc'!M525) -> 0.044 | ... AQ48: =IF($S$33="Market",'[2]WACC Calc'!AJ160,'[2]WACC Calc'!AJ525) -> 0.05
K49: Interest Rate Nominal | L49: Moderate | M49: =IF($S$33="Market",'[2]WACC Calc'!F161,'[2]WACC Calc'!F526) -> 0.04 | N49: =IF($S$33="Market",'[2]WACC Calc'!G161,'[2]WACC Calc'!G526) -> 0.04 | O49: =IF($S$33="Market",'[2]WACC Calc'!H161,'[2]WACC Calc'!H526) -> 0.04 | P49: =IF($S$33="Market",'[2]WACC Calc'!I161,'[2]WACC Calc'!I526) -> 0.04 | Q49: =IF($S$33="Market",'[2]WACC Calc'!J161,'[2]WACC Calc'!J526) -> 0.04 | R49: =IF($S$33="Market",'[2]WACC Calc'!K161,'[2]WACC Calc'!K526) -> 0.04 | S49: =IF($S$33="Market",'[2]WACC Calc'!L161,'[2]WACC Calc'!L526) -> 0.042 | T49: =IF($S$33="Market",'[2]WACC Calc'!M161,'[2]WACC Calc'!M526) -> 0.044 | ... AQ49: =IF($S$33="Market",'[2]WACC Calc'!AJ161,'[2]WACC Calc'!AJ526) -> 0.05
K50: Interest Rate Nominal | L50: Conservative | M50: =IF($S$33="Market",'[2]WACC Calc'!F162,'[2]WACC Calc'!F527) -> 0.04 | N50: =IF($S$33="Market",'[2]WACC Calc'!G162,'[2]WACC Calc'!G527) -> 0.04 | O50: =IF($S$33="Market",'[2]WACC Calc'!H162,'[2]WACC Calc'!H527) -> 0.04 | P50: =IF($S$33="Market",'[2]WACC Calc'!I162,'[2]WACC Calc'!I527) -> 0.04 | Q50: =IF($S$33="Market",'[2]WACC Calc'!J162,'[2]WACC Calc'!J527) -> 0.04 | R50: =IF($S$33="Market",'[2]WACC Calc'!K162,'[2]WACC Calc'!K527) -> 0.04 | S50: =IF($S$33="Market",'[2]WACC Calc'!L162,'[2]WACC Calc'!L527) -> 0.042 | T50: =IF($S$33="Market",'[2]WACC Calc'!M162,'[2]WACC Calc'!M527) -> 0.044 | ... AQ50: =IF($S$33="Market",'[2]WACC Calc'!AJ162,'[2]WACC Calc'!AJ527) -> 0.05
K51: Calculated Interest Rate Real | L51: Advanced | M51: =(1+M48)/(1+M$47) - 1 -> 0.014634146 | N51: =(1+N48)/(1+N$47) - 1 -> 0.014634146 | O51: =(1+O48)/(1+O$47) - 1 -> 0.014634146 | P51: =(1+P48)/(1+P$47) - 1 -> 0.014634146 | Q51: =(1+Q48)/(1+Q$47) - 1 -> 0.014634146 | R51: =(1+R48)/(1+R$47) - 1 -> 0.014634146 | S51: =(1+S48)/(1+S$47) - 1 -> 0.016585366 | T51: =(1+T48)/(1+T$47) - 1 -> 0.018536585 | ... AQ51: =(1+AQ48)/(1+AQ$47) - 1 -> 0.024390244
K52: Calculated Interest Rate Real | L52: Moderate | M52: =(1+M49)/(1+M$47) - 1 -> 0.014634146 | N52: =(1+N49)/(1+N$47) - 1 -> 0.014634146 | O52: =(1+O49)/(1+O$47) - 1 -> 0.014634146 | P52: =(1+P49)/(1+P$47) - 1 -> 0.014634146 | Q52: =(1+Q49)/(1+Q$47) - 1 -> 0.014634146 | R52: =(1+R49)/(1+R$47) - 1 -> 0.014634146 | S52: =(1+S49)/(1+S$47) - 1 -> 0.016585366 | T52: =(1+T49)/(1+T$47) - 1 -> 0.018536585 | ... AQ52: =(1+AQ49)/(1+AQ$47) - 1 -> 0.024390244
K53: Calculated Interest Rate Real | L53: Conservative | M53: =(1+M50)/(1+M$47) - 1 -> 0.014634146 | N53: =(1+N50)/(1+N$47) - 1 -> 0.014634146 | O53: =(1+O50)/(1+O$47) - 1 -> 0.014634146 | P53: =(1+P50)/(1+P$47) - 1 -> 0.014634146 | Q53: =(1+Q50)/(1+Q$47) - 1 -> 0.014634146 | R53: =(1+R50)/(1+R$47) - 1 -> 0.014634146 | S53: =(1+S50)/(1+S$47) - 1 -> 0.016585366 | T53: =(1+T50)/(1+T$47) - 1 -> 0.018536585 | ... AQ53: =(1+AQ50)/(1+AQ$47) - 1 -> 0.024390244
K54: Interest During Construction - Nominal | L54: * | M54: =IF($S$33="Market",'[2]WACC Calc'!F166,'[2]WACC Calc'!F531) -> 0.035 | N54: =IF($S$33="Market",'[2]WACC Calc'!G166,'[2]WACC Calc'!G531) -> 0.035 | O54: =IF($S$33="Market",'[2]WACC Calc'!H166,'[2]WACC Calc'!H531) -> 0.035 | P54: =IF($S$33="Market",'[2]WACC Calc'!I166,'[2]WACC Calc'!I531) -> 0.035 | Q54: =IF($S$33="Market",'[2]WACC Calc'!J166,'[2]WACC Calc'!J531) -> 0.035 | R54: =IF($S$33="Market",'[2]WACC Calc'!K166,'[2]WACC Calc'!K531) -> 0.035 | S54: =IF($S$33="Market",'[2]WACC Calc'!L166,'[2]WACC Calc'!L531) -> 0.037 | T54: =IF($S$33="Market",'[2]WACC Calc'!M166,'[2]WACC Calc'!M531) -> 0.039 | ... AQ54: =IF($S$33="Market",'[2]WACC Calc'!AJ166,'[2]WACC Calc'!AJ531) -> 0.045
K55: Rate of Return on Equity Nominal | L55: Advanced | M55: =IF($S$33="Market",'[2]WACC Calc'!F167,'[2]WACC Calc'!F532) -> 0.0875 | N55: =IF($S$33="Market",'[2]WACC Calc'!G167,'[2]WACC Calc'!G532) -> 0.0875 | O55: =IF($S$33="Market",'[2]WACC Calc'!H167,'[2]WACC Calc'!H532) -> 0.0875 | P55: =IF($S$33="Market",'[2]WACC Calc'!I167,'[2]WACC Calc'!I532) -> 0.0875 | Q55: =IF($S$33="Market",'[2]WACC Calc'!J167,'[2]WACC Calc'!J532) -> 0.0875 | R55: =IF($S$33="Market",'[2]WACC Calc'!K167,'[2]WACC Calc'!K532) -> 0.0875 | S55: =IF($S$33="Market",'[2]WACC Calc'!L167,'[2]WACC Calc'!L532) -> 0.0875 | T55: =IF($S$33="Market",'[2]WACC Calc'!M167,'[2]WACC Calc'!M532) -> 0.0875 | ... AQ55: =IF($S$33="Market",'[2]WACC Calc'!AJ167,'[2]WACC Calc'!AJ532) -> 0.0875
K56: Rate of Return on Equity Nominal | L56: Moderate | M56: =IF($S$33="Market",'[2]WACC Calc'!F168,'[2]WACC Calc'!F533) -> 0.0875 | N56: =IF($S$33="Market",'[2]WACC Calc'!G168,'[2]WACC Calc'!G533) -> 0.0875 | O56: =IF($S$33="Market",'[2]WACC Calc'!H168,'[2]WACC Calc'!H533) -> 0.0875 | P56: =IF($S$33="Market",'[2]WACC Calc'!I168,'[2]WACC Calc'!I533) -> 0.0875 | Q56: =IF($S$33="Market",'[2]WACC Calc'!J168,'[2]WACC Calc'!J533) -> 0.0875 | R56: =IF($S$33="Market",'[2]WACC Calc'!K168,'[2]WACC Calc'!K533) -> 0.0875 | S56: =IF($S$33="Market",'[2]WACC Calc'!L168,'[2]WACC Calc'!L533) -> 0.0875 | T56: =IF($S$33="Market",'[2]WACC Calc'!M168,'[2]WACC Calc'!M533) -> 0.0875 | ... AQ56: =IF($S$33="Market",'[2]WACC Calc'!AJ168,'[2]WACC Calc'!AJ533) -> 0.0875
K57: Rate of Return on Equity Nominal | L57: Conservative | M57: =IF($S$33="Market",'[2]WACC Calc'!F169,'[2]WACC Calc'!F534) -> 0.0875 | N57: =IF($S$33="Market",'[2]WACC Calc'!G169,'[2]WACC Calc'!G534) -> 0.0875 | O57: =IF($S$33="Market",'[2]WACC Calc'!H169,'[2]WACC Calc'!H534) -> 0.0875 | P57: =IF($S$33="Market",'[2]WACC Calc'!I169,'[2]WACC Calc'!I534) -> 0.0875 | Q57: =IF($S$33="Market",'[2]WACC Calc'!J169,'[2]WACC Calc'!J534) -> 0.0875 | R57: =IF($S$33="Market",'[2]WACC Calc'!K169,'[2]WACC Calc'!K534) -> 0.0875 | S57: =IF($S$33="Market",'[2]WACC Calc'!L169,'[2]WACC Calc'!L534) -> 0.0875 | T57: =IF($S$33="Market",'[2]WACC Calc'!M169,'[2]WACC Calc'!M534) -> 0.0875 | ... AQ57: =IF($S$33="Market",'[2]WACC Calc'!AJ169,'[2]WACC Calc'!AJ534) -> 0.0875
K58: Calculated Rate of Return on Equity Real | L58: Advanced | M58: =(1+M55)/(1+M$47) - 1 -> 0.06097561 | N58: =(1+N55)/(1+N$47) - 1 -> 0.06097561 | O58: =(1+O55)/(1+O$47) - 1 -> 0.06097561 | P58: =(1+P55)/(1+P$47) - 1 -> 0.06097561 | Q58: =(1+Q55)/(1+Q$47) - 1 -> 0.06097561 | R58: =(1+R55)/(1+R$47) - 1 -> 0.06097561 | S58: =(1+S55)/(1+S$47) - 1 -> 0.06097561 | T58: =(1+T55)/(1+T$47) - 1 -> 0.06097561 | ... AQ58: =(1+AQ55)/(1+AQ$47) - 1 -> 0.06097561
K59: Calculated Rate of Return on Equity Real | L59: Moderate | M59: =(1+M56)/(1+M$47) - 1 -> 0.06097561 | N59: =(1+N56)/(1+N$47) - 1 -> 0.06097561 | O59: =(1+O56)/(1+O$47) - 1 -> 0.06097561 | P59: =(1+P56)/(1+P$47) - 1 -> 0.06097561 | Q59: =(1+Q56)/(1+Q$47) - 1 -> 0.06097561 | R59: =(1+R56)/(1+R$47) - 1 -> 0.06097561 | S59: =(1+S56)/(1+S$47) - 1 -> 0.06097561 | T59: =(1+T56)/(1+T$47) - 1 -> 0.06097561 | ... AQ59: =(1+AQ56)/(1+AQ$47) - 1 -> 0.06097561
K60: Calculated Rate of Return on Equity Real | L60: Conservative | M60: =(1+M57)/(1+M$47) - 1 -> 0.06097561 | N60: =(1+N57)/(1+N$47) - 1 -> 0.06097561 | O60: =(1+O57)/(1+O$47) - 1 -> 0.06097561 | P60: =(1+P57)/(1+P$47) - 1 -> 0.06097561 | Q60: =(1+Q57)/(1+Q$47) - 1 -> 0.06097561 | R60: =(1+R57)/(1+R$47) - 1 -> 0.06097561 | S60: =(1+S57)/(1+S$47) - 1 -> 0.06097561 | T60: =(1+T57)/(1+T$47) - 1 -> 0.06097561 | ... AQ60: =(1+AQ57)/(1+AQ$47) - 1 -> 0.06097561
K61: Debt Fraction | L61: Advanced | M61: =IF($S$33="Market",'[2]WACC Calc'!F173,'[2]WACC Calc'!F538) -> 0.53788826 | N61: =IF($S$33="Market",'[2]WACC Calc'!G173,'[2]WACC Calc'!G538) -> 0.53788826 | O61: =IF($S$33="Market",'[2]WACC Calc'!H173,'[2]WACC Calc'!H538) -> 0.53788826 | P61: =IF($S$33="Market",'[2]WACC Calc'!I173,'[2]WACC Calc'!I538) -> 0.53788826 | Q61: =IF($S$33="Market",'[2]WACC Calc'!J173,'[2]WACC Calc'!J538) -> 0.56721612 | R61: =IF($S$33="Market",'[2]WACC Calc'!K173,'[2]WACC Calc'!K538) -> 0.56721612 | S61: =IF($S$33="Market",'[2]WACC Calc'!L173,'[2]WACC Calc'!L538) -> 0.6845276 | T61: =IF($S$33="Market",'[2]WACC Calc'!M173,'[2]WACC Calc'!M538) -> 0.68086539 | ... AQ61: =IF($S$33="Market",'[2]WACC Calc'!AJ173,'[2]WACC Calc'!AJ538) -> 0.66987878
K62: Debt Fraction | L62: Moderate | M62: =IF($S$33="Market",'[2]WACC Calc'!F174,'[2]WACC Calc'!F539) -> 0.53788826 | N62: =IF($S$33="Market",'[2]WACC Calc'!G174,'[2]WACC Calc'!G539) -> 0.53788826 | O62: =IF($S$33="Market",'[2]WACC Calc'!H174,'[2]WACC Calc'!H539) -> 0.53788826 | P62: =IF($S$33="Market",'[2]WACC Calc'!I174,'[2]WACC Calc'!I539) -> 0.53788826 | Q62: =IF($S$33="Market",'[2]WACC Calc'!J174,'[2]WACC Calc'!J539) -> 0.56721612 | R62: =IF($S$33="Market",'[2]WACC Calc'!K174,'[2]WACC Calc'!K539) -> 0.56721612 | S62: =IF($S$33="Market",'[2]WACC Calc'!L174,'[2]WACC Calc'!L539) -> 0.6845276 | T62: =IF($S$33="Market",'[2]WACC Calc'!M174,'[2]WACC Calc'!M539) -> 0.68086539 | ... AQ62: =IF($S$33="Market",'[2]WACC Calc'!AJ174,'[2]WACC Calc'!AJ539) -> 0.66987878
K63: Debt Fraction | L63: Conservative | M63: =IF($S$33="Market",'[2]WACC Calc'!F175,'[2]WACC Calc'!F540) -> 0.53788826 | N63: =IF($S$33="Market",'[2]WACC Calc'!G175,'[2]WACC Calc'!G540) -> 0.53788826 | O63: =IF($S$33="Market",'[2]WACC Calc'!H175,'[2]WACC Calc'!H540) -> 0.53788826 | P63: =IF($S$33="Market",'[2]WACC Calc'!I175,'[2]WACC Calc'!I540) -> 0.53788826 | Q63: =IF($S$33="Market",'[2]WACC Calc'!J175,'[2]WACC Calc'!J540) -> 0.56721612 | R63: =IF($S$33="Market",'[2]WACC Calc'!K175,'[2]WACC Calc'!K540) -> 0.56721612 | S63: =IF($S$33="Market",'[2]WACC Calc'!L175,'[2]WACC Calc'!L540) -> 0.6845276 | T63: =IF($S$33="Market",'[2]WACC Calc'!M175,'[2]WACC Calc'!M540) -> 0.68086539 | ... AQ63: =IF($S$33="Market",'[2]WACC Calc'!AJ175,'[2]WACC Calc'!AJ540) -> 0.66987878
K64: Tax Rate (Federal and State) | L64: * | M64: =IF($S$33="Market",'[2]WACC Calc'!F176,'[2]WACC Calc'!F541) -> 0.2574 | N64: =IF($S$33="Market",'[2]WACC Calc'!G176,'[2]WACC Calc'!G541) -> 0.2574 | O64: =IF($S$33="Market",'[2]WACC Calc'!H176,'[2]WACC Calc'!H541) -> 0.2574 | P64: =IF($S$33="Market",'[2]WACC Calc'!I176,'[2]WACC Calc'!I541) -> 0.2574 | Q64: =IF($S$33="Market",'[2]WACC Calc'!J176,'[2]WACC Calc'!J541) -> 0.2574 | R64: =IF($S$33="Market",'[2]WACC Calc'!K176,'[2]WACC Calc'!K541) -> 0.2574 | S64: =IF($S$33="Market",'[2]WACC Calc'!L176,'[2]WACC Calc'!L541) -> 0.2574 | T64: =IF($S$33="Market",'[2]WACC Calc'!M176,'[2]WACC Calc'!M541) -> 0.2574 | ... AQ64: =IF($S$33="Market",'[2]WACC Calc'!AJ176,'[2]WACC Calc'!AJ541) -> 0.2574
K65: WACC Nominal | L65: Advanced | M65: =M61*M48*(1-M$64)+(1-M61)*(M55) -> 0.05641221 | N65: =N61*N48*(1-N$64)+(1-N61)*(N55) -> 0.05641221 | O65: =O61*O48*(1-O$64)+(1-O61)*(O55) -> 0.05641221 | P65: =P61*P48*(1-P$64)+(1-P61)*(P55) -> 0.05641221 | Q65: =Q61*Q48*(1-Q$64)+(1-Q61)*(Q55) -> 0.054717177 | R65: =R61*R48*(1-R$64)+(1-R61)*(R55) -> 0.054717177 | S65: =S61*S48*(1-S$64)+(1-S61)*(S55) -> 0.048953703 | T65: =T61*T48*(1-T$64)+(1-T61)*(T55) -> 0.050171146 | ... AQ65: =AQ61*AQ48*(1-AQ$64)+(1-AQ61)*(AQ55) -> 0.053758206
K66: WACC Nominal | L66: Moderate | M66: =M62*M49*(1-M$64)+(1-M62)*(M56) -> 0.05641221 | N66: =N62*N49*(1-N$64)+(1-N62)*(N56) -> 0.05641221 | O66: =O62*O49*(1-O$64)+(1-O62)*(O56) -> 0.05641221 | P66: =P62*P49*(1-P$64)+(1-P62)*(P56) -> 0.05641221 | Q66: =Q62*Q49*(1-Q$64)+(1-Q62)*(Q56) -> 0.054717177 | R66: =R62*R49*(1-R$64)+(1-R62)*(R56) -> 0.054717177 | S66: =S62*S49*(1-S$64)+(1-S62)*(S56) -> 0.048953703 | T66: =T62*T49*(1-T$64)+(1-T62)*(T56) -> 0.050171146 | ... AQ66: =AQ62*AQ49*(1-AQ$64)+(1-AQ62)*(AQ56) -> 0.053758206
K67: WACC Nominal | L67: Conservative | M67: =M63*M50*(1-M$64)+(1-M63)*(M57) -> 0.05641221 | N67: =N63*N50*(1-N$64)+(1-N63)*(N57) -> 0.05641221 | O67: =O63*O50*(1-O$64)+(1-O63)*(O57) -> 0.05641221 | P67: =P63*P50*(1-P$64)+(1-P63)*(P57) -> 0.05641221 | Q67: =Q63*Q50*(1-Q$64)+(1-Q63)*(Q57) -> 0.054717177 | R67: =R63*R50*(1-R$64)+(1-R63)*(R57) -> 0.054717177 | S67: =S63*S50*(1-S$64)+(1-S63)*(S57) -> 0.048953703 | T67: =T63*T50*(1-T$64)+(1-T63)*(T57) -> 0.050171146 | ... AQ67: =AQ63*AQ50*(1-AQ$64)+(1-AQ63)*(AQ57) -> 0.053758206
K68: WACC Real | L68: Advanced | M68: =(1+M65)/(1+M$47) - 1 -> 0.030646059 | N68: =(1+N65)/(1+N$47) - 1 -> 0.030646059 | O68: =(1+O65)/(1+O$47) - 1 -> 0.030646059 | P68: =(1+P65)/(1+P$47) - 1 -> 0.030646059 | Q68: =(1+Q65)/(1+Q$47) - 1 -> 0.028992368 | R68: =(1+R65)/(1+R$47) - 1 -> 0.028992368 | S68: =(1+S65)/(1+S$47) - 1 -> 0.023369467 | T68: =(1+T65)/(1+T$47) - 1 -> 0.024557216 | ... AQ68: =(1+AQ65)/(1+AQ$47) - 1 -> 0.028056786
K69: WACC Real | L69: Moderate | M69: =(1+M66)/(1+M$47) - 1 -> 0.030646059 | N69: =(1+N66)/(1+N$47) - 1 -> 0.030646059 | O69: =(1+O66)/(1+O$47) - 1 -> 0.030646059 | P69: =(1+P66)/(1+P$47) - 1 -> 0.030646059 | Q69: =(1+Q66)/(1+Q$47) - 1 -> 0.028992368 | R69: =(1+R66)/(1+R$47) - 1 -> 0.028992368 | S69: =(1+S66)/(1+S$47) - 1 -> 0.023369467 | T69: =(1+T66)/(1+T$47) - 1 -> 0.024557216 | ... AQ69: =(1+AQ66)/(1+AQ$47) - 1 -> 0.028056786
K70: WACC Real | L70: Conservative | M70: =(1+M67)/(1+M$47) - 1 -> 0.030646059 | N70: =(1+N67)/(1+N$47) - 1 -> 0.030646059 | O70: =(1+O67)/(1+O$47) - 1 -> 0.030646059 | P70: =(1+P67)/(1+P$47) - 1 -> 0.030646059 | Q70: =(1+Q67)/(1+Q$47) - 1 -> 0.028992368 | R70: =(1+R67)/(1+R$47) - 1 -> 0.028992368 | S70: =(1+S67)/(1+S$47) - 1 -> 0.023369467 | T70: =(1+T67)/(1+T$47) - 1 -> 0.024557216 | ... AQ70: =(1+AQ67)/(1+AQ$47) - 1 -> 0.028056786
K71: Capital Recovery Factor (CRF) Nominal | L71: Advanced | M71: =M65 / (1 - (1 / (1 + M65)^$O$33)) -> 0.069882082 | N71: =N65 / (1 - (1 / (1 + N65)^$O$33)) -> 0.069882082 | O71: =O65 / (1 - (1 / (1 + O65)^$O$33)) -> 0.069882082 | P71: =P65 / (1 - (1 / (1 + P65)^$O$33)) -> 0.069882082 | Q71: =Q65 / (1 - (1 / (1 + Q65)^$O$33)) -> 0.068590616 | R71: =R65 / (1 - (1 / (1 + R65)^$O$33)) -> 0.068590616 | S71: =S65 / (1 - (1 / (1 + S65)^$O$33)) -> 0.064277638 | T71: =T65 / (1 - (1 / (1 + T65)^$O$33)) -> 0.065178401 | ... AQ71: =AQ65 / (1 - (1 / (1 + AQ65)^$O$33)) -> 0.067864526
K72: Capital Recovery Factor (CRF) Nominal | L72: Moderate | M72: =M66 / (1 - (1 / (1 + M66)^$O$33)) -> 0.069882082 | N72: =N66 / (1 - (1 / (1 + N66)^$O$33)) -> 0.069882082 | O72: =O66 / (1 - (1 / (1 + O66)^$O$33)) -> 0.069882082 | P72: =P66 / (1 - (1 / (1 + P66)^$O$33)) -> 0.069882082 | Q72: =Q66 / (1 - (1 / (1 + Q66)^$O$33)) -> 0.068590616 | R72: =R66 / (1 - (1 / (1 + R66)^$O$33)) -> 0.068590616 | S72: =S66 / (1 - (1 / (1 + S66)^$O$33)) -> 0.064277638 | T72: =T66 / (1 - (1 / (1 + T66)^$O$33)) -> 0.065178401 | ... AQ72: =AQ66 / (1 - (1 / (1 + AQ66)^$O$33)) -> 0.067864526
K73: Capital Recovery Factor (CRF) Nominal | L73: Conservative | M73: =M67 / (1 - (1 / (1 + M67)^$O$33)) -> 0.069882082 | N73: =N67 / (1 - (1 / (1 + N67)^$O$33)) -> 0.069882082 | O73: =O67 / (1 - (1 / (1 + O67)^$O$33)) -> 0.069882082 | P73: =P67 / (1 - (1 / (1 + P67)^$O$33)) -> 0.069882082 | Q73: =Q67 / (1 - (1 / (1 + Q67)^$O$33)) -> 0.068590616 | R73: =R67 / (1 - (1 / (1 + R67)^$O$33)) -> 0.068590616 | S73: =S67 / (1 - (1 / (1 + S67)^$O$33)) -> 0.064277638 | T73: =T67 / (1 - (1 / (1 + T67)^$O$33)) -> 0.065178401 | ... AQ73: =AQ67 / (1 - (1 / (1 + AQ67)^$O$33)) -> 0.067864526
K74: Capital Recovery Factor (CRF) Real | L74: Advanced | M74: =M68 / (1 - (1 / (1 + M68)^$O$33)) -> 0.051446249 | N74: =N68 / (1 - (1 / (1 + N68)^$O$33)) -> 0.051446249 | O74: =O68 / (1 - (1 / (1 + O68)^$O$33)) -> 0.051446249 | P74: =P68 / (1 - (1 / (1 + P68)^$O$33)) -> 0.051446249 | Q74: =Q68 / (1 - (1 / (1 + Q68)^$O$33)) -> 0.050356985 | R74: =R68 / (1 - (1 / (1 + R68)^$O$33)) -> 0.050356985 | S74: =S68 / (1 - (1 / (1 + S68)^$O$33)) -> 0.046744998 | T74: =T68 / (1 - (1 / (1 + T68)^$O$33)) -> 0.047496015 | ... AQ74: =AQ68 / (1 - (1 / (1 + AQ68)^$O$33)) -> 0.049746109
K75: Capital Recovery Factor (CRF) Real | L75: Moderate | M75: =M69 / (1 - (1 / (1 + M69)^$O$33)) -> 0.051446249 | N75: =N69 / (1 - (1 / (1 + N69)^$O$33)) -> 0.051446249 | O75: =O69 / (1 - (1 / (1 + O69)^$O$33)) -> 0.051446249 | P75: =P69 / (1 - (1 / (1 + P69)^$O$33)) -> 0.051446249 | Q75: =Q69 / (1 - (1 / (1 + Q69)^$O$33)) -> 0.050356985 | R75: =R69 / (1 - (1 / (1 + R69)^$O$33)) -> 0.050356985 | S75: =S69 / (1 - (1 / (1 + S69)^$O$33)) -> 0.046744998 | T75: =T69 / (1 - (1 / (1 + T69)^$O$33)) -> 0.047496015 | ... AQ75: =AQ69 / (1 - (1 / (1 + AQ69)^$O$33)) -> 0.049746109
K76: Capital Recovery Factor (CRF) Real | L76: Conservative | M76: =M70 / (1 - (1 / (1 + M70)^$O$33)) -> 0.051446249 | N76: =N70 / (1 - (1 / (1 + N70)^$O$33)) -> 0.051446249 | O76: =O70 / (1 - (1 / (1 + O70)^$O$33)) -> 0.051446249 | P76: =P70 / (1 - (1 / (1 + P70)^$O$33)) -> 0.051446249 | Q76: =Q70 / (1 - (1 / (1 + Q70)^$O$33)) -> 0.050356985 | R76: =R70 / (1 - (1 / (1 + R70)^$O$33)) -> 0.050356985 | S76: =S70 / (1 - (1 / (1 + S70)^$O$33)) -> 0.046744998 | T76: =T70 / (1 - (1 / (1 + T70)^$O$33)) -> 0.047496015 | ... AQ76: =AQ70 / (1 - (1 / (1 + AQ70)^$O$33)) -> 0.049746109
D81: X | G81: Future Projections
M82: Basis Year
M83: 2020 | N83: 2021 | O83: 2022 | P83: 2023 | Q83: 2024 | R83: 2025 | S83: 2026 | T83: 2027 | U83: 2028 | V83: 2029 | W83: 2030 | X83: 2031 | Y83: 2032 | Z83: 2033 | AA83: 2034 | AB83: 2035 | AC83: 2036 | AD83: 2037 | AE83: 2038 | AF83: 2039 | AG83: 2040 | AH83: 2041 | AI83: 2042 | AJ83: 2043 | AK83: 2044 | AL83: 2045 | AM83: 2046 | AN83: 2047 | AO83: 2048 | AP83: 2049 | AQ83: 2050
H84: Techno-Economic Cost and Performance Parameters | J84: Net Capacity Factor (%) | K84: Commercial PV - Class 10 | L84: Advanced | M84: 0.12191978 | N84: 0.12409451 | O84: 0.12626924 | P84: 0.12844397 | Q84: 0.1306187 | R84: 0.13279343 | S84: 0.13496816 | T84: 0.1371429 | U84: 0.13931763 | V84: 0.14149236 | W84: 0.14366709 | X84: 0.14397941 | Y84: 0.14429173 | Z84: 0.14460405 | AA84: 0.14491637 | AB84: 0.14522869 | AC84: 0.14554101 | AD84: 0.14585333 | AE84: 0.14616565 | AF84: 0.14647797 | AG84: 0.14679029 | AH84: 0.1471026 | AI84: 0.14741492 | AJ84: 0.14772724 | AK84: 0.14803956 | AL84: 0.14835188 | AM84: 0.1486642 | AN84: 0.14897652 | AO84: 0.14928884 | AP84: 0.14960116 | AQ84: 0.14991348
K85: Commercial PV - Class 10 | L85: Moderate | M85: 0.12103743 | N85: 0.12232982 | O85: 0.1236222 | P85: 0.12491459 | Q85: 0.12620697 | R85: 0.12749935 | S85: 0.12879174 | T85: 0.13008412 | U85: 0.13137651 | V85: 0.13266889 | W85: 0.13396127 | X85: 0.13444656 | Y85: 0.13493186 | Z85: 0.13541715 | AA85: 0.13590244 | AB85: 0.13638773 | AC85: 0.13687302 | AD85: 0.13735831 | AE85: 0.1378436 | AF85: 0.13832889 | AG85: 0.13881418 | AH85: 0.13929947 | AI85: 0.13978476 | AJ85: 0.14027005 | AK85: 0.14075534 | AL85: 0.14124063 | AM85: 0.14172592 | AN85: 0.14221122 | AO85: 0.14269651 | AP85: 0.1431818 | AQ85: 0.14366709
K86: Commercial PV - Class 10 | L86: Conservative | M86: 0.11974505 | N86: 0.11974505 | O86: 0.11974505 | P86: 0.11974505 | Q86: 0.11974505 | R86: 0.11974505 | S86: 0.11974505 | T86: 0.11974505 | U86: 0.11974505 | V86: 0.11974505 | W86: 0.11974505 | X86: 0.12045586 | Y86: 0.12116667 | Z86: 0.12187748 | AA86: 0.12258829 | AB86: 0.12329911 | AC86: 0.12400992 | AD86: 0.12472073 | AE86: 0.12543154 | AF86: 0.12614235 | AG86: 0.12685316 | AH86: 0.12756397 | AI86: 0.12827478 | AJ86: 0.1289856 | AK86: 0.12969641 | AL86: 0.13040722 | AM86: 0.13111803 | AN86: 0.13182884 | AO86: 0.13253965 | AP86: 0.13325046 | AQ86: 0.13396127
K87: Commercial PV - Class 9 | L87: Advanced | M87: 0.13402935 | N87: 0.13642009 | O87: 0.13881082 | P87: 0.14120156 | Q87: 0.14359229 | R87: 0.14598302 | S87: 0.14837376 | T87: 0.15076449 | U87: 0.15315523 | V87: 0.15554596 | W87: 0.15793669 | X87: 0.15828004 | Y87: 0.15862338 | Z87: 0.15896672 | AA87: 0.15931006 | AB87: 0.1596534 | AC87: 0.15999674 | AD87: 0.16034008 | AE87: 0.16068342 | AF87: 0.16102676 | AG87: 0.1613701 | AH87: 0.16171344 | AI87: 0.16205678 | AJ87: 0.16240012 | AK87: 0.16274346 | AL87: 0.1630868 | AM87: 0.16343014 | AN87: 0.16377349 | AO87: 0.16411683 | AP87: 0.16446017 | AQ87: 0.16480351
K88: Commercial PV - Class 9 | L88: Moderate | M88: 0.13305937 | N88: 0.13448012 | O88: 0.13590087 | P88: 0.13732162 | Q88: 0.13874237 | R88: 0.14016311 | S88: 0.14158386 | T88: 0.14300461 | U88: 0.14442536 | V88: 0.14584611 | W88: 0.14726686 | X88: 0.14780035 | Y88: 0.14833384 | Z88: 0.14886733 | AA88: 0.14940083 | AB88: 0.14993432 | AC88: 0.15046781 | AD88: 0.1510013 | AE88: 0.15153479 | AF88: 0.15206829 | AG88: 0.15260178 | AH88: 0.15313527 | AI88: 0.15366876 | AJ88: 0.15420225 | AK88: 0.15473574 | AL88: 0.15526924 | AM88: 0.15580273 | AN88: 0.15633622 | AO88: 0.15686971 | AP88: 0.1574032 | AQ88: 0.15793669
K89: Commercial PV - Class 9 | L89: Conservative | M89: 0.13163862 | N89: 0.13163862 | O89: 0.13163862 | P89: 0.13163862 | Q89: 0.13163862 | R89: 0.13163862 | S89: 0.13163862 | T89: 0.13163862 | U89: 0.13163862 | V89: 0.13163862 | W89: 0.13163862 | X89: 0.13242003 | Y89: 0.13320144 | Z89: 0.13398286 | AA89: 0.13476427 | AB89: 0.13554568 | AC89: 0.13632709 | AD89: 0.1371085 | AE89: 0.13788992 | AF89: 0.13867133 | AG89: 0.13945274 | AH89: 0.14023415 | AI89: 0.14101556 | AJ89: 0.14179698 | AK89: 0.14257839 | AL89: 0.1433598 | AM89: 0.14414121 | AN89: 0.14492262 | AO89: 0.14570404 | AP89: 0.14648545 | AQ89: 0.14726686
K90: Commercial PV - Class 8 | L90: Advanced | M90: 0.13962985 | N90: 0.14212049 | O90: 0.14461112 | P90: 0.14710175 | Q90: 0.14959238 | R90: 0.15208302 | S90: 0.15457365 | T90: 0.15706428 | U90: 0.15955491 | V90: 0.16204555 | W90: 0.16453618 | X90: 0.16489386 | Y90: 0.16525155 | Z90: 0.16560924 | AA90: 0.16596693 | AB90: 0.16632461 | AC90: 0.1666823 | AD90: 0.16703999 | AE90: 0.16739768 | AF90: 0.16775536 | AG90: 0.16811305 | AH90: 0.16847074 | AI90: 0.16882843 | AJ90: 0.16918611 | AK90: 0.1695438 | AL90: 0.16990149 | AM90: 0.17025917 | AN90: 0.17061686 | AO90: 0.17097455 | AP90: 0.17133224 | AQ90: 0.17168992
K91: Commercial PV - Class 8 | L91: Moderate | M91: 0.13861934 | N91: 0.14009945 | O91: 0.14157957 | P91: 0.14305969 | Q91: 0.1445398 | R91: 0.14601992 | S91: 0.14750003 | T91: 0.14898015 | U91: 0.15046027 | V91: 0.15194038 | W91: 0.1534205 | X91: 0.15397628 | Y91: 0.15453206 | Z91: 0.15508785 | AA91: 0.15564363 | AB91: 0.15619942 | AC91: 0.1567552 | AD91: 0.15731099 | AE91: 0.15786677 | AF91: 0.15842255 | AG91: 0.15897834 | AH91: 0.15953412 | AI91: 0.16008991 | AJ91: 0.16064569 | AK91: 0.16120147 | AL91: 0.16175726 | AM91: 0.16231304 | AN91: 0.16286883 | AO91: 0.16342461 | AP91: 0.16398039 | AQ91: 0.16453618
K92: Commercial PV - Class 8 | L92: Conservative | M92: 0.13713922 | N92: 0.13713922 | O92: 0.13713922 | P92: 0.13713922 | Q92: 0.13713922 | R92: 0.13713922 | S92: 0.13713922 | T92: 0.13713922 | U92: 0.13713922 | V92: 0.13713922 | W92: 0.13713922 | X92: 0.13795329 | Y92: 0.13876735 | Z92: 0.13958141 | AA92: 0.14039548 | AB92: 0.14120954 | AC92: 0.1420236 | AD92: 0.14283767 | AE92: 0.14365173 | AF92: 0.1444658 | AG92: 0.14527986 | AH92: 0.14609392 | AI92: 0.14690799 | AJ92: 0.14772205 | AK92: 0.14853611 | AL92: 0.14935018 | AM92: 0.15016424 | AN92: 0.15097831 | AO92: 0.15179237 | AP92: 0.15260643 | AQ92: 0.1534205
K93: Commercial PV - Class 7 | L93: Advanced | M93: 0.14702029 | N93: 0.14964274 | O93: 0.1522652 | P93: 0.15488766 | Q93: 0.15751012 | R93: 0.16013258 | S93: 0.16275504 | T93: 0.16537749 | U93: 0.16799995 | V93: 0.17062241 | W93: 0.17324487 | X93: 0.17362149 | Y93: 0.17399811 | Z93: 0.17437473 | AA93: 0.17475135 | AB93: 0.17512797 | AC93: 0.17550458 | AD93: 0.1758812 | AE93: 0.17625782 | AF93: 0.17663444 | AG93: 0.17701106 | AH93: 0.17738768 | AI93: 0.1777643 | AJ93: 0.17814092 | AK93: 0.17851754 | AL93: 0.17889416 | AM93: 0.17927078 | AN93: 0.1796474 | AO93: 0.18002402 | AP93: 0.18040064 | AQ93: 0.18077725
K94: Commercial PV - Class 7 | L94: Moderate | M94: 0.14595628 | N94: 0.14751474 | O94: 0.1490732 | P94: 0.15063165 | Q94: 0.15219011 | R94: 0.15374857 | S94: 0.15530702 | T94: 0.15686548 | U94: 0.15842394 | V94: 0.15998239 | W94: 0.16154085 | X94: 0.16212605 | Y94: 0.16271125 | Z94: 0.16329645 | AA94: 0.16388165 | AB94: 0.16446685 | AC94: 0.16505206 | AD94: 0.16563726 | AE94: 0.16622246 | AF94: 0.16680766 | AG94: 0.16739286 | AH94: 0.16797806 | AI94: 0.16856326 | AJ94: 0.16914846 | AK94: 0.16973366 | AL94: 0.17031886 | AM94: 0.17090407 | AN94: 0.17148927 | AO94: 0.17207447 | AP94: 0.17265967 | AQ94: 0.17324487
K95: Commercial PV - Class 7 | L95: Conservative | M95: 0.14439783 | N95: 0.14439783 | O95: 0.14439783 | P95: 0.14439783 | Q95: 0.14439783 | R95: 0.14439783 | S95: 0.14439783 | T95: 0.14439783 | U95: 0.14439783 | V95: 0.14439783 | W95: 0.14439783 | X95: 0.14525498 | Y95: 0.14611213 | Z95: 0.14696928 | AA95: 0.14782643 | AB95: 0.14868358 | AC95: 0.14954073 | AD95: 0.15039789 | AE95: 0.15125504 | AF95: 0.15211219 | AG95: 0.15296934 | AH95: 0.15382649 | AI95: 0.15468364 | AJ95: 0.15554079 | AK95: 0.15639794 | AL95: 0.15725509 | AM95: 0.15811225 | AN95: 0.1589694 | AO95: 0.15982655 | AP95: 0.1606837 | AQ95: 0.16154085
K96: Commercial PV - Class 6 | L96: Advanced | M96: 0.1543034 | N96: 0.15705577 | O96: 0.15980814 | P96: 0.16256051 | Q96: 0.16531288 | R96: 0.16806525 | S96: 0.17081762 | T96: 0.17356999 | U96: 0.17632236 | V96: 0.17907473 | W96: 0.1818271 | X96: 0.18222237 | Y96: 0.18261765 | Z96: 0.18301292 | AA96: 0.1834082 | AB96: 0.18380348 | AC96: 0.18419875 | AD96: 0.18459403 | AE96: 0.18498931 | AF96: 0.18538458 | AG96: 0.18577986 | AH96: 0.18617514 | AI96: 0.18657041 | AJ96: 0.18696569 | AK96: 0.18736096 | AL96: 0.18775624 | AM96: 0.18815152 | AN96: 0.18854679 | AO96: 0.18894207 | AP96: 0.18933735 | AQ96: 0.18973262
... K113: Commercial PV - Class 1 | L113: Conservative | M113: 0.18626187 | N113: 0.18626187 | O113: 0.18626187 | P113: 0.18626187 | Q113: 0.18626187 | R113: 0.18626187 | S113: 0.18626187 | T113: 0.18626187 | U113: 0.18626187 | V113: 0.18626187 | W113: 0.18626187 | X113: 0.18736753 | Y113: 0.18847319 | Z113: 0.18957885 | AA113: 0.19068451 | AB113: 0.19179016 | AC113: 0.19289582 | AD113: 0.19400148 | AE113: 0.19510714 | AF113: 0.19621279 | AG113: 0.19731845 | AH113: 0.19842411 | AI113: 0.19952977 | AJ113: 0.20063542 | AK113: 0.20174108 | AL113: 0.20284674 | AM113: 0.2039524 | AN113: 0.20505805 | AO113: 0.20616371 | AP113: 0.20726937 | AQ113: 0.20837503
M115: 2020 | N115: 2021 | O115: 2022 | P115: 2023 | Q115: 2024 | R115: 2025 | S115: 2026 | T115: 2027 | U115: 2028 | V115: 2029 | W115: 2030 | X115: 2031 | Y115: 2032 | Z115: 2033 | AA115: 2034 | AB115: 2035 | AC115: 2036 | AD115: 2037 | AE115: 2038 | AF115: 2039 | AG115: 2040 | AH115: 2041 | AI115: 2042 | AJ115: 2043 | AK115: 2044 | AL115: 2045 | AM115: 2046 | AN115: 2047 | AO115: 2048 | AP115: 2049 | AQ115: 2050
J116: Annual Energy Production (kWh/kW) | K116: Commercial PV - Class 10 | L116: Advanced | M116: =M84*8760 -> 1068.0173 | N116: =N84*8760 -> 1087.0679 | O116: =O84*8760 -> 1106.1186 | P116: =P84*8760 -> 1125.1692 | Q116: =Q84*8760 -> 1144.2198 | R116: =R84*8760 -> 1163.2705 | S116: =S84*8760 -> 1182.3211 | T116: =T84*8760 -> 1201.3718 | ... AQ116: =AQ84*8760 -> 1313.2421
K117: Commercial PV - Class 10 | L117: Moderate | M117: =M85*8760 -> 1060.2879 | N117: =N85*8760 -> 1071.6092 | O117: =O85*8760 -> 1082.9305 | P117: =P85*8760 -> 1094.2518 | Q117: =Q85*8760 -> 1105.5731 | R117: =R85*8760 -> 1116.8943 | S117: =S85*8760 -> 1128.2156 | T117: =T85*8760 -> 1139.5369 | ... AQ117: =AQ85*8760 -> 1258.5237
K118: Commercial PV - Class 10 | L118: Conservative | M118: =M86*8760 -> 1048.9666 | N118: =N86*8760 -> 1048.9666 | O118: =O86*8760 -> 1048.9666 | P118: =P86*8760 -> 1048.9666 | Q118: =Q86*8760 -> 1048.9666 | R118: =R86*8760 -> 1048.9666 | S118: =S86*8760 -> 1048.9666 | T118: =T86*8760 -> 1048.9666 | ... AQ118: =AQ86*8760 -> 1173.5008
K119: Commercial PV - Class 9 | L119: Advanced | M119: =M87*8760 -> 1174.0971 | N119: =N87*8760 -> 1195.04 | O119: =O87*8760 -> 1215.9828 | P119: =P87*8760 -> 1236.9256 | Q119: =Q87*8760 -> 1257.8685 | R119: =R87*8760 -> 1278.8113 | S119: =S87*8760 -> 1299.7541 | T119: =T87*8760 -> 1320.697 | ... AQ119: =AQ87*8760 -> 1443.6787
K120: Commercial PV - Class 9 | L120: Moderate | M120: =M88*8760 -> 1165.6001 | N120: =N88*8760 -> 1178.0458 | O120: =O88*8760 -> 1190.4916 | P120: =P88*8760 -> 1202.9374 | Q120: =Q88*8760 -> 1215.3831 | R120: =R88*8760 -> 1227.8289 | S120: =S88*8760 -> 1240.2746 | T120: =T88*8760 -> 1252.7204 | ... AQ120: =AQ88*8760 -> 1383.5254
K121: Commercial PV - Class 9 | L121: Conservative | M121: =M89*8760 -> 1153.1543 | N121: =N89*8760 -> 1153.1543 | O121: =O89*8760 -> 1153.1543 | P121: =P89*8760 -> 1153.1543 | Q121: =Q89*8760 -> 1153.1543 | R121: =R89*8760 -> 1153.1543 | S121: =S89*8760 -> 1153.1543 | T121: =T89*8760 -> 1153.1543 | ... AQ121: =AQ89*8760 -> 1290.0577
K122: Commercial PV - Class 8 | L122: Advanced | M122: =M90*8760 -> 1223.1575 | N122: =N90*8760 -> 1244.9755 | O122: =O90*8760 -> 1266.7934 | P122: =P90*8760 -> 1288.6113 | Q122: =Q90*8760 -> 1310.4293 | R122: =R90*8760 -> 1332.2472 | S122: =S90*8760 -> 1354.0652 | T122: =T90*8760 -> 1375.8831 | ... AQ122: =AQ90*8760 -> 1504.0037
K123: Commercial PV - Class 8 | L123: Moderate | M123: =M91*8760 -> 1214.3054 | N123: =N91*8760 -> 1227.2712 | O123: =O91*8760 -> 1240.237 | P123: =P91*8760 -> 1253.2028 | Q123: =Q91*8760 -> 1266.1687 | R123: =R91*8760 -> 1279.1345 | S123: =S91*8760 -> 1292.1003 | T123: =T91*8760 -> 1305.0661 | ... AQ123: =AQ91*8760 -> 1441.3369
K124: Commercial PV - Class 8 | L124: Conservative | M124: =M92*8760 -> 1201.3396 | N124: =N92*8760 -> 1201.3396 | O124: =O92*8760 -> 1201.3396 | P124: =P92*8760 -> 1201.3396 | Q124: =Q92*8760 -> 1201.3396 | R124: =R92*8760 -> 1201.3396 | S124: =S92*8760 -> 1201.3396 | T124: =T92*8760 -> 1201.3396 | ... AQ124: =AQ92*8760 -> 1343.9636
K125: Commercial PV - Class 7 | L125: Advanced | M125: =M93*8760 -> 1287.8977 | N125: =N93*8760 -> 1310.8704 | O125: =O93*8760 -> 1333.8432 | P125: =P93*8760 -> 1356.8159 | Q125: =Q93*8760 -> 1379.7886 | R125: =R93*8760 -> 1402.7614 | S125: =S93*8760 -> 1425.7341 | T125: =T93*8760 -> 1448.7068 | ... AQ125: =AQ93*8760 -> 1583.6087
K126: Commercial PV - Class 7 | L126: Moderate | M126: =M94*8760 -> 1278.5771 | N126: =N94*8760 -> 1292.2291 | O126: =O94*8760 -> 1305.8812 | P126: =P94*8760 -> 1319.5333 | Q126: =Q94*8760 -> 1333.1854 | R126: =R94*8760 -> 1346.8374 | S126: =S94*8760 -> 1360.4895 | T126: =T94*8760 -> 1374.1416 | ... AQ126: =AQ94*8760 -> 1517.6251
K127: Commercial PV - Class 7 | L127: Conservative | M127: =M95*8760 -> 1264.925 | N127: =N95*8760 -> 1264.925 | O127: =O95*8760 -> 1264.925 | P127: =P95*8760 -> 1264.925 | Q127: =Q95*8760 -> 1264.925 | R127: =R95*8760 -> 1264.925 | S127: =S95*8760 -> 1264.925 | T127: =T95*8760 -> 1264.925 | ... AQ127: =AQ95*8760 -> 1415.0978
K128: Commercial PV - Class 6 | L128: Advanced | M128: =M96*8760 -> 1351.6978 | N128: =N96*8760 -> 1375.8085 | O128: =O96*8760 -> 1399.9193 | P128: =P96*8760 -> 1424.03 | Q128: =Q96*8760 -> 1448.1408 | R128: =R96*8760 -> 1472.2516 | S128: =S96*8760 -> 1496.3623 | T128: =T96*8760 -> 1520.4731 | ... AQ128: =AQ96*8760 -> 1662.0578
... K145: Commercial PV - Class 1 | L145: Conservative | M145: =M113*8760 -> 1631.654 | N145: =N113*8760 -> 1631.654 | O145: =O113*8760 -> 1631.654 | P145: =P113*8760 -> 1631.654 | Q145: =Q113*8760 -> 1631.654 | R145: =R113*8760 -> 1631.654 | S145: =S113*8760 -> 1631.654 | T145: =T113*8760 -> 1631.654 | ... AQ145: =AQ113*8760 -> 1825.3652
M147: 2020 | N147: 2021 | O147: 2022 | P147: 2023 | Q147: 2024 | R147: 2025 | S147: 2026 | T147: 2027 | U147: 2028 | V147: 2029 | W147: 2030 | X147: 2031 | Y147: 2032 | Z147: 2033 | AA147: 2034 | AB147: 2035 | AC147: 2036 | AD147: 2037 | AE147: 2038 | AF147: 2039 | AG147: 2040 | AH147: 2041 | AI147: 2042 | AJ147: 2043 | AK147: 2044 | AL147: 2045 | AM147: 2046 | AN147: 2047 | AO147: 2048 | AP147: 2049 | AQ147: 2050 | AR147: =AQ147+1 -> 2051 | AS147: =AR147+1 -> 2052 | AT147: =AS147+1 -> 2053 | AU147: =AT147+1 -> 2054 | AV147: =AU147+1 -> 2055 | AW147: =AV147+1 -> 2056 | AX147: =AW147+1 -> 2057 | AY147: =AX147+1 -> 2058 | ... BK147: =BJ147+1 -> 2070
J148: CAPEX ($/kW) | K148: Commercial PV - Class 10 | L148: Advanced | M148: =M$375*(M180+M277) -> 1783.5623 | N148: =N$375*(N180+N277) -> 1597.9942 | O148: =O$375*(O180+O277) -> 1499.2068 | P148: =P$375*(P180+P277) -> 1400.4195 | Q148: =Q$375*(Q180+Q277) -> 1301.6321 | R148: =R$375*(R180+R277) -> 1202.8448 | S148: =S$375*(S180+S277) -> 1104.9045 | T148: =T$375*(T180+T277) -> 1006.812 | ... AQ148: =AQ$375*(AQ180+AQ277) -> 528.18568
K149: Commercial PV - Class 10 | L149: Moderate | M149: =M$376*(M181+M278) -> 1783.5623 | N149: =N$376*(N181+N278) -> 1597.9942 | O149: =O$376*(O181+O278) -> 1523.0419 | P149: =P$376*(P181+P278) -> 1448.0895 | Q149: =Q$376*(Q181+Q278) -> 1373.1372 | R149: =R$376*(R181+R278) -> 1298.1849 | S149: =S$376*(S181+S278) -> 1224.1711 | T149: =T$376*(T181+T278) -> 1150.0415 | ... BK149: =BK$376*(BK181+BK278) -> 527.00722
K150: Commercial PV - Class 10 | L150: Conservative | M150: =M$377*(M182+M279) -> 1783.5623 | N150: =N$377*(N182+N279) -> 1597.9942 | O150: =O$377*(O182+O279) -> 1585.8047 | P150: =P$377*(P182+P279) -> 1573.6152 | Q150: =Q$377*(Q182+Q279) -> 1561.4256 | R150: =R$377*(R182+R279) -> 1549.2361 | S150: =S$377*(S182+S279) -> 1538.226 | T150: =T$377*(T182+T279) -> 1527.196 | ... AQ150: =AQ$377*(AQ182+AQ279) -> 926.95913
K151: Commercial PV - Class 9 | L151: Advanced | M151: =M$375*(M183+M280) -> 1783.5623 | N151: =N$375*(N183+N280) -> 1597.9942 | O151: =O$375*(O183+O280) -> 1499.2068 | P151: =P$375*(P183+P280) -> 1400.4195 | Q151: =Q$375*(Q183+Q280) -> 1301.6321 | R151: =R$375*(R183+R280) -> 1202.8448 | S151: =S$375*(S183+S280) -> 1104.9045 | T151: =T$375*(T183+T280) -> 1006.812 | ... AQ151: =AQ$375*(AQ183+AQ280) -> 528.18568
K152: Commercial PV - Class 9 | L152: Moderate | M152: =M$376*(M184+M281) -> 1783.5623 | N152: =N$376*(N184+N281) -> 1597.9942 | O152: =O$376*(O184+O281) -> 1523.0419 | P152: =P$376*(P184+P281) -> 1448.0895 | Q152: =Q$376*(Q184+Q281) -> 1373.1372 | R152: =R$376*(R184+R281) -> 1298.1849 | S152: =S$376*(S184+S281) -> 1224.1711 | T152: =T$376*(T184+T281) -> 1150.0415 | ... AQ152: =AQ$376*(AQ184+AQ281) -> 711.62246
K153: Commercial PV - Class 9 | L153: Conservative | M153: =M$377*(M185+M282) -> 1783.5623 | N153: =N$377*(N185+N282) -> 1597.9942 | O153: =O$377*(O185+O282) -> 1585.8047 | P153: =P$377*(P185+P282) -> 1573.6152 | Q153: =Q$377*(Q185+Q282) -> 1561.4256 | R153: =R$377*(R185+R282) -> 1549.2361 | S153: =S$377*(S185+S282) -> 1538.226 | T153: =T$377*(T185+T282) -> 1527.196 | ... AQ153: =AQ$377*(AQ185+AQ282) -> 926.95913
K154: Commercial PV - Class 8 | L154: Advanced | M154: =M$375*(M186+M283) -> 1783.5623 | N154: =N$375*(N186+N283) -> 1597.9942 | O154: =O$375*(O186+O283) -> 1499.2068 | P154: =P$375*(P186+P283) -> 1400.4195 | Q154: =Q$375*(Q186+Q283) -> 1301.6321 | R154: =R$375*(R186+R283) -> 1202.8448 | S154: =S$375*(S186+S283) -> 1104.9045 | T154: =T$375*(T186+T283) -> 1006.812 | ... AQ154: =AQ$375*(AQ186+AQ283) -> 528.18568
K155: Commercial PV - Class 8 | L155: Moderate | M155: =M$376*(M187+M284) -> 1783.5623 | N155: =N$376*(N187+N284) -> 1597.9942 | O155: =O$376*(O187+O284) -> 1523.0419 | P155: =P$376*(P187+P284) -> 1448.0895 | Q155: =Q$376*(Q187+Q284) -> 1373.1372 | R155: =R$376*(R187+R284) -> 1298.1849 | S155: =S$376*(S187+S284) -> 1224.1711 | T155: =T$376*(T187+T284) -> 1150.0415 | ... AQ155: =AQ$376*(AQ187+AQ284) -> 711.62246
...

Sheet NREL calcs
C1: Commercial PV - Class 10 - Moderate
C2: 2019$/kw | D2: 2012$/kw
B3: 2019 | C3: =INDEX('Solar - PV Dist. Comm 2021'!$L$165:$BK$165,MATCH('NREL calcs'!$B3,'Solar - PV Dist. Comm 2021'!$L$163:$BK$163,0)) -> 1806.4626 | D3: =C3*About!$B$32 -> 1622.3025
B4: 2020 | C4: =INDEX('Solar - PV Dist. Comm 2022'!$M$149:$BK$149,MATCH('NREL calcs'!$B4,'Solar - PV Dist. Comm 2022'!$M$147:$BK$147,0)) -> 1783.5623 | D4: =C4*About!$B$33 -> 1582.2171
B5: 2021 | C5: =INDEX('Solar - PV Dist. Comm 2022'!$M$149:$BK$149,MATCH('NREL calcs'!$B5,'Solar - PV Dist. Comm 2022'!$M$147:$BK$147,0)) -> 1597.9942 | D5: =C5*About!$B$33 -> 1417.5977
B6: 2022 | C6: =INDEX('Solar - PV Dist. Comm 2022'!$M$149:$BK$149,MATCH('NREL calcs'!$B6,'Solar - PV Dist. Comm 2022'!$M$147:$BK$147,0)) -> 1523.0419 | D6: =C6*About!$B$33 -> 1351.1067
B7: 2023 | C7: =INDEX('Solar - PV Dist. Comm 2022'!$M$149:$BK$149,MATCH('NREL calcs'!$B7,'Solar - PV Dist. Comm 2022'!$M$147:$BK$147,0)) -> 1448.0895 | D7: =C7*About!$B$33 -> 1284.6157
B8: 2024 | C8: =INDEX('Solar - PV Dist. Comm 2022'!$M$149:$BK$149,MATCH('NREL calcs'!$B8,'Solar - PV Dist. Comm 2022'!$M$147:$BK$147,0)) -> 1373.1372 | D8: =C8*About!$B$33 -> 1218.1247
B9: 2025 | C9: =INDEX('Solar - PV Dist. Comm 2022'!$M$149:$BK$149,MATCH('NREL calcs'!$B9,'Solar - PV Dist. Comm 2022'!$M$147:$BK$147,0)) -> 1298.1849 | D9: =C9*About!$B$33 -> 1151.6337
B10: 2026 | C10: =INDEX('Solar - PV Dist. Comm 2022'!$M$149:$BK$149,MATCH('NREL calcs'!$B10,'Solar - PV Dist. Comm 2022'!$M$147:$BK$147,0)) -> 1224.1711 | D10: =C10*About!$B$33 -> 1085.9753
B11: 2027 | C11: =INDEX('Solar - PV Dist. Comm 2022'!$M$149:$BK$149,MATCH('NREL calcs'!$B11,'Solar - PV Dist. Comm 2022'!$M$147:$BK$147,0)) -> 1150.0415 | D11: =C11*About!$B$33 -> 1020.2141
B12: 2028 | C12: =INDEX('Solar - PV Dist. Comm 2022'!$M$149:$BK$149,MATCH('NREL calcs'!$B12,'Solar - PV Dist. Comm 2022'!$M$147:$BK$147,0)) -> 1075.7962 | D12: =C12*About!$B$33 -> 954.35029
B13: 2029 | C13: =INDEX('Solar - PV Dist. Comm 2022'!$M$149:$BK$149,MATCH('NREL calcs'!$B13,'Solar - PV Dist. Comm 2022'!$M$147:$BK$147,0)) -> 1001.4353 | D13: =C13*About!$B$33 -> 888.38398
B14: 2030 | C14: =INDEX('Solar - PV Dist. Comm 2022'!$M$149:$BK$149,MATCH('NREL calcs'!$B14,'Solar - PV Dist. Comm 2022'!$M$147:$BK$147,0)) -> 926.95913 | D14: =C14*About!$B$33 -> 822.31534
B15: 2031 | C15: =INDEX('Solar - PV Dist. Comm 2022'!$M$149:$BK$149,MATCH('NREL calcs'!$B15,'Solar - PV Dist. Comm 2022'!$M$147:$BK$147,0)) -> 916.1923 | D15: =C15*About!$B$33 -> 812.76396
... B54: 2070 | C54: =INDEX('Solar - PV Dist. Comm 2022'!$M$149:$BK$149,MATCH('NREL calcs'!$B54,'Solar - PV Dist. Comm 2022'!$M$147:$BK$147,0)) -> 527.00722 | D54: =C54*About!$B$33 -> 467.51373

Sheet NREL ATB
A1: Tab Solar - PV Dist. Res
C3: 2018 | D3: 2019 | E3: 2020 | F3: 2021 | G3: 2022 | H3: 2023 | I3: 2024 | J3: 2025 | K3: 2026 | L3: 2027 | M3: 2028 | N3: 2029 | O3: 2030 | P3: 2031 | Q3: 2032 | R3: 2033 | S3: 2034 | T3: 2035 | U3: 2036 | V3: 2037 | W3: 2038 | X3: 2039 | Y3: 2040 | Z3: 2041 | AA3: 2042 | AB3: 2043 | AC3: 2044 | AD3: 2045 | AE3: 2046 | AF3: 2047 | AG3: 2048 | AH3: 2049 | AI3: 2050
A4: Overnight Capital Cost ($/kW) | B4: Res PV - Seattle - Advanced | C4: 3054.3182 | D4: 2796.2451 | E4: 2620.0098 | F4: 2443.7745 | G4: 2267.5393 | H4: 2091.304 | I4: 1915.0687 | J4: 1738.8334 | K4: 1562.5982 | L4: 1386.3629 | M4: 1210.1276 | N4: 1033.8924 | O4: 857.65708 | P4: 844.89528 | Q4: 832.13347 | R4: 819.37166 | S4: 806.60985 | T4: 793.84804 | U4: 781.08623 | V4: 768.32443 | W4: 755.56262 | X4: 742.80081 | Y4: 730.039 | Z4: 717.27719 | AA4: 704.51539 | AB4: 691.75358 | AC4: 678.99177 | AD4: 666.22996 | AE4: 653.46815 | AF4: 640.70635 | AG4: 627.94454 | AH4: 615.18273 | AI4: 602.42092
B5: Res PV - Seattle - Moderate | C5: 3054.3182 | D5: 2796.2451 | E5: 2644.2787 | F5: 2492.3123 | G5: 2340.3458 | H5: 2188.3794 | I5: 2036.413 | J5: 1884.4466 | K5: 1732.4802 | L5: 1580.5138 | M5: 1428.5474 | N5: 1276.581 | O5: 1124.6146 | P5: 1111.2667 | Q5: 1097.9188 | R5: 1084.571 | S5: 1071.2231 | T5: 1057.8752 | U5: 1044.5273 | V5: 1031.1795 | W5: 1017.8316 | X5: 1004.4837 | Y5: 991.13583 | Z5: 977.78796 | AA5: 964.44008 | AB5: 951.09221 | AC5: 937.74433 | AD5: 924.39646 | AE5: 911.04858 | AF5: 897.70071 | AG5: 884.35283 | AH5: 871.00496 | AI5: 857.65708
B6: Res PV - Seattle - Conservative | C6: 3054.3182 | D6: 2796.2451 | E6: 2762.9654 | F6: 2729.6857 | G6: 2696.406 | H6: 2663.1263 | I6: 2629.8467 | J6: 2596.567 | K6: 2563.2873 | L6: 2530.0076 | M6: 2496.7279 | N6: 2463.4482 | O6: 2430.1685 | P6: 2364.8909 | Q6: 2299.6132 | R6: 2234.3355 | S6: 2169.0578 | T6: 2103.7801 | U6: 2038.5024 | V6: 1973.2247 | W6: 1907.947 | X6: 1842.6693 | Y6: 1777.3916 | Z6: 1712.1139 | AA6: 1646.8362 | AB6: 1581.5585 | AC6: 1516.2808 | AD6: 1451.0031 | AE6: 1385.7254 | AF6: 1320.4477 | AG6: 1255.17 | AH6: 1189.8923 | AI6: 1124.6146
B7: Res PV - Chicago - Advanced | C7: 3054.3182 | D7: 2796.2451 | E7: 2620.0098 | F7: 2443.7745 | G7: 2267.5393 | H7: 2091.304 | I7: 1915.0687 | J7: 1738.8334 | K7: 1562.5982 | L7: 1386.3629 | M7: 1210.1276 | N7: 1033.8924 | O7: 857.65708 | P7: 844.89528 | Q7: 832.13347 | R7: 819.37166 | S7: 806.60985 | T7: 793.84804 | U7: 781.08623 | V7: 768.32443 | W7: 755.56262 | X7: 742.80081 | Y7: 730.039 | Z7: 717.27719 | AA7: 704.51539 | AB7: 691.75358 | AC7: 678.99177 | AD7: 666.22996 | AE7: 653.46815 | AF7: 640.70635 | AG7: 627.94454 | AH7: 615.18273 | AI7: 602.42092
B8: Res PV - Chicago - Moderate | C8: 3054.3182 | D8: 2796.2451 | E8: 2644.2787 | F8: 2492.3123 | G8: 2340.3458 | H8: 2188.3794 | I8: 2036.413 | J8: 1884.4466 | K8: 1732.4802 | L8: 1580.5138 | M8: 1428.5474 | N8: 1276.581 | O8: 1124.6146 | P8: 1111.2667 | Q8: 1097.9188 | R8: 1084.571 | S8: 1071.2231 | T8: 1057.8752 | U8: 1044.5273 | V8: 1031.1795 | W8: 1017.8316 | X8: 1004.4837 | Y8: 991.13583 | Z8: 977.78796 | AA8: 964.44008 | AB8: 951.09221 | AC8: 937.74433 | AD8: 924.39646 | AE8: 911.04858 | AF8: 897.70071 | AG8: 884.35283 | AH8: 871.00496 | AI8: 857.65708
B9: Res PV - Chicago - Conservative | C9: 3054.3182 | D9: 2796.2451 | E9: 2762.9654 | F9: 2729.6857 | G9: 2696.406 | H9: 2663.1263 | I9: 2629.8467 | J9: 2596.567 | K9: 2563.2873 | L9: 2530.0076 | M9: 2496.7279 | N9: 2463.4482 | O9: 2430.1685 | P9: 2364.8909 | Q9: 2299.6132 | R9: 2234.3355 | S9: 2169.0578 | T9: 2103.7801 | U9: 2038.5024 | V9: 1973.2247 | W9: 1907.947 | X9: 1842.6693 | Y9: 1777.3916 | Z9: 1712.1139 | AA9: 1646.8362 | AB9: 1581.5585 | AC9: 1516.2808 | AD9: 1451.0031 | AE9: 1385.7254 | AF9: 1320.4477 | AG9: 1255.17 | AH9: 1189.8923 | AI9: 1124.6146
B10: Res PV - Kansas City - Advanced | C10: 3054.3182 | D10: 2796.2451 | E10: 2620.0098 | F10: 2443.7745 | G10: 2267.5393 | H10: 2091.304 | I10: 1915.0687 | J10: 1738.8334 | K10: 1562.5982 | L10: 1386.3629 | M10: 1210.1276 | N10: 1033.8924 | O10: 857.65708 | P10: 844.89528 | Q10: 832.13347 | R10: 819.37166 | S10: 806.60985 | T10: 793.84804 | U10: 781.08623 | V10: 768.32443 | W10: 755.56262 | X10: 742.80081 | Y10: 730.039 | Z10: 717.27719 | AA10: 704.51539 | AB10: 691.75358 | AC10: 678.99177 | AD10: 666.22996 | AE10: 653.46815 | AF10: 640.70635 | AG10: 627.94454 | AH10: 615.18273 | AI10: 602.42092
B11: Res PV - Kansas City - Moderate | C11: 3054.3182 | D11: 2796.2451 | E11: 2644.2787 | F11: 2492.3123 | G11: 2340.3458 | H11: 2188.3794 | I11: 2036.413 | J11: 1884.4466 | K11: 1732.4802 | L11: 1580.5138 | M11: 1428.5474 | N11: 1276.581 | O11: 1124.6146 | P11: 1111.2667 | Q11: 1097.9188 | R11: 1084.571 | S11: 1071.2231 | T11: 1057.8752 | U11: 1044.5273 | V11: 1031.1795 | W11: 1017.8316 | X11: 1004.4837 | Y11: 991.13583 | Z11: 977.78796 | AA11: 964.44008 | AB11: 951.09221 | AC11: 937.74433 | AD11: 924.39646 | AE11: 911.04858 | AF11: 897.70071 | AG11: 884.35283 | AH11: 871.00496 | AI11: 857.65708
B12: Res PV - Kansas City - Conservative | C12: 3054.3182 | D12: 2796.2451 | E12: 2762.9654 | F12: 2729.6857 | G12: 2696.406 | H12: 2663.1263 | I12: 2629.8467 | J12: 2596.567 | K12: 2563.2873 | L12: 2530.0076 | M12: 2496.7279 | N12: 2463.4482 | O12: 2430.1685 | P12: 2364.8909 | Q12: 2299.6132 | R12: 2234.3355 | S12: 2169.0578 | T12: 2103.7801 | U12: 2038.5024 | V12: 1973.2247 | W12: 1907.947 | X12: 1842.6693 | Y12: 1777.3916 | Z12: 1712.1139 | AA12: 1646.8362 | AB12: 1581.5585 | AC12: 1516.2808 | AD12: 1451.0031 | AE12: 1385.7254 | AF12: 1320.4477 | AG12: 1255.17 | AH12: 1189.8923 | AI12: 1124.6146
B13: Res PV - Los Angeles - Advanced | C13: 3054.3182 | D13: 2796.2451 | E13: 2620.0098 | F13: 2443.7745 | G13: 2267.5393 | H13: 2091.304 | I13: 1915.0687 | J13: 1738.8334 | K13: 1562.5982 | L13: 1386.3629 | M13: 1210.1276 | N13: 1033.8924 | O13: 857.65708 | P13: 844.89528 | Q13: 832.13347 | R13: 819.37166 | S13: 806.60985 | T13: 793.84804 | U13: 781.08623 | V13: 768.32443 | W13: 755.56262 | X13: 742.80081 | Y13: 730.039 | Z13: 717.27719 | AA13: 704.51539 | AB13: 691.75358 | AC13: 678.99177 | AD13: 666.22996 | AE13: 653.46815 | AF13: 640.70635 | AG13: 627.94454 | AH13: 615.18273 | AI13: 602.42092
B14: Res PV - Los Angeles - Moderate | C14: 3054.3182 | D14: 2796.2451 | E14: 2644.2787 | F14: 2492.3123 | G14: 2340.3458 | H14: 2188.3794 | I14: 2036.413 | J14: 1884.4466 | K14: 1732.4802 | L14: 1580.5138 | M14: 1428.5474 | N14: 1276.581 | O14: 1124.6146 | P14: 1111.2667 | Q14: 1097.9188 | R14: 1084.571 | S14: 1071.2231 | T14: 1057.8752 | U14: 1044.5273 | V14: 1031.1795 | W14: 1017.8316 | X14: 1004.4837 | Y14: 991.13583 | Z14: 977.78796 | AA14: 964.44008 | AB14: 951.09221 | AC14: 937.74433 | AD14: 924.39646 | AE14: 911.04858 | AF14: 897.70071 | AG14: 884.35283 | AH14: 871.00496 | AI14: 857.65708
B15: Res PV - Los Angeles - Conservative | C15: 3054.3182 | D15: 2796.2451 | E15: 2762.9654 | F15: 2729.6857 | G15: 2696.406 | H15: 2663.1263 | I15: 2629.8467 | J15: 2596.567 | K15: 2563.2873 | L15: 2530.0076 | M15: 2496.7279 | N15: 2463.4482 | O15: 2430.1685 | P15: 2364.8909 | Q15: 2299.6132 | R15: 2234.3355 | S15: 2169.0578 | T15: 2103.7801 | U15: 2038.5024 | V15: 1973.2247 | W15: 1907.947 | X15: 1842.6693 | Y15: 1777.3916 | Z15: 1712.1139 | AA15: 1646.8362 | AB15: 1581.5585 | AC15: 1516.2808 | AD15: 1451.0031 | AE15: 1385.7254 | AF15: 1320.4477 | AG15: 1255.17 | AH15: 1189.8923 | AI15: 1124.6146
B16: Res PV - Daggett, CA - Advanced | C16: 3054.3182 | D16: 2796.2451 | E16: 2620.0098 | F16: 2443.7745 | G16: 2267.5393 | H16: 2091.304 | I16: 1915.0687 | J16: 1738.8334 | K16: 1562.5982 | L16: 1386.3629 | M16: 1210.1276 | N16: 1033.8924 | O16: 857.65708 | P16: 844.89528 | Q16: 832.13347 | R16: 819.37166 | S16: 806.60985 | T16: 793.84804 | U16: 781.08623 | V16: 768.32443 | W16: 755.56262 | X16: 742.80081 | Y16: 730.039 | Z16: 717.27719 | AA16: 704.51539 | AB16: 691.75358 | AC16: 678.99177 | AD16: 666.22996 | AE16: 653.46815 | AF16: 640.70635 | AG16: 627.94454 | AH16: 615.18273 | AI16: 602.42092
... B18: Res PV - Daggett, CA - Conservative | C18: 3054.3182 | D18: 2796.2451 | E18: 2762.9654 | F18: 2729.6857 | G18: 2696.406 | H18: 2663.1263 | I18: 2629.8467 | J18: 2596.567 | K18: 2563.2873 | L18: 2530.0076 | M18: 2496.7279 | N18: 2463.4482 | O18: 2430.1685 | P18: 2364.8909 | Q18: 2299.6132 | R18: 2234.3355 | S18: 2169.0578 | T18: 2103.7801 | U18: 2038.5024 | V18: 1973.2247 | W18: 1907.947 | X18: 1842.6693 | Y18: 1777.3916 | Z18: 1712.1139 | AA18: 1646.8362 | AB18: 1581.5585 | AC18: 1516.2808 | AD18: 1451.0031 | AE18: 1385.7254 | AF18: 1320.4477 | AG18: 1255.17 | AH18: 1189.8923 | AI18: 1124.6146
A20: Representative Dist. Res system is fixed-tilt roof mounted with capacity of 5 kW
A21: Overnight Capital Cost, Capacity Factor, Fixed O&M, and Variable O&M costs
A22: represent $/kW DC; however LCOE reflects $/MWh AC.
A23: Capacity factors chosen here to reflect range of across the continental U.S. using NREL PVWATTS

Sheet Soft Cost Data
A1: Solar PV
A3: Solar PV Type | B3: Non-Hardware Cost %
A4: Residential | B4: 0.63
A5: Commercial | B5: 0.56
A6: Utility-Scale | B6: 0.35
A8: For distributed PV on buildings, we use the average
A9: of residential and commercial soft cost shares.
A10: Buildings | B10: =AVERAGE(B4:B5) -> 0.595

Sheet CpUDSC-totalcost
A1: Unit: $/MW | B1: Distributed Solar Total Cap Cost
A2: 2019 | B2: =(INDEX('NREL calcs'!$D$3:$D$54,MATCH('CpUDSC-totalcost'!$A2,'NREL calcs'!$B$3:$B$54,0))*1000)/'DC to AC'!$A$3 -> 1888594.2
A3: 2020 | B3: =(INDEX('NREL calcs'!$D$3:$D$54,MATCH('CpUDSC-totalcost'!$A3,'NREL calcs'!$B$3:$B$54,0))*1000)/'DC to AC'!$A$3 -> 1841929.2
A4: 2021 | B4: =(INDEX('NREL calcs'!$D$3:$D$54,MATCH('CpUDSC-totalcost'!$A4,'NREL calcs'!$B$3:$B$54,0))*1000)/'DC to AC'!$A$3 -> 1650288.4
A5: 2022 | B5: =(INDEX('NREL calcs'!$D$3:$D$54,MATCH('CpUDSC-totalcost'!$A5,'NREL calcs'!$B$3:$B$54,0))*1000)/'DC to AC'!$A$3 -> 1572883.2
A6: 2023 | B6: =(INDEX('NREL calcs'!$D$3:$D$54,MATCH('CpUDSC-totalcost'!$A6,'NREL calcs'!$B$3:$B$54,0))*1000)/'DC to AC'!$A$3 -> 1495478.1
A7: 2024 | B7: =(INDEX('NREL calcs'!$D$3:$D$54,MATCH('CpUDSC-totalcost'!$A7,'NREL calcs'!$B$3:$B$54,0))*1000)/'DC to AC'!$A$3 -> 1418073
A8: 2025 | B8: =(INDEX('NREL calcs'!$D$3:$D$54,MATCH('CpUDSC-totalcost'!$A8,'NREL calcs'!$B$3:$B$54,0))*1000)/'DC to AC'!$A$3 -> 1340667.8
A9: 2026 | B9: =(INDEX('NREL calcs'!$D$3:$D$54,MATCH('CpUDSC-totalcost'!$A9,'NREL calcs'!$B$3:$B$54,0))*1000)/'DC to AC'!$A$3 -> 1264232
A10: 2027 | B10: =(INDEX('NREL calcs'!$D$3:$D$54,MATCH('CpUDSC-totalcost'!$A10,'NREL calcs'!$B$3:$B$54,0))*1000)/'DC to AC'!$A$3 -> 1187676.5
A11: 2028 | B11: =(INDEX('NREL calcs'!$D$3:$D$54,MATCH('CpUDSC-totalcost'!$A11,'NREL calcs'!$B$3:$B$54,0))*1000)/'DC to AC'!$A$3 -> 1111001.5
A12: 2029 | B12: =(INDEX('NREL calcs'!$D$3:$D$54,MATCH('CpUDSC-totalcost'!$A12,'NREL calcs'!$B$3:$B$54,0))*1000)/'DC to AC'!$A$3 -> 1034207.2
A13: 2030 | B13: =(INDEX('NREL calcs'!$D$3:$D$54,MATCH('CpUDSC-totalcost'!$A13,'NREL calcs'!$B$3:$B$54,0))*1000)/'DC to AC'!$A$3 -> 957293.76
... A53: 2070 | B53: =(INDEX('NREL calcs'!$D$3:$D$54,MATCH('CpUDSC-totalcost'!$A53,'NREL calcs'!$B$3:$B$54,0))*1000)/'DC to AC'!$A$3 -> 544253.47

Sheet CpUDSC-softcosts
A1: Unit: $/MW | B1: Distributed Solar Soft Costs
A2: 2019 | B2: ='Soft Cost Data'!$B$10*'CpUDSC-totalcost'!B2 -> 1123713.6
A3: 2020 | B3: ='Soft Cost Data'!$B$10*'CpUDSC-totalcost'!B3 -> 1095947.8
A4: 2021 | B4: ='Soft Cost Data'!$B$10*'CpUDSC-totalcost'!B4 -> 981921.57
A5: 2022 | B5: ='Soft Cost Data'!$B$10*'CpUDSC-totalcost'!B5 -> 935865.52
A6: 2023 | B6: ='Soft Cost Data'!$B$10*'CpUDSC-totalcost'!B6 -> 889809.47
A7: 2024 | B7: ='Soft Cost Data'!$B$10*'CpUDSC-totalcost'!B7 -> 843753.42
A8: 2025 | B8: ='Soft Cost Data'!$B$10*'CpUDSC-totalcost'!B8 -> 797697.36
A9: 2026 | B9: ='Soft Cost Data'!$B$10*'CpUDSC-totalcost'!B9 -> 752218.04
A10: 2027 | B10: ='Soft Cost Data'!$B$10*'CpUDSC-totalcost'!B10 -> 706667.51
A11: 2028 | B11: ='Soft Cost Data'!$B$10*'CpUDSC-totalcost'!B11 -> 661045.89
A12: 2029 | B12: ='Soft Cost Data'!$B$10*'CpUDSC-totalcost'!B12 -> 615353.28
A13: 2030 | B13: ='Soft Cost Data'!$B$10*'CpUDSC-totalcost'!B13 -> 569589.78
... A53: 2070 | B53: ='Soft Cost Data'!$B$10*'CpUDSC-totalcost'!B53 -> 323830.82
