Workbook
Name asdf: About!#REF!
Name cpi_2010to2012: About!#REF!
Name cpi_2013to2012: About!#REF!
Name cpi_2014to2012: About!#REF!
Name cpi_2016to2012: About!#REF!
Name cpi_2017to2012: About!#REF!
Name cpi_2018to2012: About!#REF!
Name cpi_2019to2012: About!#REF!
Name cpi_2020to2012: About!#REF!
Name cpi_2021to2012: About!#REF!
Name H2_kg_to_MMBtu: [1]Constants!$D$7
Name kWh_to_Btu: [1]Constants!$D$4
Name US_salestax: About!#REF!

Sheet About
A1: BNVP BAU New Vehicle Price
A4: Source: | B4: Exchange Rates
B5: 2019
B6: https://www.exchangerates.org.uk/USD-IDR-spot-exchange-rates-history-2019.html
B8: Indonesia - Investments
B9: Import tariff (CBU vehicles)
B10: 2016
B11: https://www.indonesia-investments.com/news/todays-headlines/indonesian-demand-for-imported-cbu-cars-still-strong/item6501?
B13: Global Fleet
B14: VAT (PPN)
B15: 2025
B16: https://www.globalfleet.com/en/taxation-and-legislation/asia-pacific/analysis/tax-turbulence-guiding-fleets-through-indonesias-vat-storm?a=YHE11&t%5B0%5D=Indonesia&t%5B1%5D=Taxation&curl=1
B18: Global Fleet
B19: Luxury goods tax (PPnBM)
B20: 2025
B21: https://www.globalfleet.com/en/taxation-and-legislation/asia-pacific/analysis/tax-turbulence-guiding-fleets-through-indonesias-vat-storm?a=YHE11&t%5B0%5D=Indonesia&t%5B1%5D=Taxation&curl=1
B23: Mordor Intellligence
B24: Dealer margin & logistics
B25: 2024
B26: https://www.mordorintelligence.com/industry-reports/indonesia-freight-logistics-market
B28: World Bank
B29: Final Consumption Expenditure
B30: 2010-2023
B31: https://databank.worldbank.org/reports.aspx?source=2&series=NE.CON.TOTL.CD&country=
B33: Channel News Asia
B34: Prices of electric motorcycles
B35: 2025
B36: https://www.channelnewsasia.com/asia/indonesia-electric-motorcycle-subsidy-vehicle-assistance-program-3734736
A41: Currency Year
A42: The figures from the Center for Automotive Research come from a 2010 Automotive Yearbook
A43: and therefore are likely in 2010 dollars.
A44: The figures from TruckerToTrucker were collected in early 2015 and therefore use 2015 | B44: 2014 to 2012, for TruckerToTrucker
A45: dollars, but because we don't have a 2015 annual CPI-U figure available yet, we use 2014. | B45: 2013 to 2012, for American Public Transit Association
A46: 0.987 | B46: 2013 to 2012
A47: 0.953 | B47: 2016 to 2012
A48: 0.9366596 | B48: 2017 to 2012
A49: 0.914 | B49: 2018 to 2012
A50: 0.89805482 | B50: 2019 to 2012
A51: 0.88711067 | B51: 2020 to 2012
A52: 0.84730413 | B52: 2021 to 2012
A53: See "cpi.xlsx" in the InputData folder for source information.
A57: Note: | B57: To estimate the adjusted vehicle price for Indonesia based on a U.S. vehicle price, we compute an adjustment factor that combines two key elements: the FCE-based scaling and a correction factor accounting for country-specific cost components. First, we calculate the ratio of Final Consumption Expenditure (FCE) per capita between Indonesia and the U.S. to reflect differences in purchasing power and spending capacity. This gives a base scaling factor. Then, apply a correction factor to capture additional costs associated with importing vehicles into Indonesia. This correction factor is the sum of typical vehicle-related costs, such as import tariffs on completely built-up (CBU) vehicles, value-added tax (VAT or PPN), luxury goods tax (PPnBM), and dealer margins or logistics fees. For passenger cars, instead of using FCE, we directly estimate the scaling by comparing average Indonesian passenger car prices to U.S. passenger vehicle prices.

Sheet NVP-Indonesia
A1: Year | B1: 2011 | C1: 2012 | D1: 2013 | E1: 2014 | F1: 2015 | G1: 2016 | H1: 2017 | I1: 2018 | J1: 2019 | K1: 2020 | L1: 2021 | M1: 2022 | N1: 2023
A2: Average new car price (million Rupiah) | B2: 193 | C2: =ROUNDUP(($B$2+(($N$2-$B$2)/($N$1-$B$1))*(C1-$B$1)),0) -> 206 | D2: =ROUNDUP(($B$2+(($N$2-$B$2)/($N$1-$B$1))*(D1-$B$1)),0) -> 219 | E2: =ROUNDUP(($B$2+(($N$2-$B$2)/($N$1-$B$1))*(E1-$B$1)),0) -> 232 | F2: =ROUNDUP(($B$2+(($N$2-$B$2)/($N$1-$B$1))*(F1-$B$1)),0) -> 245 | G2: =ROUNDUP(($B$2+(($N$2-$B$2)/($N$1-$B$1))*(G1-$B$1)),0) -> 258 | H2: =ROUNDUP(($B$2+(($N$2-$B$2)/($N$1-$B$1))*(H1-$B$1)),0) -> 270 | I2: =ROUNDUP(($B$2+(($N$2-$B$2)/($N$1-$B$1))*(I1-$B$1)),0) -> 283 | J2: =ROUNDUP(($B$2+(($N$2-$B$2)/($N$1-$B$1))*(J1-$B$1)),0) -> 296 | ... M2: =ROUNDUP(($B$2+(($N$2-$B$2)/($N$1-$B$1))*(M1-$B$1)),0) -> 335 | N2: 347
A3: Million Rupiah to Rupiah | B3: 1000000
A4: 1 USD to Rupiah (2019) | B4: 14135.41
A5: 1 Rupiah to USD (2019) | B5: =1/B4 -> 7.0744322e-05
A6: Average new car price (USD) | B6: =ROUNDUP(B2*$B$3*$B$5,0) -> 13654 | C6: =ROUNDUP(C2*$B$3*$B$5,0) -> 14574 | D6: =ROUNDUP(D2*$B$3*$B$5,0) -> 15494 | E6: =ROUNDUP(E2*$B$3*$B$5,0) -> 16413 | F6: =ROUNDUP(F2*$B$3*$B$5,0) -> 17333 | G6: =ROUNDUP(G2*$B$3*$B$5,0) -> 18253 | H6: =ROUNDUP(H2*$B$3*$B$5,0) -> 19101 | I6: =ROUNDUP(I2*$B$3*$B$5,0) -> 20021 | ... N6: =ROUNDUP(N2*$B$3*$B$5,0) -> 24549
A8: Percentage increase overtime | B8: 0.05
A10: Year | B10: 2020 | C10: 2021 | D10: 2022 | E10: 2023 | F10: 2024 | G10: 2025 | H10: 2026 | I10: 2027 | J10: 2028 | K10: 2029 | L10: 2030 | M10: 2031 | N10: 2032 | O10: 2033 | P10: 2034 | Q10: 2035 | R10: 2036 | S10: 2037 | T10: 2038 | U10: 2039 | V10: 2040 | W10: 2041 | X10: 2042 | Y10: 2043 | Z10: 2044 | AA10: 2045 | AB10: 2046 | AC10: 2047 | AD10: 2048 | AE10: 2049 | AF10: 2050 | AG10: 2051 | AH10: 2052 | AI10: 2053 | AJ10: 2054 | AK10: 2055 | AL10: 2056 | AM10: 2057 | AN10: 2058 | AO10: 2059 | AP10: 2060 | AQ10: 2061 | AR10: 2062 | AS10: 2063 | AT10: 2064 | AU10: 2065 | AV10: 2066 | AW10: 2067 | AX10: 2068 | AY10: 2069 | AZ10: 2070
A11: Average new car price (2012 USD) - Percentage Increase | B11: =K6 -> 21860 | C11: =L6 -> 22780 | D11: =M6 -> 23700 | E11: =N6 -> 24549 | F11: =ROUNDUP(E11+E11*$B$8, 0) -> 25777 | G11: =ROUNDUP(F11+F11*$B$8, 0) -> 27066 | H11: =ROUNDUP(G11+G11*$B$8, 0) -> 28420 | I11: =ROUNDUP(H11+H11*$B$8, 0) -> 29841 | J11: =ROUNDUP(I11+I11*$B$8, 0) -> 31334 | K11: =ROUNDUP(J11+J11*$B$8, 0) -> 32901 | L11: =ROUNDUP(K11+K11*$B$8, 0) -> 34547 | M11: =ROUNDUP(L11+L11*$B$8, 0) -> 36275 | ... AZ11: =ROUNDUP(AY11+AY11*$B$8, 0) -> 243261
A12: Average new car price (2012 USD) - Linear Forecast | B12: =B11 -> 21860 | C12: =C11 -> 22780 | D12: =D11 -> 23700 | E12: =E11 -> 24549 | F12: =ROUNDUP(_xlfn.FORECAST.LINEAR(F10,$B$12:$E$12,$B$10:$E$10), 0) -> 25469 | G12: =ROUNDUP(_xlfn.FORECAST.LINEAR(G10,$B$12:$E$12,$B$10:$E$10), 0) -> 26368 | H12: =ROUNDUP(_xlfn.FORECAST.LINEAR(H10,$B$12:$E$12,$B$10:$E$10), 0) -> 27267 | I12: =ROUNDUP(_xlfn.FORECAST.LINEAR(I10,$B$12:$E$12,$B$10:$E$10), 0) -> 28166 | J12: =ROUNDUP(_xlfn.FORECAST.LINEAR(J10,$B$12:$E$12,$B$10:$E$10), 0) -> 29064 | K12: =ROUNDUP(_xlfn.FORECAST.LINEAR(K10,$B$12:$E$12,$B$10:$E$10), 0) -> 29963 | L12: =ROUNDUP(_xlfn.FORECAST.LINEAR(L10,$B$12:$E$12,$B$10:$E$10), 0) -> 30862 | M12: =ROUNDUP(_xlfn.FORECAST.LINEAR(M10,$B$12:$E$12,$B$10:$E$10), 0) -> 31760 | ... AZ12: =ROUNDUP(_xlfn.FORECAST.LINEAR(AZ10,$B$12:$E$12,$B$10:$E$10), 0) -> 66810
A14: Indonesia New Vehicle Price
A16: BNVP-motorbikes-psgr | W16: >> Projections by SO (fitting the curve and put the constant values after 2045)
A17: Price ($/vehicle) | B17: 2020 | C17: 2021 | D17: 2022 | E17: 2023 | F17: 2024 | G17: 2025 | H17: 2026 | I17: 2027 | J17: 2028 | K17: 2029 | L17: 2030 | M17: 2031 | N17: 2032 | O17: 2033 | P17: 2034 | Q17: 2035 | R17: 2036 | S17: 2037 | T17: 2038 | U17: 2039 | V17: 2040 | W17: 2041 | X17: 2042 | Y17: 2043 | Z17: 2044 | AA17: 2045 | AB17: 2046 | AC17: 2047 | AD17: 2048 | AE17: 2049 | AF17: 2050 | AG17: 2051 | AH17: 2052 | AI17: 2053 | AJ17: 2054 | AK17: 2055 | AL17: 2056 | AM17: 2057 | AN17: 2058 | AO17: 2059 | AP17: 2060 | AQ17: 2061 | AR17: 2062 | AS17: 2063 | AT17: 2064 | AU17: 2065 | AV17: 2066 | AW17: 2067 | AX17: 2068 | AY17: 2069 | AZ17: 2070
A18: battery electric vehicle | B18: ='Indonesia - Motorcycles'!M12*About!A52 -> 1957.5015 | C18: =B18-(($B$18-$L$18)/COUNT($C$17:$L$17)) -> 1844.9131 | D18: =C18-(($B$18-$L$18)/COUNT($C$17:$L$17)) -> 1732.3247 | E18: =D18-(($B$18-$L$18)/COUNT($C$17:$L$17)) -> 1619.7363 | F18: =E18-(($B$18-$L$18)/COUNT($C$17:$L$17)) -> 1507.1479 | G18: =F18-(($B$18-$L$18)/COUNT($C$17:$L$17)) -> 1394.5595 | H18: =G18-(($B$18-$L$18)/COUNT($C$17:$L$17)) -> 1281.9711 | I18: =H18-(($B$18-$L$18)/COUNT($C$17:$L$17)) -> 1169.3827 | J18: =I18-(($B$18-$L$18)/COUNT($C$17:$L$17)) -> 1056.7944 | K18: =J18-(($B$18-$L$18)/COUNT($C$17:$L$17)) -> 944.20595 | L18: ='Indonesia - Motorcycles'!M22*About!A52 -> 831.61755 | M18: =L18-(($L$18-$V$18)/COUNT($M$17:$V$17)) -> 782.80597 | N18: =M18-(($L$18-$V$18)/COUNT($M$17:$V$17)) -> 733.99438 | O18: =N18-(($L$18-$V$18)/COUNT($M$17:$V$17)) -> 685.18279 | P18: =O18-(($L$18-$V$18)/COUNT($M$17:$V$17)) -> 636.3712 | Q18: =P18-(($L$18-$V$18)/COUNT($M$17:$V$17)) -> 587.55961 | R18: =Q18-(($L$18-$V$18)/COUNT($M$17:$V$17)) -> 538.74803 | S18: =R18-(($L$18-$V$18)/COUNT($M$17:$V$17)) -> 489.93644 | T18: =S18-(($L$18-$V$18)/COUNT($M$17:$V$17)) -> 441.12485 | U18: =T18-(($L$18-$V$18)/COUNT($M$17:$V$17)) -> 392.31326 | V18: ='Indonesia - Motorcycles'!M28*About!A52 -> 343.50167 | W18: =V18*(1-0.14) -> 295.41144 | X18: =W18*(1-0.14) -> 254.05384 | Y18: =X18*(1-0.14) -> 218.4863 | Z18: =Y18*(1-0.14) -> 187.89822 | AA18: =Z18*(1-0.14) -> 161.59247 | AB18: =AA18*About!A52 -> 136.91797 | AC18: =$AB$18 -> 136.91797 | AD18: =$AB$18 -> 136.91797 | AE18: =$AB$18 -> 136.91797 | AF18: =$AB$18 -> 136.91797 | AG18: =$AB$18 -> 136.91797 | AH18: =$AB$18 -> 136.91797 | AI18: =$AB$18 -> 136.91797 | AJ18: =$AB$18 -> 136.91797 | ... AZ18: =$AB$18 -> 136.91797
A19: natural gas vehicle | B19: 0 | C19: 0 | D19: 0 | E19: 0 | F19: 0 | G19: 0 | H19: 0 | I19: 0 | J19: 0 | K19: 0 | L19: 0 | M19: 0 | N19: 0 | O19: 0 | P19: 0 | Q19: 0 | R19: 0 | S19: 0 | T19: 0 | U19: 0 | V19: 0 | W19: 0 | X19: 0 | Y19: 0 | Z19: 0 | AA19: 0 | AB19: 0 | AC19: 0 | AD19: 0 | AE19: 0 | AF19: 0 | AG19: 0 | AH19: 0 | AI19: 0 | AJ19: 0 | AK19: 0 | AL19: 0 | AM19: 0 | AN19: 0 | AO19: 0 | AP19: 0 | AQ19: 0 | AR19: 0 | AS19: 0 | AT19: 0 | AU19: 0 | AV19: 0 | AW19: 0 | AX19: 0 | AY19: 0 | AZ19: 0
A20: gasoline vehicle | B20: ='Indonesia - Motorcycles'!M10*About!A52 -> 539.84723 | C20: =B20-(($B$20-$L$20)/COUNT($C$17:$L$17)) -> 543.89483 | D20: =C20-(($B$20-$L$20)/COUNT($C$17:$L$17)) -> 547.94242 | E20: =D20-(($B$20-$L$20)/COUNT($C$17:$L$17)) -> 551.99002 | F20: =E20-(($B$20-$L$20)/COUNT($C$17:$L$17)) -> 556.03761 | G20: =F20-(($B$20-$L$20)/COUNT($C$17:$L$17)) -> 560.0852 | H20: =G20-(($B$20-$L$20)/COUNT($C$17:$L$17)) -> 564.1328 | I20: =H20-(($B$20-$L$20)/COUNT($C$17:$L$17)) -> 568.18039 | J20: =I20-(($B$20-$L$20)/COUNT($C$17:$L$17)) -> 572.22799 | K20: =J20-(($B$20-$L$20)/COUNT($C$17:$L$17)) -> 576.27558 | L20: ='Indonesia - Motorcycles'!M20*About!A52 -> 580.32318 | M20: =$L$20 -> 580.32318 | N20: =$L$20 -> 580.32318 | O20: =$L$20 -> 580.32318 | P20: =$L$20 -> 580.32318 | Q20: =$L$20 -> 580.32318 | R20: =$L$20 -> 580.32318 | S20: =$L$20 -> 580.32318 | T20: =$L$20 -> 580.32318 | U20: =$L$20 -> 580.32318 | V20: =$L$20*About!A52 -> 491.71023 | W20: =$L$20 -> 580.32318 | X20: =$L$20 -> 580.32318 | Y20: =$L$20 -> 580.32318 | Z20: =$L$20 -> 580.32318 | AA20: =$L$20 -> 580.32318 | AB20: =$L$20 -> 580.32318 | AC20: =$L$20 -> 580.32318 | AD20: =$L$20 -> 580.32318 | ... AZ20: =$L$20 -> 580.32318
A21: diesel vehicle | B21: 0 | C21: 0 | D21: 0 | E21: 0 | F21: 0 | G21: 0 | H21: 0 | I21: 0 | J21: 0 | K21: 0 | L21: 0 | M21: 0 | N21: 0 | O21: 0 | P21: 0 | Q21: 0 | R21: 0 | S21: 0 | T21: 0 | U21: 0 | V21: 0 | W21: 0 | X21: 0 | Y21: 0 | Z21: 0 | AA21: 0 | AB21: 0 | AC21: 0 | AD21: 0 | AE21: 0 | AF21: 0 | AG21: 0 | AH21: 0 | AI21: 0 | AJ21: 0 | AK21: 0 | AL21: 0 | AM21: 0 | AN21: 0 | AO21: 0 | AP21: 0 | AQ21: 0 | AR21: 0 | AS21: 0 | AT21: 0 | AU21: 0 | AV21: 0 | AW21: 0 | AX21: 0 | AY21: 0 | AZ21: 0
A22: plugin hybrid vehicle | B22: 0 | C22: 0 | D22: 0 | E22: 0 | F22: 0 | G22: 0 | H22: 0 | I22: 0 | J22: 0 | K22: 0 | L22: 0 | M22: 0 | N22: 0 | O22: 0 | P22: 0 | Q22: 0 | R22: 0 | S22: 0 | T22: 0 | U22: 0 | V22: 0 | W22: 0 | X22: 0 | Y22: 0 | Z22: 0 | AA22: 0 | AB22: 0 | AC22: 0 | AD22: 0 | AE22: 0 | AF22: 0 | AG22: 0 | AH22: 0 | AI22: 0 | AJ22: 0 | AK22: 0 | AL22: 0 | AM22: 0 | AN22: 0 | AO22: 0 | AP22: 0 | AQ22: 0 | AR22: 0 | AS22: 0 | AT22: 0 | AU22: 0 | AV22: 0 | AW22: 0 | AX22: 0 | AY22: 0 | AZ22: 0
A23: LPG vehicle | B23: 0 | C23: 0 | D23: 0 | E23: 0 | F23: 0 | G23: 0 | H23: 0 | I23: 0 | J23: 0 | K23: 0 | L23: 0 | M23: 0 | N23: 0 | O23: 0 | P23: 0 | Q23: 0 | R23: 0 | S23: 0 | T23: 0 | U23: 0 | V23: 0 | W23: 0 | X23: 0 | Y23: 0 | Z23: 0 | AA23: 0 | AB23: 0 | AC23: 0 | AD23: 0 | AE23: 0 | AF23: 0 | AG23: 0 | AH23: 0 | AI23: 0 | AJ23: 0 | AK23: 0 | AL23: 0 | AM23: 0 | AN23: 0 | AO23: 0 | AP23: 0 | AQ23: 0 | AR23: 0 | AS23: 0 | AT23: 0 | AU23: 0 | AV23: 0 | AW23: 0 | AX23: 0 | AY23: 0 | AZ23: 0
A24: hydrogen vehicle | B24: 0 | C24: 0 | D24: 0 | E24: 0 | F24: 0 | G24: 0 | H24: 0 | I24: 0 | J24: 0 | K24: 0 | L24: 0 | M24: 0 | N24: 0 | O24: 0 | P24: 0 | Q24: 0 | R24: 0 | S24: 0 | T24: 0 | U24: 0 | V24: 0 | W24: 0 | X24: 0 | Y24: 0 | Z24: 0 | AA24: 0 | AB24: 0 | AC24: 0 | AD24: 0 | AE24: 0 | AF24: 0 | AG24: 0 | AH24: 0 | AI24: 0 | AJ24: 0 | AK24: 0 | AL24: 0 | AM24: 0 | AN24: 0 | AO24: 0 | AP24: 0 | AQ24: 0 | AR24: 0 | AS24: 0 | AT24: 0 | AU24: 0 | AV24: 0 | AW24: 0 | AX24: 0 | AY24: 0 | AZ24: 0
A26: Source: 1) ChannelAsiaNews (See 'About' - https://www.channelnewsasia.com/asia/indonesia-electric-motorcycle-subsidy-vehicle-assistance-program-3734736)
A27: Prices for these electric motorcycles range from 4.8 million rupiah to 37.75 million rupiah.
A28: Source: 2) ICCT (See 'Motorcycles - 2030' tab)
A29: Updated with the 2012 USD from 2021
A43: NOT UPDATED BELOW - PROJECTIONS TO BE CALIBRATED
A44: BNVP-HDVs-psgr
A45: Price ($/vehicle) | B45: 2020 | C45: 2021 | D45: 2022 | E45: 2023 | F45: 2024 | G45: 2025 | H45: 2026 | I45: 2027 | J45: 2028 | K45: 2029 | L45: 2030 | M45: 2031 | N45: 2032 | O45: 2033 | P45: 2034 | Q45: 2035 | R45: 2036 | S45: 2037 | T45: 2038 | U45: 2039 | V45: 2040 | W45: 2041 | X45: 2042 | Y45: 2043 | Z45: 2044 | AA45: 2045 | AB45: 2046 | AC45: 2047 | AD45: 2048 | AE45: 2049 | AF45: 2050 | AG45: 2051 | AH45: 2052 | AI45: 2053 | AJ45: 2054 | AK45: 2055 | AL45: 2056 | AM45: 2057 | AN45: 2058 | AO45: 2059 | AP45: 2060 | AQ45: 2061 | AR45: 2062 | AS45: 2063 | AT45: 2064 | AU45: 2065 | AV45: 2066 | AW45: 2067 | AX45: 2068 | AY45: 2069 | AZ45: 2070
A46: battery electric vehicle | B46: =$D$46 -> 371621.62 | C46: =$D$46 -> 371621.62 | D46: ='Indonesia - HDV '!D21 -> 371621.62 | E46: =$D$46 -> 371621.62 | F46: =$D$46 -> 371621.62 | G46: =$D$46 -> 371621.62 | H46: =$D$46 -> 371621.62 | I46: =$D$46 -> 371621.62 | J46: =$D$46 -> 371621.62 | K46: =$D$46 -> 371621.62 | L46: =$D$46 -> 371621.62 | ... AZ46: =$D$46 -> 371621.62
A47: natural gas vehicle | B47: =$D$47 -> 135608.11 | C47: =$D$47 -> 135608.11 | D47: ='Indonesia - HDV '!D22 -> 135608.11 | E47: =$D$47 -> 135608.11 | F47: =$D$47 -> 135608.11 | G47: =$D$47 -> 135608.11 | H47: =$D$47 -> 135608.11 | I47: =$D$47 -> 135608.11 | J47: =$D$47 -> 135608.11 | K47: =$D$47 -> 135608.11 | L47: =$D$47 -> 135608.11 | ... AZ47: =$D$47 -> 135608.11
A48: gasoline vehicle | B48: =$D$48 -> 84353.201 | C48: =$D$48 -> 84353.201 | D48: ='Indonesia - HDV '!D23 -> 84353.201 | E48: =$D$48 -> 84353.201 | F48: =$D$48 -> 84353.201 | G48: =$D$48 -> 84353.201 | H48: =$D$48 -> 84353.201 | I48: =$D$48 -> 84353.201 | J48: =$D$48 -> 84353.201 | K48: =$D$48 -> 84353.201 | L48: =$D$48 -> 84353.201 | ... AZ48: =$D$48 -> 84353.201
A49: diesel vehicle | B49: =$D$49 -> 84353.201 | C49: =$D$49 -> 84353.201 | D49: ='Indonesia - HDV '!D24 -> 84353.201 | E49: =$D$49 -> 84353.201 | F49: =$D$49 -> 84353.201 | G49: =$D$49 -> 84353.201 | H49: =$D$49 -> 84353.201 | I49: =$D$49 -> 84353.201 | J49: =$D$49 -> 84353.201 | K49: =$D$49 -> 84353.201 | L49: =$D$49 -> 84353.201 | ... AZ49: =$D$49 -> 84353.201
A50: plugin hybrid vehicle | B50: =$D$50 -> 371621.62 | C50: =$D$50 -> 371621.62 | D50: ='Indonesia - HDV '!D25 -> 371621.62 | E50: =$D$50 -> 371621.62 | F50: =$D$50 -> 371621.62 | G50: =$D$50 -> 371621.62 | H50: =$D$50 -> 371621.62 | I50: =$D$50 -> 371621.62 | J50: =$D$50 -> 371621.62 | K50: =$D$50 -> 371621.62 | L50: =$D$50 -> 371621.62 | ... AZ50: =$D$50 -> 371621.62
A51: LPG vehicle | B51: =$D$51 -> 109980.65 | C51: =$D$51 -> 109980.65 | D51: ='Indonesia - HDV '!D26 -> 109980.65 | E51: =$D$51 -> 109980.65 | F51: =$D$51 -> 109980.65 | G51: =$D$51 -> 109980.65 | H51: =$D$51 -> 109980.65 | I51: =$D$51 -> 109980.65 | J51: =$D$51 -> 109980.65 | K51: =$D$51 -> 109980.65 | L51: =$D$51 -> 109980.65 | ... AZ51: =$D$51 -> 109980.65
A52: hydrogen vehicle | B52: =$D$52 -> 1420000 | C52: =$D$52 -> 1420000 | D52: ='Indonesia - HDV '!D27 -> 1420000 | E52: =$D$52 -> 1420000 | F52: =$D$52 -> 1420000 | G52: =$D$52 -> 1420000 | H52: =$D$52 -> 1420000 | I52: =$D$52 -> 1420000 | J52: =$D$52 -> 1420000 | K52: =$D$52 -> 1420000 | L52: =$D$52 -> 1420000 | ... AZ52: =$D$52 -> 1420000
A54: BNVP-HDVs-frgt
A55: Price ($/vehicle) | B55: 2020 | C55: 2021 | D55: 2022 | E55: 2023 | F55: 2024 | G55: 2025 | H55: 2026 | I55: 2027 | J55: 2028 | K55: 2029 | L55: 2030 | M55: 2031 | N55: 2032 | O55: 2033 | P55: 2034 | Q55: 2035 | R55: 2036 | S55: 2037 | T55: 2038 | U55: 2039 | V55: 2040 | W55: 2041 | X55: 2042 | Y55: 2043 | Z55: 2044 | AA55: 2045 | AB55: 2046 | AC55: 2047 | AD55: 2048 | AE55: 2049 | AF55: 2050 | AG55: 2051 | AH55: 2052 | AI55: 2053 | AJ55: 2054 | AK55: 2055 | AL55: 2056 | AM55: 2057 | AN55: 2058 | AO55: 2059 | AP55: 2060 | AQ55: 2061 | AR55: 2062 | AS55: 2063 | AT55: 2064 | AU55: 2065 | AV55: 2066 | AW55: 2067 | AX55: 2068 | AY55: 2069 | AZ55: 2070
A56: battery electric vehicle | B56: 212323.26 | C56: 212323.26 | D56: 212323.26 | E56: 212323.26 | F56: 212323.26 | G56: 212323.26 | H56: 212323.26 | I56: 212323.26 | J56: 212323.26 | K56: 212323.26 | L56: 212323.26 | M56: 212323.26 | N56: 212323.26 | O56: 212323.26 | P56: 212323.26 | Q56: 212323.26 | R56: 212323.26 | S56: 212323.26 | T56: 212323.26 | U56: 212323.26 | V56: 212323.26 | W56: 212323.26 | X56: 212323.26 | Y56: 212323.26 | Z56: 212323.26 | AA56: 212323.26 | AB56: 212323.26 | AC56: 212323.26 | AD56: 212323.26 | AE56: 212323.26 | AF56: 212323.26 | AG56: 212323.26 | AH56: 212323.26 | AI56: 212323.26 | AJ56: 212323.26 | AK56: 212323.26 | AL56: 212323.26 | AM56: 212323.26 | AN56: 212323.26 | AO56: 212323.26 | AP56: 212323.26 | AQ56: 212323.26 | AR56: 212323.26 | AS56: 212323.26 | AT56: 212323.26 | AU56: 212323.26 | AV56: 212323.26 | AW56: 212323.26 | AX56: 212323.26 | AY56: 212323.26 | AZ56: 212323.26
A57: natural gas vehicle | B57: 169081.01 | C57: 167864.65 | D57: 168589.54 | E57: 169720.85 | F57: 170592.77 | G57: 171447.35 | H57: 172235.77 | I57: 172949.86 | J57: 173710.9 | K57: 174435.56 | L57: 175106.83 | M57: 175831.33 | N57: 176390.34 | O57: 177133.8 | P57: 177567.08 | Q57: 177918.6 | R57: 178228.46 | S57: 178533.03 | T57: 178816.19 | U57: 179106.91 | V57: 179311.24 | W57: 179543.09 | X57: 179737.16 | Y57: 179898.98 | Z57: 180064.57 | AA57: 180221.06 | AB57: 180365 | AC57: 180516.08 | AD57: 180668.22 | AE57: 180802.25 | AF57: 180937.41 | AG57: 183362.21 | AH57: 183799.51 | AI57: 184236.81 | AJ57: 184674.12 | AK57: 185111.42 | AL57: 185548.72 | AM57: 185986.03 | AN57: 186423.33 | AO57: 186860.63 | AP57: 187297.94 | AQ57: 187735.24 | AR57: 188172.54 | AS57: 188609.85 | AT57: 189047.15 | AU57: 189484.45 | AV57: 189921.76 | AW57: 190359.06 | AX57: 190796.36 | AY57: 191233.67 | AZ57: 191670.97
A58: gasoline vehicle | B58: 116533.08 | C58: 116533.08 | D58: 116533.08 | E58: 116533.08 | F58: 116533.08 | G58: 116533.08 | H58: 116533.08 | I58: 116533.08 | J58: 116533.08 | K58: 116533.08 | L58: 116533.08 | M58: 116533.08 | N58: 116533.08 | O58: 116533.08 | P58: 116533.08 | Q58: 116533.08 | R58: 116533.08 | S58: 116533.08 | T58: 116533.08 | U58: 116533.08 | V58: 116533.08 | W58: 116533.08 | X58: 116533.08 | Y58: 116533.08 | Z58: 116533.08 | AA58: 116533.08 | AB58: 116533.08 | AC58: 116533.08 | AD58: 116533.08 | AE58: 116533.08 | AF58: 116533.08 | AG58: 116533.08 | AH58: 116533.08 | AI58: 116533.08 | AJ58: 116533.08 | AK58: 116533.08 | AL58: 116533.08 | AM58: 116533.08 | AN58: 116533.08 | AO58: 116533.08 | AP58: 116533.08 | AQ58: 116533.08 | AR58: 116533.08 | AS58: 116533.08 | AT58: 116533.08 | AU58: 116533.08 | AV58: 116533.08 | AW58: 116533.08 | AX58: 116533.08 | AY58: 116533.08 | AZ58: 116533.08
A59: diesel vehicle | B59: 116533.08 | C59: 116533.08 | D59: 116533.08 | E59: 116533.08 | F59: 116533.08 | G59: 116533.08 | H59: 116533.08 | I59: 116533.08 | J59: 116533.08 | K59: 116533.08 | L59: 116533.08 | M59: 116533.08 | N59: 116533.08 | O59: 116533.08 | P59: 116533.08 | Q59: 116533.08 | R59: 116533.08 | S59: 116533.08 | T59: 116533.08 | U59: 116533.08 | V59: 116533.08 | W59: 116533.08 | X59: 116533.08 | Y59: 116533.08 | Z59: 116533.08 | AA59: 116533.08 | AB59: 116533.08 | AC59: 116533.08 | AD59: 116533.08 | AE59: 116533.08 | AF59: 116533.08 | AG59: 116533.08 | AH59: 116533.08 | AI59: 116533.08 | AJ59: 116533.08 | AK59: 116533.08 | AL59: 116533.08 | AM59: 116533.08 | AN59: 116533.08 | AO59: 116533.08 | AP59: 116533.08 | AQ59: 116533.08 | AR59: 116533.08 | AS59: 116533.08 | AT59: 116533.08 | AU59: 116533.08 | AV59: 116533.08 | AW59: 116533.08 | AX59: 116533.08 | AY59: 116533.08 | AZ59: 116533.08
A60: plugin hybrid vehicle | B60: 292717.2 | C60: 296718.81 | D60: 296290.7 | E60: 297748.17 | F60: 298074.13 | G60: 298962.66 | H60: 299325.72 | I60: 299532.53 | J60: 299964.75 | K60: 300521.89 | L60: 301144.75 | M60: 301941.6 | N60: 302627.45 | O60: 303546.26 | P60: 304016.24 | Q60: 304390.28 | R60: 304725.79 | S60: 304997.87 | T60: 305173.43 | U60: 305303.86 | V60: 305293.78 | W60: 305340.79 | X60: 305317.62 | Y60: 305243.4 | Z60: 305169.62 | AA60: 305090.87 | AB60: 304998.45 | AC60: 304921.39 | AD60: 304846.72 | AE60: 304781.55 | AF60: 304698.59 | AG60: 307771.62 | AH60: 308109.3 | AI60: 308446.99 | AJ60: 308784.68 | AK60: 309122.37 | AL60: 309460.05 | AM60: 309797.74 | AN60: 310135.43 | AO60: 310473.12 | AP60: 310810.81 | AQ60: 311148.49 | AR60: 311486.18 | AS60: 311823.87 | AT60: 312161.56 | AU60: 312499.25 | AV60: 312836.93 | AW60: 313174.62 | AX60: 313512.31 | AY60: 313850 | AZ60: 314187.69
A61: LPG vehicle | B61: 165261.41 | C61: 167968.05 | D61: 167812.53 | E61: 168104.89 | F61: 168501.33 | G61: 169239.93 | H61: 169857.02 | I61: 170173.73 | J61: 170454.12 | K61: 170757.69 | L61: 171042.29 | M61: 171325.26 | N61: 171566.63 | O61: 171856.26 | P61: 172052.29 | Q61: 172229.28 | R61: 172412.22 | S61: 172596.6 | T61: 172769.38 | U61: 172952.48 | V61: 173109.98 | W61: 173267.84 | X61: 173424.4 | Y61: 173572.83 | Z61: 173726.42 | AA61: 173884.67 | AB61: 174041.59 | AC61: 174203.86 | AD61: 174365.89 | AE61: 174529.91 | AF61: 174633.32 | AG61: 175657.12 | AH61: 175906.46 | AI61: 176155.81 | AJ61: 176405.16 | AK61: 176654.51 | AL61: 176903.86 | AM61: 177153.2 | AN61: 177402.55 | AO61: 177651.9 | AP61: 177901.25 | AQ61: 178150.59 | AR61: 178399.94 | AS61: 178649.29 | AT61: 178898.64 | AU61: 179147.99 | AV61: 179397.33 | AW61: 179646.68 | AX61: 179896.03 | AY61: 180145.38 | AZ61: 180394.73
A62: hydrogen vehicle | B62: 356070.43 | C62: 355992.99 | D62: 348292.91 | E62: 341514.46 | F62: 334667.5 | G62: 327580.47 | H62: 321354.44 | I62: 315624.63 | J62: 310159.33 | K62: 304951.81 | L62: 299987.32 | M62: 295261.86 | N62: 290736.67 | O62: 286454.31 | P62: 282251.31 | Q62: 278221.4 | R62: 274383.01 | S62: 270722.24 | T62: 267231.6 | U62: 263906.64 | V62: 260728.33 | W62: 257703.15 | X62: 254817.74 | Y62: 252065.91 | Z62: 249444.05 | AA62: 246944.88 | AB62: 244561.24 | AC62: 242290.65 | AD62: 240124.93 | AE62: 238062.64 | AF62: 236002.34 | AG62: 220232.29 | AH62: 216157.88 | AI62: 212083.46 | AJ62: 208009.05 | AK62: 203934.63 | AL62: 199860.22 | AM62: 195785.8 | AN62: 191711.38 | AO62: 187636.97 | AP62: 183562.55 | AQ62: 179488.14 | AR62: 175413.72 | AS62: 171339.31 | AT62: 167264.89 | AU62: 163190.48 | AV62: 159116.06 | AW62: 155041.64 | AX62: 150967.23 | AY62: 146892.81 | AZ62: 142818.4
A65: US New Vehicle Price
A66: BNVP-LDVs-psgr
A67: Price ($/vehicle) | B67: 2020 | C67: 2021 | D67: 2022 | E67: 2023 | F67: 2024 | G67: 2025 | H67: 2026 | I67: 2027 | J67: 2028 | K67: 2029 | L67: 2030 | M67: 2031 | N67: 2032 | O67: 2033 | P67: 2034 | Q67: 2035 | R67: 2036 | S67: 2037 | T67: 2038 | U67: 2039 | V67: 2040 | W67: 2041 | X67: 2042 | Y67: 2043 | Z67: 2044 | AA67: 2045 | AB67: 2046 | AC67: 2047 | AD67: 2048 | AE67: 2049 | AF67: 2050 | AG67: 2051 | AH67: 2052 | AI67: 2053 | AJ67: 2054 | AK67: 2055 | AL67: 2056 | AM67: 2057 | AN67: 2058 | AO67: 2059 | AP67: 2060 | AQ67: 2061 | AR67: 2062 | AS67: 2063 | AT67: 2064 | AU67: 2065 | AV67: 2066 | AW67: 2067 | AX67: 2068 | AY67: 2069 | AZ67: 2070
A68: battery electric vehicle | B68: 49825.128 | C68: 44974.651 | D68: 44014.219 | E68: 42953.309 | F68: 42057.542 | G68: 41521.193 | H68: 40991.55 | I68: 40480.256 | J68: 40050.501 | K68: 39618.7 | L68: 39193.065 | M68: 38851.711 | N68: 38445.374 | O68: 38068.778 | P68: 37707.033 | Q68: 37365.394 | R68: 37011.736 | S68: 36641.185 | T68: 36270.533 | U68: 35909.696 | V68: 35548.372 | W68: 35209.229 | X68: 34885.052 | Y68: 34557.402 | Z68: 34243.998 | AA68: 33954.038 | AB68: 33631.495 | AC68: 33320.219 | AD68: 33037.653 | AE68: 32722.528 | AF68: 32420.62 | AG68: 31015.295 | AH68: 30583.827 | AI68: 30152.359 | AJ68: 29720.891 | AK68: 29289.424 | AL68: 28857.956 | AM68: 28426.488 | AN68: 27995.02 | AO68: 27563.552 | AP68: 27132.085 | AQ68: 26700.617 | AR68: 26269.149 | AS68: 25837.681 | AT68: 25406.213 | AU68: 24974.746 | AV68: 24543.278 | AW68: 24111.81 | AX68: 23680.342 | AY68: 23248.875 | AZ68: 22817.407
A69: natural gas vehicle | B69: 36759.75 | C69: 36495.301 | D69: 36652.899 | E69: 36898.855 | F69: 37088.42 | G69: 37274.214 | H69: 37445.623 | I69: 37600.873 | J69: 37766.33 | K69: 37923.877 | L69: 38069.817 | M69: 38227.33 | N69: 38348.863 | O69: 38510.498 | P69: 38604.697 | Q69: 38681.121 | R69: 38748.487 | S69: 38814.705 | T69: 38876.265 | U69: 38939.471 | V69: 38983.894 | W69: 39034.301 | X69: 39076.492 | Y69: 39111.674 | Z69: 39147.674 | AA69: 39181.697 | AB69: 39212.991 | AC69: 39245.837 | AD69: 39278.913 | AE69: 39308.052 | AF69: 39337.439 | AG69: 39864.611 | AH69: 39959.684 | AI69: 40054.758 | AJ69: 40149.832 | AK69: 40244.906 | AL69: 40339.979 | AM69: 40435.053 | AN69: 40530.127 | AO69: 40625.2 | AP69: 40720.274 | AQ69: 40815.348 | AR69: 40910.422 | AS69: 41005.495 | AT69: 41100.569 | AU69: 41195.643 | AV69: 41290.717 | AW69: 41385.79 | AX69: 41480.864 | AY69: 41575.938 | AZ69: 41671.011
A70: gasoline vehicle | B70: 32342.636 | C70: 31217.363 | D70: 31436.447 | E70: 31582.449 | F70: 31757.9 | G70: 31937.089 | H70: 32051.631 | I70: 32113.77 | J70: 32185.62 | K70: 32243.903 | L70: 32274.622 | M70: 32331.769 | N70: 32347.685 | O70: 32381.444 | P70: 32396.375 | Q70: 32409.373 | R70: 32401.629 | S70: 32380.855 | T70: 32354.526 | U70: 32332.246 | V70: 32299.489 | W70: 32277.911 | X70: 32262.981 | Y70: 32240.582 | Z70: 32222.923 | AA70: 32218.675 | AB70: 32189.558 | AC70: 32165.915 | AD70: 32160.914 | AE70: 32130.598 | AF70: 32106.973 | AG70: 32390.103 | AH70: 32404.896 | AI70: 32419.689 | AJ70: 32434.482 | AK70: 32449.275 | AL70: 32464.068 | AM70: 32478.861 | AN70: 32493.654 | AO70: 32508.447 | AP70: 32523.24 | AQ70: 32538.033 | AR70: 32552.826 | AS70: 32567.619 | AT70: 32582.412 | AU70: 32597.205 | AV70: 32611.998 | AW70: 32626.791 | AX70: 32641.584 | AY70: 32656.377 | AZ70: 32671.17
A71: diesel vehicle | B71: 35443.546 | C71: 34572.73 | D71: 34849.204 | E71: 34983.821 | F71: 35151.364 | G71: 35326.619 | H71: 35410.191 | I71: 35435.494 | J71: 35474.588 | K71: 35499.908 | L71: 35487.978 | M71: 35511.964 | N71: 35480.242 | O71: 35474.108 | P71: 35461.937 | Q71: 35455.995 | R71: 35422.177 | S71: 35366.464 | T71: 35302.941 | U71: 35244.577 | V71: 35170.962 | W71: 35114.649 | X71: 35067.006 | Y71: 35011.117 | Z71: 34962.564 | AA71: 34932.466 | AB71: 34867.704 | AC71: 34811.011 | AD71: 34778.001 | AE71: 34711.17 | AF71: 34656.058 | AG71: 34943.404 | AH71: 34928.902 | AI71: 34914.4 | AJ71: 34899.898 | AK71: 34885.396 | AL71: 34870.893 | AM71: 34856.391 | AN71: 34841.889 | AO71: 34827.387 | AP71: 34812.885 | AQ71: 34798.383 | AR71: 34783.881 | AS71: 34769.379 | AT71: 34754.877 | AU71: 34740.375 | AV71: 34725.873 | AW71: 34711.371 | AX71: 34696.868 | AY71: 34682.366 | AZ71: 34667.864
A72: plugin hybrid vehicle | B72: 36885.812 | C72: 37390.063 | D72: 37336.116 | E72: 37519.774 | F72: 37560.849 | G72: 37672.814 | H72: 37718.564 | I72: 37744.624 | J72: 37799.089 | K72: 37869.295 | L72: 37947.783 | M72: 38048.195 | N72: 38134.621 | O72: 38250.401 | P72: 38309.624 | Q72: 38356.758 | R72: 38399.036 | S72: 38433.322 | T72: 38455.444 | U72: 38471.88 | V72: 38470.609 | W72: 38476.534 | X72: 38473.613 | Y72: 38464.26 | Z72: 38454.964 | AA72: 38445.041 | AB72: 38433.395 | AC72: 38423.684 | AD72: 38414.275 | AE72: 38406.062 | AF72: 38395.608 | AG72: 38782.846 | AH72: 38825.399 | AI72: 38867.951 | AJ72: 38910.504 | AK72: 38953.056 | AL72: 38995.609 | AM72: 39038.162 | AN72: 39080.714 | AO72: 39123.267 | AP72: 39165.82 | AQ72: 39208.372 | AR72: 39250.925 | AS72: 39293.478 | AT72: 39336.03 | AU72: 39378.583 | AV72: 39421.136 | AW72: 39463.688 | AX72: 39506.241 | AY72: 39548.794 | AZ72: 39591.346
A73: LPG vehicle | B73: 35929.333 | C73: 36517.782 | D73: 36483.97 | E73: 36547.532 | F73: 36633.721 | G73: 36794.3 | H73: 36928.46 | I73: 36997.316 | J73: 37058.276 | K73: 37124.274 | L73: 37186.148 | M73: 37247.67 | N73: 37300.144 | O73: 37363.114 | P73: 37405.731 | Q73: 37444.211 | R73: 37483.983 | S73: 37524.069 | T73: 37561.633 | U73: 37601.442 | V73: 37635.684 | W73: 37670.003 | X73: 37704.042 | Y73: 37736.312 | Z73: 37769.703 | AA73: 37804.107 | AB73: 37838.223 | AC73: 37873.503 | AD73: 37908.731 | AE73: 37944.389 | AF73: 37966.872 | AG73: 38189.454 | AH73: 38243.665 | AI73: 38297.875 | AJ73: 38352.086 | AK73: 38406.296 | AL73: 38460.507 | AM73: 38514.717 | AN73: 38568.928 | AO73: 38623.138 | AP73: 38677.349 | AQ73: 38731.559 | AR73: 38785.77 | AS73: 38839.98 | AT73: 38894.191 | AU73: 38948.401 | AV73: 39002.612 | AW73: 39056.822 | AX73: 39111.032 | AY73: 39165.243 | AZ73: 39219.453
A74: hydrogen vehicle | B74: 65082.118 | C74: 65067.963 | D74: 63660.552 | E74: 62421.595 | F74: 61170.116 | G74: 59874.757 | H74: 58736.772 | I74: 57689.483 | J74: 56690.542 | K74: 55738.719 | L74: 54831.315 | M74: 53967.601 | N74: 53140.492 | O74: 52357.768 | P74: 51589.549 | Q74: 50852.967 | R74: 50151.391 | S74: 49482.28 | T74: 48844.264 | U74: 48236.533 | V74: 47655.606 | W74: 47102.665 | X74: 46575.275 | Y74: 46072.297 | Z74: 45593.078 | AA74: 45136.282 | AB74: 44700.604 | AC74: 44285.587 | AD74: 43889.741 | AE74: 43512.798 | AF74: 43136.219 | AG74: 40253.789 | AH74: 39509.072 | AI74: 38764.355 | AJ74: 38019.639 | AK74: 37274.922 | AL74: 36530.205 | AM74: 35785.489 | AN74: 35040.772 | AO74: 34296.055 | AP74: 33551.339 | AQ74: 32806.622 | AR74: 32061.905 | AS74: 31317.189 | AT74: 30572.472 | AU74: 29827.755 | AV74: 29083.039 | AW74: 28338.322 | AX74: 27593.605 | AY74: 26848.889 | AZ74: 26104.172
A76: BNVP-LDVs-frgt
A77: Price ($/vehicle) | B77: 2020 | C77: 2021 | D77: 2022 | E77: 2023 | F77: 2024 | G77: 2025 | H77: 2026 | I77: 2027 | J77: 2028 | K77: 2029 | L77: 2030 | M77: 2031 | N77: 2032 | O77: 2033 | P77: 2034 | Q77: 2035 | R77: 2036 | S77: 2037 | T77: 2038 | U77: 2039 | V77: 2040 | W77: 2041 | X77: 2042 | Y77: 2043 | Z77: 2044 | AA77: 2045 | AB77: 2046 | AC77: 2047 | AD77: 2048 | AE77: 2049 | AF77: 2050 | AG77: 2051 | AH77: 2052 | AI77: 2053 | AJ77: 2054 | AK77: 2055 | AL77: 2056 | AM77: 2057 | AN77: 2058 | AO77: 2059 | AP77: 2060 | AQ77: 2061 | AR77: 2062 | AS77: 2063 | AT77: 2064 | AU77: 2065 | AV77: 2066 | AW77: 2067 | AX77: 2068 | AY77: 2069 | AZ77: 2070
A78: battery electric vehicle | B78: 74481.202 | C78: 74481.202 | D78: 74481.202 | E78: 74481.202 | F78: 74481.202 | G78: 74481.202 | H78: 74481.202 | I78: 74481.202 | J78: 74481.202 | K78: 74481.202 | L78: 74481.202 | M78: 74481.202 | N78: 74481.202 | O78: 74481.202 | P78: 74481.202 | Q78: 74481.202 | R78: 74481.202 | S78: 74481.202 | T78: 74481.202 | U78: 74481.202 | V78: 74481.202 | W78: 74481.202 | X78: 74481.202 | Y78: 74481.202 | Z78: 74481.202 | AA78: 74481.202 | AB78: 74481.202 | AC78: 74481.202 | AD78: 74481.202 | AE78: 74481.202 | AF78: 74481.202 | AG78: 74481.202 | AH78: 74481.202 | AI78: 74481.202 | AJ78: 74481.202 | AK78: 74481.202 | AL78: 74481.202 | AM78: 74481.202 | AN78: 74481.202 | AO78: 74481.202 | AP78: 74481.202 | AQ78: 74481.202 | AR78: 74481.202 | AS78: 74481.202 | AT78: 74481.202 | AU78: 74481.202 | AV78: 74481.202 | AW78: 74481.202 | AX78: 74481.202 | AY78: 74481.202 | AZ78: 74481.202
A79: natural gas vehicle | B79: 51983.088 | C79: 51609.123 | D79: 51831.988 | E79: 52179.801 | F79: 52447.871 | G79: 52710.607 | H79: 52953.003 | I79: 53172.546 | J79: 53406.524 | K79: 53629.316 | L79: 53835.695 | M79: 54058.438 | N79: 54230.301 | O79: 54458.874 | P79: 54592.084 | Q79: 54700.157 | R79: 54795.422 | S79: 54889.063 | T79: 54976.117 | U79: 55065.499 | V79: 55128.319 | W79: 55199.6 | X79: 55259.265 | Y79: 55309.016 | Z79: 55359.925 | AA79: 55408.038 | AB79: 55452.292 | AC79: 55498.74 | AD79: 55545.514 | AE79: 55586.72 | AF79: 55628.278 | AG79: 56373.767 | AH79: 56508.214 | AI79: 56642.66 | AJ79: 56777.107 | AK79: 56911.554 | AL79: 57046 | AM79: 57180.447 | AN79: 57314.894 | AO79: 57449.34 | AP79: 57583.787 | AQ79: 57718.234 | AR79: 57852.68 | AS79: 57987.127 | AT79: 58121.574 | AU79: 58256.02 | AV79: 58390.467 | AW79: 58524.914 | AX79: 58659.36 | AY79: 58793.807 | AZ79: 58928.254
A80: gasoline vehicle | B80: 45736.713 | C80: 45736.713 | D80: 45736.713 | E80: 45736.713 | F80: 45736.713 | G80: 45736.713 | H80: 45736.713 | I80: 45736.713 | J80: 45736.713 | K80: 45736.713 | L80: 45736.713 | M80: 45736.713 | N80: 45736.713 | O80: 45736.713 | P80: 45736.713 | Q80: 45736.713 | R80: 45736.713 | S80: 45736.713 | T80: 45736.713 | U80: 45736.713 | V80: 45736.713 | W80: 45736.713 | X80: 45736.713 | Y80: 45736.713 | Z80: 45736.713 | AA80: 45736.713 | AB80: 45736.713 | AC80: 45736.713 | AD80: 45736.713 | AE80: 45736.713 | AF80: 45736.713 | AG80: 45736.713 | AH80: 45736.713 | AI80: 45736.713 | AJ80: 45736.713 | AK80: 45736.713 | AL80: 45736.713 | AM80: 45736.713 | AN80: 45736.713 | AO80: 45736.713 | AP80: 45736.713 | AQ80: 45736.713 | AR80: 45736.713 | AS80: 45736.713 | AT80: 45736.713 | AU80: 45736.713 | AV80: 45736.713 | AW80: 45736.713 | AX80: 45736.713 | AY80: 45736.713 | AZ80: 45736.713
A81: diesel vehicle | B81: 50818.57 | C81: 50818.57 | D81: 50818.57 | E81: 50818.57 | F81: 50818.57 | G81: 50818.57 | H81: 50818.57 | I81: 50818.57 | J81: 50818.57 | K81: 50818.57 | L81: 50818.57 | M81: 50818.57 | N81: 50818.57 | O81: 50818.57 | P81: 50818.57 | Q81: 50818.57 | R81: 50818.57 | S81: 50818.57 | T81: 50818.57 | U81: 50818.57 | V81: 50818.57 | W81: 50818.57 | X81: 50818.57 | Y81: 50818.57 | Z81: 50818.57 | AA81: 50818.57 | AB81: 50818.57 | AC81: 50818.57 | AD81: 50818.57 | AE81: 50818.57 | AF81: 50818.57 | AG81: 50818.57 | AH81: 50818.57 | AI81: 50818.57 | AJ81: 50818.57 | AK81: 50818.57 | AL81: 50818.57 | AM81: 50818.57 | AN81: 50818.57 | AO81: 50818.57 | AP81: 50818.57 | AQ81: 50818.57 | AR81: 50818.57 | AS81: 50818.57 | AT81: 50818.57 | AU81: 50818.57 | AV81: 50818.57 | AW81: 50818.57 | AX81: 50818.57 | AY81: 50818.57 | AZ81: 50818.57
A82: plugin hybrid vehicle | B82: 52161.357 | C82: 52874.433 | D82: 52798.145 | E82: 53057.862 | F82: 53115.947 | G82: 53274.28 | H82: 53338.977 | I82: 53375.829 | J82: 53452.85 | K82: 53552.129 | L82: 53663.122 | M82: 53805.119 | N82: 53927.335 | O82: 54091.064 | P82: 54174.813 | Q82: 54241.466 | R82: 54301.253 | S82: 54349.738 | T82: 54381.021 | U82: 54404.263 | V82: 54402.467 | W82: 54410.845 | X82: 54406.715 | Y82: 54393.489 | Z82: 54380.342 | AA82: 54366.31 | AB82: 54349.841 | AC82: 54336.108 | AD82: 54322.803 | AE82: 54311.189 | AF82: 54296.405 | AG82: 54844.01 | AH82: 54904.185 | AI82: 54964.36 | AJ82: 55024.535 | AK82: 55084.71 | AL82: 55144.885 | AM82: 55205.06 | AN82: 55265.235 | AO82: 55325.41 | AP82: 55385.585 | AQ82: 55445.76 | AR82: 55505.935 | AS82: 55566.11 | AT82: 55626.285 | AU82: 55686.46 | AV82: 55746.635 | AW82: 55806.81 | AX82: 55866.985 | AY82: 55927.16 | AZ82: 55987.335
A83: LPG vehicle | B83: 50808.77 | C83: 51640.914 | D83: 51593.1 | E83: 51682.984 | F83: 51804.867 | G83: 52031.947 | H83: 52221.667 | I83: 52319.038 | J83: 52405.243 | K83: 52498.573 | L83: 52586.071 | M83: 52673.071 | N83: 52747.277 | O83: 52836.324 | P83: 52896.59 | Q83: 52951.005 | R83: 53007.249 | S83: 53063.936 | T83: 53117.056 | U83: 53173.35 | V83: 53221.773 | W83: 53270.305 | X83: 53318.44 | Y83: 53364.075 | Z83: 53411.295 | AA83: 53459.946 | AB83: 53508.19 | AC83: 53558.081 | AD83: 53607.897 | AE83: 53658.322 | AF83: 53690.117 | AG83: 54004.877 | AH83: 54081.538 | AI83: 54158.198 | AJ83: 54234.859 | AK83: 54311.52 | AL83: 54388.181 | AM83: 54464.841 | AN83: 54541.502 | AO83: 54618.163 | AP83: 54694.823 | AQ83: 54771.484 | AR83: 54848.145 | AS83: 54924.806 | AT83: 55001.466 | AU83: 55078.127 | AV83: 55154.788 | AW83: 55231.448 | AX83: 55308.109 | AY83: 55384.77 | AZ83: 55461.43
A84: hydrogen vehicle | B84: 93314.03 | C84: 93293.735 | D84: 91275.805 | E84: 89499.402 | F84: 87705.045 | G84: 85847.774 | H84: 84216.142 | I84: 82714.551 | J84: 81282.281 | K84: 79917.567 | L84: 78616.541 | M84: 77378.157 | N84: 76192.258 | O84: 75069.996 | P84: 73968.533 | Q84: 72912.43 | R84: 71906.517 | S84: 70947.153 | T84: 70032.372 | U84: 69161.015 | V84: 68328.087 | W84: 67535.288 | X84: 66779.121 | Y84: 66057.957 | Z84: 65370.857 | AA84: 64715.909 | AB84: 64091.238 | AC84: 63496.192 | AD84: 62928.631 | AE84: 62388.175 | AF84: 61848.24 | AG84: 57715.443 | AH84: 56647.677 | AI84: 55579.91 | AJ84: 54512.143 | AK84: 53444.377 | AL84: 52376.61 | AM84: 51308.843 | AN84: 50241.077 | AO84: 49173.31 | AP84: 48105.543 | AQ84: 47037.777 | AR84: 45970.01 | AS84: 44902.243 | AT84: 43834.477 | AU84: 42766.71 | AV84: 41698.943 | AW84: 40631.177 | AX84: 39563.41 | AY84: 38495.643 | AZ84: 37427.877
A86: BNVP-HDVs-psgr
A87: Price ($/vehicle) | B87: 2020 | C87: 2021 | D87: 2022 | E87: 2023 | F87: 2024 | G87: 2025 | H87: 2026 | I87: 2027 | J87: 2028 | K87: 2029 | L87: 2030 | M87: 2031 | N87: 2032 | O87: 2033 | P87: 2034 | Q87: 2035 | R87: 2036 | S87: 2037 | T87: 2038 | U87: 2039 | V87: 2040 | W87: 2041 | X87: 2042 | Y87: 2043 | Z87: 2044 | AA87: 2045 | AB87: 2046 | AC87: 2047 | AD87: 2048 | AE87: 2049 | AF87: 2050 | AG87: 2051 | AH87: 2052 | AI87: 2053 | AJ87: 2054 | AK87: 2055 | AL87: 2056 | AM87: 2057 | AN87: 2058 | AO87: 2059 | AP87: 2060 | AQ87: 2061 | AR87: 2062 | AS87: 2063 | AT87: 2064 | AU87: 2065 | AV87: 2066 | AW87: 2067 | AX87: 2068 | AY87: 2069 | AZ87: 2070
A88: battery electric vehicle | B88: 787140.4 | C88: 787140.4 | D88: 787140.4 | E88: 787140.4 | F88: 787140.4 | G88: 787140.4 | H88: 787140.4 | I88: 787140.4 | J88: 787140.4 | K88: 787140.4 | L88: 787140.4 | M88: 787140.4 | N88: 787140.4 | O88: 787140.4 | P88: 787140.4 | Q88: 787140.4 | R88: 787140.4 | S88: 787140.4 | T88: 787140.4 | U88: 787140.4 | V88: 787140.4 | W88: 787140.4 | X88: 787140.4 | Y88: 787140.4 | Z88: 787140.4 | AA88: 787140.4 | AB88: 787140.4 | AC88: 787140.4 | AD88: 787140.4 | AE88: 787140.4 | AF88: 787140.4 | AG88: 787140.4 | AH88: 787140.4 | AI88: 787140.4 | AJ88: 787140.4 | AK88: 787140.4 | AL88: 787140.4 | AM88: 787140.4 | AN88: 787140.4 | AO88: 787140.4 | AP88: 787140.4 | AQ88: 787140.4 | AR88: 787140.4 | AS88: 787140.4 | AT88: 787140.4 | AU88: 787140.4 | AV88: 787140.4 | AW88: 787140.4 | AX88: 787140.4 | AY88: 787140.4 | AZ88: 787140.4
A89: natural gas vehicle | B89: 543571.43 | C89: 539660.99 | D89: 541991.42 | E89: 545628.4 | F89: 548431.52 | G89: 551178.88 | H89: 553713.53 | I89: 556009.23 | J89: 558455.87 | K89: 560785.54 | L89: 562943.58 | M89: 565272.73 | N89: 567069.86 | O89: 569459.98 | P89: 570852.91 | Q89: 571983 | R89: 572979.15 | S89: 573958.33 | T89: 574868.62 | U89: 575803.27 | V89: 576460.15 | W89: 577205.52 | X89: 577829.42 | Y89: 578349.65 | Z89: 578881.99 | AA89: 579385.1 | AB89: 579847.85 | AC89: 580333.54 | AD89: 580822.64 | AE89: 581253.52 | AF89: 581688.07 | AG89: 589483.43 | AH89: 590889.3 | AI89: 592295.17 | AJ89: 593701.03 | AK89: 595106.9 | AL89: 596512.77 | AM89: 597918.64 | AN89: 599324.51 | AO89: 600730.38 | AP89: 602136.24 | AQ89: 603542.11 | AR89: 604947.98 | AS89: 606353.85 | AT89: 607759.72 | AU89: 609165.58 | AV89: 610571.45 | AW89: 611977.32 | AX89: 613383.19 | AY89: 614789.06 | AZ89: 616194.93
A90: gasoline vehicle | B90: 425813.12 | C90: 425813.12 | D90: 425813.12 | E90: 425813.12 | F90: 425813.12 | G90: 425813.12 | H90: 425813.12 | I90: 425813.12 | J90: 425813.12 | K90: 425813.12 | L90: 425813.12 | M90: 425813.12 | N90: 425813.12 | O90: 425813.12 | P90: 425813.12 | Q90: 425813.12 | R90: 425813.12 | S90: 425813.12 | T90: 425813.12 | U90: 425813.12 | V90: 425813.12 | W90: 425813.12 | X90: 425813.12 | Y90: 425813.12 | Z90: 425813.12 | AA90: 425813.12 | AB90: 425813.12 | AC90: 425813.12 | AD90: 425813.12 | AE90: 425813.12 | AF90: 425813.12 | AG90: 425813.12 | AH90: 425813.12 | AI90: 425813.12 | AJ90: 425813.12 | AK90: 425813.12 | AL90: 425813.12 | AM90: 425813.12 | AN90: 425813.12 | AO90: 425813.12 | AP90: 425813.12 | AQ90: 425813.12 | AR90: 425813.12 | AS90: 425813.12 | AT90: 425813.12 | AU90: 425813.12 | AV90: 425813.12 | AW90: 425813.12 | AX90: 425813.12 | AY90: 425813.12 | AZ90: 425813.12
A91: diesel vehicle | B91: 425813.12 | C91: 425813.12 | D91: 425813.12 | E91: 425813.12 | F91: 425813.12 | G91: 425813.12 | H91: 425813.12 | I91: 425813.12 | J91: 425813.12 | K91: 425813.12 | L91: 425813.12 | M91: 425813.12 | N91: 425813.12 | O91: 425813.12 | P91: 425813.12 | Q91: 425813.12 | R91: 425813.12 | S91: 425813.12 | T91: 425813.12 | U91: 425813.12 | V91: 425813.12 | W91: 425813.12 | X91: 425813.12 | Y91: 425813.12 | Z91: 425813.12 | AA91: 425813.12 | AB91: 425813.12 | AC91: 425813.12 | AD91: 425813.12 | AE91: 425813.12 | AF91: 425813.12 | AG91: 425813.12 | AH91: 425813.12 | AI91: 425813.12 | AJ91: 425813.12 | AK91: 425813.12 | AL91: 425813.12 | AM91: 425813.12 | AN91: 425813.12 | AO91: 425813.12 | AP91: 425813.12 | AQ91: 425813.12 | AR91: 425813.12 | AS91: 425813.12 | AT91: 425813.12 | AU91: 425813.12 | AV91: 425813.12 | AW91: 425813.12 | AX91: 425813.12 | AY91: 425813.12 | AZ91: 425813.12
A92: plugin hybrid vehicle | B92: 616714.29 | C92: 625145.13 | D92: 624243.15 | E92: 627313.84 | F92: 628000.59 | G92: 629872.59 | H92: 630637.52 | I92: 631073.23 | J92: 631983.87 | K92: 633157.67 | L92: 634469.96 | M92: 636148.81 | N92: 637593.8 | O92: 639529.6 | P92: 640519.78 | Q92: 641307.83 | R92: 642014.7 | S92: 642587.95 | T92: 642957.82 | U92: 643232.62 | V92: 643211.38 | W92: 643310.43 | X92: 643261.6 | Y92: 643105.23 | Z92: 642949.79 | AA92: 642783.89 | AB92: 642589.17 | AC92: 642426.81 | AD92: 642269.5 | AE92: 642132.18 | AF92: 641957.39 | AG92: 648431.84 | AH92: 649143.3 | AI92: 649854.76 | AJ92: 650566.22 | AK92: 651277.68 | AL92: 651989.14 | AM92: 652700.6 | AN92: 653412.06 | AO92: 654123.53 | AP92: 654834.99 | AQ92: 655546.45 | AR92: 656257.91 | AS92: 656969.37 | AT92: 657680.83 | AU92: 658392.29 | AV92: 659103.75 | AW92: 659815.22 | AX92: 660526.68 | AY92: 661238.14 | AZ92: 661949.6
A93: LPG vehicle | B93: 556134.73 | C93: 565243.08 | D93: 564719.73 | E93: 565703.57 | F93: 567037.66 | G93: 569523.2 | H93: 571599.8 | I93: 572665.59 | J93: 573609.15 | K93: 574630.71 | L93: 575588.44 | M93: 576540.71 | N93: 577352.94 | O93: 578327.62 | P93: 578987.27 | Q93: 579582.88 | R93: 580198.5 | S93: 580818.97 | T93: 581400.42 | U93: 582016.59 | V93: 582546.61 | W93: 583077.82 | X93: 583604.69 | Y93: 584104.19 | Z93: 584621.04 | AA93: 585153.56 | AB93: 585681.63 | AC93: 586227.71 | AD93: 586772.99 | AE93: 587324.92 | AF93: 587672.93 | AG93: 591118.18 | AH93: 591957.28 | AI93: 592796.38 | AJ93: 593635.49 | AK93: 594474.59 | AL93: 595313.69 | AM93: 596152.79 | AN93: 596991.89 | AO93: 597830.99 | AP93: 598670.09 | AQ93: 599509.19 | AR93: 600348.29 | AS93: 601187.39 | AT93: 602026.49 | AU93: 602865.6 | AV93: 603704.7 | AW93: 604543.8 | AX93: 605382.9 | AY93: 606222 | AZ93: 607061.1
A94: hydrogen vehicle | B94: 856850.98 | C94: 856664.62 | D94: 838135.09 | E94: 821823.37 | F94: 805346.78 | G94: 788292.49 | H94: 773310.12 | I94: 759521.84 | J94: 746370.1 | K94: 733838.69 | L94: 721892.09 | M94: 710520.7 | N94: 699631.24 | O94: 689326.14 | P94: 679212.01 | Q94: 669514.4 | R94: 660277.66 | S94: 651468.36 | T94: 643068.43 | U94: 635067.24 | V94: 627418.93 | W94: 620139.09 | X94: 613195.62 | Y94: 606573.58 | Z94: 600264.33 | AA94: 594250.29 | AB94: 588514.29 | AC94: 583050.31 | AD94: 577838.72 | AE94: 572876.01 | AF94: 567918.08 | AG94: 529968.9 | AH94: 520164.19 | AI94: 510359.48 | AJ94: 500554.78 | AK94: 490750.07 | AL94: 480945.36 | AM94: 471140.65 | AN94: 461335.94 | AO94: 451531.23 | AP94: 441726.52 | AQ94: 431921.81 | AR94: 422117.1 | AS94: 412312.4 | AT94: 402507.69 | AU94: 392702.98 | AV94: 382898.27 | AW94: 373093.56 | AX94: 363288.85 | AY94: 353484.14 | AZ94: 343679.43
A96: BNVP-HDVs-frgt
A97: Price ($/vehicle) | B97: 2020 | C97: 2021 | D97: 2022 | E97: 2023 | F97: 2024 | G97: 2025 | H97: 2026 | I97: 2027 | J97: 2028 | K97: 2029 | L97: 2030 | M97: 2031 | N97: 2032 | O97: 2033 | P97: 2034 | Q97: 2035 | R97: 2036 | S97: 2037 | T97: 2038 | U97: 2039 | V97: 2040 | W97: 2041 | X97: 2042 | Y97: 2043 | Z97: 2044 | AA97: 2045 | AB97: 2046 | AC97: 2047 | AD97: 2048 | AE97: 2049 | AF97: 2050 | AG97: 2051 | AH97: 2052 | AI97: 2053 | AJ97: 2054 | AK97: 2055 | AL97: 2056 | AM97: 2057 | AN97: 2058 | AO97: 2059 | AP97: 2060 | AQ97: 2061 | AR97: 2062 | AS97: 2063 | AT97: 2064 | AU97: 2065 | AV97: 2066 | AW97: 2067 | AX97: 2068 | AY97: 2069 | AZ97: 2070
A98: battery electric vehicle | B98: 212323.26 | C98: 212323.26 | D98: 212323.26 | E98: 212323.26 | F98: 212323.26 | G98: 212323.26 | H98: 212323.26 | I98: 212323.26 | J98: 212323.26 | K98: 212323.26 | L98: 212323.26 | M98: 212323.26 | N98: 212323.26 | O98: 212323.26 | P98: 212323.26 | Q98: 212323.26 | R98: 212323.26 | S98: 212323.26 | T98: 212323.26 | U98: 212323.26 | V98: 212323.26 | W98: 212323.26 | X98: 212323.26 | Y98: 212323.26 | Z98: 212323.26 | AA98: 212323.26 | AB98: 212323.26 | AC98: 212323.26 | AD98: 212323.26 | AE98: 212323.26 | AF98: 212323.26 | AG98: 212323.26 | AH98: 212323.26 | AI98: 212323.26 | AJ98: 212323.26 | AK98: 212323.26 | AL98: 212323.26 | AM98: 212323.26 | AN98: 212323.26 | AO98: 212323.26 | AP98: 212323.26 | AQ98: 212323.26 | AR98: 212323.26 | AS98: 212323.26 | AT98: 212323.26 | AU98: 212323.26 | AV98: 212323.26 | AW98: 212323.26 | AX98: 212323.26 | AY98: 212323.26 | AZ98: 212323.26
A99: natural gas vehicle | B99: 169081.01 | C99: 167864.65 | D99: 168589.54 | E99: 169720.85 | F99: 170592.77 | G99: 171447.35 | H99: 172235.77 | I99: 172949.86 | J99: 173710.9 | K99: 174435.56 | L99: 175106.83 | M99: 175831.33 | N99: 176390.34 | O99: 177133.8 | P99: 177567.08 | Q99: 177918.6 | R99: 178228.46 | S99: 178533.03 | T99: 178816.19 | U99: 179106.91 | V99: 179311.24 | W99: 179543.09 | X99: 179737.16 | Y99: 179898.98 | Z99: 180064.57 | AA99: 180221.06 | AB99: 180365 | AC99: 180516.08 | AD99: 180668.22 | AE99: 180802.25 | AF99: 180937.41 | AG99: 183362.21 | AH99: 183799.51 | AI99: 184236.81 | AJ99: 184674.12 | AK99: 185111.42 | AL99: 185548.72 | AM99: 185986.03 | AN99: 186423.33 | AO99: 186860.63 | AP99: 187297.94 | AQ99: 187735.24 | AR99: 188172.54 | AS99: 188609.85 | AT99: 189047.15 | AU99: 189484.45 | AV99: 189921.76 | AW99: 190359.06 | AX99: 190796.36 | AY99: 191233.67 | AZ99: 191670.97
A100: gasoline vehicle | B100: 116533.08 | C100: 116533.08 | D100: 116533.08 | E100: 116533.08 | F100: 116533.08 | G100: 116533.08 | H100: 116533.08 | I100: 116533.08 | J100: 116533.08 | K100: 116533.08 | L100: 116533.08 | M100: 116533.08 | N100: 116533.08 | O100: 116533.08 | P100: 116533.08 | Q100: 116533.08 | R100: 116533.08 | S100: 116533.08 | T100: 116533.08 | U100: 116533.08 | V100: 116533.08 | W100: 116533.08 | X100: 116533.08 | Y100: 116533.08 | Z100: 116533.08 | AA100: 116533.08 | AB100: 116533.08 | AC100: 116533.08 | AD100: 116533.08 | AE100: 116533.08 | AF100: 116533.08 | AG100: 116533.08 | AH100: 116533.08 | AI100: 116533.08 | AJ100: 116533.08 | AK100: 116533.08 | AL100: 116533.08 | AM100: 116533.08 | AN100: 116533.08 | AO100: 116533.08 | AP100: 116533.08 | AQ100: 116533.08 | AR100: 116533.08 | AS100: 116533.08 | AT100: 116533.08 | AU100: 116533.08 | AV100: 116533.08 | AW100: 116533.08 | AX100: 116533.08 | AY100: 116533.08 | AZ100: 116533.08
A101: diesel vehicle | B101: 116533.08 | C101: 116533.08 | D101: 116533.08 | E101: 116533.08 | F101: 116533.08 | G101: 116533.08 | H101: 116533.08 | I101: 116533.08 | J101: 116533.08 | K101: 116533.08 | L101: 116533.08 | M101: 116533.08 | N101: 116533.08 | O101: 116533.08 | P101: 116533.08 | Q101: 116533.08 | R101: 116533.08 | S101: 116533.08 | T101: 116533.08 | U101: 116533.08 | V101: 116533.08 | W101: 116533.08 | X101: 116533.08 | Y101: 116533.08 | Z101: 116533.08 | AA101: 116533.08 | AB101: 116533.08 | AC101: 116533.08 | AD101: 116533.08 | AE101: 116533.08 | AF101: 116533.08 | AG101: 116533.08 | AH101: 116533.08 | AI101: 116533.08 | AJ101: 116533.08 | AK101: 116533.08 | AL101: 116533.08 | AM101: 116533.08 | AN101: 116533.08 | AO101: 116533.08 | AP101: 116533.08 | AQ101: 116533.08 | AR101: 116533.08 | AS101: 116533.08 | AT101: 116533.08 | AU101: 116533.08 | AV101: 116533.08 | AW101: 116533.08 | AX101: 116533.08 | AY101: 116533.08 | AZ101: 116533.08
A102: plugin hybrid vehicle | B102: 292717.2 | C102: 296718.81 | D102: 296290.7 | E102: 297748.17 | F102: 298074.13 | G102: 298962.66 | H102: 299325.72 | I102: 299532.53 | J102: 299964.75 | K102: 300521.89 | L102: 301144.75 | M102: 301941.6 | N102: 302627.45 | O102: 303546.26 | P102: 304016.24 | Q102: 304390.28 | R102: 304725.79 | S102: 304997.87 | T102: 305173.43 | U102: 305303.86 | V102: 305293.78 | W102: 305340.79 | X102: 305317.62 | Y102: 305243.4 | Z102: 305169.62 | AA102: 305090.87 | AB102: 304998.45 | AC102: 304921.39 | AD102: 304846.72 | AE102: 304781.55 | AF102: 304698.59 | AG102: 307771.62 | AH102: 308109.3 | AI102: 308446.99 | AJ102: 308784.68 | AK102: 309122.37 | AL102: 309460.05 | AM102: 309797.74 | AN102: 310135.43 | AO102: 310473.12 | AP102: 310810.81 | AQ102: 311148.49 | AR102: 311486.18 | AS102: 311823.87 | AT102: 312161.56 | AU102: 312499.25 | AV102: 312836.93 | AW102: 313174.62 | AX102: 313512.31 | AY102: 313850 | AZ102: 314187.69
A103: LPG vehicle | B103: 165261.41 | C103: 167968.05 | D103: 167812.53 | E103: 168104.89 | F103: 168501.33 | G103: 169239.93 | H103: 169857.02 | I103: 170173.73 | J103: 170454.12 | K103: 170757.69 | L103: 171042.29 | M103: 171325.26 | N103: 171566.63 | O103: 171856.26 | P103: 172052.29 | Q103: 172229.28 | R103: 172412.22 | S103: 172596.6 | T103: 172769.38 | U103: 172952.48 | V103: 173109.98 | W103: 173267.84 | X103: 173424.4 | Y103: 173572.83 | Z103: 173726.42 | AA103: 173884.67 | AB103: 174041.59 | AC103: 174203.86 | AD103: 174365.89 | AE103: 174529.91 | AF103: 174633.32 | AG103: 175657.12 | AH103: 175906.46 | AI103: 176155.81 | AJ103: 176405.16 | AK103: 176654.51 | AL103: 176903.86 | AM103: 177153.2 | AN103: 177402.55 | AO103: 177651.9 | AP103: 177901.25 | AQ103: 178150.59 | AR103: 178399.94 | AS103: 178649.29 | AT103: 178898.64 | AU103: 179147.99 | AV103: 179397.33 | AW103: 179646.68 | AX103: 179896.03 | AY103: 180145.38 | AZ103: 180394.73
A104: hydrogen vehicle | B104: 356070.43 | C104: 355992.99 | D104: 348292.91 | E104: 341514.46 | F104: 334667.5 | G104: 327580.47 | H104: 321354.44 | I104: 315624.63 | J104: 310159.33 | K104: 304951.81 | L104: 299987.32 | M104: 295261.86 | N104: 290736.67 | O104: 286454.31 | P104: 282251.31 | Q104: 278221.4 | R104: 274383.01 | S104: 270722.24 | T104: 267231.6 | U104: 263906.64 | V104: 260728.33 | W104: 257703.15 | X104: 254817.74 | Y104: 252065.91 | Z104: 249444.05 | AA104: 246944.88 | AB104: 244561.24 | AC104: 242290.65 | AD104: 240124.93 | AE104: 238062.64 | AF104: 236002.34 | AG104: 220232.29 | AH104: 216157.88 | AI104: 212083.46 | AJ104: 208009.05 | AK104: 203934.63 | AL104: 199860.22 | AM104: 195785.8 | AN104: 191711.38 | AO104: 187636.97 | AP104: 183562.55 | AQ104: 179488.14 | AR104: 175413.72 | AS104: 171339.31 | AT104: 167264.89 | AU104: 163190.48 | AV104: 159116.06 | AW104: 155041.64 | AX104: 150967.23 | AY104: 146892.81 | AZ104: 142818.4
A106: BNVP-aircraft-psgr
A107: Price ($/vehicle) | B107: 2020 | C107: 2021 | D107: 2022 | E107: 2023 | F107: 2024 | G107: 2025 | H107: 2026 | I107: 2027 | J107: 2028 | K107: 2029 | L107: 2030 | M107: 2031 | N107: 2032 | O107: 2033 | P107: 2034 | Q107: 2035 | R107: 2036 | S107: 2037 | T107: 2038 | U107: 2039 | V107: 2040 | W107: 2041 | X107: 2042 | Y107: 2043 | Z107: 2044 | AA107: 2045 | AB107: 2046 | AC107: 2047 | AD107: 2048 | AE107: 2049 | AF107: 2050 | AG107: 2051 | AH107: 2052 | AI107: 2053 | AJ107: 2054 | AK107: 2055 | AL107: 2056 | AM107: 2057 | AN107: 2058 | AO107: 2059 | AP107: 2060 | AQ107: 2061 | AR107: 2062 | AS107: 2063 | AT107: 2064 | AU107: 2065 | AV107: 2066 | AW107: 2067 | AX107: 2068 | AY107: 2069 | AZ107: 2070
A108: battery electric vehicle | B108: 1.198482e+08 | C108: 1.198482e+08 | D108: 1.198482e+08 | E108: 1.198482e+08 | F108: 1.198482e+08 | G108: 1.198482e+08 | H108: 1.198482e+08 | I108: 1.198482e+08 | J108: 1.198482e+08 | K108: 1.198482e+08 | L108: 1.198482e+08 | M108: 1.198482e+08 | N108: 1.198482e+08 | O108: 1.198482e+08 | P108: 1.198482e+08 | Q108: 1.198482e+08 | R108: 1.198482e+08 | S108: 1.198482e+08 | T108: 1.198482e+08 | U108: 1.198482e+08 | V108: 1.198482e+08 | W108: 1.198482e+08 | X108: 1.198482e+08 | Y108: 1.198482e+08 | Z108: 1.198482e+08 | AA108: 1.198482e+08 | AB108: 1.198482e+08 | AC108: 1.198482e+08 | AD108: 1.198482e+08 | AE108: 1.198482e+08 | AF108: 1.198482e+08 | AG108: 1.198482e+08 | AH108: 1.198482e+08 | AI108: 1.198482e+08 | AJ108: 1.198482e+08 | AK108: 1.198482e+08 | AL108: 1.198482e+08 | AM108: 1.198482e+08 | AN108: 1.198482e+08 | AO108: 1.198482e+08 | AP108: 1.198482e+08 | AQ108: 1.198482e+08 | AR108: 1.198482e+08 | AS108: 1.198482e+08 | AT108: 1.198482e+08 | AU108: 1.198482e+08 | AV108: 1.198482e+08 | AW108: 1.198482e+08 | AX108: 1.198482e+08 | AY108: 1.198482e+08 | AZ108: 1.198482e+08
A109: natural gas vehicle | B109: 0 | C109: 0 | D109: 0 | E109: 0 | F109: 0 | G109: 0 | H109: 0 | I109: 0 | J109: 0 | K109: 0 | L109: 0 | M109: 0 | N109: 0 | O109: 0 | P109: 0 | Q109: 0 | R109: 0 | S109: 0 | T109: 0 | U109: 0 | V109: 0 | W109: 0 | X109: 0 | Y109: 0 | Z109: 0 | AA109: 0 | AB109: 0 | AC109: 0 | AD109: 0 | AE109: 0 | AF109: 0 | AG109: 0 | AH109: 0 | AI109: 0 | AJ109: 0 | AK109: 0 | AL109: 0 | AM109: 0 | AN109: 0 | AO109: 0 | AP109: 0 | AQ109: 0 | AR109: 0 | AS109: 0 | AT109: 0 | AU109: 0 | AV109: 0 | AW109: 0 | AX109: 0 | AY109: 0 | AZ109: 0
A110: gasoline vehicle | B110: 0 | C110: 0 | D110: 0 | E110: 0 | F110: 0 | G110: 0 | H110: 0 | I110: 0 | J110: 0 | K110: 0 | L110: 0 | M110: 0 | N110: 0 | O110: 0 | P110: 0 | Q110: 0 | R110: 0 | S110: 0 | T110: 0 | U110: 0 | V110: 0 | W110: 0 | X110: 0 | Y110: 0 | Z110: 0 | AA110: 0 | AB110: 0 | AC110: 0 | AD110: 0 | AE110: 0 | AF110: 0 | AG110: 0 | AH110: 0 | AI110: 0 | AJ110: 0 | AK110: 0 | AL110: 0 | AM110: 0 | AN110: 0 | AO110: 0 | AP110: 0 | AQ110: 0 | AR110: 0 | AS110: 0 | AT110: 0 | AU110: 0 | AV110: 0 | AW110: 0 | AX110: 0 | AY110: 0 | AZ110: 0
A111: diesel vehicle | B111: 64833333 | C111: 64833333 | D111: 64833333 | E111: 64833333 | F111: 64833333 | G111: 64833333 | H111: 64833333 | I111: 64833333 | J111: 64833333 | K111: 64833333 | L111: 64833333 | M111: 64833333 | N111: 64833333 | O111: 64833333 | P111: 64833333 | Q111: 64833333 | R111: 64833333 | S111: 64833333 | T111: 64833333 | U111: 64833333 | V111: 64833333 | W111: 64833333 | X111: 64833333 | Y111: 64833333 | Z111: 64833333 | AA111: 64833333 | AB111: 64833333 | AC111: 64833333 | AD111: 64833333 | AE111: 64833333 | AF111: 64833333 | AG111: 64833333 | AH111: 64833333 | AI111: 64833333 | AJ111: 64833333 | AK111: 64833333 | AL111: 64833333 | AM111: 64833333 | AN111: 64833333 | AO111: 64833333 | AP111: 64833333 | AQ111: 64833333 | AR111: 64833333 | AS111: 64833333 | AT111: 64833333 | AU111: 64833333 | AV111: 64833333 | AW111: 64833333 | AX111: 64833333 | AY111: 64833333 | AZ111: 64833333
A112: plugin hybrid vehicle | B112: 0 | C112: 0 | D112: 0 | E112: 0 | F112: 0 | G112: 0 | H112: 0 | I112: 0 | J112: 0 | K112: 0 | L112: 0 | M112: 0 | N112: 0 | O112: 0 | P112: 0 | Q112: 0 | R112: 0 | S112: 0 | T112: 0 | U112: 0 | V112: 0 | W112: 0 | X112: 0 | Y112: 0 | Z112: 0 | AA112: 0 | AB112: 0 | AC112: 0 | AD112: 0 | AE112: 0 | AF112: 0 | AG112: 0 | AH112: 0 | AI112: 0 | AJ112: 0 | AK112: 0 | AL112: 0 | AM112: 0 | AN112: 0 | AO112: 0 | AP112: 0 | AQ112: 0 | AR112: 0 | AS112: 0 | AT112: 0 | AU112: 0 | AV112: 0 | AW112: 0 | AX112: 0 | AY112: 0 | AZ112: 0
A113: LPG vehicle | B113: 0 | C113: 0 | D113: 0 | E113: 0 | F113: 0 | G113: 0 | H113: 0 | I113: 0 | J113: 0 | K113: 0 | L113: 0 | M113: 0 | N113: 0 | O113: 0 | P113: 0 | Q113: 0 | R113: 0 | S113: 0 | T113: 0 | U113: 0 | V113: 0 | W113: 0 | X113: 0 | Y113: 0 | Z113: 0 | AA113: 0 | AB113: 0 | AC113: 0 | AD113: 0 | AE113: 0 | AF113: 0 | AG113: 0 | AH113: 0 | AI113: 0 | AJ113: 0 | AK113: 0 | AL113: 0 | AM113: 0 | AN113: 0 | AO113: 0 | AP113: 0 | AQ113: 0 | AR113: 0 | AS113: 0 | AT113: 0 | AU113: 0 | AV113: 0 | AW113: 0 | AX113: 0 | AY113: 0 | AZ113: 0
A114: hydrogen vehicle | B114: 1.3046217e+08 | C114: 1.304338e+08 | D114: 1.2761253e+08 | E114: 1.2512895e+08 | F114: 1.2262026e+08 | G114: 1.2002361e+08 | H114: 1.1774243e+08 | I114: 1.1564306e+08 | J114: 1.1364061e+08 | K114: 1.117326e+08 | L114: 1.0991364e+08 | M114: 1.0818226e+08 | N114: 1.0652426e+08 | O114: 1.0495522e+08 | P114: 1.0341527e+08 | Q114: 1.0193873e+08 | R114: 1.0053237e+08 | S114: 99191084 | T114: 97912130 | U114: 96693887 | V114: 95529373 | W114: 94420961 | X114: 93363765 | Y114: 92355508 | Z114: 91394875 | AA114: 90479192 | AB114: 89605842 | AC114: 88773909 | AD114: 87980403 | AE114: 87224793 | AF114: 86469910 | AG114: 80691855 | AH114: 79199012 | AI114: 77706169 | AJ114: 76213327 | AK114: 74720484 | AL114: 73227642 | AM114: 71734799 | AN114: 70241956 | AO114: 68749114 | AP114: 67256271 | AQ114: 65763429 | AR114: 64270586 | AS114: 62777744 | AT114: 61284901 | AU114: 59792058 | AV114: 58299216 | AW114: 56806373 | AX114: 55313531 | AY114: 53820688 | AZ114: 52327845
A116: BNVP-rail-psgr
A117: Price ($/vehicle) | B117: 2020 | C117: 2021 | D117: 2022 | E117: 2023 | F117: 2024 | G117: 2025 | H117: 2026 | I117: 2027 | J117: 2028 | K117: 2029 | L117: 2030 | M117: 2031 | N117: 2032 | O117: 2033 | P117: 2034 | Q117: 2035 | R117: 2036 | S117: 2037 | T117: 2038 | U117: 2039 | V117: 2040 | W117: 2041 | X117: 2042 | Y117: 2043 | Z117: 2044 | AA117: 2045 | AB117: 2046 | AC117: 2047 | AD117: 2048 | AE117: 2049 | AF117: 2050 | AG117: 2051 | AH117: 2052 | AI117: 2053 | AJ117: 2054 | AK117: 2055 | AL117: 2056 | AM117: 2057 | AN117: 2058 | AO117: 2059 | AP117: 2060 | AQ117: 2061 | AR117: 2062 | AS117: 2063 | AT117: 2064 | AU117: 2065 | AV117: 2066 | AW117: 2067 | AX117: 2068 | AY117: 2069 | AZ117: 2070
A118: battery electric vehicle | B118: 4166666.7 | C118: 4166666.7 | D118: 4166666.7 | E118: 4166666.7 | F118: 4166666.7 | G118: 4166666.7 | H118: 4166666.7 | I118: 4166666.7 | J118: 4166666.7 | K118: 4166666.7 | L118: 4166666.7 | M118: 4166666.7 | N118: 4166666.7 | O118: 4166666.7 | P118: 4166666.7 | Q118: 4166666.7 | R118: 4166666.7 | S118: 4166666.7 | T118: 4166666.7 | U118: 4166666.7 | V118: 4166666.7 | W118: 4166666.7 | X118: 4166666.7 | Y118: 4166666.7 | Z118: 4166666.7 | AA118: 4166666.7 | AB118: 4166666.7 | AC118: 4166666.7 | AD118: 4166666.7 | AE118: 4166666.7 | AF118: 4166666.7 | AG118: 4166666.7 | AH118: 4166666.7 | AI118: 4166666.7 | AJ118: 4166666.7 | AK118: 4166666.7 | AL118: 4166666.7 | AM118: 4166666.7 | AN118: 4166666.7 | AO118: 4166666.7 | AP118: 4166666.7 | AQ118: 4166666.7 | AR118: 4166666.7 | AS118: 4166666.7 | AT118: 4166666.7 | AU118: 4166666.7 | AV118: 4166666.7 | AW118: 4166666.7 | AX118: 4166666.7 | AY118: 4166666.7 | AZ118: 4166666.7
A119: natural gas vehicle | B119: 0 | C119: 0 | D119: 0 | E119: 0 | F119: 0 | G119: 0 | H119: 0 | I119: 0 | J119: 0 | K119: 0 | L119: 0 | M119: 0 | N119: 0 | O119: 0 | P119: 0 | Q119: 0 | R119: 0 | S119: 0 | T119: 0 | U119: 0 | V119: 0 | W119: 0 | X119: 0 | Y119: 0 | Z119: 0 | AA119: 0 | AB119: 0 | AC119: 0 | AD119: 0 | AE119: 0 | AF119: 0 | AG119: 0 | AH119: 0 | AI119: 0 | AJ119: 0 | AK119: 0 | AL119: 0 | AM119: 0 | AN119: 0 | AO119: 0 | AP119: 0 | AQ119: 0 | AR119: 0 | AS119: 0 | AT119: 0 | AU119: 0 | AV119: 0 | AW119: 0 | AX119: 0 | AY119: 0 | AZ119: 0
A120: gasoline vehicle | B120: 0 | C120: 0 | D120: 0 | E120: 0 | F120: 0 | G120: 0 | H120: 0 | I120: 0 | J120: 0 | K120: 0 | L120: 0 | M120: 0 | N120: 0 | O120: 0 | P120: 0 | Q120: 0 | R120: 0 | S120: 0 | T120: 0 | U120: 0 | V120: 0 | W120: 0 | X120: 0 | Y120: 0 | Z120: 0 | AA120: 0 | AB120: 0 | AC120: 0 | AD120: 0 | AE120: 0 | AF120: 0 | AG120: 0 | AH120: 0 | AI120: 0 | AJ120: 0 | AK120: 0 | AL120: 0 | AM120: 0 | AN120: 0 | AO120: 0 | AP120: 0 | AQ120: 0 | AR120: 0 | AS120: 0 | AT120: 0 | AU120: 0 | AV120: 0 | AW120: 0 | AX120: 0 | AY120: 0 | AZ120: 0
A121: diesel vehicle | B121: 2245137 | C121: 2245137 | D121: 2245137 | E121: 2245137 | F121: 2245137 | G121: 2245137 | H121: 2245137 | I121: 2245137 | J121: 2245137 | K121: 2245137 | L121: 2245137 | M121: 2245137 | N121: 2245137 | O121: 2245137 | P121: 2245137 | Q121: 2245137 | R121: 2245137 | S121: 2245137 | T121: 2245137 | U121: 2245137 | V121: 2245137 | W121: 2245137 | X121: 2245137 | Y121: 2245137 | Z121: 2245137 | AA121: 2245137 | AB121: 2245137 | AC121: 2245137 | AD121: 2245137 | AE121: 2245137 | AF121: 2245137 | AG121: 2245137 | AH121: 2245137 | AI121: 2245137 | AJ121: 2245137 | AK121: 2245137 | AL121: 2245137 | AM121: 2245137 | AN121: 2245137 | AO121: 2245137 | AP121: 2245137 | AQ121: 2245137 | AR121: 2245137 | AS121: 2245137 | AT121: 2245137 | AU121: 2245137 | AV121: 2245137 | AW121: 2245137 | AX121: 2245137 | AY121: 2245137 | AZ121: 2245137
A122: plugin hybrid vehicle | B122: 0 | C122: 0 | D122: 0 | E122: 0 | F122: 0 | G122: 0 | H122: 0 | I122: 0 | J122: 0 | K122: 0 | L122: 0 | M122: 0 | N122: 0 | O122: 0 | P122: 0 | Q122: 0 | R122: 0 | S122: 0 | T122: 0 | U122: 0 | V122: 0 | W122: 0 | X122: 0 | Y122: 0 | Z122: 0 | AA122: 0 | AB122: 0 | AC122: 0 | AD122: 0 | AE122: 0 | AF122: 0 | AG122: 0 | AH122: 0 | AI122: 0 | AJ122: 0 | AK122: 0 | AL122: 0 | AM122: 0 | AN122: 0 | AO122: 0 | AP122: 0 | AQ122: 0 | AR122: 0 | AS122: 0 | AT122: 0 | AU122: 0 | AV122: 0 | AW122: 0 | AX122: 0 | AY122: 0 | AZ122: 0
A123: LPG vehicle | B123: 0 | C123: 0 | D123: 0 | E123: 0 | F123: 0 | G123: 0 | H123: 0 | I123: 0 | J123: 0 | K123: 0 | L123: 0 | M123: 0 | N123: 0 | O123: 0 | P123: 0 | Q123: 0 | R123: 0 | S123: 0 | T123: 0 | U123: 0 | V123: 0 | W123: 0 | X123: 0 | Y123: 0 | Z123: 0 | AA123: 0 | AB123: 0 | AC123: 0 | AD123: 0 | AE123: 0 | AF123: 0 | AG123: 0 | AH123: 0 | AI123: 0 | AJ123: 0 | AK123: 0 | AL123: 0 | AM123: 0 | AN123: 0 | AO123: 0 | AP123: 0 | AQ123: 0 | AR123: 0 | AS123: 0 | AT123: 0 | AU123: 0 | AV123: 0 | AW123: 0 | AX123: 0 | AY123: 0 | AZ123: 0
A124: hydrogen vehicle | B124: 2963580.9 | C124: 2962936.3 | D124: 2898848.4 | E124: 2842431.3 | F124: 2785443.9 | G124: 2726458.4 | H124: 2674639.1 | I124: 2626949.7 | J124: 2581461.9 | K124: 2538119.7 | L124: 2496800.1 | M124: 2457470 | N124: 2419806.7 | O124: 2384164.6 | P124: 2349183 | Q124: 2315642 | R124: 2283694.9 | S124: 2253226.3 | T124: 2224173.6 | U124: 2196499.9 | V124: 2170046.8 | W124: 2144868.1 | X124: 2120852.8 | Y124: 2097949.3 | Z124: 2076127.5 | AA124: 2055326.8 | AB124: 2035487.8 | AC124: 2016589.6 | AD124: 1998564.3 | AE124: 1981399.8 | AF124: 1964251.9 | AG124: 1832997.5 | AH124: 1799086.1 | AI124: 1765174.6 | AJ124: 1731263.2 | AK124: 1697351.8 | AL124: 1663440.3 | AM124: 1629528.9 | AN124: 1595617.4 | AO124: 1561706 | AP124: 1527794.6 | AQ124: 1493883.1 | AR124: 1459971.7 | AS124: 1426060.3 | AT124: 1392148.8 | AU124: 1358237.4 | AV124: 1324326 | AW124: 1290414.5 | AX124: 1256503.1 | AY124: 1222591.6 | AZ124: 1188680.2
A126: BNVP-aircraft-frgt
A127: Price ($/vehicle) | B127: 2020 | C127: 2021 | D127: 2022 | E127: 2023 | F127: 2024 | G127: 2025 | H127: 2026 | I127: 2027 | J127: 2028 | K127: 2029 | L127: 2030 | M127: 2031 | N127: 2032 | O127: 2033 | P127: 2034 | Q127: 2035 | R127: 2036 | S127: 2037 | T127: 2038 | U127: 2039 | V127: 2040 | W127: 2041 | X127: 2042 | Y127: 2043 | Z127: 2044 | AA127: 2045 | AB127: 2046 | AC127: 2047 | AD127: 2048 | AE127: 2049 | AF127: 2050 | AG127: 2051 | AH127: 2052 | AI127: 2053 | AJ127: 2054 | AK127: 2055 | AL127: 2056 | AM127: 2057 | AN127: 2058 | AO127: 2059 | AP127: 2060 | AQ127: 2061 | AR127: 2062 | AS127: 2063 | AT127: 2064 | AU127: 2065 | AV127: 2066 | AW127: 2067 | AX127: 2068 | AY127: 2069 | AZ127: 2070
...

Sheet Indonesia - Motorcycles
B3: India's projection
L5: US$1 = INR 74
L9: 2020
K10: Conventional | L10: 47148 | M10: =L10/74 -> 637.13514
K11: BEV100 | L11: 141905 | M11: =L11/74 -> 1917.6351
K12: BEV150 | L12: 170960 | M12: =L12/74 -> 2310.2703 | N12: < used
K13: BEV250 | L13: 229069 | M13: =L13/74 -> 3095.527
L19: 2030
K20: Conventional | L20: 50683 | M20: =L20/74 -> 684.90541
K21: BEV100 | L21: 59007 | M21: =L21/74 -> 797.39189
K22: BEV150 | L22: 72630 | M22: =L22/74 -> 981.48649 | N22: < used
K23: BEV250 | L23: 99877 | M23: =L23/74 -> 1349.6892
L25: 2040
K26: Conventional | L26: 70000 | M26: =L26/74 -> 945.94595
K27: BEV100 | L27: 28000 | M27: =L27/74 -> 378.37838
K28: BEV150 | L28: 30000 | M28: =L28/74 -> 405.40541 | N28: < used
B32: Source: ICCT (2021) https://theicct.org/sites/default/files/publications/E2W-cost-2030-India-jul2021.pdf

Sheet Indonesia - HDV 
B4: Indonesia's HDV passenger
B15: Source: ICCT (2023) | G15: Source: ITDP (2023)
G16: IDR/USD: 15,200, based on exchange rate on October 4, 2022
B17: Exchange rate: 1 USD=14,800 IDR (the average rate in August 2022). | L17: Used the weighted average
G18: Next steps | H18: if possible using the weighted average for HDVs prices | L18: Diesel | O18: ITDP (2023) | P18: ICCT (2023) | Q18: Average
B19: BNVP-HDVs-psgr | C19: Initial EPS prices | D19: ICCT prices | H19: otherwise using unweighted average | L19: Single Bus | M19: ='Number of Vehicles'!C3 -> 0.26664825 | N19: 2341 | O19: =N19*1000000/15200 -> 154013.16 | P19: =2594715750/14800 -> 175318.63 | Q19: =AVERAGE(O19:P19) -> 164665.89
B20: Price ($/vehicle) | C20: 2022 | D20: 2022 | E20: Source | L20: Articulated Bus | M20: ='Number of Vehicles'!C4 -> 0.071014092 | N20: 4800 | O20: =N20*1000000/15200 -> 315789.47 | Q20: =O20 -> 315789.47
B21: battery electric vehicle | C21: 787140.4 | D21: =5500000000/14800 -> 371621.62 | E21: ICCT (2023) | L21: Medium Bus | M21: ='Number of Vehicles'!C5 -> 0.074053606 | N21: 958 | O21: =N21*1000000/15200 -> 63026.316 | Q21: =O21 -> 63026.316
B22: natural gas vehicle | C22: 541991.42 | D22: =2007000000/14800 -> 135608.11 | E22: ICCT (2023) | L22: Microbus | M22: ='Number of Vehicles'!C6 -> 0.58828406 | N22: 345 | O22: =N22*1000000/15200 -> 22697.368 | Q22: =O22 -> 22697.368
B23: gasoline vehicle | C23: 425813.12 | D23: =Q23 -> 84353.201 | E23: Weighted average of ICCT (2023)'s Mercedes Benz Diesel Single Bus and ITDP (2023)'s prices | Q23: =SUMPRODUCT(Q19:Q22,M19:M22)/SUM(M19:M22) -> 84353.201
B24: diesel vehicle | C24: 425813.12 | D24: =Q23 -> 84353.201 | E24: Weighted average of ICCT (2023)'s Mercedes Benz Diesel Single Bus and ITDP (2023)'s prices
B25: plugin hybrid vehicle | C25: 624243.15 | D25: =D21 -> 371621.62 | E25: Same as EV
B26: LPG vehicle | C26: 564719.73 | D26: =AVERAGE(D22:D23) -> 109980.65 | E26: Average of NG, gasoline/diesel
B27: hydrogen vehicle | C27: 838135.09 | D27: 1420000 | E27: French 12-metre hydrogen fuel-cell bus (non-Indonesia source)
B30: Indonesia's HDV freight
B32: BNVP-HDVs-frgt | C32: Initial EPS prices | D32: Same as HDV-pasgr
B33: Price ($/vehicle) | C33: 2022 | D33: 2022
B34: battery electric vehicle | C34: 212323.26 | D34: =D21 -> 371621.62
B35: natural gas vehicle | C35: 168589.54 | D35: =D22 -> 135608.11
B36: gasoline vehicle | C36: 116533.08 | D36: =D23 -> 84353.201
B37: diesel vehicle | C37: 116533.08 | D37: =D24 -> 84353.201 | H37: Next steps | I37: The price provided is low for HDVs freight. If we can't find better data, it is recommended using the weighted average data for HDVs passengers
B38: plugin hybrid vehicle | C38: 296290.7 | D38: =D25 -> 371621.62 | I38: Since we couldn't find a better data, I copied and pasted from HDVs-psgr as suggested
B39: LPG vehicle | C39: 167812.53 | D39: =D26 -> 109980.65
B40: hydrogen vehicle | C40: 348292.91 | D40: =D27 -> 1420000
B42: Source:
B43: New trucks can range from around Rp 125 million (Daihatsu Gran Max PU or Tata Super Ace) to over Rp 800 million (Ford Ranger or Isuzu D Max).
B59: Source: https://changing-transport.org/wp-content/uploads/2021_IDN_Truck-Modernisation.pdf
B63: Source: Wangsa et al. (2023) https://doi.org/10.1016/j.cstp.2023.100966
B64: "The optimal tax incentive and subsidy to promote electric trucks in Indonesia: Insight for government and industry"
J68: Electric trucks | K68: =(60800+62900+61200)/3 -> 61633.333
J69: Disel trucks | K69: =(34190+34210+34200)/3 -> 34200
B75: Global Fuel Economy, Indonesia (https://www.globalfueleconomy.org/media/461034/asia_indonesia.pdf)
B76: ICCT Working Paper (https://theicct.org/wp-content/uploads/2023/01/asia-pacific-evs-cco-evs-indonesia-jan23.pdf)
B77: Mitsubishi (https://www.oto.com/en/truk-baru/mitsubishi/colt-fe-shdx)— Rp579 Juta = $36k

Sheet Number of Vehicles
A1: Number of vehicles by HDV category (i.e., Single Bus, Articulated Bus, Medium Bus, and Microbus)
A2: Category | B2: Count | C2: % | D2: Note | E2: Souce Link
A3: Single Bus | B3: 965 | C3: =B3/$B$7 -> 0.26664825 | D3: Jakarta | E3: https://itdp-indonesia.org/wp-content/uploads/2023/05/3.2.-_-3.3.-Transjakarta-E-Bus-Integrated-Long-Term-Implementation-Phase.pdf
A4: Articulated Bus | B4: 257 | C4: =B4/$B$7 -> 0.071014092 | D4: Jakarta | E4: https://itdp-indonesia.org/wp-content/uploads/2023/05/3.2.-_-3.3.-Transjakarta-E-Bus-Integrated-Long-Term-Implementation-Phase.pdf
A5: Medium Bus | B5: 268 | C5: =B5/$B$7 -> 0.074053606 | D5: Jakarta | E5: https://itdp-indonesia.org/wp-content/uploads/2023/05/3.2.-_-3.3.-Transjakarta-E-Bus-Integrated-Long-Term-Implementation-Phase.pdf
A6: Microbus | B6: 2129 | C6: =B6/$B$7 -> 0.58828406 | D6: Jakarta | E6: https://itdp-indonesia.org/wp-content/uploads/2023/05/3.2.-_-3.3.-Transjakarta-E-Bus-Integrated-Long-Term-Implementation-Phase.pdf
A7: Total | B7: =SUM(B3:B6) -> 3619 | C7: =B7/$B$7 -> 1
A9: All buses | B9: 241000 | D9: In 2022, the number of buses in use was roughly 241 thousand units in Indonesia, indicating a steady increase over the last years. Starting in April 2019, old buses in Jakarta, Indonesia, were not allowed to operate anymore as an attempt to reduce the air pollution in Indonesia. | E9: https://www.statista.com/statistics/978937/indonesia-number-of-buses-use/#:~:text=In%202022%2C%20the%20number%20of,increase%20over%20the%20last%20years.
A10: All buses | B10: 271500 | D10: Market forecast | E10: https://www.researchandmarkets.com/reports/5806834/indonesia-bus-industry-research-report?srsltid=AfmBOooC7WdPcPYG8Fzm8pMPRLZvYSE_UKLWn64ooBzzkwRnleggi0Z8
A11: Electric buses | B11: 124 | D11: Only 124 electric buses are being used in urban public transport systems across three cities currently, accounting for just 0.80% of the target the Ministry of Transportation has set for 2030 just a few years from now. | E11: https://itdp.org/2024/07/15/building-momentum-for-transport-electrification-in-indonesia/

Sheet BNVP-LDVs-psgr
A1: Price ($/vehicle) | B1: 2020 | C1: 2021 | D1: 2022 | E1: 2023 | F1: 2024 | G1: 2025 | H1: 2026 | I1: 2027 | J1: 2028 | K1: 2029 | L1: 2030 | M1: 2031 | N1: 2032 | O1: 2033 | P1: 2034 | Q1: 2035 | R1: 2036 | S1: 2037 | T1: 2038 | U1: 2039 | V1: 2040 | W1: 2041 | X1: 2042 | Y1: 2043 | Z1: 2044 | AA1: 2045 | AB1: 2046 | AC1: 2047 | AD1: 2048 | AE1: 2049 | AF1: 2050 | AG1: 2051 | AH1: 2052 | AI1: 2053 | AJ1: 2054 | AK1: 2055 | AL1: 2056 | AM1: 2057 | AN1: 2058 | AO1: 2059 | AP1: 2060 | AQ1: 2061 | AR1: 2062 | AS1: 2063 | AT1: 2064 | AU1: 2065 | AV1: 2066 | AW1: 2067 | AX1: 2068 | AY1: 2069 | AZ1: 2070
A2: battery electric vehicle | B2: =('NVP-Indonesia'!$B$12+'NVP-Indonesia'!$B$12*'NVP-Indonesia'!$B191) -> 21521.202 | C2: =(B2+B2*'NVP-Indonesia'!$B191) -> 21187.654 | D2: =(C2+C2*'NVP-Indonesia'!$B191) -> 20859.276 | E2: =(D2+D2*'NVP-Indonesia'!$B191) -> 20535.987 | F2: =(E2+E2*'NVP-Indonesia'!$B191) -> 20217.709 | G2: =(F2+F2*'NVP-Indonesia'!$B191) -> 19904.364 | H2: =(G2+G2*'NVP-Indonesia'!$B191) -> 19595.875 | I2: =(H2+H2*'NVP-Indonesia'!$B191) -> 19292.167 | J2: =(I2+I2*'NVP-Indonesia'!$B191) -> 18993.166 | ... AZ2: =(AY2+AY2*'NVP-Indonesia'!$B191) -> 9855.6297
A3: natural gas vehicle | B3: =('NVP-Indonesia'!$B$12+'NVP-Indonesia'!$B$12*'NVP-Indonesia'!$B192) -> 21914.895 | C3: =(B3+B3*'NVP-Indonesia'!$B192) -> 21969.927 | D3: =(C3+C3*'NVP-Indonesia'!$B192) -> 22025.098 | E3: =(D3+D3*'NVP-Indonesia'!$B192) -> 22080.407 | F3: =(E3+E3*'NVP-Indonesia'!$B192) -> 22135.855 | G3: =(F3+F3*'NVP-Indonesia'!$B192) -> 22191.443 | H3: =(G3+G3*'NVP-Indonesia'!$B192) -> 22247.17 | I3: =(H3+H3*'NVP-Indonesia'!$B192) -> 22303.037 | J3: =(I3+I3*'NVP-Indonesia'!$B192) -> 22359.044 | ... AZ3: =(AY3+AY3*'NVP-Indonesia'!$B192) -> 24842.82
A4: gasoline vehicle | B4: =('NVP-Indonesia'!$B$12+'NVP-Indonesia'!$B$12*'NVP-Indonesia'!$B193) -> 21864.419 | C4: =(B4+B4*'NVP-Indonesia'!$B193) -> 21868.839 | D4: =(C4+C4*'NVP-Indonesia'!$B193) -> 21873.26 | E4: =(D4+D4*'NVP-Indonesia'!$B193) -> 21877.682 | F4: =(E4+E4*'NVP-Indonesia'!$B193) -> 21882.104 | G4: =(F4+F4*'NVP-Indonesia'!$B193) -> 21886.528 | H4: =(G4+G4*'NVP-Indonesia'!$B193) -> 21890.952 | I4: =(H4+H4*'NVP-Indonesia'!$B193) -> 21895.378 | J4: =(I4+I4*'NVP-Indonesia'!$B193) -> 21899.804 | ... AZ4: =(AY4+AY4*'NVP-Indonesia'!$B193) -> 22086.516
A5: diesel vehicle | B5: =('NVP-Indonesia'!$B$12+'NVP-Indonesia'!$B$12*'NVP-Indonesia'!$B194) -> 21850.328 | C5: =(B5+B5*'NVP-Indonesia'!$B194) -> 21840.66 | D5: =(C5+C5*'NVP-Indonesia'!$B194) -> 21830.996 | E5: =(D5+D5*'NVP-Indonesia'!$B194) -> 21821.337 | F5: =(E5+E5*'NVP-Indonesia'!$B194) -> 21811.682 | G5: =(F5+F5*'NVP-Indonesia'!$B194) -> 21802.031 | H5: =(G5+G5*'NVP-Indonesia'!$B194) -> 21792.384 | I5: =(H5+H5*'NVP-Indonesia'!$B194) -> 21782.742 | J5: =(I5+I5*'NVP-Indonesia'!$B194) -> 21773.104 | ... AZ5: =(AY5+AY5*'NVP-Indonesia'!$B194) -> 21372.133
A6: plugin hybrid vehicle | B6: =('NVP-Indonesia'!$B$12+'NVP-Indonesia'!$B$12*'NVP-Indonesia'!$B195) -> 21890.968 | C6: =(B6+B6*'NVP-Indonesia'!$B195) -> 21921.981 | D6: =(C6+C6*'NVP-Indonesia'!$B195) -> 21953.037 | E6: =(D6+D6*'NVP-Indonesia'!$B195) -> 21984.137 | F6: =(E6+E6*'NVP-Indonesia'!$B195) -> 22015.282 | G6: =(F6+F6*'NVP-Indonesia'!$B195) -> 22046.47 | H6: =(G6+G6*'NVP-Indonesia'!$B195) -> 22077.703 | I6: =(H6+H6*'NVP-Indonesia'!$B195) -> 22108.98 | J6: =(I6+I6*'NVP-Indonesia'!$B195) -> 22140.301 | ... AZ6: =(AY6+AY6*'NVP-Indonesia'!$B195) -> 23496.647
A7: LPG vehicle | B7: =('NVP-Indonesia'!$B$12+'NVP-Indonesia'!$B$12*'NVP-Indonesia'!$B196) -> 21898.341 | C7: =(B7+B7*'NVP-Indonesia'!$B196) -> 21936.748 | D7: =(C7+C7*'NVP-Indonesia'!$B196) -> 21975.224 | E7: =(D7+D7*'NVP-Indonesia'!$B196) -> 22013.766 | F7: =(E7+E7*'NVP-Indonesia'!$B196) -> 22052.376 | G7: =(F7+F7*'NVP-Indonesia'!$B196) -> 22091.054 | H7: =(G7+G7*'NVP-Indonesia'!$B196) -> 22129.8 | I7: =(H7+H7*'NVP-Indonesia'!$B196) -> 22168.614 | J7: =(I7+I7*'NVP-Indonesia'!$B196) -> 22207.496 | ... AZ7: =(AY7+AY7*'NVP-Indonesia'!$B196) -> 23903.615
A8: hydrogen vehicle | B8: =('NVP-Indonesia'!$B$12+'NVP-Indonesia'!$B$12*'NVP-Indonesia'!$B197) -> 21464.221 | C8: =(B8+B8*'NVP-Indonesia'!$B197) -> 21075.607 | D8: =(C8+C8*'NVP-Indonesia'!$B197) -> 20694.029 | E8: =(D8+D8*'NVP-Indonesia'!$B197) -> 20319.36 | F8: =(E8+E8*'NVP-Indonesia'!$B197) -> 19951.474 | G8: =(F8+F8*'NVP-Indonesia'!$B197) -> 19590.249 | H8: =(G8+G8*'NVP-Indonesia'!$B197) -> 19235.563 | I8: =(H8+H8*'NVP-Indonesia'!$B197) -> 18887.3 | J8: =(I8+I8*'NVP-Indonesia'!$B197) -> 18545.342 | ... AZ8: =(AY8+AY8*'NVP-Indonesia'!$B197) -> 8609.2113

Sheet BNVP-LDVs-frgt
A1: Price ($/vehicle) | B1: 2020 | C1: 2021 | D1: 2022 | E1: 2023 | F1: 2024 | G1: 2025 | H1: 2026 | I1: 2027 | J1: 2028 | K1: 2029 | L1: 2030 | M1: 2031 | N1: 2032 | O1: 2033 | P1: 2034 | Q1: 2035 | R1: 2036 | S1: 2037 | T1: 2038 | U1: 2039 | V1: 2040 | W1: 2041 | X1: 2042 | Y1: 2043 | Z1: 2044 | AA1: 2045 | AB1: 2046 | AC1: 2047 | AD1: 2048 | AE1: 2049 | AF1: 2050 | AG1: 2051 | AH1: 2052 | AI1: 2053 | AJ1: 2054 | AK1: 2055 | AL1: 2056 | AM1: 2057 | AN1: 2058 | AO1: 2059 | AP1: 2060 | AQ1: 2061 | AR1: 2062 | AS1: 2063 | AT1: 2064 | AU1: 2065 | AV1: 2066 | AW1: 2067 | AX1: 2068 | AY1: 2069 | AZ1: 2070
A2: battery electric vehicle | B2: ='NVP-Indonesia'!B78*'NVP-Indonesia'!$B$227 -> 58095.337 | C2: 0 | D2: 0 | E2: 0 | F2: 0 | G2: 0 | H2: 0 | I2: 0 | J2: 0 | K2: 0 | L2: 0 | M2: 0 | N2: 0 | O2: 0 | P2: 0 | Q2: 0 | R2: 0 | S2: 0 | T2: 0 | U2: 0 | V2: 0 | W2: 0 | X2: 0 | Y2: 0 | Z2: 0 | AA2: 0 | AB2: 0 | AC2: 0 | AD2: 0 | AE2: 0 | AF2: 0 | AG2: 0 | AH2: 0 | AI2: 0 | AJ2: 0 | AK2: 0 | AL2: 0 | AM2: 0 | AN2: 0 | AO2: 0 | AP2: 0 | AQ2: 0 | AR2: 0 | AS2: 0 | AT2: 0 | AU2: 0 | AV2: 0 | AW2: 0 | AX2: 0 | AY2: 0 | AZ2: 0
A3: natural gas vehicle | B3: ='NVP-Indonesia'!B79*'NVP-Indonesia'!$B$227 -> 40546.809 | C3: ='NVP-Indonesia'!C79*'NVP-Indonesia'!$B$227 -> 40255.116 | D3: ='NVP-Indonesia'!D79*'NVP-Indonesia'!$B$227 -> 40428.95 | E3: ='NVP-Indonesia'!E79*'NVP-Indonesia'!$B$227 -> 40700.245 | F3: ='NVP-Indonesia'!F79*'NVP-Indonesia'!$B$227 -> 40909.339 | G3: ='NVP-Indonesia'!G79*'NVP-Indonesia'!$B$227 -> 41114.274 | H3: ='NVP-Indonesia'!H79*'NVP-Indonesia'!$B$227 -> 41303.342 | I3: ='NVP-Indonesia'!I79*'NVP-Indonesia'!$B$227 -> 41474.586 | ... AZ3: ='NVP-Indonesia'!AZ79*'NVP-Indonesia'!$B$227 -> 45964.038
A4: gasoline vehicle | B4: ='NVP-Indonesia'!B80*'NVP-Indonesia'!$B$227 -> 35674.636 | C4: ='NVP-Indonesia'!C80*'NVP-Indonesia'!$B$227 -> 35674.636 | D4: ='NVP-Indonesia'!D80*'NVP-Indonesia'!$B$227 -> 35674.636 | E4: ='NVP-Indonesia'!E80*'NVP-Indonesia'!$B$227 -> 35674.636 | F4: ='NVP-Indonesia'!F80*'NVP-Indonesia'!$B$227 -> 35674.636 | G4: ='NVP-Indonesia'!G80*'NVP-Indonesia'!$B$227 -> 35674.636 | H4: ='NVP-Indonesia'!H80*'NVP-Indonesia'!$B$227 -> 35674.636 | I4: ='NVP-Indonesia'!I80*'NVP-Indonesia'!$B$227 -> 35674.636 | ... AZ4: ='NVP-Indonesia'!AZ80*'NVP-Indonesia'!$B$227 -> 35674.636
A5: diesel vehicle | B5: ='NVP-Indonesia'!B81*'NVP-Indonesia'!$B$227 -> 39638.484 | C5: ='NVP-Indonesia'!C81*'NVP-Indonesia'!$B$227 -> 39638.484 | D5: ='NVP-Indonesia'!D81*'NVP-Indonesia'!$B$227 -> 39638.484 | E5: ='NVP-Indonesia'!E81*'NVP-Indonesia'!$B$227 -> 39638.484 | F5: ='NVP-Indonesia'!F81*'NVP-Indonesia'!$B$227 -> 39638.484 | G5: ='NVP-Indonesia'!G81*'NVP-Indonesia'!$B$227 -> 39638.484 | H5: ='NVP-Indonesia'!H81*'NVP-Indonesia'!$B$227 -> 39638.484 | I5: ='NVP-Indonesia'!I81*'NVP-Indonesia'!$B$227 -> 39638.484 | ... AZ5: ='NVP-Indonesia'!AZ81*'NVP-Indonesia'!$B$227 -> 39638.484
A6: plugin hybrid vehicle | B6: ='NVP-Indonesia'!B82*'NVP-Indonesia'!$B$227 -> 40685.859 | C6: ='NVP-Indonesia'!C82*'NVP-Indonesia'!$B$227 -> 41242.058 | D6: ='NVP-Indonesia'!D82*'NVP-Indonesia'!$B$227 -> 41182.553 | E6: ='NVP-Indonesia'!E82*'NVP-Indonesia'!$B$227 -> 41385.132 | F6: ='NVP-Indonesia'!F82*'NVP-Indonesia'!$B$227 -> 41430.439 | G6: ='NVP-Indonesia'!G82*'NVP-Indonesia'!$B$227 -> 41553.938 | H6: ='NVP-Indonesia'!H82*'NVP-Indonesia'!$B$227 -> 41604.402 | I6: ='NVP-Indonesia'!I82*'NVP-Indonesia'!$B$227 -> 41633.147 | ... AZ6: ='NVP-Indonesia'!AZ82*'NVP-Indonesia'!$B$227 -> 43670.122
A7: LPG vehicle | B7: ='NVP-Indonesia'!B83*'NVP-Indonesia'!$B$227 -> 39630.84 | C7: ='NVP-Indonesia'!C83*'NVP-Indonesia'!$B$227 -> 40279.913 | D7: ='NVP-Indonesia'!D83*'NVP-Indonesia'!$B$227 -> 40242.618 | E7: ='NVP-Indonesia'!E83*'NVP-Indonesia'!$B$227 -> 40312.727 | F7: ='NVP-Indonesia'!F83*'NVP-Indonesia'!$B$227 -> 40407.796 | G7: ='NVP-Indonesia'!G83*'NVP-Indonesia'!$B$227 -> 40584.919 | H7: ='NVP-Indonesia'!H83*'NVP-Indonesia'!$B$227 -> 40732.9 | I7: ='NVP-Indonesia'!I83*'NVP-Indonesia'!$B$227 -> 40808.85 | ... AZ7: ='NVP-Indonesia'!AZ83*'NVP-Indonesia'!$B$227 -> 43259.916
A8: hydrogen vehicle | B8: ='NVP-Indonesia'!B84*'NVP-Indonesia'!$B$227 -> 72784.944 | C8: ='NVP-Indonesia'!C84*'NVP-Indonesia'!$B$227 -> 72769.113 | D8: ='NVP-Indonesia'!D84*'NVP-Indonesia'!$B$227 -> 71195.128 | E8: ='NVP-Indonesia'!E84*'NVP-Indonesia'!$B$227 -> 69809.534 | F8: ='NVP-Indonesia'!F84*'NVP-Indonesia'!$B$227 -> 68409.935 | G8: ='NVP-Indonesia'!G84*'NVP-Indonesia'!$B$227 -> 66961.263 | H8: ='NVP-Indonesia'!H84*'NVP-Indonesia'!$B$227 -> 65688.591 | I8: ='NVP-Indonesia'!I84*'NVP-Indonesia'!$B$227 -> 64517.35 | ... AZ8: ='NVP-Indonesia'!AZ84*'NVP-Indonesia'!$B$227 -> 29193.744

Sheet BNVP-HDVs-psgr
A1: Price ($/vehicle) | B1: 2020 | C1: 2021 | D1: 2022 | E1: 2023 | F1: 2024 | G1: 2025 | H1: 2026 | I1: 2027 | J1: 2028 | K1: 2029 | L1: 2030 | M1: 2031 | N1: 2032 | O1: 2033 | P1: 2034 | Q1: 2035 | R1: 2036 | S1: 2037 | T1: 2038 | U1: 2039 | V1: 2040 | W1: 2041 | X1: 2042 | Y1: 2043 | Z1: 2044 | AA1: 2045 | AB1: 2046 | AC1: 2047 | AD1: 2048 | AE1: 2049 | AF1: 2050 | AG1: 2051 | AH1: 2052 | AI1: 2053 | AJ1: 2054 | AK1: 2055 | AL1: 2056 | AM1: 2057 | AN1: 2058 | AO1: 2059 | AP1: 2060 | AQ1: 2061 | AR1: 2062 | AS1: 2063 | AT1: 2064 | AU1: 2065 | AV1: 2066 | AW1: 2067 | AX1: 2068 | AY1: 2069 | AZ1: 2070
A2: battery electric vehicle | B2: ='Indonesia - HDV '!D34 -> 371621.62 | C2: =0 -> 0 | D2: =C2+C2*'NVP-Indonesia'!C202 -> 0 | E2: =D2+D2*'NVP-Indonesia'!D202 -> 0 | F2: =E2+E2*'NVP-Indonesia'!E202 -> 0 | G2: =F2+F2*'NVP-Indonesia'!F202 -> 0 | H2: =G2+G2*'NVP-Indonesia'!G202 -> 0 | I2: =H2+H2*'NVP-Indonesia'!H202 -> 0 | J2: =I2+I2*'NVP-Indonesia'!I202 -> 0 | K2: =J2+J2*'NVP-Indonesia'!J202 -> 0 | ... AZ2: =AY2+AY2*'NVP-Indonesia'!AY202 -> 0
A3: natural gas vehicle | B3: ='Indonesia - HDV '!D35 -> 135608.11 | C3: =B3+B3*'NVP-Indonesia'!B203 -> 135948.65 | D3: =C3+C3*'NVP-Indonesia'!C203 -> 135948.65 | E3: =D3+D3*'NVP-Indonesia'!D203 -> 135948.65 | F3: =E3+E3*'NVP-Indonesia'!E203 -> 135948.65 | G3: =F3+F3*'NVP-Indonesia'!F203 -> 135948.65 | H3: =G3+G3*'NVP-Indonesia'!G203 -> 135948.65 | I3: =H3+H3*'NVP-Indonesia'!H203 -> 135948.65 | J3: =I3+I3*'NVP-Indonesia'!I203 -> 135948.65 | ... AZ3: =AY3+AY3*'NVP-Indonesia'!AY203 -> 135948.65
A4: gasoline vehicle | B4: ='Indonesia - HDV '!D36 -> 84353.201 | C4: =B4+B4*'NVP-Indonesia'!B204 -> 84353.201 | D4: =C4+C4*'NVP-Indonesia'!C204 -> 84353.201 | E4: =D4+D4*'NVP-Indonesia'!D204 -> 84353.201 | F4: =E4+E4*'NVP-Indonesia'!E204 -> 84353.201 | G4: =F4+F4*'NVP-Indonesia'!F204 -> 84353.201 | H4: =G4+G4*'NVP-Indonesia'!G204 -> 84353.201 | I4: =H4+H4*'NVP-Indonesia'!H204 -> 84353.201 | J4: =I4+I4*'NVP-Indonesia'!I204 -> 84353.201 | ... AZ4: =AY4+AY4*'NVP-Indonesia'!AY204 -> 84353.201
A5: diesel vehicle | B5: ='Indonesia - HDV '!D37 -> 84353.201 | C5: =B5+B5*'NVP-Indonesia'!B205 -> 84353.201 | D5: =C5+C5*'NVP-Indonesia'!C205 -> 84353.201 | E5: =D5+D5*'NVP-Indonesia'!D205 -> 84353.201 | F5: =E5+E5*'NVP-Indonesia'!E205 -> 84353.201 | G5: =F5+F5*'NVP-Indonesia'!F205 -> 84353.201 | H5: =G5+G5*'NVP-Indonesia'!G205 -> 84353.201 | I5: =H5+H5*'NVP-Indonesia'!H205 -> 84353.201 | J5: =I5+I5*'NVP-Indonesia'!I205 -> 84353.201 | ... AZ5: =AY5+AY5*'NVP-Indonesia'!AY205 -> 84353.201
A6: plugin hybrid vehicle | B6: ='Indonesia - HDV '!D38 -> 371621.62 | C6: =B6+B6*'NVP-Indonesia'!B206 -> 372148.09 | D6: =C6+C6*'NVP-Indonesia'!C206 -> 372148.09 | E6: =D6+D6*'NVP-Indonesia'!D206 -> 372148.09 | F6: =E6+E6*'NVP-Indonesia'!E206 -> 372148.09 | G6: =F6+F6*'NVP-Indonesia'!F206 -> 372148.09 | H6: =G6+G6*'NVP-Indonesia'!G206 -> 372148.09 | I6: =H6+H6*'NVP-Indonesia'!H206 -> 372148.09 | J6: =I6+I6*'NVP-Indonesia'!I206 -> 372148.09 | ... AZ6: =AY6+AY6*'NVP-Indonesia'!AY206 -> 372148.09
A7: LPG vehicle | B7: ='Indonesia - HDV '!D39 -> 109980.65 | C7: =B7+B7*'NVP-Indonesia'!B207 -> 110173.55 | D7: =C7+C7*'NVP-Indonesia'!C207 -> 110173.55 | E7: =D7+D7*'NVP-Indonesia'!D207 -> 110173.55 | F7: =E7+E7*'NVP-Indonesia'!E207 -> 110173.55 | G7: =F7+F7*'NVP-Indonesia'!F207 -> 110173.55 | H7: =G7+G7*'NVP-Indonesia'!G207 -> 110173.55 | I7: =H7+H7*'NVP-Indonesia'!H207 -> 110173.55 | J7: =I7+I7*'NVP-Indonesia'!I207 -> 110173.55 | ... AZ7: =AY7+AY7*'NVP-Indonesia'!AY207 -> 110173.55
A8: hydrogen vehicle | B8: ='Indonesia - HDV '!D40 -> 1420000 | C8: =B8+B8*'NVP-Indonesia'!B208 -> 1394290.6 | D8: =C8+C8*'NVP-Indonesia'!C208 -> 1394290.6 | E8: =D8+D8*'NVP-Indonesia'!D208 -> 1394290.6 | F8: =E8+E8*'NVP-Indonesia'!E208 -> 1394290.6 | G8: =F8+F8*'NVP-Indonesia'!F208 -> 1394290.6 | H8: =G8+G8*'NVP-Indonesia'!G208 -> 1394290.6 | I8: =H8+H8*'NVP-Indonesia'!H208 -> 1394290.6 | J8: =I8+I8*'NVP-Indonesia'!I208 -> 1394290.6 | ... AZ8: =AY8+AY8*'NVP-Indonesia'!AY208 -> 1394290.6

Sheet BNVP-HDVs-frgt
A1: Price ($/vehicle) | B1: 2020 | C1: 2021 | D1: 2022 | E1: 2023 | F1: 2024 | G1: 2025 | H1: 2026 | I1: 2027 | J1: 2028 | K1: 2029 | L1: 2030 | M1: 2031 | N1: 2032 | O1: 2033 | P1: 2034 | Q1: 2035 | R1: 2036 | S1: 2037 | T1: 2038 | U1: 2039 | V1: 2040 | W1: 2041 | X1: 2042 | Y1: 2043 | Z1: 2044 | AA1: 2045 | AB1: 2046 | AC1: 2047 | AD1: 2048 | AE1: 2049 | AF1: 2050 | AG1: 2051 | AH1: 2052 | AI1: 2053 | AJ1: 2054 | AK1: 2055 | AL1: 2056 | AM1: 2057 | AN1: 2058 | AO1: 2059 | AP1: 2060 | AQ1: 2061 | AR1: 2062 | AS1: 2063 | AT1: 2064 | AU1: 2065 | AV1: 2066 | AW1: 2067 | AX1: 2068 | AY1: 2069 | AZ1: 2070
A2: battery electric vehicle | B2: ='Indonesia - HDV '!D34 -> 371621.62 | C2: 0 | D2: 0 | E2: 0 | F2: 0 | G2: 0 | H2: 0 | I2: 0 | J2: 0 | K2: 0 | L2: 0 | M2: 0 | N2: 0 | O2: 0 | P2: 0 | Q2: 0 | R2: 0 | S2: 0 | T2: 0 | U2: 0 | V2: 0 | W2: 0 | X2: 0 | Y2: 0 | Z2: 0 | AA2: 0 | AB2: 0 | AC2: 0 | AD2: 0 | AE2: 0 | AF2: 0 | AG2: 0 | AH2: 0 | AI2: 0 | AJ2: 0 | AK2: 0 | AL2: 0 | AM2: 0 | AN2: 0 | AO2: 0 | AP2: 0 | AQ2: 0 | AR2: 0 | AS2: 0 | AT2: 0 | AU2: 0 | AV2: 0 | AW2: 0 | AX2: 0 | AY2: 0 | AZ2: 0
A3: natural gas vehicle | B3: ='Indonesia - HDV '!D35 -> 135608.11 | C3: =B3 -> 135608.11 | D3: =C3 -> 135608.11 | E3: =D3 -> 135608.11 | F3: =E3 -> 135608.11 | G3: =F3 -> 135608.11 | H3: =G3 -> 135608.11 | I3: =H3 -> 135608.11 | J3: =I3 -> 135608.11 | ... AZ3: =AY3 -> 135608.11
A4: gasoline vehicle | B4: ='NVP-Indonesia'!B100*'NVP-Indonesia'!$B$227 -> 90895.799 | C4: ='NVP-Indonesia'!C100*'NVP-Indonesia'!$B$227 -> 90895.799 | D4: ='NVP-Indonesia'!D100*'NVP-Indonesia'!$B$227 -> 90895.799 | E4: ='NVP-Indonesia'!E100*'NVP-Indonesia'!$B$227 -> 90895.799 | F4: ='NVP-Indonesia'!F100*'NVP-Indonesia'!$B$227 -> 90895.799 | G4: ='NVP-Indonesia'!G100*'NVP-Indonesia'!$B$227 -> 90895.799 | H4: ='NVP-Indonesia'!H100*'NVP-Indonesia'!$B$227 -> 90895.799 | I4: ='NVP-Indonesia'!I100*'NVP-Indonesia'!$B$227 -> 90895.799 | ... AZ4: ='NVP-Indonesia'!AZ100*'NVP-Indonesia'!$B$227 -> 90895.799
A5: diesel vehicle | B5: ='NVP-Indonesia'!B101*'NVP-Indonesia'!$B$227 -> 90895.799 | C5: ='NVP-Indonesia'!C101*'NVP-Indonesia'!$B$227 -> 90895.799 | D5: ='NVP-Indonesia'!D101*'NVP-Indonesia'!$B$227 -> 90895.799 | E5: ='NVP-Indonesia'!E101*'NVP-Indonesia'!$B$227 -> 90895.799 | F5: ='NVP-Indonesia'!F101*'NVP-Indonesia'!$B$227 -> 90895.799 | G5: ='NVP-Indonesia'!G101*'NVP-Indonesia'!$B$227 -> 90895.799 | H5: ='NVP-Indonesia'!H101*'NVP-Indonesia'!$B$227 -> 90895.799 | I5: ='NVP-Indonesia'!I101*'NVP-Indonesia'!$B$227 -> 90895.799 | ... AZ5: ='NVP-Indonesia'!AZ101*'NVP-Indonesia'!$B$227 -> 90895.799
A6: plugin hybrid vehicle | B6: ='Indonesia - HDV '!D38 -> 371621.62 | C6: =B6 -> 371621.62 | D6: =C6 -> 371621.62 | E6: =D6 -> 371621.62 | F6: =E6 -> 371621.62 | G6: =F6 -> 371621.62 | H6: =G6 -> 371621.62 | I6: =H6 -> 371621.62 | J6: =I6 -> 371621.62 | ... AZ6: =AY6 -> 371621.62
A7: LPG vehicle | B7: ='NVP-Indonesia'!B103*'NVP-Indonesia'!$B$227 -> 128903.9 | C7: =B7 -> 128903.9 | D7: =C7 -> 128903.9 | E7: =D7 -> 128903.9 | F7: =E7 -> 128903.9 | G7: =F7 -> 128903.9 | H7: =G7 -> 128903.9 | I7: =H7 -> 128903.9 | J7: =I7 -> 128903.9 | ... AZ7: =AY7 -> 128903.9
A8: hydrogen vehicle | B8: ='Indonesia - HDV '!D40 -> 1420000 | C8: =B8 -> 1420000 | D8: =C8 -> 1420000 | E8: =D8 -> 1420000 | F8: =E8 -> 1420000 | G8: =F8 -> 1420000 | H8: =G8 -> 1420000 | I8: =H8 -> 1420000 | J8: =I8 -> 1420000 | ... AZ8: =AY8 -> 1420000

Sheet BNVP-aircraft-psgr
A1: Price ($/vehicle) | B1: 2020 | C1: 2021 | D1: 2022 | E1: 2023 | F1: 2024 | G1: 2025 | H1: 2026 | I1: 2027 | J1: 2028 | K1: 2029 | L1: 2030 | M1: 2031 | N1: 2032 | O1: 2033 | P1: 2034 | Q1: 2035 | R1: 2036 | S1: 2037 | T1: 2038 | U1: 2039 | V1: 2040 | W1: 2041 | X1: 2042 | Y1: 2043 | Z1: 2044 | AA1: 2045 | AB1: 2046 | AC1: 2047 | AD1: 2048 | AE1: 2049 | AF1: 2050 | AG1: 2051 | AH1: 2052 | AI1: 2053 | AJ1: 2054 | AK1: 2055 | AL1: 2056 | AM1: 2057 | AN1: 2058 | AO1: 2059 | AP1: 2060 | AQ1: 2061 | AR1: 2062 | AS1: 2063 | AT1: 2064 | AU1: 2065 | AV1: 2066 | AW1: 2067 | AX1: 2068 | AY1: 2069 | AZ1: 2070
A2: battery electric vehicle | B2: ='NVP-Indonesia'!B108*'NVP-Indonesia'!$B$227 -> 93481595 | C2: 0 | D2: =C2 -> 0 | E2: =D2 -> 0 | F2: =E2 -> 0 | G2: =F2 -> 0 | H2: =G2 -> 0 | I2: =H2 -> 0 | J2: =I2 -> 0 | K2: =J2 -> 0 | ... AZ2: =AY2 -> 0
A3: natural gas vehicle | B3: 999999999 | C3: 999999999 | D3: 999999999 | E3: 999999999 | F3: 999999999 | G3: 999999999 | H3: 999999999 | I3: 999999999 | J3: 999999999 | K3: 999999999 | L3: 999999999 | M3: 999999999 | N3: 999999999 | O3: 999999999 | P3: 999999999 | Q3: 999999999 | R3: 999999999 | S3: 999999999 | T3: 999999999 | U3: 999999999 | V3: 999999999 | W3: 999999999 | X3: 999999999 | Y3: 999999999 | Z3: 999999999 | AA3: 999999999 | AB3: 999999999 | AC3: 999999999 | AD3: 999999999 | AE3: 999999999 | AF3: 999999999 | AG3: 999999999 | AH3: 999999999 | AI3: 999999999 | AJ3: 999999999 | AK3: 999999999 | AL3: 999999999 | AM3: 999999999 | AN3: 999999999 | AO3: 999999999 | AP3: 999999999 | AQ3: 999999999 | AR3: 999999999 | AS3: 999999999 | AT3: 999999999 | AU3: 999999999 | AV3: 999999999 | AW3: 999999999 | AX3: 999999999 | AY3: 999999999 | AZ3: 999999999
A4: gasoline vehicle | B4: 999999999 | C4: 999999999 | D4: 999999999 | E4: 999999999 | F4: 999999999 | G4: 999999999 | H4: 999999999 | I4: 999999999 | J4: 999999999 | K4: 999999999 | L4: 999999999 | M4: 999999999 | N4: 999999999 | O4: 999999999 | P4: 999999999 | Q4: 999999999 | R4: 999999999 | S4: 999999999 | T4: 999999999 | U4: 999999999 | V4: 999999999 | W4: 999999999 | X4: 999999999 | Y4: 999999999 | Z4: 999999999 | AA4: 999999999 | AB4: 999999999 | AC4: 999999999 | AD4: 999999999 | AE4: 999999999 | AF4: 999999999 | AG4: 999999999 | AH4: 999999999 | AI4: 999999999 | AJ4: 999999999 | AK4: 999999999 | AL4: 999999999 | AM4: 999999999 | AN4: 999999999 | AO4: 999999999 | AP4: 999999999 | AQ4: 999999999 | AR4: 999999999 | AS4: 999999999 | AT4: 999999999 | AU4: 999999999 | AV4: 999999999 | AW4: 999999999 | AX4: 999999999 | AY4: 999999999 | AZ4: 999999999
A5: diesel vehicle | B5: ='NVP-Indonesia'!B111*'NVP-Indonesia'!$B$227 -> 50570000 | C5: =$B5 -> 50570000 | D5: =$B5 -> 50570000 | E5: =$B5 -> 50570000 | F5: =$B5 -> 50570000 | G5: =$B5 -> 50570000 | H5: =$B5 -> 50570000 | I5: =$B5 -> 50570000 | J5: =$B5 -> 50570000 | ... AF5: =$B5 -> 50570000 | AG5: =_xlfn.FORECAST.LINEAR(AG$1,$B5:$AF5,$B$1:$AF$1) -> 50570000 | AH5: =_xlfn.FORECAST.LINEAR(AH$1,$B5:$AF5,$B$1:$AF$1) -> 50570000 | AI5: =_xlfn.FORECAST.LINEAR(AI$1,$B5:$AF5,$B$1:$AF$1) -> 50570000 | AJ5: =_xlfn.FORECAST.LINEAR(AJ$1,$B5:$AF5,$B$1:$AF$1) -> 50570000 | AK5: =_xlfn.FORECAST.LINEAR(AK$1,$B5:$AF5,$B$1:$AF$1) -> 50570000 | AL5: =_xlfn.FORECAST.LINEAR(AL$1,$B5:$AF5,$B$1:$AF$1) -> 50570000 | AM5: =_xlfn.FORECAST.LINEAR(AM$1,$B5:$AF5,$B$1:$AF$1) -> 50570000 | AN5: =_xlfn.FORECAST.LINEAR(AN$1,$B5:$AF5,$B$1:$AF$1) -> 50570000 | ... AZ5: =_xlfn.FORECAST.LINEAR(AZ$1,$B5:$AF5,$B$1:$AF$1) -> 50570000
A6: plugin hybrid vehicle | B6: 999999999 | C6: 999999999 | D6: 999999999 | E6: 999999999 | F6: 999999999 | G6: 999999999 | H6: 999999999 | I6: 999999999 | J6: 999999999 | K6: 999999999 | L6: 999999999 | M6: 999999999 | N6: 999999999 | O6: 999999999 | P6: 999999999 | Q6: 999999999 | R6: 999999999 | S6: 999999999 | T6: 999999999 | U6: 999999999 | V6: 999999999 | W6: 999999999 | X6: 999999999 | Y6: 999999999 | Z6: 999999999 | AA6: 999999999 | AB6: 999999999 | AC6: 999999999 | AD6: 999999999 | AE6: 999999999 | AF6: 999999999 | AG6: 999999999 | AH6: 999999999 | AI6: 999999999 | AJ6: 999999999 | AK6: 999999999 | AL6: 999999999 | AM6: 999999999 | AN6: 999999999 | AO6: 999999999 | AP6: 999999999 | AQ6: 999999999 | AR6: 999999999 | AS6: 999999999 | AT6: 999999999 | AU6: 999999999 | AV6: 999999999 | AW6: 999999999 | AX6: 999999999 | AY6: 999999999 | AZ6: 999999999
A7: LPG vehicle | B7: 999999999 | C7: 999999999 | D7: 999999999 | E7: 999999999 | F7: 999999999 | G7: 999999999 | H7: 999999999 | I7: 999999999 | J7: 999999999 | K7: 999999999 | L7: 999999999 | M7: 999999999 | N7: 999999999 | O7: 999999999 | P7: 999999999 | Q7: 999999999 | R7: 999999999 | S7: 999999999 | T7: 999999999 | U7: 999999999 | V7: 999999999 | W7: 999999999 | X7: 999999999 | Y7: 999999999 | Z7: 999999999 | AA7: 999999999 | AB7: 999999999 | AC7: 999999999 | AD7: 999999999 | AE7: 999999999 | AF7: 999999999 | AG7: 999999999 | AH7: 999999999 | AI7: 999999999 | AJ7: 999999999 | AK7: 999999999 | AL7: 999999999 | AM7: 999999999 | AN7: 999999999 | AO7: 999999999 | AP7: 999999999 | AQ7: 999999999 | AR7: 999999999 | AS7: 999999999 | AT7: 999999999 | AU7: 999999999 | AV7: 999999999 | AW7: 999999999 | AX7: 999999999 | AY7: 999999999 | AZ7: 999999999
A8: hydrogen vehicle | B8: ='NVP-Indonesia'!B114*'NVP-Indonesia'!$B$227 -> 1.017605e+08 | C8: =B8 -> 1.017605e+08 | D8: =C8 -> 1.017605e+08 | E8: =D8 -> 1.017605e+08 | F8: =E8 -> 1.017605e+08 | G8: =F8 -> 1.017605e+08 | H8: =G8 -> 1.017605e+08 | I8: =H8 -> 1.017605e+08 | J8: =I8 -> 1.017605e+08 | ... AZ8: =AY8 -> 1.017605e+08

Sheet BNVP-rail-psgr
A1: Price ($/vehicle) | B1: 2020 | C1: 2021 | D1: 2022 | E1: 2023 | F1: 2024 | G1: 2025 | H1: 2026 | I1: 2027 | J1: 2028 | K1: 2029 | L1: 2030 | M1: 2031 | N1: 2032 | O1: 2033 | P1: 2034 | Q1: 2035 | R1: 2036 | S1: 2037 | T1: 2038 | U1: 2039 | V1: 2040 | W1: 2041 | X1: 2042 | Y1: 2043 | Z1: 2044 | AA1: 2045 | AB1: 2046 | AC1: 2047 | AD1: 2048 | AE1: 2049 | AF1: 2050 | AG1: 2051 | AH1: 2052 | AI1: 2053 | AJ1: 2054 | AK1: 2055 | AL1: 2056 | AM1: 2057 | AN1: 2058 | AO1: 2059 | AP1: 2060 | AQ1: 2061 | AR1: 2062 | AS1: 2063 | AT1: 2064 | AU1: 2065 | AV1: 2066 | AW1: 2067 | AX1: 2068 | AY1: 2069 | AZ1: 2070
A2: battery electric vehicle | B2: ='NVP-Indonesia'!B118*'NVP-Indonesia'!$B$227 -> 3250000 | C2: 0 | D2: =C2 -> 0 | E2: =D2 -> 0 | F2: =E2 -> 0 | G2: =F2 -> 0 | H2: =G2 -> 0 | I2: =H2 -> 0 | J2: =I2 -> 0 | K2: =J2 -> 0 | ... AZ2: =AY2 -> 0
A3: natural gas vehicle | B3: 999999999 | C3: 999999999 | D3: 999999999 | E3: 999999999 | F3: 999999999 | G3: 999999999 | H3: 999999999 | I3: 999999999 | J3: 999999999 | K3: 999999999 | L3: 999999999 | M3: 999999999 | N3: 999999999 | O3: 999999999 | P3: 999999999 | Q3: 999999999 | R3: 999999999 | S3: 999999999 | T3: 999999999 | U3: 999999999 | V3: 999999999 | W3: 999999999 | X3: 999999999 | Y3: 999999999 | Z3: 999999999 | AA3: 999999999 | AB3: 999999999 | AC3: 999999999 | AD3: 999999999 | AE3: 999999999 | AF3: 999999999 | AG3: 999999999 | AH3: 999999999 | AI3: 999999999 | AJ3: 999999999 | AK3: 999999999 | AL3: 999999999 | AM3: 999999999 | AN3: 999999999 | AO3: 999999999 | AP3: 999999999 | AQ3: 999999999 | AR3: 999999999 | AS3: 999999999 | AT3: 999999999 | AU3: 999999999 | AV3: 999999999 | AW3: 999999999 | AX3: 999999999 | AY3: 999999999 | AZ3: 999999999
A4: gasoline vehicle | B4: 999999999 | C4: 999999999 | D4: 999999999 | E4: 999999999 | F4: 999999999 | G4: 999999999 | H4: 999999999 | I4: 999999999 | J4: 999999999 | K4: 999999999 | L4: 999999999 | M4: 999999999 | N4: 999999999 | O4: 999999999 | P4: 999999999 | Q4: 999999999 | R4: 999999999 | S4: 999999999 | T4: 999999999 | U4: 999999999 | V4: 999999999 | W4: 999999999 | X4: 999999999 | Y4: 999999999 | Z4: 999999999 | AA4: 999999999 | AB4: 999999999 | AC4: 999999999 | AD4: 999999999 | AE4: 999999999 | AF4: 999999999 | AG4: 999999999 | AH4: 999999999 | AI4: 999999999 | AJ4: 999999999 | AK4: 999999999 | AL4: 999999999 | AM4: 999999999 | AN4: 999999999 | AO4: 999999999 | AP4: 999999999 | AQ4: 999999999 | AR4: 999999999 | AS4: 999999999 | AT4: 999999999 | AU4: 999999999 | AV4: 999999999 | AW4: 999999999 | AX4: 999999999 | AY4: 999999999 | AZ4: 999999999
A5: diesel vehicle | B5: ='NVP-Indonesia'!B121*'NVP-Indonesia'!$B$227 -> 1751206.9 | C5: =$B5 -> 1751206.9 | D5: =$B5 -> 1751206.9 | E5: =$B5 -> 1751206.9 | F5: =$B5 -> 1751206.9 | G5: =$B5 -> 1751206.9 | H5: =$B5 -> 1751206.9 | I5: =$B5 -> 1751206.9 | J5: =$B5 -> 1751206.9 | ... AF5: =$B5 -> 1751206.9 | AG5: =_xlfn.FORECAST.LINEAR(AG$1,$B5:$AF5,$B$1:$AF$1) -> 1751206.9 | AH5: =_xlfn.FORECAST.LINEAR(AH$1,$B5:$AF5,$B$1:$AF$1) -> 1751206.9 | AI5: =_xlfn.FORECAST.LINEAR(AI$1,$B5:$AF5,$B$1:$AF$1) -> 1751206.9 | AJ5: =_xlfn.FORECAST.LINEAR(AJ$1,$B5:$AF5,$B$1:$AF$1) -> 1751206.9 | AK5: =_xlfn.FORECAST.LINEAR(AK$1,$B5:$AF5,$B$1:$AF$1) -> 1751206.9 | AL5: =_xlfn.FORECAST.LINEAR(AL$1,$B5:$AF5,$B$1:$AF$1) -> 1751206.9 | AM5: =_xlfn.FORECAST.LINEAR(AM$1,$B5:$AF5,$B$1:$AF$1) -> 1751206.9 | AN5: =_xlfn.FORECAST.LINEAR(AN$1,$B5:$AF5,$B$1:$AF$1) -> 1751206.9 | ... AZ5: =_xlfn.FORECAST.LINEAR(AZ$1,$B5:$AF5,$B$1:$AF$1) -> 1751206.9
A6: plugin hybrid vehicle | B6: 999999999 | C6: 999999999 | D6: 999999999 | E6: 999999999 | F6: 999999999 | G6: 999999999 | H6: 999999999 | I6: 999999999 | J6: 999999999 | K6: 999999999 | L6: 999999999 | M6: 999999999 | N6: 999999999 | O6: 999999999 | P6: 999999999 | Q6: 999999999 | R6: 999999999 | S6: 999999999 | T6: 999999999 | U6: 999999999 | V6: 999999999 | W6: 999999999 | X6: 999999999 | Y6: 999999999 | Z6: 999999999 | AA6: 999999999 | AB6: 999999999 | AC6: 999999999 | AD6: 999999999 | AE6: 999999999 | AF6: 999999999 | AG6: 999999999 | AH6: 999999999 | AI6: 999999999 | AJ6: 999999999 | AK6: 999999999 | AL6: 999999999 | AM6: 999999999 | AN6: 999999999 | AO6: 999999999 | AP6: 999999999 | AQ6: 999999999 | AR6: 999999999 | AS6: 999999999 | AT6: 999999999 | AU6: 999999999 | AV6: 999999999 | AW6: 999999999 | AX6: 999999999 | AY6: 999999999 | AZ6: 999999999
A7: LPG vehicle | B7: 999999999 | C7: 999999999 | D7: 999999999 | E7: 999999999 | F7: 999999999 | G7: 999999999 | H7: 999999999 | I7: 999999999 | J7: 999999999 | K7: 999999999 | L7: 999999999 | M7: 999999999 | N7: 999999999 | O7: 999999999 | P7: 999999999 | Q7: 999999999 | R7: 999999999 | S7: 999999999 | T7: 999999999 | U7: 999999999 | V7: 999999999 | W7: 999999999 | X7: 999999999 | Y7: 999999999 | Z7: 999999999 | AA7: 999999999 | AB7: 999999999 | AC7: 999999999 | AD7: 999999999 | AE7: 999999999 | AF7: 999999999 | AG7: 999999999 | AH7: 999999999 | AI7: 999999999 | AJ7: 999999999 | AK7: 999999999 | AL7: 999999999 | AM7: 999999999 | AN7: 999999999 | AO7: 999999999 | AP7: 999999999 | AQ7: 999999999 | AR7: 999999999 | AS7: 999999999 | AT7: 999999999 | AU7: 999999999 | AV7: 999999999 | AW7: 999999999 | AX7: 999999999 | AY7: 999999999 | AZ7: 999999999
A8: hydrogen vehicle | B8: ='NVP-Indonesia'!B124*'NVP-Indonesia'!$B$227 -> 2311593.1 | C8: =$B$8*'BNVP-HDVs-frgt'!C8/'BNVP-HDVs-frgt'!$B$8 -> 2311593.1 | D8: =$B$8*'BNVP-HDVs-frgt'!D8/'BNVP-HDVs-frgt'!$B$8 -> 2311593.1 | E8: =$B$8*'BNVP-HDVs-frgt'!E8/'BNVP-HDVs-frgt'!$B$8 -> 2311593.1 | F8: =$B$8*'BNVP-HDVs-frgt'!F8/'BNVP-HDVs-frgt'!$B$8 -> 2311593.1 | G8: =$B$8*'BNVP-HDVs-frgt'!G8/'BNVP-HDVs-frgt'!$B$8 -> 2311593.1 | H8: =$B$8*'BNVP-HDVs-frgt'!H8/'BNVP-HDVs-frgt'!$B$8 -> 2311593.1 | I8: =$B$8*'BNVP-HDVs-frgt'!I8/'BNVP-HDVs-frgt'!$B$8 -> 2311593.1 | J8: =$B$8*'BNVP-HDVs-frgt'!J8/'BNVP-HDVs-frgt'!$B$8 -> 2311593.1 | ... AF8: =$B$8*'BNVP-HDVs-frgt'!AF8/'BNVP-HDVs-frgt'!$B$8 -> 2311593.1 | AG8: =_xlfn.FORECAST.LINEAR(AG$1,$B8:$AF8,$B$1:$AF$1) -> 2311593.1 | AH8: =_xlfn.FORECAST.LINEAR(AH$1,$B8:$AF8,$B$1:$AF$1) -> 2311593.1 | AI8: =_xlfn.FORECAST.LINEAR(AI$1,$B8:$AF8,$B$1:$AF$1) -> 2311593.1 | AJ8: =_xlfn.FORECAST.LINEAR(AJ$1,$B8:$AF8,$B$1:$AF$1) -> 2311593.1 | AK8: =_xlfn.FORECAST.LINEAR(AK$1,$B8:$AF8,$B$1:$AF$1) -> 2311593.1 | AL8: =_xlfn.FORECAST.LINEAR(AL$1,$B8:$AF8,$B$1:$AF$1) -> 2311593.1 | AM8: =_xlfn.FORECAST.LINEAR(AM$1,$B8:$AF8,$B$1:$AF$1) -> 2311593.1 | AN8: =_xlfn.FORECAST.LINEAR(AN$1,$B8:$AF8,$B$1:$AF$1) -> 2311593.1 | ... AZ8: =_xlfn.FORECAST.LINEAR(AZ$1,$B8:$AF8,$B$1:$AF$1) -> 2311593.1

Sheet BNVP-aircraft-frgt
A1: Price ($/vehicle) | B1: 2020 | C1: 2021 | D1: 2022 | E1: 2023 | F1: 2024 | G1: 2025 | H1: 2026 | I1: 2027 | J1: 2028 | K1: 2029 | L1: 2030 | M1: 2031 | N1: 2032 | O1: 2033 | P1: 2034 | Q1: 2035 | R1: 2036 | S1: 2037 | T1: 2038 | U1: 2039 | V1: 2040 | W1: 2041 | X1: 2042 | Y1: 2043 | Z1: 2044 | AA1: 2045 | AB1: 2046 | AC1: 2047 | AD1: 2048 | AE1: 2049 | AF1: 2050 | AG1: 2051 | AH1: 2052 | AI1: 2053 | AJ1: 2054 | AK1: 2055 | AL1: 2056 | AM1: 2057 | AN1: 2058 | AO1: 2059 | AP1: 2060 | AQ1: 2061 | AR1: 2062 | AS1: 2063 | AT1: 2064 | AU1: 2065 | AV1: 2066 | AW1: 2067 | AX1: 2068 | AY1: 2069 | AZ1: 2070
A2: battery electric vehicle | B2: ='NVP-Indonesia'!B128*'NVP-Indonesia'!$B$227 -> 93481595 | C2: 0 | D2: =C2 -> 0 | E2: =D2 -> 0 | F2: =E2 -> 0 | G2: =F2 -> 0 | H2: =G2 -> 0 | I2: =H2 -> 0 | J2: =I2 -> 0 | K2: =J2 -> 0 | ... AZ2: =AY2 -> 0
A3: natural gas vehicle | B3: 999999999 | C3: 999999999 | D3: 999999999 | E3: 999999999 | F3: 999999999 | G3: 999999999 | H3: 999999999 | I3: 999999999 | J3: 999999999 | K3: 999999999 | L3: 999999999 | M3: 999999999 | N3: 999999999 | O3: 999999999 | P3: 999999999 | Q3: 999999999 | R3: 999999999 | S3: 999999999 | T3: 999999999 | U3: 999999999 | V3: 999999999 | W3: 999999999 | X3: 999999999 | Y3: 999999999 | Z3: 999999999 | AA3: 999999999 | AB3: 999999999 | AC3: 999999999 | AD3: 999999999 | AE3: 999999999 | AF3: 999999999 | AG3: 999999999 | AH3: 999999999 | AI3: 999999999 | AJ3: 999999999 | AK3: 999999999 | AL3: 999999999 | AM3: 999999999 | AN3: 999999999 | AO3: 999999999 | AP3: 999999999 | AQ3: 999999999 | AR3: 999999999 | AS3: 999999999 | AT3: 999999999 | AU3: 999999999 | AV3: 999999999 | AW3: 999999999 | AX3: 999999999 | AY3: 999999999 | AZ3: 999999999
A4: gasoline vehicle | B4: 999999999 | C4: 999999999 | D4: 999999999 | E4: 999999999 | F4: 999999999 | G4: 999999999 | H4: 999999999 | I4: 999999999 | J4: 999999999 | K4: 999999999 | L4: 999999999 | M4: 999999999 | N4: 999999999 | O4: 999999999 | P4: 999999999 | Q4: 999999999 | R4: 999999999 | S4: 999999999 | T4: 999999999 | U4: 999999999 | V4: 999999999 | W4: 999999999 | X4: 999999999 | Y4: 999999999 | Z4: 999999999 | AA4: 999999999 | AB4: 999999999 | AC4: 999999999 | AD4: 999999999 | AE4: 999999999 | AF4: 999999999 | AG4: 999999999 | AH4: 999999999 | AI4: 999999999 | AJ4: 999999999 | AK4: 999999999 | AL4: 999999999 | AM4: 999999999 | AN4: 999999999 | AO4: 999999999 | AP4: 999999999 | AQ4: 999999999 | AR4: 999999999 | AS4: 999999999 | AT4: 999999999 | AU4: 999999999 | AV4: 999999999 | AW4: 999999999 | AX4: 999999999 | AY4: 999999999 | AZ4: 999999999
A5: diesel vehicle | B5: ='NVP-Indonesia'!B131*'NVP-Indonesia'!$B$227 -> 50570000 | C5: =$B5 -> 50570000 | D5: =$B5 -> 50570000 | E5: =$B5 -> 50570000 | F5: =$B5 -> 50570000 | G5: =$B5 -> 50570000 | H5: =$B5 -> 50570000 | I5: =$B5 -> 50570000 | J5: =$B5 -> 50570000 | ... AF5: =$B5 -> 50570000 | AG5: =_xlfn.FORECAST.LINEAR(AG$1,$B5:$AF5,$B$1:$AF$1) -> 50570000 | AH5: =_xlfn.FORECAST.LINEAR(AH$1,$B5:$AF5,$B$1:$AF$1) -> 50570000 | AI5: =_xlfn.FORECAST.LINEAR(AI$1,$B5:$AF5,$B$1:$AF$1) -> 50570000 | AJ5: =_xlfn.FORECAST.LINEAR(AJ$1,$B5:$AF5,$B$1:$AF$1) -> 50570000 | AK5: =_xlfn.FORECAST.LINEAR(AK$1,$B5:$AF5,$B$1:$AF$1) -> 50570000 | AL5: =_xlfn.FORECAST.LINEAR(AL$1,$B5:$AF5,$B$1:$AF$1) -> 50570000 | AM5: =_xlfn.FORECAST.LINEAR(AM$1,$B5:$AF5,$B$1:$AF$1) -> 50570000 | AN5: =_xlfn.FORECAST.LINEAR(AN$1,$B5:$AF5,$B$1:$AF$1) -> 50570000 | ... AZ5: =_xlfn.FORECAST.LINEAR(AZ$1,$B5:$AF5,$B$1:$AF$1) -> 50570000
A6: plugin hybrid vehicle | B6: 999999999 | C6: 999999999 | D6: 999999999 | E6: 999999999 | F6: 999999999 | G6: 999999999 | H6: 999999999 | I6: 999999999 | J6: 999999999 | K6: 999999999 | L6: 999999999 | M6: 999999999 | N6: 999999999 | O6: 999999999 | P6: 999999999 | Q6: 999999999 | R6: 999999999 | S6: 999999999 | T6: 999999999 | U6: 999999999 | V6: 999999999 | W6: 999999999 | X6: 999999999 | Y6: 999999999 | Z6: 999999999 | AA6: 999999999 | AB6: 999999999 | AC6: 999999999 | AD6: 999999999 | AE6: 999999999 | AF6: 999999999 | AG6: 999999999 | AH6: 999999999 | AI6: 999999999 | AJ6: 999999999 | AK6: 999999999 | AL6: 999999999 | AM6: 999999999 | AN6: 999999999 | AO6: 999999999 | AP6: 999999999 | AQ6: 999999999 | AR6: 999999999 | AS6: 999999999 | AT6: 999999999 | AU6: 999999999 | AV6: 999999999 | AW6: 999999999 | AX6: 999999999 | AY6: 999999999 | AZ6: 999999999
A7: LPG vehicle | B7: 999999999 | C7: 999999999 | D7: 999999999 | E7: 999999999 | F7: 999999999 | G7: 999999999 | H7: 999999999 | I7: 999999999 | J7: 999999999 | K7: 999999999 | L7: 999999999 | M7: 999999999 | N7: 999999999 | O7: 999999999 | P7: 999999999 | Q7: 999999999 | R7: 999999999 | S7: 999999999 | T7: 999999999 | U7: 999999999 | V7: 999999999 | W7: 999999999 | X7: 999999999 | Y7: 999999999 | Z7: 999999999 | AA7: 999999999 | AB7: 999999999 | AC7: 999999999 | AD7: 999999999 | AE7: 999999999 | AF7: 999999999 | AG7: 999999999 | AH7: 999999999 | AI7: 999999999 | AJ7: 999999999 | AK7: 999999999 | AL7: 999999999 | AM7: 999999999 | AN7: 999999999 | AO7: 999999999 | AP7: 999999999 | AQ7: 999999999 | AR7: 999999999 | AS7: 999999999 | AT7: 999999999 | AU7: 999999999 | AV7: 999999999 | AW7: 999999999 | AX7: 999999999 | AY7: 999999999 | AZ7: 999999999
A8: hydrogen vehicle | B8: ='NVP-Indonesia'!B134*'NVP-Indonesia'!$B$227 -> 1.017605e+08 | C8: =B8 -> 1.017605e+08 | D8: =C8 -> 1.017605e+08 | E8: =D8 -> 1.017605e+08 | F8: =E8 -> 1.017605e+08 | G8: =F8 -> 1.017605e+08 | H8: =G8 -> 1.017605e+08 | I8: =H8 -> 1.017605e+08 | J8: =I8 -> 1.017605e+08 | ... AZ8: =AY8 -> 1.017605e+08

Sheet BNVP-rail-frgt
A1: Price ($/vehicle) | B1: 2020 | C1: 2021 | D1: 2022 | E1: 2023 | F1: 2024 | G1: 2025 | H1: 2026 | I1: 2027 | J1: 2028 | K1: 2029 | L1: 2030 | M1: 2031 | N1: 2032 | O1: 2033 | P1: 2034 | Q1: 2035 | R1: 2036 | S1: 2037 | T1: 2038 | U1: 2039 | V1: 2040 | W1: 2041 | X1: 2042 | Y1: 2043 | Z1: 2044 | AA1: 2045 | AB1: 2046 | AC1: 2047 | AD1: 2048 | AE1: 2049 | AF1: 2050 | AG1: 2051 | AH1: 2052 | AI1: 2053 | AJ1: 2054 | AK1: 2055 | AL1: 2056 | AM1: 2057 | AN1: 2058 | AO1: 2059 | AP1: 2060 | AQ1: 2061 | AR1: 2062 | AS1: 2063 | AT1: 2064 | AU1: 2065 | AV1: 2066 | AW1: 2067 | AX1: 2068 | AY1: 2069 | AZ1: 2070
A2: battery electric vehicle | B2: ='NVP-Indonesia'!B138*'NVP-Indonesia'!$B$227 -> 3900000 | C2: 0 | D2: =C2 -> 0 | E2: =D2 -> 0 | F2: =E2 -> 0 | G2: =F2 -> 0 | H2: =G2 -> 0 | I2: =H2 -> 0 | J2: =I2 -> 0 | K2: =J2 -> 0 | ... AF2: =AE2 -> 0 | AG2: =_xlfn.FORECAST.LINEAR(AG$1,$B2:$AF2,$B$1:$AF$1) -> -251612.9 | AH2: =_xlfn.FORECAST.LINEAR(AH$1,$B2:$AF2,$B$1:$AF$1) -> -275201.61 | AI2: =_xlfn.FORECAST.LINEAR(AI$1,$B2:$AF2,$B$1:$AF$1) -> -298790.32 | AJ2: =_xlfn.FORECAST.LINEAR(AJ$1,$B2:$AF2,$B$1:$AF$1) -> -322379.03 | AK2: =_xlfn.FORECAST.LINEAR(AK$1,$B2:$AF2,$B$1:$AF$1) -> -345967.74 | AL2: =_xlfn.FORECAST.LINEAR(AL$1,$B2:$AF2,$B$1:$AF$1) -> -369556.45 | AM2: =_xlfn.FORECAST.LINEAR(AM$1,$B2:$AF2,$B$1:$AF$1) -> -393145.16 | AN2: =_xlfn.FORECAST.LINEAR(AN$1,$B2:$AF2,$B$1:$AF$1) -> -416733.87 | ... AZ2: =_xlfn.FORECAST.LINEAR(AZ$1,$B2:$AF2,$B$1:$AF$1) -> -699798.39
A3: natural gas vehicle | B3: 999999999 | C3: 999999999 | D3: 999999999 | E3: 999999999 | F3: 999999999 | G3: 999999999 | H3: 999999999 | I3: 999999999 | J3: 999999999 | K3: 999999999 | L3: 999999999 | M3: 999999999 | N3: 999999999 | O3: 999999999 | P3: 999999999 | Q3: 999999999 | R3: 999999999 | S3: 999999999 | T3: 999999999 | U3: 999999999 | V3: 999999999 | W3: 999999999 | X3: 999999999 | Y3: 999999999 | Z3: 999999999 | AA3: 999999999 | AB3: 999999999 | AC3: 999999999 | AD3: 999999999 | AE3: 999999999 | AF3: 999999999 | AG3: 999999999 | AH3: 999999999 | AI3: 999999999 | AJ3: 999999999 | AK3: 999999999 | AL3: 999999999 | AM3: 999999999 | AN3: 999999999 | AO3: 999999999 | AP3: 999999999 | AQ3: 999999999 | AR3: 999999999 | AS3: 999999999 | AT3: 999999999 | AU3: 999999999 | AV3: 999999999 | AW3: 999999999 | AX3: 999999999 | AY3: 999999999 | AZ3: 999999999
A4: gasoline vehicle | B4: 999999999 | C4: 999999999 | D4: 999999999 | E4: 999999999 | F4: 999999999 | G4: 999999999 | H4: 999999999 | I4: 999999999 | J4: 999999999 | K4: 999999999 | L4: 999999999 | M4: 999999999 | N4: 999999999 | O4: 999999999 | P4: 999999999 | Q4: 999999999 | R4: 999999999 | S4: 999999999 | T4: 999999999 | U4: 999999999 | V4: 999999999 | W4: 999999999 | X4: 999999999 | Y4: 999999999 | Z4: 999999999 | AA4: 999999999 | AB4: 999999999 | AC4: 999999999 | AD4: 999999999 | AE4: 999999999 | AF4: 999999999 | AG4: 999999999 | AH4: 999999999 | AI4: 999999999 | AJ4: 999999999 | AK4: 999999999 | AL4: 999999999 | AM4: 999999999 | AN4: 999999999 | AO4: 999999999 | AP4: 999999999 | AQ4: 999999999 | AR4: 999999999 | AS4: 999999999 | AT4: 999999999 | AU4: 999999999 | AV4: 999999999 | AW4: 999999999 | AX4: 999999999 | AY4: 999999999 | AZ4: 999999999
A5: diesel vehicle | B5: ='NVP-Indonesia'!B141*'NVP-Indonesia'!$B$227 -> 2101448.3 | C5: =$B5 -> 2101448.3 | D5: =$B5 -> 2101448.3 | E5: =$B5 -> 2101448.3 | F5: =$B5 -> 2101448.3 | G5: =$B5 -> 2101448.3 | H5: =$B5 -> 2101448.3 | I5: =$B5 -> 2101448.3 | J5: =$B5 -> 2101448.3 | ... AF5: =$B5 -> 2101448.3 | AG5: =_xlfn.FORECAST.LINEAR(AG$1,$B5:$AF5,$B$1:$AF$1) -> 2101448.3 | AH5: =_xlfn.FORECAST.LINEAR(AH$1,$B5:$AF5,$B$1:$AF$1) -> 2101448.3 | AI5: =_xlfn.FORECAST.LINEAR(AI$1,$B5:$AF5,$B$1:$AF$1) -> 2101448.3 | AJ5: =_xlfn.FORECAST.LINEAR(AJ$1,$B5:$AF5,$B$1:$AF$1) -> 2101448.3 | AK5: =_xlfn.FORECAST.LINEAR(AK$1,$B5:$AF5,$B$1:$AF$1) -> 2101448.3 | AL5: =_xlfn.FORECAST.LINEAR(AL$1,$B5:$AF5,$B$1:$AF$1) -> 2101448.3 | AM5: =_xlfn.FORECAST.LINEAR(AM$1,$B5:$AF5,$B$1:$AF$1) -> 2101448.3 | AN5: =_xlfn.FORECAST.LINEAR(AN$1,$B5:$AF5,$B$1:$AF$1) -> 2101448.3 | ... AZ5: =_xlfn.FORECAST.LINEAR(AZ$1,$B5:$AF5,$B$1:$AF$1) -> 2101448.3
A6: plugin hybrid vehicle | B6: 999999999 | C6: 999999999 | D6: 999999999 | E6: 999999999 | F6: 999999999 | G6: 999999999 | H6: 999999999 | I6: 999999999 | J6: 999999999 | K6: 999999999 | L6: 999999999 | M6: 999999999 | N6: 999999999 | O6: 999999999 | P6: 999999999 | Q6: 999999999 | R6: 999999999 | S6: 999999999 | T6: 999999999 | U6: 999999999 | V6: 999999999 | W6: 999999999 | X6: 999999999 | Y6: 999999999 | Z6: 999999999 | AA6: 999999999 | AB6: 999999999 | AC6: 999999999 | AD6: 999999999 | AE6: 999999999 | AF6: 999999999 | AG6: 999999999 | AH6: 999999999 | AI6: 999999999 | AJ6: 999999999 | AK6: 999999999 | AL6: 999999999 | AM6: 999999999 | AN6: 999999999 | AO6: 999999999 | AP6: 999999999 | AQ6: 999999999 | AR6: 999999999 | AS6: 999999999 | AT6: 999999999 | AU6: 999999999 | AV6: 999999999 | AW6: 999999999 | AX6: 999999999 | AY6: 999999999 | AZ6: 999999999
A7: LPG vehicle | B7: 999999999 | C7: 999999999 | D7: 999999999 | E7: 999999999 | F7: 999999999 | G7: 999999999 | H7: 999999999 | I7: 999999999 | J7: 999999999 | K7: 999999999 | L7: 999999999 | M7: 999999999 | N7: 999999999 | O7: 999999999 | P7: 999999999 | Q7: 999999999 | R7: 999999999 | S7: 999999999 | T7: 999999999 | U7: 999999999 | V7: 999999999 | W7: 999999999 | X7: 999999999 | Y7: 999999999 | Z7: 999999999 | AA7: 999999999 | AB7: 999999999 | AC7: 999999999 | AD7: 999999999 | AE7: 999999999 | AF7: 999999999 | AG7: 999999999 | AH7: 999999999 | AI7: 999999999 | AJ7: 999999999 | AK7: 999999999 | AL7: 999999999 | AM7: 999999999 | AN7: 999999999 | AO7: 999999999 | AP7: 999999999 | AQ7: 999999999 | AR7: 999999999 | AS7: 999999999 | AT7: 999999999 | AU7: 999999999 | AV7: 999999999 | AW7: 999999999 | AX7: 999999999 | AY7: 999999999 | AZ7: 999999999
A8: hydrogen vehicle | B8: ='NVP-Indonesia'!B144*'NVP-Indonesia'!$B$227 -> 6514489.6 | C8: =$B$8*('BNVP-HDVs-frgt'!C8/'BNVP-HDVs-frgt'!$B$8) -> 6514489.6 | D8: =$B$8*('BNVP-HDVs-frgt'!D8/'BNVP-HDVs-frgt'!$B$8) -> 6514489.6 | E8: =$B$8*('BNVP-HDVs-frgt'!E8/'BNVP-HDVs-frgt'!$B$8) -> 6514489.6 | F8: =$B$8*('BNVP-HDVs-frgt'!F8/'BNVP-HDVs-frgt'!$B$8) -> 6514489.6 | G8: =$B$8*('BNVP-HDVs-frgt'!G8/'BNVP-HDVs-frgt'!$B$8) -> 6514489.6 | H8: =$B$8*('BNVP-HDVs-frgt'!H8/'BNVP-HDVs-frgt'!$B$8) -> 6514489.6 | I8: =$B$8*('BNVP-HDVs-frgt'!I8/'BNVP-HDVs-frgt'!$B$8) -> 6514489.6 | J8: =$B$8*('BNVP-HDVs-frgt'!J8/'BNVP-HDVs-frgt'!$B$8) -> 6514489.6 | ... AF8: =$B$8*('BNVP-HDVs-frgt'!AF8/'BNVP-HDVs-frgt'!$B$8) -> 6514489.6 | AG8: =_xlfn.FORECAST.LINEAR(AG$1,$B8:$AF8,$B$1:$AF$1) -> 6514489.6 | AH8: =_xlfn.FORECAST.LINEAR(AH$1,$B8:$AF8,$B$1:$AF$1) -> 6514489.6 | AI8: =_xlfn.FORECAST.LINEAR(AI$1,$B8:$AF8,$B$1:$AF$1) -> 6514489.6 | AJ8: =_xlfn.FORECAST.LINEAR(AJ$1,$B8:$AF8,$B$1:$AF$1) -> 6514489.6 | AK8: =_xlfn.FORECAST.LINEAR(AK$1,$B8:$AF8,$B$1:$AF$1) -> 6514489.6 | AL8: =_xlfn.FORECAST.LINEAR(AL$1,$B8:$AF8,$B$1:$AF$1) -> 6514489.6 | AM8: =_xlfn.FORECAST.LINEAR(AM$1,$B8:$AF8,$B$1:$AF$1) -> 6514489.6 | AN8: =_xlfn.FORECAST.LINEAR(AN$1,$B8:$AF8,$B$1:$AF$1) -> 6514489.6 | ... AZ8: =_xlfn.FORECAST.LINEAR(AZ$1,$B8:$AF8,$B$1:$AF$1) -> 6514489.6

Sheet BNVP-ships-psgr
A1: Price ($/vehicle) | B1: 2020 | C1: 2021 | D1: 2022 | E1: 2023 | F1: 2024 | G1: 2025 | H1: 2026 | I1: 2027 | J1: 2028 | K1: 2029 | L1: 2030 | M1: 2031 | N1: 2032 | O1: 2033 | P1: 2034 | Q1: 2035 | R1: 2036 | S1: 2037 | T1: 2038 | U1: 2039 | V1: 2040 | W1: 2041 | X1: 2042 | Y1: 2043 | Z1: 2044 | AA1: 2045 | AB1: 2046 | AC1: 2047 | AD1: 2048 | AE1: 2049 | AF1: 2050 | AG1: 2051 | AH1: 2052 | AI1: 2053 | AJ1: 2054 | AK1: 2055 | AL1: 2056 | AM1: 2057 | AN1: 2058 | AO1: 2059 | AP1: 2060 | AQ1: 2061 | AR1: 2062 | AS1: 2063 | AT1: 2064 | AU1: 2065 | AV1: 2066 | AW1: 2067 | AX1: 2068 | AY1: 2069 | AZ1: 2070
A2: battery electric vehicle | B2: ='NVP-Indonesia'!B148*'NVP-Indonesia'!$B$227 -> 43256.265 | C2: 0 | D2: =C2 -> 0 | E2: =D2 -> 0 | F2: =E2 -> 0 | G2: =F2 -> 0 | H2: =G2 -> 0 | I2: =H2 -> 0 | J2: =I2 -> 0 | K2: =J2 -> 0 | ... AF2: =AE2 -> 0 | AG2: =_xlfn.FORECAST.LINEAR(AG$1,$B2:$AF2,$B$1:$AF$1) -> -2790.7268 | AH2: =_xlfn.FORECAST.LINEAR(AH$1,$B2:$AF2,$B$1:$AF$1) -> -3052.3574 | AI2: =_xlfn.FORECAST.LINEAR(AI$1,$B2:$AF2,$B$1:$AF$1) -> -3313.988 | AJ2: =_xlfn.FORECAST.LINEAR(AJ$1,$B2:$AF2,$B$1:$AF$1) -> -3575.6187 | AK2: =_xlfn.FORECAST.LINEAR(AK$1,$B2:$AF2,$B$1:$AF$1) -> -3837.2493 | AL2: =_xlfn.FORECAST.LINEAR(AL$1,$B2:$AF2,$B$1:$AF$1) -> -4098.8799 | AM2: =_xlfn.FORECAST.LINEAR(AM$1,$B2:$AF2,$B$1:$AF$1) -> -4360.5106 | AN2: =_xlfn.FORECAST.LINEAR(AN$1,$B2:$AF2,$B$1:$AF$1) -> -4622.1412 | ... AZ2: =_xlfn.FORECAST.LINEAR(AZ$1,$B2:$AF2,$B$1:$AF$1) -> -7761.7088
A3: natural gas vehicle | B3: 999999999 | C3: 999999999 | D3: 999999999 | E3: 999999999 | F3: 999999999 | G3: 999999999 | H3: 999999999 | I3: 999999999 | J3: 999999999 | K3: 999999999 | L3: 999999999 | M3: 999999999 | N3: 999999999 | O3: 999999999 | P3: 999999999 | Q3: 999999999 | R3: 999999999 | S3: 999999999 | T3: 999999999 | U3: 999999999 | V3: 999999999 | W3: 999999999 | X3: 999999999 | Y3: 999999999 | Z3: 999999999 | AA3: 999999999 | AB3: 999999999 | AC3: 999999999 | AD3: 999999999 | AE3: 999999999 | AF3: 999999999 | AG3: 999999999 | AH3: 999999999 | AI3: 999999999 | AJ3: 999999999 | AK3: 999999999 | AL3: 999999999 | AM3: 999999999 | AN3: 999999999 | AO3: 999999999 | AP3: 999999999 | AQ3: 999999999 | AR3: 999999999 | AS3: 999999999 | AT3: 999999999 | AU3: 999999999 | AV3: 999999999 | AW3: 999999999 | AX3: 999999999 | AY3: 999999999 | AZ3: 999999999
A4: gasoline vehicle | B4: ='NVP-Indonesia'!B150*'NVP-Indonesia'!$B$227 -> 23400 | C4: =C$5 -> 23400 | D4: =D$5 -> 23400 | E4: =E$5 -> 23400 | F4: =F$5 -> 23400 | G4: =G$5 -> 23400 | H4: =H$5 -> 23400 | I4: =I$5 -> 23400 | J4: =J$5 -> 23400 | ... AF4: =AF$5 -> 23400 | AG4: =_xlfn.FORECAST.LINEAR(AG$1,$B4:$AF4,$B$1:$AF$1) -> 23400 | AH4: =_xlfn.FORECAST.LINEAR(AH$1,$B4:$AF4,$B$1:$AF$1) -> 23400 | AI4: =_xlfn.FORECAST.LINEAR(AI$1,$B4:$AF4,$B$1:$AF$1) -> 23400 | AJ4: =_xlfn.FORECAST.LINEAR(AJ$1,$B4:$AF4,$B$1:$AF$1) -> 23400 | AK4: =_xlfn.FORECAST.LINEAR(AK$1,$B4:$AF4,$B$1:$AF$1) -> 23400 | AL4: =_xlfn.FORECAST.LINEAR(AL$1,$B4:$AF4,$B$1:$AF$1) -> 23400 | AM4: =_xlfn.FORECAST.LINEAR(AM$1,$B4:$AF4,$B$1:$AF$1) -> 23400 | AN4: =_xlfn.FORECAST.LINEAR(AN$1,$B4:$AF4,$B$1:$AF$1) -> 23400 | ... AZ4: =_xlfn.FORECAST.LINEAR(AZ$1,$B4:$AF4,$B$1:$AF$1) -> 23400
A5: diesel vehicle | B5: ='NVP-Indonesia'!B151*'NVP-Indonesia'!$B$227 -> 23400 | C5: =$B5 -> 23400 | D5: =$B5 -> 23400 | E5: =$B5 -> 23400 | F5: =$B5 -> 23400 | G5: =$B5 -> 23400 | H5: =$B5 -> 23400 | I5: =$B5 -> 23400 | J5: =$B5 -> 23400 | ... AF5: =$B5 -> 23400 | AG5: =_xlfn.FORECAST.LINEAR(AG$1,$B5:$AF5,$B$1:$AF$1) -> 23400 | AH5: =_xlfn.FORECAST.LINEAR(AH$1,$B5:$AF5,$B$1:$AF$1) -> 23400 | AI5: =_xlfn.FORECAST.LINEAR(AI$1,$B5:$AF5,$B$1:$AF$1) -> 23400 | AJ5: =_xlfn.FORECAST.LINEAR(AJ$1,$B5:$AF5,$B$1:$AF$1) -> 23400 | AK5: =_xlfn.FORECAST.LINEAR(AK$1,$B5:$AF5,$B$1:$AF$1) -> 23400 | AL5: =_xlfn.FORECAST.LINEAR(AL$1,$B5:$AF5,$B$1:$AF$1) -> 23400 | AM5: =_xlfn.FORECAST.LINEAR(AM$1,$B5:$AF5,$B$1:$AF$1) -> 23400 | AN5: =_xlfn.FORECAST.LINEAR(AN$1,$B5:$AF5,$B$1:$AF$1) -> 23400 | ... AZ5: =_xlfn.FORECAST.LINEAR(AZ$1,$B5:$AF5,$B$1:$AF$1) -> 23400
A6: plugin hybrid vehicle | B6: 999999999 | C6: 999999999 | D6: 999999999 | E6: 999999999 | F6: 999999999 | G6: 999999999 | H6: 999999999 | I6: 999999999 | J6: 999999999 | K6: 999999999 | L6: 999999999 | M6: 999999999 | N6: 999999999 | O6: 999999999 | P6: 999999999 | Q6: 999999999 | R6: 999999999 | S6: 999999999 | T6: 999999999 | U6: 999999999 | V6: 999999999 | W6: 999999999 | X6: 999999999 | Y6: 999999999 | Z6: 999999999 | AA6: 999999999 | AB6: 999999999 | AC6: 999999999 | AD6: 999999999 | AE6: 999999999 | AF6: 999999999 | AG6: 999999999 | AH6: 999999999 | AI6: 999999999 | AJ6: 999999999 | AK6: 999999999 | AL6: 999999999 | AM6: 999999999 | AN6: 999999999 | AO6: 999999999 | AP6: 999999999 | AQ6: 999999999 | AR6: 999999999 | AS6: 999999999 | AT6: 999999999 | AU6: 999999999 | AV6: 999999999 | AW6: 999999999 | AX6: 999999999 | AY6: 999999999 | AZ6: 999999999
A7: LPG vehicle | B7: 999999999 | C7: 999999999 | D7: 999999999 | E7: 999999999 | F7: 999999999 | G7: 999999999 | H7: 999999999 | I7: 999999999 | J7: 999999999 | K7: 999999999 | L7: 999999999 | M7: 999999999 | N7: 999999999 | O7: 999999999 | P7: 999999999 | Q7: 999999999 | R7: 999999999 | S7: 999999999 | T7: 999999999 | U7: 999999999 | V7: 999999999 | W7: 999999999 | X7: 999999999 | Y7: 999999999 | Z7: 999999999 | AA7: 999999999 | AB7: 999999999 | AC7: 999999999 | AD7: 999999999 | AE7: 999999999 | AF7: 999999999 | AG7: 999999999 | AH7: 999999999 | AI7: 999999999 | AJ7: 999999999 | AK7: 999999999 | AL7: 999999999 | AM7: 999999999 | AN7: 999999999 | AO7: 999999999 | AP7: 999999999 | AQ7: 999999999 | AR7: 999999999 | AS7: 999999999 | AT7: 999999999 | AU7: 999999999 | AV7: 999999999 | AW7: 999999999 | AX7: 999999999 | AY7: 999999999 | AZ7: 999999999
A8: hydrogen vehicle | B8: ='NVP-Indonesia'!B154*'NVP-Indonesia'!$B$227 -> 47087.119 | C8: =C$5*('BNVP-HDVs-psgr'!C$8/'BNVP-HDVs-psgr'!C$5) -> 386783.2 | D8: =D$5*('BNVP-HDVs-psgr'!D$8/'BNVP-HDVs-psgr'!D$5) -> 386783.2 | E8: =E$5*('BNVP-HDVs-psgr'!E$8/'BNVP-HDVs-psgr'!E$5) -> 386783.2 | F8: =F$5*('BNVP-HDVs-psgr'!F$8/'BNVP-HDVs-psgr'!F$5) -> 386783.2 | G8: =G$5*('BNVP-HDVs-psgr'!G$8/'BNVP-HDVs-psgr'!G$5) -> 386783.2 | H8: =H$5*('BNVP-HDVs-psgr'!H$8/'BNVP-HDVs-psgr'!H$5) -> 386783.2 | I8: =I$5*('BNVP-HDVs-psgr'!I$8/'BNVP-HDVs-psgr'!I$5) -> 386783.2 | J8: =J$5*('BNVP-HDVs-psgr'!J$8/'BNVP-HDVs-psgr'!J$5) -> 386783.2 | ... AF8: =AF$5*('BNVP-HDVs-psgr'!AF$8/'BNVP-HDVs-psgr'!AF$5) -> 386783.2 | AG8: =_xlfn.FORECAST.LINEAR(AG$1,$B8:$AF8,$B$1:$AF$1) -> 408699.07 | AH8: =_xlfn.FORECAST.LINEAR(AH$1,$B8:$AF8,$B$1:$AF$1) -> 410753.69 | AI8: =_xlfn.FORECAST.LINEAR(AI$1,$B8:$AF8,$B$1:$AF$1) -> 412808.3 | AJ8: =_xlfn.FORECAST.LINEAR(AJ$1,$B8:$AF8,$B$1:$AF$1) -> 414862.91 | AK8: =_xlfn.FORECAST.LINEAR(AK$1,$B8:$AF8,$B$1:$AF$1) -> 416917.53 | AL8: =_xlfn.FORECAST.LINEAR(AL$1,$B8:$AF8,$B$1:$AF$1) -> 418972.14 | AM8: =_xlfn.FORECAST.LINEAR(AM$1,$B8:$AF8,$B$1:$AF$1) -> 421026.76 | AN8: =_xlfn.FORECAST.LINEAR(AN$1,$B8:$AF8,$B$1:$AF$1) -> 423081.37 | ... AZ8: =_xlfn.FORECAST.LINEAR(AZ$1,$B8:$AF8,$B$1:$AF$1) -> 447736.73

Sheet BNVP-ships-frgt
A1: Price ($/vehicle) | B1: 2020 | C1: 2021 | D1: 2022 | E1: 2023 | F1: 2024 | G1: 2025 | H1: 2026 | I1: 2027 | J1: 2028 | K1: 2029 | L1: 2030 | M1: 2031 | N1: 2032 | O1: 2033 | P1: 2034 | Q1: 2035 | R1: 2036 | S1: 2037 | T1: 2038 | U1: 2039 | V1: 2040 | W1: 2041 | X1: 2042 | Y1: 2043 | Z1: 2044 | AA1: 2045 | AB1: 2046 | AC1: 2047 | AD1: 2048 | AE1: 2049 | AF1: 2050 | AG1: 2051 | AH1: 2052 | AI1: 2053 | AJ1: 2054 | AK1: 2055 | AL1: 2056 | AM1: 2057 | AN1: 2058 | AO1: 2059 | AP1: 2060 | AQ1: 2061 | AR1: 2062 | AS1: 2063 | AT1: 2064 | AU1: 2065 | AV1: 2066 | AW1: 2067 | AX1: 2068 | AY1: 2069 | AZ1: 2070
A2: battery electric vehicle | B2: ='NVP-Indonesia'!B158*'NVP-Indonesia'!$B$227 -> 14418755 | C2: 0 | D2: =C2 -> 0 | E2: =D2 -> 0 | F2: =E2 -> 0 | G2: =F2 -> 0 | H2: =G2 -> 0 | I2: =H2 -> 0 | J2: =I2 -> 0 | K2: =J2 -> 0 | ... AF2: =AE2 -> 0 | AG2: =_xlfn.FORECAST.LINEAR(AG$1,$B2:$AF2,$B$1:$AF$1) -> -930242.26 | AH2: =_xlfn.FORECAST.LINEAR(AH$1,$B2:$AF2,$B$1:$AF$1) -> -1017452.5 | AI2: =_xlfn.FORECAST.LINEAR(AI$1,$B2:$AF2,$B$1:$AF$1) -> -1104662.7 | AJ2: =_xlfn.FORECAST.LINEAR(AJ$1,$B2:$AF2,$B$1:$AF$1) -> -1191872.9 | AK2: =_xlfn.FORECAST.LINEAR(AK$1,$B2:$AF2,$B$1:$AF$1) -> -1279083.1 | AL2: =_xlfn.FORECAST.LINEAR(AL$1,$B2:$AF2,$B$1:$AF$1) -> -1366293.3 | AM2: =_xlfn.FORECAST.LINEAR(AM$1,$B2:$AF2,$B$1:$AF$1) -> -1453503.5 | AN2: =_xlfn.FORECAST.LINEAR(AN$1,$B2:$AF2,$B$1:$AF$1) -> -1540713.7 | ... AZ2: =_xlfn.FORECAST.LINEAR(AZ$1,$B2:$AF2,$B$1:$AF$1) -> -2587236.3
A3: natural gas vehicle | B3: 999999999 | C3: 999999999 | D3: 999999999 | E3: 999999999 | F3: 999999999 | G3: 999999999 | H3: 999999999 | I3: 999999999 | J3: 999999999 | K3: 999999999 | L3: 999999999 | M3: 999999999 | N3: 999999999 | O3: 999999999 | P3: 999999999 | Q3: 999999999 | R3: 999999999 | S3: 999999999 | T3: 999999999 | U3: 999999999 | V3: 999999999 | W3: 999999999 | X3: 999999999 | Y3: 999999999 | Z3: 999999999 | AA3: 999999999 | AB3: 999999999 | AC3: 999999999 | AD3: 999999999 | AE3: 999999999 | AF3: 999999999 | AG3: 999999999 | AH3: 999999999 | AI3: 999999999 | AJ3: 999999999 | AK3: 999999999 | AL3: 999999999 | AM3: 999999999 | AN3: 999999999 | AO3: 999999999 | AP3: 999999999 | AQ3: 999999999 | AR3: 999999999 | AS3: 999999999 | AT3: 999999999 | AU3: 999999999 | AV3: 999999999 | AW3: 999999999 | AX3: 999999999 | AY3: 999999999 | AZ3: 999999999
A4: gasoline vehicle | B4: 999999999 | C4: 999999999 | D4: 999999999 | E4: 999999999 | F4: 999999999 | G4: 999999999 | H4: 999999999 | I4: 999999999 | J4: 999999999 | K4: 999999999 | L4: 999999999 | M4: 999999999 | N4: 999999999 | O4: 999999999 | P4: 999999999 | Q4: 999999999 | R4: 999999999 | S4: 999999999 | T4: 999999999 | U4: 999999999 | V4: 999999999 | W4: 999999999 | X4: 999999999 | Y4: 999999999 | Z4: 999999999 | AA4: 999999999 | AB4: 999999999 | AC4: 999999999 | AD4: 999999999 | AE4: 999999999 | AF4: 999999999 | AG4: 999999999 | AH4: 999999999 | AI4: 999999999 | AJ4: 999999999 | AK4: 999999999 | AL4: 999999999 | AM4: 999999999 | AN4: 999999999 | AO4: 999999999 | AP4: 999999999 | AQ4: 999999999 | AR4: 999999999 | AS4: 999999999 | AT4: 999999999 | AU4: 999999999 | AV4: 999999999 | AW4: 999999999 | AX4: 999999999 | AY4: 999999999 | AZ4: 999999999
A5: diesel vehicle | B5: ='NVP-Indonesia'!B161*'NVP-Indonesia'!$B$227 -> 7800000 | C5: =$B5 -> 7800000 | D5: =$B5 -> 7800000 | E5: =$B5 -> 7800000 | F5: =$B5 -> 7800000 | G5: =$B5 -> 7800000 | H5: =$B5 -> 7800000 | I5: =$B5 -> 7800000 | J5: =$B5 -> 7800000 | ... AF5: =$B5 -> 7800000 | AG5: =_xlfn.FORECAST.LINEAR(AG$1,$B5:$AF5,$B$1:$AF$1) -> 7800000 | AH5: =_xlfn.FORECAST.LINEAR(AH$1,$B5:$AF5,$B$1:$AF$1) -> 7800000 | AI5: =_xlfn.FORECAST.LINEAR(AI$1,$B5:$AF5,$B$1:$AF$1) -> 7800000 | AJ5: =_xlfn.FORECAST.LINEAR(AJ$1,$B5:$AF5,$B$1:$AF$1) -> 7800000 | AK5: =_xlfn.FORECAST.LINEAR(AK$1,$B5:$AF5,$B$1:$AF$1) -> 7800000 | AL5: =_xlfn.FORECAST.LINEAR(AL$1,$B5:$AF5,$B$1:$AF$1) -> 7800000 | AM5: =_xlfn.FORECAST.LINEAR(AM$1,$B5:$AF5,$B$1:$AF$1) -> 7800000 | AN5: =_xlfn.FORECAST.LINEAR(AN$1,$B5:$AF5,$B$1:$AF$1) -> 7800000 | ... AZ5: =_xlfn.FORECAST.LINEAR(AZ$1,$B5:$AF5,$B$1:$AF$1) -> 7800000
A6: plugin hybrid vehicle | B6: 999999999 | C6: 999999999 | D6: 999999999 | E6: 999999999 | F6: 999999999 | G6: 999999999 | H6: 999999999 | I6: 999999999 | J6: 999999999 | K6: 999999999 | L6: 999999999 | M6: 999999999 | N6: 999999999 | O6: 999999999 | P6: 999999999 | Q6: 999999999 | R6: 999999999 | S6: 999999999 | T6: 999999999 | U6: 999999999 | V6: 999999999 | W6: 999999999 | X6: 999999999 | Y6: 999999999 | Z6: 999999999 | AA6: 999999999 | AB6: 999999999 | AC6: 999999999 | AD6: 999999999 | AE6: 999999999 | AF6: 999999999 | AG6: 999999999 | AH6: 999999999 | AI6: 999999999 | AJ6: 999999999 | AK6: 999999999 | AL6: 999999999 | AM6: 999999999 | AN6: 999999999 | AO6: 999999999 | AP6: 999999999 | AQ6: 999999999 | AR6: 999999999 | AS6: 999999999 | AT6: 999999999 | AU6: 999999999 | AV6: 999999999 | AW6: 999999999 | AX6: 999999999 | AY6: 999999999 | AZ6: 999999999
A7: LPG vehicle | B7: 999999999 | C7: 999999999 | D7: 999999999 | E7: 999999999 | F7: 999999999 | G7: 999999999 | H7: 999999999 | I7: 999999999 | J7: 999999999 | K7: 999999999 | L7: 999999999 | M7: 999999999 | N7: 999999999 | O7: 999999999 | P7: 999999999 | Q7: 999999999 | R7: 999999999 | S7: 999999999 | T7: 999999999 | U7: 999999999 | V7: 999999999 | W7: 999999999 | X7: 999999999 | Y7: 999999999 | Z7: 999999999 | AA7: 999999999 | AB7: 999999999 | AC7: 999999999 | AD7: 999999999 | AE7: 999999999 | AF7: 999999999 | AG7: 999999999 | AH7: 999999999 | AI7: 999999999 | AJ7: 999999999 | AK7: 999999999 | AL7: 999999999 | AM7: 999999999 | AN7: 999999999 | AO7: 999999999 | AP7: 999999999 | AQ7: 999999999 | AR7: 999999999 | AS7: 999999999 | AT7: 999999999 | AU7: 999999999 | AV7: 999999999 | AW7: 999999999 | AX7: 999999999 | AY7: 999999999 | AZ7: 999999999
A8: hydrogen vehicle | B8: ='NVP-Indonesia'!B164*'NVP-Indonesia'!$B$227 -> 15695706 | C8: =C$5*('BNVP-HDVs-psgr'!C$8/'BNVP-HDVs-psgr'!C$5) -> 1.2892773e+08 | D8: =D$5*('BNVP-HDVs-psgr'!D$8/'BNVP-HDVs-psgr'!D$5) -> 1.2892773e+08 | E8: =E$5*('BNVP-HDVs-psgr'!E$8/'BNVP-HDVs-psgr'!E$5) -> 1.2892773e+08 | F8: =F$5*('BNVP-HDVs-psgr'!F$8/'BNVP-HDVs-psgr'!F$5) -> 1.2892773e+08 | G8: =G$5*('BNVP-HDVs-psgr'!G$8/'BNVP-HDVs-psgr'!G$5) -> 1.2892773e+08 | H8: =H$5*('BNVP-HDVs-psgr'!H$8/'BNVP-HDVs-psgr'!H$5) -> 1.2892773e+08 | I8: =I$5*('BNVP-HDVs-psgr'!I$8/'BNVP-HDVs-psgr'!I$5) -> 1.2892773e+08 | J8: =J$5*('BNVP-HDVs-psgr'!J$8/'BNVP-HDVs-psgr'!J$5) -> 1.2892773e+08 | ... AF8: =AF$5*('BNVP-HDVs-psgr'!AF$8/'BNVP-HDVs-psgr'!AF$5) -> 1.2892773e+08 | AG8: =_xlfn.FORECAST.LINEAR(AG$1,$B8:$AF8,$B$1:$AF$1) -> 1.3623302e+08 | AH8: =_xlfn.FORECAST.LINEAR(AH$1,$B8:$AF8,$B$1:$AF$1) -> 1.369179e+08 | AI8: =_xlfn.FORECAST.LINEAR(AI$1,$B8:$AF8,$B$1:$AF$1) -> 1.3760277e+08 | AJ8: =_xlfn.FORECAST.LINEAR(AJ$1,$B8:$AF8,$B$1:$AF$1) -> 1.3828764e+08 | AK8: =_xlfn.FORECAST.LINEAR(AK$1,$B8:$AF8,$B$1:$AF$1) -> 1.3897251e+08 | AL8: =_xlfn.FORECAST.LINEAR(AL$1,$B8:$AF8,$B$1:$AF$1) -> 1.3965738e+08 | AM8: =_xlfn.FORECAST.LINEAR(AM$1,$B8:$AF8,$B$1:$AF$1) -> 1.4034225e+08 | AN8: =_xlfn.FORECAST.LINEAR(AN$1,$B8:$AF8,$B$1:$AF$1) -> 1.4102712e+08 | ... AZ8: =_xlfn.FORECAST.LINEAR(AZ$1,$B8:$AF8,$B$1:$AF$1) -> 1.4924558e+08

Sheet BNVP-motorbikes-psgr
A1: Price ($/vehicle) | B1: 2020 | C1: 2021 | D1: 2022 | E1: 2023 | F1: 2024 | G1: 2025 | H1: 2026 | I1: 2027 | J1: 2028 | K1: 2029 | L1: 2030 | M1: 2031 | N1: 2032 | O1: 2033 | P1: 2034 | Q1: 2035 | R1: 2036 | S1: 2037 | T1: 2038 | U1: 2039 | V1: 2040 | W1: 2041 | X1: 2042 | Y1: 2043 | Z1: 2044 | AA1: 2045 | AB1: 2046 | AC1: 2047 | AD1: 2048 | AE1: 2049 | AF1: 2050 | AG1: 2051 | AH1: 2052 | AI1: 2053 | AJ1: 2054 | AK1: 2055 | AL1: 2056 | AM1: 2057 | AN1: 2058 | AO1: 2059 | AP1: 2060 | AQ1: 2061 | AR1: 2062 | AS1: 2063 | AT1: 2064 | AU1: 2065 | AV1: 2066 | AW1: 2067 | AX1: 2068 | AY1: 2069 | AZ1: 2070
A2: battery electric vehicle | B2: ='NVP-Indonesia'!B18 -> 1957.5015 | C2: ='NVP-Indonesia'!C18 -> 1844.9131 | D2: ='NVP-Indonesia'!D18 -> 1732.3247 | E2: ='NVP-Indonesia'!E18 -> 1619.7363 | F2: ='NVP-Indonesia'!F18 -> 1507.1479 | G2: ='NVP-Indonesia'!G18 -> 1394.5595 | H2: ='NVP-Indonesia'!H18 -> 1281.9711 | I2: ='NVP-Indonesia'!I18 -> 1169.3827 | ... AZ2: ='NVP-Indonesia'!AZ18 -> 136.91797
A3: natural gas vehicle | B3: 999999999 | C3: 999999999 | D3: 999999999 | E3: 999999999 | F3: 999999999 | G3: 999999999 | H3: 999999999 | I3: 999999999 | J3: 999999999 | K3: 999999999 | L3: 999999999 | M3: 999999999 | N3: 999999999 | O3: 999999999 | P3: 999999999 | Q3: 999999999 | R3: 999999999 | S3: 999999999 | T3: 999999999 | U3: 999999999 | V3: 999999999 | W3: 999999999 | X3: 999999999 | Y3: 999999999 | Z3: 999999999 | AA3: 999999999 | AB3: 999999999 | AC3: 999999999 | AD3: 999999999 | AE3: 999999999 | AF3: 999999999 | AG3: 999999999 | AH3: 999999999 | AI3: 999999999 | AJ3: 999999999 | AK3: 999999999 | AL3: 999999999 | AM3: 999999999 | AN3: 999999999 | AO3: 999999999 | AP3: 999999999 | AQ3: 999999999 | AR3: 999999999 | AS3: 999999999 | AT3: 999999999 | AU3: 999999999 | AV3: 999999999 | AW3: 999999999 | AX3: 999999999 | AY3: 999999999 | AZ3: 999999999
A4: gasoline vehicle | B4: ='NVP-Indonesia'!B20 -> 539.84723 | C4: ='NVP-Indonesia'!C20 -> 543.89483 | D4: ='NVP-Indonesia'!D20 -> 547.94242 | E4: ='NVP-Indonesia'!E20 -> 551.99002 | F4: ='NVP-Indonesia'!F20 -> 556.03761 | G4: ='NVP-Indonesia'!G20 -> 560.0852 | H4: ='NVP-Indonesia'!H20 -> 564.1328 | I4: ='NVP-Indonesia'!I20 -> 568.18039 | ... AZ4: ='NVP-Indonesia'!AZ20 -> 580.32318
A5: diesel vehicle | B5: 999999999 | C5: 999999999 | D5: 999999999 | E5: 999999999 | F5: 999999999 | G5: 999999999 | H5: 999999999 | I5: 999999999 | J5: 999999999 | K5: 999999999 | L5: 999999999 | M5: 999999999 | N5: 999999999 | O5: 999999999 | P5: 999999999 | Q5: 999999999 | R5: 999999999 | S5: 999999999 | T5: 999999999 | U5: 999999999 | V5: 999999999 | W5: 999999999 | X5: 999999999 | Y5: 999999999 | Z5: 999999999 | AA5: 999999999 | AB5: 999999999 | AC5: 999999999 | AD5: 999999999 | AE5: 999999999 | AF5: 999999999 | AG5: 999999999 | AH5: 999999999 | AI5: 999999999 | AJ5: 999999999 | AK5: 999999999 | AL5: 999999999 | AM5: 999999999 | AN5: 999999999 | AO5: 999999999 | AP5: 999999999 | AQ5: 999999999 | AR5: 999999999 | AS5: 999999999 | AT5: 999999999 | AU5: 999999999 | AV5: 999999999 | AW5: 999999999 | AX5: 999999999 | AY5: 999999999 | AZ5: 999999999
A6: plugin hybrid vehicle | B6: 999999999 | C6: 999999999 | D6: 999999999 | E6: 999999999 | F6: 999999999 | G6: 999999999 | H6: 999999999 | I6: 999999999 | J6: 999999999 | K6: 999999999 | L6: 999999999 | M6: 999999999 | N6: 999999999 | O6: 999999999 | P6: 999999999 | Q6: 999999999 | R6: 999999999 | S6: 999999999 | T6: 999999999 | U6: 999999999 | V6: 999999999 | W6: 999999999 | X6: 999999999 | Y6: 999999999 | Z6: 999999999 | AA6: 999999999 | AB6: 999999999 | AC6: 999999999 | AD6: 999999999 | AE6: 999999999 | AF6: 999999999 | AG6: 999999999 | AH6: 999999999 | AI6: 999999999 | AJ6: 999999999 | AK6: 999999999 | AL6: 999999999 | AM6: 999999999 | AN6: 999999999 | AO6: 999999999 | AP6: 999999999 | AQ6: 999999999 | AR6: 999999999 | AS6: 999999999 | AT6: 999999999 | AU6: 999999999 | AV6: 999999999 | AW6: 999999999 | AX6: 999999999 | AY6: 999999999 | AZ6: 999999999
A7: LPG vehicle | B7: 999999999 | C7: 999999999 | D7: 999999999 | E7: 999999999 | F7: 999999999 | G7: 999999999 | H7: 999999999 | I7: 999999999 | J7: 999999999 | K7: 999999999 | L7: 999999999 | M7: 999999999 | N7: 999999999 | O7: 999999999 | P7: 999999999 | Q7: 999999999 | R7: 999999999 | S7: 999999999 | T7: 999999999 | U7: 999999999 | V7: 999999999 | W7: 999999999 | X7: 999999999 | Y7: 999999999 | Z7: 999999999 | AA7: 999999999 | AB7: 999999999 | AC7: 999999999 | AD7: 999999999 | AE7: 999999999 | AF7: 999999999 | AG7: 999999999 | AH7: 999999999 | AI7: 999999999 | AJ7: 999999999 | AK7: 999999999 | AL7: 999999999 | AM7: 999999999 | AN7: 999999999 | AO7: 999999999 | AP7: 999999999 | AQ7: 999999999 | AR7: 999999999 | AS7: 999999999 | AT7: 999999999 | AU7: 999999999 | AV7: 999999999 | AW7: 999999999 | AX7: 999999999 | AY7: 999999999 | AZ7: 999999999
A8: hydrogen vehicle | B8: 999999999 | C8: 999999999 | D8: 999999999 | E8: 999999999 | F8: 999999999 | G8: 999999999 | H8: 999999999 | I8: 999999999 | J8: 999999999 | K8: 999999999 | L8: 999999999 | M8: 999999999 | N8: 999999999 | O8: 999999999 | P8: 999999999 | Q8: 999999999 | R8: 999999999 | S8: 999999999 | T8: 999999999 | U8: 999999999 | V8: 999999999 | W8: 999999999 | X8: 999999999 | Y8: 999999999 | Z8: 999999999 | AA8: 999999999 | AB8: 999999999 | AC8: 999999999 | AD8: 999999999 | AE8: 999999999 | AF8: 999999999 | AG8: 999999999 | AH8: 999999999 | AI8: 999999999 | AJ8: 999999999 | AK8: 999999999 | AL8: 999999999 | AM8: 999999999 | AN8: 999999999 | AO8: 999999999 | AP8: 999999999 | AQ8: 999999999 | AR8: 999999999 | AS8: 999999999 | AT8: 999999999 | AU8: 999999999 | AV8: 999999999 | AW8: 999999999 | AX8: 999999999 | AY8: 999999999 | AZ8: 999999999

Sheet BNVP-motorbikes-frgt
A1: Price ($/vehicle) | B1: 2020 | C1: 2021 | D1: 2022 | E1: 2023 | F1: 2024 | G1: 2025 | H1: 2026 | I1: 2027 | J1: 2028 | K1: 2029 | L1: 2030 | M1: 2031 | N1: 2032 | O1: 2033 | P1: 2034 | Q1: 2035 | R1: 2036 | S1: 2037 | T1: 2038 | U1: 2039 | V1: 2040 | W1: 2041 | X1: 2042 | Y1: 2043 | Z1: 2044 | AA1: 2045 | AB1: 2046 | AC1: 2047 | AD1: 2048 | AE1: 2049 | AF1: 2050 | AG1: 2051 | AH1: 2052 | AI1: 2053 | AJ1: 2054 | AK1: 2055 | AL1: 2056 | AM1: 2057 | AN1: 2058 | AO1: 2059 | AP1: 2060 | AQ1: 2061 | AR1: 2062 | AS1: 2063 | AT1: 2064 | AU1: 2065 | AV1: 2066 | AW1: 2067 | AX1: 2068 | AY1: 2069 | AZ1: 2070
A2: battery electric vehicle | B2: 0 | C2: ='NVP-Indonesia'!C178*'NVP-Indonesia'!$B$227 -> 0 | D2: ='NVP-Indonesia'!D178*'NVP-Indonesia'!$B$227 -> 0 | E2: ='NVP-Indonesia'!E178*'NVP-Indonesia'!$B$227 -> 0 | F2: ='NVP-Indonesia'!F178*'NVP-Indonesia'!$B$227 -> 0 | G2: ='NVP-Indonesia'!G178*'NVP-Indonesia'!$B$227 -> 0 | H2: ='NVP-Indonesia'!H178*'NVP-Indonesia'!$B$227 -> 0 | I2: ='NVP-Indonesia'!I178*'NVP-Indonesia'!$B$227 -> 0 | J2: ='NVP-Indonesia'!J178*'NVP-Indonesia'!$B$227 -> 0 | ... AZ2: ='NVP-Indonesia'!AZ178*'NVP-Indonesia'!$B$227 -> 0
A3: natural gas vehicle | B3: 0 | C3: 0 | D3: 0 | E3: 0 | F3: 0 | G3: 0 | H3: 0 | I3: 0 | J3: 0 | K3: 0 | L3: 0 | M3: 0 | N3: 0 | O3: 0 | P3: 0 | Q3: 0 | R3: 0 | S3: 0 | T3: 0 | U3: 0 | V3: 0 | W3: 0 | X3: 0 | Y3: 0 | Z3: 0 | AA3: 0 | AB3: 0 | AC3: 0 | AD3: 0 | AE3: 0 | AF3: 0 | AG3: 0 | AH3: 0 | AI3: 0 | AJ3: 0 | AK3: 0 | AL3: 0 | AM3: 0 | AN3: 0 | AO3: 0 | AP3: 0 | AQ3: 0 | AR3: 0 | AS3: 0 | AT3: 0 | AU3: 0 | AV3: 0 | AW3: 0 | AX3: 0 | AY3: 0 | AZ3: 0
A4: gasoline vehicle | B4: 0 | C4: 0 | D4: 0 | E4: 0 | F4: 0 | G4: 0 | H4: 0 | I4: 0 | J4: 0 | K4: 0 | L4: 0 | M4: 0 | N4: 0 | O4: 0 | P4: 0 | Q4: 0 | R4: 0 | S4: 0 | T4: 0 | U4: 0 | V4: 0 | W4: 0 | X4: 0 | Y4: 0 | Z4: 0 | AA4: 0 | AB4: 0 | AC4: 0 | AD4: 0 | AE4: 0 | AF4: 0 | AG4: 0 | AH4: 0 | AI4: 0 | AJ4: 0 | AK4: 0 | AL4: 0 | AM4: 0 | AN4: 0 | AO4: 0 | AP4: 0 | AQ4: 0 | AR4: 0 | AS4: 0 | AT4: 0 | AU4: 0 | AV4: 0 | AW4: 0 | AX4: 0 | AY4: 0 | AZ4: 0
A5: diesel vehicle | B5: 0 | C5: 0 | D5: 0 | E5: 0 | F5: 0 | G5: 0 | H5: 0 | I5: 0 | J5: 0 | K5: 0 | L5: 0 | M5: 0 | N5: 0 | O5: 0 | P5: 0 | Q5: 0 | R5: 0 | S5: 0 | T5: 0 | U5: 0 | V5: 0 | W5: 0 | X5: 0 | Y5: 0 | Z5: 0 | AA5: 0 | AB5: 0 | AC5: 0 | AD5: 0 | AE5: 0 | AF5: 0 | AG5: 0 | AH5: 0 | AI5: 0 | AJ5: 0 | AK5: 0 | AL5: 0 | AM5: 0 | AN5: 0 | AO5: 0 | AP5: 0 | AQ5: 0 | AR5: 0 | AS5: 0 | AT5: 0 | AU5: 0 | AV5: 0 | AW5: 0 | AX5: 0 | AY5: 0 | AZ5: 0
A6: plugin hybrid vehicle | B6: 0 | C6: 0 | D6: 0 | E6: 0 | F6: 0 | G6: 0 | H6: 0 | I6: 0 | J6: 0 | K6: 0 | L6: 0 | M6: 0 | N6: 0 | O6: 0 | P6: 0 | Q6: 0 | R6: 0 | S6: 0 | T6: 0 | U6: 0 | V6: 0 | W6: 0 | X6: 0 | Y6: 0 | Z6: 0 | AA6: 0 | AB6: 0 | AC6: 0 | AD6: 0 | AE6: 0 | AF6: 0 | AG6: 0 | AH6: 0 | AI6: 0 | AJ6: 0 | AK6: 0 | AL6: 0 | AM6: 0 | AN6: 0 | AO6: 0 | AP6: 0 | AQ6: 0 | AR6: 0 | AS6: 0 | AT6: 0 | AU6: 0 | AV6: 0 | AW6: 0 | AX6: 0 | AY6: 0 | AZ6: 0
A7: LPG vehicle | B7: 0 | C7: 0 | D7: 0 | E7: 0 | F7: 0 | G7: 0 | H7: 0 | I7: 0 | J7: 0 | K7: 0 | L7: 0 | M7: 0 | N7: 0 | O7: 0 | P7: 0 | Q7: 0 | R7: 0 | S7: 0 | T7: 0 | U7: 0 | V7: 0 | W7: 0 | X7: 0 | Y7: 0 | Z7: 0 | AA7: 0 | AB7: 0 | AC7: 0 | AD7: 0 | AE7: 0 | AF7: 0 | AG7: 0 | AH7: 0 | AI7: 0 | AJ7: 0 | AK7: 0 | AL7: 0 | AM7: 0 | AN7: 0 | AO7: 0 | AP7: 0 | AQ7: 0 | AR7: 0 | AS7: 0 | AT7: 0 | AU7: 0 | AV7: 0 | AW7: 0 | AX7: 0 | AY7: 0 | AZ7: 0
A8: hydrogen vehicle | B8: 0 | C8: 0 | D8: 0 | E8: 0 | F8: 0 | G8: 0 | H8: 0 | I8: 0 | J8: 0 | K8: 0 | L8: 0 | M8: 0 | N8: 0 | O8: 0 | P8: 0 | Q8: 0 | R8: 0 | S8: 0 | T8: 0 | U8: 0 | V8: 0 | W8: 0 | X8: 0 | Y8: 0 | Z8: 0 | AA8: 0 | AB8: 0 | AC8: 0 | AD8: 0 | AE8: 0 | AF8: 0 | AG8: 0 | AH8: 0 | AI8: 0 | AJ8: 0 | AK8: 0 | AL8: 0 | AM8: 0 | AN8: 0 | AO8: 0 | AP8: 0 | AQ8: 0 | AR8: 0 | AS8: 0 | AT8: 0 | AU8: 0 | AV8: 0 | AW8: 0 | AX8: 0 | AY8: 0 | AZ8: 0
