Workbook

Sheet About
A1: SCoC Social Cost of Carbon
A3: Source: | B3: Interagency Working Group on Social Cost of Carbon, United States Government
B4: 2015
B5: Technical Update of the Social Cost of Carbon for Regulatory Impact Analysis
B6: https://www.whitehouse.gov/sites/default/files/omb/inforeg/scc-tsd-final-july-2015.pdf
B7: Page 17, Table A1
A9: Notes:
A10: When considering the Social Cost of Carbon, meant to capture the long-term economic damage caused by one
A11: ton of carbon dioxide emitted, the U.S. government typically uses the figures based on
A12: a 3% discount rate, so this is the rate we use in this model.
A13: Note that this differs from the discount rate specified in the "DR Discount Rate" variable, which is
A14: based on the Office of Management and Budget guidelines for analysis of prospective investments and policies.
A16: We adjust 2007 dollars to 2012 dollars using the following conversion factor:
A17: 1.109
A18: See "cpi.xlsx" in the InputData folder for source information.

Sheet SourceData
A1: Source Data in 2007 dollars/metric ton CO2 | G1: Data in 2012 dollars/gram CO2
A2: Discount Rate | B2: 0.05 | C2: 0.03 | D2: 0.025 | E2: 0.03 | G2: Discount Rate | H2: 0.05 | I2: 0.03 | J2: 0.025 | K2: 0.03
A3: Percentile | B3: Avg | C3: Avg | D3: Avg | E3: 95th% | G3: Percentile | H3: Avg | I3: Avg | J3: Avg | K3: 95th%
A4: 2010 | B4: 10 | C4: 31 | D4: 50 | E4: 86 | G4: =A4 -> 2010 | H4: =B4*(About!$A$17)/10^6 -> 1.109e-05 | I4: =C4*(About!$A$17)/10^6 -> 3.4379e-05 | J4: =D4*(About!$A$17)/10^6 -> 5.545e-05 | K4: =E4*(About!$A$17)/10^6 -> 9.5374e-05
A5: 2011 | B5: 11 | C5: 32 | D5: 51 | E5: 90 | G5: =A5 -> 2011 | H5: =B5*(About!$A$17)/10^6 -> 1.2199e-05 | I5: =C5*(About!$A$17)/10^6 -> 3.5488e-05 | J5: =D5*(About!$A$17)/10^6 -> 5.6559e-05 | K5: =E5*(About!$A$17)/10^6 -> 9.981e-05
A6: 2012 | B6: 11 | C6: 33 | D6: 53 | E6: 93 | G6: =A6 -> 2012 | H6: =B6*(About!$A$17)/10^6 -> 1.2199e-05 | I6: =C6*(About!$A$17)/10^6 -> 3.6597e-05 | J6: =D6*(About!$A$17)/10^6 -> 5.8777e-05 | K6: =E6*(About!$A$17)/10^6 -> 0.000103137
A7: 2013 | B7: 11 | C7: 34 | D7: 54 | E7: 97 | G7: =A7 -> 2013 | H7: =B7*(About!$A$17)/10^6 -> 1.2199e-05 | I7: =C7*(About!$A$17)/10^6 -> 3.7706e-05 | J7: =D7*(About!$A$17)/10^6 -> 5.9886e-05 | K7: =E7*(About!$A$17)/10^6 -> 0.000107573
A8: 2014 | B8: 11 | C8: 35 | D8: 55 | E8: 101 | G8: =A8 -> 2014 | H8: =B8*(About!$A$17)/10^6 -> 1.2199e-05 | I8: =C8*(About!$A$17)/10^6 -> 3.8815e-05 | J8: =D8*(About!$A$17)/10^6 -> 6.0995e-05 | K8: =E8*(About!$A$17)/10^6 -> 0.000112009
A9: 2015 | B9: 11 | C9: 36 | D9: 56 | E9: 105 | G9: =A9 -> 2015 | H9: =B9*(About!$A$17)/10^6 -> 1.2199e-05 | I9: =C9*(About!$A$17)/10^6 -> 3.9924e-05 | J9: =D9*(About!$A$17)/10^6 -> 6.2104e-05 | K9: =E9*(About!$A$17)/10^6 -> 0.000116445
A10: 2016 | B10: 11 | C10: 38 | D10: 57 | E10: 108 | G10: =A10 -> 2016 | H10: =B10*(About!$A$17)/10^6 -> 1.2199e-05 | I10: =C10*(About!$A$17)/10^6 -> 4.2142e-05 | J10: =D10*(About!$A$17)/10^6 -> 6.3213e-05 | K10: =E10*(About!$A$17)/10^6 -> 0.000119772
A11: 2017 | B11: 11 | C11: 39 | D11: 59 | E11: 112 | G11: =A11 -> 2017 | H11: =B11*(About!$A$17)/10^6 -> 1.2199e-05 | I11: =C11*(About!$A$17)/10^6 -> 4.3251e-05 | J11: =D11*(About!$A$17)/10^6 -> 6.5431e-05 | K11: =E11*(About!$A$17)/10^6 -> 0.000124208
A12: 2018 | B12: 12 | C12: 40 | D12: 60 | E12: 116 | G12: =A12 -> 2018 | H12: =B12*(About!$A$17)/10^6 -> 1.3308e-05 | I12: =C12*(About!$A$17)/10^6 -> 4.436e-05 | J12: =D12*(About!$A$17)/10^6 -> 6.654e-05 | K12: =E12*(About!$A$17)/10^6 -> 0.000128644
A13: 2019 | B13: 12 | C13: 41 | D13: 61 | E13: 120 | G13: =A13 -> 2019 | H13: =B13*(About!$A$17)/10^6 -> 1.3308e-05 | I13: =C13*(About!$A$17)/10^6 -> 4.5469e-05 | J13: =D13*(About!$A$17)/10^6 -> 6.7649e-05 | K13: =E13*(About!$A$17)/10^6 -> 0.00013308
A14: 2020 | B14: 12 | C14: 42 | D14: 62 | E14: 123 | G14: =A14 -> 2020 | H14: =B14*(About!$A$17)/10^6 -> 1.3308e-05 | I14: =C14*(About!$A$17)/10^6 -> 4.6578e-05 | J14: =D14*(About!$A$17)/10^6 -> 6.8758e-05 | K14: =E14*(About!$A$17)/10^6 -> 0.000136407
A15: 2021 | B15: 12 | C15: 42 | D15: 63 | E15: 126 | G15: =A15 -> 2021 | H15: =B15*(About!$A$17)/10^6 -> 1.3308e-05 | I15: =C15*(About!$A$17)/10^6 -> 4.6578e-05 | J15: =D15*(About!$A$17)/10^6 -> 6.9867e-05 | K15: =E15*(About!$A$17)/10^6 -> 0.000139734
... A44: 2050 | B44: 26 | C44: 69 | D44: 95 | E44: 212 | G44: =A44 -> 2050 | H44: =B44*(About!$A$17)/10^6 -> 2.8834e-05 | I44: =C44*(About!$A$17)/10^6 -> 7.6521e-05 | J44: =D44*(About!$A$17)/10^6 -> 0.000105355 | K44: =E44*(About!$A$17)/10^6 -> 0.000235108
A45: 2051 | B45: =_xlfn.FORECAST.LINEAR(A45,B4:B44,A4:A44) -> 25.146341 | C45: =_xlfn.FORECAST.LINEAR(B45,C4:C44,B4:B44) -> 69.238104 | D45: =_xlfn.FORECAST.LINEAR(C45,D4:D44,C4:C44) -> 95.349353 | E45: =_xlfn.FORECAST.LINEAR(D45,E4:E44,D4:D44) -> 214.48217 | G45: 2051 | H45: =B45*(About!$A$17)/10^6 -> 2.7887293e-05 | I45: =C45*(About!$A$17)/10^6 -> 7.6785057e-05 | J45: =D45*(About!$A$17)/10^6 -> 0.00010574243 | K45: =E45*(About!$A$17)/10^6 -> 0.00023786073
A46: 2052 | B46: =_xlfn.FORECAST.LINEAR(A46,B5:B45,A5:A45) -> 25.625253 | C46: =_xlfn.FORECAST.LINEAR(B46,C5:C45,B5:B45) -> 70.135071 | D46: =_xlfn.FORECAST.LINEAR(C46,D5:D45,C5:C45) -> 96.430907 | E46: =_xlfn.FORECAST.LINEAR(D46,E5:E45,D5:D45) -> 217.39446 | G46: 2052 | H46: =B46*(About!$A$17)/10^6 -> 2.8418405e-05 | I46: =C46*(About!$A$17)/10^6 -> 7.7779794e-05 | J46: =D46*(About!$A$17)/10^6 -> 0.00010694188 | K46: =E46*(About!$A$17)/10^6 -> 0.00024109045
A47: 2053 | B47: =_xlfn.FORECAST.LINEAR(A47,B6:B46,A6:A46) -> 26.147913 | C47: =_xlfn.FORECAST.LINEAR(B47,C6:C46,B6:B46) -> 71.094553 | D47: =_xlfn.FORECAST.LINEAR(C47,D6:D46,C6:C46) -> 97.578922 | E47: =_xlfn.FORECAST.LINEAR(D47,E6:E46,D6:D46) -> 220.53613 | G47: 2053 | H47: =B47*(About!$A$17)/10^6 -> 2.8998035e-05 | I47: =C47*(About!$A$17)/10^6 -> 7.8843859e-05 | J47: =D47*(About!$A$17)/10^6 -> 0.00010821502 | K47: =E47*(About!$A$17)/10^6 -> 0.00024457457
A48: 2054 | B48: =_xlfn.FORECAST.LINEAR(A48,B7:B47,A7:A47) -> 26.668057 | C48: =_xlfn.FORECAST.LINEAR(B48,C7:C47,B7:B47) -> 72.033713 | D48: =_xlfn.FORECAST.LINEAR(C48,D7:D47,C7:C47) -> 98.747695 | E48: =_xlfn.FORECAST.LINEAR(D48,E7:E47,D7:D47) -> 223.59619 | G48: 2054 | H48: =B48*(About!$A$17)/10^6 -> 2.9574875e-05 | I48: =C48*(About!$A$17)/10^6 -> 7.9885388e-05 | J48: =D48*(About!$A$17)/10^6 -> 0.00010951119 | K48: =E48*(About!$A$17)/10^6 -> 0.00024796817
A49: 2055 | B49: =_xlfn.FORECAST.LINEAR(A49,B8:B48,A8:A48) -> 27.183528 | C49: =_xlfn.FORECAST.LINEAR(B49,C8:C48,B8:B48) -> 72.952886 | D49: =_xlfn.FORECAST.LINEAR(C49,D8:D48,C8:C48) -> 99.890783 | E49: =_xlfn.FORECAST.LINEAR(D49,E8:E48,D8:D48) -> 226.61308 | G49: 2055 | H49: =B49*(About!$A$17)/10^6 -> 3.0146532e-05 | I49: =C49*(About!$A$17)/10^6 -> 8.090475e-05 | J49: =D49*(About!$A$17)/10^6 -> 0.00011077888 | K49: =E49*(About!$A$17)/10^6 -> 0.00025131391
A50: 2056 | B50: =_xlfn.FORECAST.LINEAR(A50,B9:B49,A9:A49) -> 27.691966 | C50: =_xlfn.FORECAST.LINEAR(B50,C9:C49,B9:B49) -> 73.852703 | D50: =_xlfn.FORECAST.LINEAR(C50,D9:D49,C9:C49) -> 101.00747 | E50: =_xlfn.FORECAST.LINEAR(D50,E9:E49,D9:D49) -> 229.59518 | G50: 2056 | H50: =B50*(About!$A$17)/10^6 -> 3.0710391e-05 | I50: =C50*(About!$A$17)/10^6 -> 8.1902648e-05 | J50: =D50*(About!$A$17)/10^6 -> 0.00011201729 | K50: =E50*(About!$A$17)/10^6 -> 0.00025462105
A51: 2057 | B51: =_xlfn.FORECAST.LINEAR(A51,B10:B50,A10:A50) -> 28.1908 | C51: =_xlfn.FORECAST.LINEAR(B51,C10:C50,B10:B50) -> 74.73421 | D51: =_xlfn.FORECAST.LINEAR(C51,D10:D50,C10:C50) -> 102.09748 | E51: =_xlfn.FORECAST.LINEAR(D51,E10:E50,D10:D50) -> 232.5527 | G51: 2057 | H51: =B51*(About!$A$17)/10^6 -> 3.1263598e-05 | I51: =C51*(About!$A$17)/10^6 -> 8.2880239e-05 | J51: =D51*(About!$A$17)/10^6 -> 0.00011322611 | K51: =E51*(About!$A$17)/10^6 -> 0.00025790094
A52: 2058 | B52: =_xlfn.FORECAST.LINEAR(A52,B11:B51,A11:A51) -> 28.677233 | C52: =_xlfn.FORECAST.LINEAR(B52,C11:C51,B11:B51) -> 75.64306 | D52: =_xlfn.FORECAST.LINEAR(C52,D11:D51,C11:C51) -> 103.15036 | E52: =_xlfn.FORECAST.LINEAR(D52,E11:E51,D11:D51) -> 235.41407 | G52: 2058 | H52: =B52*(About!$A$17)/10^6 -> 3.1803052e-05 | I52: =C52*(About!$A$17)/10^6 -> 8.3888154e-05 | J52: =D52*(About!$A$17)/10^6 -> 0.00011439374 | K52: =E52*(About!$A$17)/10^6 -> 0.0002610742
A53: 2059 | B53: =_xlfn.FORECAST.LINEAR(A53,B12:B52,A12:A52) -> 29.14823 | C53: =_xlfn.FORECAST.LINEAR(B53,C12:C52,B12:B52) -> 76.548404 | D53: =_xlfn.FORECAST.LINEAR(C53,D12:D52,C12:C52) -> 104.23294 | E53: =_xlfn.FORECAST.LINEAR(D53,E12:E52,D12:D52) -> 238.27651 | G53: 2059 | H53: =B53*(About!$A$17)/10^6 -> 3.2325387e-05 | I53: =C53*(About!$A$17)/10^6 -> 8.489218e-05 | J53: =D53*(About!$A$17)/10^6 -> 0.00011559433 | K53: =E53*(About!$A$17)/10^6 -> 0.00026424865
A54: 2060 | B54: =_xlfn.FORECAST.LINEAR(A54,B13:B53,A13:A53) -> 29.652943 | C54: =_xlfn.FORECAST.LINEAR(B54,C13:C53,B13:B53) -> 77.476976 | D54: =_xlfn.FORECAST.LINEAR(C54,D13:D53,C13:C53) -> 105.33231 | E54: =_xlfn.FORECAST.LINEAR(D54,E13:E53,D13:D53) -> 241.2305 | G54: 2060 | H54: =B54*(About!$A$17)/10^6 -> 3.2885114e-05 | I54: =C54*(About!$A$17)/10^6 -> 8.5921966e-05 | J54: =D54*(About!$A$17)/10^6 -> 0.00011681353 | K54: =E54*(About!$A$17)/10^6 -> 0.00026752462
A55: 2061 | B55: =_xlfn.FORECAST.LINEAR(A55,B14:B54,A14:A54) -> 30.14416 | C55: =_xlfn.FORECAST.LINEAR(B55,C14:C54,B14:B54) -> 78.402413 | D55: =_xlfn.FORECAST.LINEAR(C55,D14:D54,C14:C54) -> 106.41524 | E55: =_xlfn.FORECAST.LINEAR(D55,E14:E54,D14:D54) -> 244.19524 | G55: 2061 | H55: =B55*(About!$A$17)/10^6 -> 3.3429873e-05 | I55: =C55*(About!$A$17)/10^6 -> 8.6948276e-05 | J55: =D55*(About!$A$17)/10^6 -> 0.00011801451 | K55: =E55*(About!$A$17)/10^6 -> 0.00027081252
A56: 2062 | B56: =_xlfn.FORECAST.LINEAR(A56,B15:B55,A15:A55) -> 30.618716 | C56: =_xlfn.FORECAST.LINEAR(B56,C15:C55,B15:B55) -> 79.329451 | D56: =_xlfn.FORECAST.LINEAR(C56,D15:D55,C15:C55) -> 107.4859 | E56: =_xlfn.FORECAST.LINEAR(D56,E15:E55,D15:D55) -> 247.14068 | G56: 2062 | H56: =B56*(About!$A$17)/10^6 -> 3.3956156e-05 | I56: =C56*(About!$A$17)/10^6 -> 8.7976361e-05 | J56: =D56*(About!$A$17)/10^6 -> 0.00011920187 | K56: =E56*(About!$A$17)/10^6 -> 0.00027407902
... A64: 2070 | B64: =_xlfn.FORECAST.LINEAR(A64,B23:B63,A23:A63) -> 34.298224 | C64: =_xlfn.FORECAST.LINEAR(B64,C23:C63,B23:B63) -> 86.507343 | D64: =_xlfn.FORECAST.LINEAR(C64,D23:D63,C23:C63) -> 116.01963 | E64: =_xlfn.FORECAST.LINEAR(D64,E23:E63,D23:D63) -> 270.62643 | G64: 2070 | H64: =B64*(About!$A$17)/10^6 -> 3.8036731e-05 | I64: =C64*(About!$A$17)/10^6 -> 9.5936643e-05 | J64: =D64*(About!$A$17)/10^6 -> 0.00012866577 | K64: =E64*(About!$A$17)/10^6 -> 0.00030012471

Sheet SCoC
A1: Year | B1: Social Cost of Carbon ($/g CO2e)
A2: =SourceData!G4 -> 2010 | B2: =SourceData!I4 -> 3.4379e-05
A3: =SourceData!G5 -> 2011 | B3: =SourceData!I5 -> 3.5488e-05
A4: =SourceData!G6 -> 2012 | B4: =SourceData!I6 -> 3.6597e-05
A5: =SourceData!G7 -> 2013 | B5: =SourceData!I7 -> 3.7706e-05
A6: =SourceData!G8 -> 2014 | B6: =SourceData!I8 -> 3.8815e-05
A7: =SourceData!G9 -> 2015 | B7: =SourceData!I9 -> 3.9924e-05
A8: =SourceData!G10 -> 2016 | B8: =SourceData!I10 -> 4.2142e-05
A9: =SourceData!G11 -> 2017 | B9: =SourceData!I11 -> 4.3251e-05
A10: =SourceData!G12 -> 2018 | B10: =SourceData!I12 -> 4.436e-05
A11: =SourceData!G13 -> 2019 | B11: =SourceData!I13 -> 4.5469e-05
A12: =SourceData!G14 -> 2020 | B12: =SourceData!I14 -> 4.6578e-05
A13: =SourceData!G15 -> 2021 | B13: =SourceData!I15 -> 4.6578e-05
... A42: =SourceData!G44 -> 2050 | B42: =SourceData!I44 -> 7.6521e-05
A43: 2051 | B43: =SourceData!I45 -> 7.6785057e-05
A44: 2052 | B44: =SourceData!I46 -> 7.7779794e-05
A45: 2053 | B45: =SourceData!I47 -> 7.8843859e-05
A46: 2054 | B46: =SourceData!I48 -> 7.9885388e-05
A47: 2055 | B47: =SourceData!I49 -> 8.090475e-05
A48: 2056 | B48: =SourceData!I50 -> 8.1902648e-05
A49: 2057 | B49: =SourceData!I51 -> 8.2880239e-05
A50: 2058 | B50: =SourceData!I52 -> 8.3888154e-05
A51: 2059 | B51: =SourceData!I53 -> 8.489218e-05
A52: 2060 | B52: =SourceData!I54 -> 8.5921966e-05
A53: 2061 | B53: =SourceData!I55 -> 8.6948276e-05
A54: 2062 | B54: =SourceData!I56 -> 8.7976361e-05
... A62: 2070 | B62: =SourceData!I64 -> 9.5936643e-05
