Workbook
Name a: [1]ISICrev3.1!$E:$F
Name Calculated_Relationship_HS12___HS07: '[2]Correlation HS2012-HS2007'!#REF!
Name CAP_CT: #REF!
Name CAP_GFCF: #REF!
Name CAP_IT: #REF!
Name CAP_OCon: #REF!
Name CAP_OMach: #REF!
Name CAP_Other: #REF!
Name CAP_QI: #REF!
Name CAP_RStruc: #REF!
Name CAP_Soft: #REF!
Name CAP_TraEq: #REF!
Name CAPIT: #REF!
Name CAPIT_QI: #REF!
Name capit_qph: #REF!
Name CAPNIT: #REF!
Name CAPNIT_QI: #REF!
Name capnit_qph: #REF!
Name FLAPPIE: #REF!
Name go_level_top1: OFFSET('[3]35-sector'!$E$36,MATCH(#REF!,'[3]35-sector'!$E$37:$E$71,0),2,1,8)
Name HS: '[4]HS02_CPC1.1_SITC3_ISIC3.1 (2)'!#REF!
Name M1_stone: '[3]2000'!$E$1382:$BV$1451
Name M2_stone: '[3]2000'!$E$1524:$BV$1593
Name M3_stone: '[3]2000'!$E$1737:$BV$1806
Name Matrix1: #REF!
Name rca_trad_2010: '[5]13-sector VAX_G_2010'!$C$141:$P$203
Name rca_trad_2011: '[5]13-sector VAX_G_2011'!$C$141:$P$203
Name rca_trad_2012: '[5]13-sector VAX_G_2012'!$C$141:$P$203
Name rca_trad_2013: '[5]13-sector VAX_G_2013'!$C$141:$P$203
Name rca_trad_2014: '[5]13-sector VAX_G_2014'!$C$141:$P$203
Name rca_trad_2015: '[5]13-sector VAX_G_2015'!$C$141:$P$203
Name rca_trad_2016: '[5]13-sector VAX_G_2016'!$C$141:$P$203
Name rca_trad_2017: '[5]13-sector VAX_G_2017'!$C$141:$P$203
Name rca_vax_2010: '[5]13-sector VAX_G_2010'!$C$209:$P$271
Name rca_vax_2011: '[5]13-sector VAX_G_2011'!$C$209:$P$271
Name rca_vax_2012: '[5]13-sector VAX_G_2012'!$C$209:$P$271
Name rca_vax_2013: '[5]13-sector VAX_G_2013'!$C$209:$P$271
Name rca_vax_2014: '[5]13-sector VAX_G_2014'!$C$209:$P$271
Name rca_vax_2015: '[5]13-sector VAX_G_2015'!$C$209:$P$271
Name rca_vax_2016: '[5]13-sector VAX_G_2016'!$C$209:$P$271
Name rca_vax_2017: '[5]13-sector VAX_G_2017'!$C$209:$P$271
Name sector_list: #REF!
Name Sectors: #REF!
Name SUNBURST: '[5]35-sector'!#REF!
Name VAConL: #REF!
Name vax_g_2010: '[5]13-sector VAX_G_2010'!$T$5:$AI$67
Name vax_g_2011: '[5]13-sector VAX_G_2011'!$T$5:$AI$67
Name vax_g_2012: '[5]13-sector VAX_G_2012'!$T$5:$AI$67
Name vax_g_2013: '[5]13-sector VAX_G_2013'!$T$5:$AI$67
Name vax_g_2014: '[5]13-sector VAX_G_2014'!$T$5:$AI$67
Name vax_g_2015: '[5]13-sector VAX_G_2015'!$T$5:$AI$67
Name vax_g_2016: '[5]13-sector VAX_G_2016'!$T$5:$AI$67
Name vax_g_2017: '[5]13-sector VAX_G_2017'!$T$5:$AI$67
Name x_2010: '[5]13-sector VAX_G_2010'!$C$5:$R$67
Name x_2011: '[5]13-sector VAX_G_2011'!$C$5:$R$67
Name x_2012: '[5]13-sector VAX_G_2012'!$C$5:$R$67
Name x_2013: '[5]13-sector VAX_G_2013'!$C$5:$R$67
Name x_2014: '[5]13-sector VAX_G_2014'!$C$5:$R$67
Name x_2015: '[5]13-sector VAX_G_2015'!$C$5:$R$67
Name x_2016: '[5]13-sector VAX_G_2016'!$C$5:$R$67

Sheet About
A1: BPCiObIC BAU Percent Change in Output by ISIC Code
A3: Source: | B3: Most Industries
B4: OECD
B5: 2021
B6: Input-Output Tables 2021 Edition (ISIC Rev. 4)
B7: https://stats.oecd.org/Index.aspx?DataSetCode=IOTS_2021
B8: Variable: TTL
B11: BPS- Statistics Indonesia
B12: Growth Rate of GDP by Industry (2010=100) (Percent), 2026
B13: 2019-2025
B14: https://www.bps.go.id/en/statistics-table/2/MTA0IzI=/growth-rate-of-gdp-by-industry--2010-100---percent-.html
B17: Electricity consumption
B18: Statistik Industri Manufaktur Indonesia, 2020
B19: 2019-2024
B20: Badan Pusat Statistik
B21: https://www.bps.go.id/en/statistics-table/2/MTA0IzI=/growth-rate-of-gdp-by-industry--2010-100---percent-.html
A24: Notes: | B24: We examine each industry to determin the appropriate trend, then carry that forward.
B25: From there, we estimate the annual percentage growth.
B27: Note that this is not linked to BIFUbC nor fuel production.

Sheet OECD 2018
B1: =DotStatQuery(C1) -> #NAME? | C1: Sorry, the query is too large to fit into the Excel cell. You will not be able to update your table with the .Stat Populator.
B2: Dataset: Input-Output Tables (IOTs) 2021 ed.
B3: Variable | D3: TTL: Total | M3: 1 | N3: 2 | O3: 3 | P3: 4 | Q3: 5 | R3: 6 | S3: 7 | T3: 8 | U3: 9 | V3: 10 | W3: 11 | X3: 12 | Y3: 13 | Z3: 14 | AA3: 15
B4: Country | D4: IDN: Indonesia
B5: From industry / sector | D5: OUTPUT: Output at basic prices
B6: Unit | D6: US Dollar, Millions
D7: 1995 | E7: 1996 | F7: 1997 | G7: 1998 | H7: 1999 | I7: 2000 | J7: 2001 | K7: 2002 | L7: 2003 | M7: 2004 | N7: 2005 | O7: 2006 | P7: 2007 | Q7: 2008 | R7: 2009 | S7: 2010 | T7: 2011 | U7: 2012 | V7: 2013 | W7: 2014 | X7: 2015 | Y7: 2016 | Z7: 2017 | AA7: 2018 | AB7: SPARK | AC7: Intercept | AD7: Slope | AE7: R2
A9: ISIC 01T03 | B9: D01T02: Agriculture, hunting, forestry | D9: 34317.2 | E9: 38860.9 | F9: 37050.6 | G9: 16258.4 | H9: 24351.3 | I9: 26274.1 | J9: 25280.6 | K9: 30755.7 | L9: 36838.9 | M9: 40118.3 | N9: 44253.6 | O9: 56841.2 | P9: 67541.6 | Q9: 79095.1 | R9: 86180.8 | S9: 110613.9 | T9: 128256.9 | U9: 132003.4 | V9: 129858.8 | W9: 126113.1 | X9: 120681.1 | Y9: 128515.9 | Z9: 139310.1 | AA9: 142726.1 | AC9: =INTERCEPT(M9:AA9,$M$7:$AA$7) -> -15047330 | AD9: =SLOPE(M9:AA9,$M$7:$AA$7) -> 7533.3021 | AE9: =RSQ(M9:AA9,$M$7:$AA$7) -> 0.86881943
B10: D03: Fishing and aquaculture | D10: 5520.9 | E10: 6287.4 | F10: 6045.8 | G10: 2681.1 | H10: 4021.7 | I10: 4353.5 | J10: 4228 | K10: 5167.5 | L10: 6212.5 | M10: 6774.5 | N10: 7533.3 | O10: 9578.6 | P10: 11357.8 | Q10: 13401.8 | R10: 14114.8 | S10: 18553.9 | T10: 21833.2 | U10: 22470.9 | V10: 22371.7 | W10: 22986.5 | X10: 23974.1 | Y10: 26461.3 | Z10: 28943.2 | AA10: 30116.1 | AC10: =INTERCEPT(M10:AA10,$M$7:$AA$7) -> -3399385.7 | AD10: =SLOPE(M10:AA10,$M$7:$AA$7) -> 1699.6936 | AE10: =RSQ(M10:AA10,$M$7:$AA$7) -> 0.97185619
A11: ISIC 05 | B11: D05T06: Mining and quarrying, energy producing products | D11: 22832.6 | E11: 26011.3 | F11: 25010.7 | G11: 11090.8 | H11: 16637.1 | I11: 18013.5 | J11: 17480.3 | K11: 21363.1 | L11: 25680.6 | M11: 28006 | N11: 31143.8 | O11: 39627.2 | P11: 46987.6 | Q11: 55453.4 | R11: 58389.6 | S11: 76742.9 | T11: 94749.2 | U11: 92616.4 | V11: 92534.8 | W11: 88476.9 | X11: 84666.1 | Y11: 90166.4 | Z11: 97743.9 | AA11: 100140.2 | AC11: =INTERCEPT(M11:AA11,$M$7:$AA$7) -> -10638070 | AD11: =SLOPE(M11:AA11,$M$7:$AA$7) -> 5325.6586 | AE11: =RSQ(M11:AA11,$M$7:$AA$7) -> 0.85025292
A12: ISIC 07T08 | B12: D07T08: Mining and quarrying, non-energy producing products | D12: 9601 | E12: 10869 | F12: 10420.2 | G12: 4557 | H12: 6788 | I12: 7545.8 | J12: 6936.4 | K12: 7835.3 | L12: 9418.8 | M12: 10271.7 | N12: 12560.1 | O12: 15919 | P12: 18625.3 | Q12: 21877.2 | R12: 22792.9 | S12: 30658.7 | T12: 35808.1 | U12: 36632.7 | V12: 36625.7 | W12: 35752 | X12: 32544.4 | Y12: 34801 | Z12: 37808.5 | AA12: 38835.3 | AC12: =INTERCEPT(M12:AA12,$M$7:$AA$7) -> -4114458.6 | AD12: =SLOPE(M12:AA12,$M$7:$AA$7) -> 2059.95 | AE12: =RSQ(M12:AA12,$M$7:$AA$7) -> 0.84353377
A13: ISIC 09 | B13: D09: Mining support service activities | D13: 1352.5 | E13: 1528.2 | F13: 1470.8 | G13: 653.1 | H13: 978.7 | I13: 1054.6 | J13: 1042.9 | K13: 1276.5 | L13: 1538.5 | M13: 1674.4 | N13: 1860.9 | O13: 2328.3 | P13: 2761.2 | Q13: 3244.8 | R13: 3436.6 | S13: 4531 | T13: 5763.8 | U13: 5936.4 | V13: 5844.9 | W13: 5680.7 | X13: 5435.9 | Y13: 5783.8 | Z13: 6263.7 | AA13: 6417.9 | AC13: =INTERCEPT(M13:AA13,$M$7:$AA$7) -> -721846.43 | AD13: =SLOPE(M13:AA13,$M$7:$AA$7) -> 361.16893 | AE13: =RSQ(M13:AA13,$M$7:$AA$7) -> 0.87897435
A14: ISIC 10T12 | B14: D10T12: Food products, beverages and tobacco | D14: 36432.7 | E14: 40567.5 | F14: 39051.5 | G14: 17318.7 | H14: 25977.6 | I14: 27973.8 | J14: 26860.4 | K14: 32906.2 | L14: 39722.4 | M14: 43227.5 | N14: 47972.5 | O14: 63456.6 | P14: 75364.5 | Q14: 88685.6 | R14: 94414.7 | S14: 124268.1 | T14: 143982.2 | U14: 148772.6 | V14: 146988.7 | W14: 143476.8 | X14: 137297.2 | Y14: 144220.8 | Z14: 156370.9 | AA14: 160201.6 | AC14: =INTERCEPT(M14:AA14,$M$7:$AA$7) -> -17228765 | AD14: =SLOPE(M14:AA14,$M$7:$AA$7) -> 8624.2393 | AE14: =RSQ(M14:AA14,$M$7:$AA$7) -> 0.86803975
A15: ISIC 13T15 | B15: D13T15: Textiles, textile products, leather and footwear | D15: 11991.1 | E15: 14775.2 | F15: 14199.3 | G15: 7277.8 | H15: 9561.6 | I15: 10900.8 | J15: 10994.6 | K15: 12443.6 | L15: 14588 | M15: 15901.2 | N15: 17604.8 | O15: 21337.4 | P15: 24544.7 | Q15: 28529.1 | R15: 30423.5 | S15: 39542.2 | T15: 45611.3 | U15: 46754.9 | V15: 46294 | W15: 45475.9 | X15: 44187.9 | Y15: 47086 | Z15: 50976 | AA15: 52239.5 | AC15: =INTERCEPT(M15:AA15,$M$7:$AA$7) -> -5361753.6 | AD15: =SLOPE(M15:AA15,$M$7:$AA$7) -> 2684.6614 | AE15: =RSQ(M15:AA15,$M$7:$AA$7) -> 0.89628504
A16: ISIC 16 | B16: D16: Wood and products of wood and cork | D16: 3625.6 | E16: 4038.1 | F16: 3887.1 | G16: 1723.8 | H16: 2585.7 | I16: 2784.7 | J16: 2676.9 | K16: 3279.4 | L16: 3958.6 | M16: 4308.1 | N16: 4780.9 | O16: 6273 | P16: 7450.3 | Q16: 8767.6 | R16: 9334 | S16: 12284.4 | T16: 14287.7 | U16: 14762 | V16: 14583.7 | W16: 14233.7 | X16: 13620.7 | Y16: 14311.9 | Z16: 15517.3 | AA16: 15897.5 | AC16: =INTERCEPT(M16:AA16,$M$7:$AA$7) -> -1710885.4 | AD16: =SLOPE(M16:AA16,$M$7:$AA$7) -> 856.41286 | AE16: =RSQ(M16:AA16,$M$7:$AA$7) -> 0.86890222
A17: ISIC 17T18 | B17: D17T18: Paper products and printing | D17: 5743 | E17: 6391.9 | F17: 6153 | G17: 2728.6 | H17: 4093 | I17: 4407.6 | J17: 4240.3 | K17: 5194.7 | L17: 6270.9 | M17: 6824.1 | N17: 7573.2 | O17: 9926.6 | P17: 11789.3 | Q17: 13872.7 | R17: 14768.8 | S17: 19439.5 | T17: 23023.6 | U17: 23789.1 | V17: 23503.4 | W17: 22940.6 | X17: 21952.5 | Y17: 23065.1 | Z17: 25005.9 | AA17: 25618.8 | AC17: =INTERCEPT(M17:AA17,$M$7:$AA$7) -> -2793795.9 | AD17: =SLOPE(M17:AA17,$M$7:$AA$7) -> 1398.3104 | AE17: =RSQ(M17:AA17,$M$7:$AA$7) -> 0.87159065
A18: ISIC 19 | B18: D19: Coke and refined petroleum products | D18: 19822.4 | E18: 21651.6 | F18: 20664.1 | G18: 9161.2 | H18: 13744.6 | I18: 15410.8 | J18: 15573.4 | K18: 18758.4 | L18: 21974.4 | M18: 24293.1 | N18: 27343.6 | O18: 36111.7 | P18: 42434.4 | Q18: 50934.7 | R18: 50299.7 | S18: 65477.8 | T18: 82684 | U18: 83146.5 | V18: 79675.9 | W18: 74951.4 | X18: 71722.4 | Y18: 82949.1 | Z18: 89846.8 | AA18: 92056.9 | AC18: =INTERCEPT(M18:AA18,$M$7:$AA$7) -> -9626379.6 | AD18: =SLOPE(M18:AA18,$M$7:$AA$7) -> 4818.4857 | AE18: =RSQ(M18:AA18,$M$7:$AA$7) -> 0.86951253
A19: ISIC 20 | B19: D20: Chemical and chemical products | D19: 9080.7 | E19: 10113.8 | F19: 9735.6 | G19: 4317.4 | H19: 6476.2 | I19: 6974.7 | J19: 6704.7 | K19: 8213.7 | L19: 9914.9 | M19: 10790.1 | N19: 11974.4 | O19: 15711.5 | P19: 18660.2 | Q19: 21959.5 | R19: 23378.3 | S19: 30768 | T19: 35785.3 | U19: 36973.2 | V19: 36526.9 | W19: 35650.1 | X19: 34114.7 | Y19: 35846.1 | Z19: 38865 | AA19: 39817.2 | AC19: =INTERCEPT(M19:AA19,$M$7:$AA$7) -> -4285129.5 | AD19: =SLOPE(M19:AA19,$M$7:$AA$7) -> 2144.9946 | AE19: =RSQ(M19:AA19,$M$7:$AA$7) -> 0.86890142
A20: ISIC 21 | B20: D21: Pharmaceuticals, medicinal chemical and botanical products | D20: 1445.2 | E20: 1530.7 | F20: 1474.9 | G20: 655 | H20: 981.5 | I20: 1052 | J20: 788.6 | K20: 966.5 | L20: 1169.4 | M20: 1270 | N20: 1409.1 | O20: 2454.1 | P20: 2913.3 | Q20: 3423.4 | R20: 3643.7 | S20: 4806.8 | T20: 4107.6 | U20: 4247.1 | V20: 4199.6 | W20: 4102 | X20: 3925.3 | Y20: 4120.8 | Z20: 4463.4 | AA20: 4573.2 | AC20: =INTERCEPT(M20:AA20,$M$7:$AA$7) -> -401621.97 | AD20: =SLOPE(M20:AA20,$M$7:$AA$7) -> 201.49143 | AE20: =RSQ(M20:AA20,$M$7:$AA$7) -> 0.67452398
A21: ISIC 22 | B21: D22: Rubber and plastics products | D21: 6713.8 | E21: 7477.7 | F21: 7198 | G21: 3192.1 | H21: 4788.2 | I21: 5156.8 | J21: 4957.1 | K21: 6072.8 | L21: 7330.5 | M21: 7977.6 | N21: 8853.2 | O21: 11616.3 | P21: 13796.4 | Q21: 16235.7 | R21: 17284.7 | S21: 22748.3 | T21: 26457.8 | U21: 27336.1 | V21: 27006.1 | W21: 26357.9 | X21: 25222.7 | Y21: 26502.8 | Z21: 28734.8 | AA21: 29438.8 | AC21: =INTERCEPT(M21:AA21,$M$7:$AA$7) -> -3168213.4 | AD21: =SLOPE(M21:AA21,$M$7:$AA$7) -> 1585.9032 | AE21: =RSQ(M21:AA21,$M$7:$AA$7) -> 0.86890196
A22: ISIC 23 | B22: D23: Other non-metallic mineral products | D22: 3746.5 | E22: 4172.7 | F22: 4016.7 | G22: 1781.3 | H22: 2671.9 | I22: 2877.6 | J22: 2766.2 | K22: 3388.8 | L22: 4090.6 | M22: 4451.7 | N22: 4940.3 | O22: 6482.2 | P22: 7698.7 | Q22: 9060 | R22: 9645.3 | S22: 12694.2 | T22: 14764.2 | U22: 15254.3 | V22: 15070.1 | W22: 14708.4 | X22: 14074.9 | Y22: 14789.3 | Z22: 16034.8 | AA22: 16427.7 | AC22: =INTERCEPT(M22:AA22,$M$7:$AA$7) -> -1767953.6 | AD22: =SLOPE(M22:AA22,$M$7:$AA$7) -> 884.97929 | AE22: =RSQ(M22:AA22,$M$7:$AA$7) -> 0.86890126
... A34: ISIC 45T47 | B34: D45T47: Wholesale and retail trade; repair of motor vehicles | D34: 44544 | E34: 50728.1 | F34: 48778.7 | G34: 21631.8 | H34: 32448 | I34: 35125.5 | J34: 34112.6 | K34: 41692.4 | L34: 50124 | M34: 54658 | N34: 60780.4 | O34: 77282.5 | P34: 91637.8 | Q34: 108129.2 | R34: 113881.9 | S34: 149697.2 | T34: 176155.5 | U34: 181301.1 | V34: 178355.6 | W34: 173211 | X34: 165750.4 | Y34: 176511.2 | Z34: 191336.5 | AA34: 196028.3 | AC34: =INTERCEPT(M34:AA34,$M$7:$AA$7) -> -20841685 | AD34: =SLOPE(M34:AA34,$M$7:$AA$7) -> 10433.283 | AE34: =RSQ(M34:AA34,$M$7:$AA$7) -> 0.87134133
A35: ISIC 49T53 | B35: COMBINED: 4953 | D35: =SUM(D36:D40) -> 18014 | E35: =SUM(E36:E40) -> 20515 | F35: =SUM(F36:F40) -> 19726.5 | G35: =SUM(G36:G40) -> 8748.1 | H35: =SUM(H36:H40) -> 13122.2 | I35: =SUM(I36:I40) -> 14205 | J35: =SUM(J36:J40) -> 13795.5 | K35: =SUM(K36:K40) -> 16860.9 | ... AA35: =SUM(AA36:AA40) -> 93728.7 | AC35: =INTERCEPT(M35:AA35,$M$7:$AA$7) -> -10294557 | AD35: =SLOPE(M35:AA35,$M$7:$AA$7) -> 5148.7082 | AE35: =RSQ(M35:AA35,$M$7:$AA$7) -> 0.95071072
B36: D49: Land transport and transport via pipelines | D36: 8988.8 | E36: 10239.8 | F36: 9846.2 | G36: 4366.5 | H36: 6549.7 | I36: 7090.5 | J36: 6883.8 | K36: 8413.3 | L36: 10114.6 | M36: 11029.8 | N36: 12265.2 | O36: 15597 | P36: 18494.1 | Q36: 21824.5 | R36: 22982.6 | S36: 30208.3 | T36: 35291.5 | U36: 36321.6 | V36: 35730.5 | W36: 34699.1 | X36: 33204.5 | Y36: 35361.1 | Z36: 38332.3 | AA36: 39272.1 | AC36: =INTERCEPT(M36:AA36,$M$7:$AA$7) -> -4151920.9 | AD36: =SLOPE(M36:AA36,$M$7:$AA$7) -> 2078.5489 | AE36: =RSQ(M36:AA36,$M$7:$AA$7) -> 0.87024344
B37: D50: Water transport | D37: 2751 | E37: 3133.8 | F37: 3013.4 | G37: 1336.3 | H37: 2004.5 | I37: 2170 | J37: 2106.8 | K37: 2574.9 | L37: 3095.5 | M37: 3375.6 | N37: 3753.7 | O37: 4773.4 | P37: 5660 | Q37: 6679.3 | R37: 7033.7 | S37: 9245.1 | T37: 10800.8 | U37: 11116 | V37: 10935.2 | W37: 10619.5 | X37: 10162.1 | Y37: 10822.1 | Z37: 11731.4 | AA37: 12019 | AC37: =INTERCEPT(M37:AA37,$M$7:$AA$7) -> -1270675.6 | AD37: =SLOPE(M37:AA37,$M$7:$AA$7) -> 636.13 | AE37: =RSQ(M37:AA37,$M$7:$AA$7) -> 0.87024326
B38: D51: Air transport | D38: 3689.2 | E38: 4202.6 | F38: 4041 | G38: 1792.1 | H38: 2688.1 | I38: 2910.1 | J38: 2825.2 | K38: 3453 | L38: 4151.2 | M38: 4526.8 | N38: 5033.8 | O38: 6401.3 | P38: 7590.3 | Q38: 8957.2 | R38: 9432.5 | S38: 12398.1 | T38: 14484.3 | U38: 14907 | V38: 14664.5 | W38: 16120.7 | X38: 19118.3 | Y38: 23951.6 | Z38: 29776.2 | AA38: 30571.1 | AC38: =INTERCEPT(M38:AA38,$M$7:$AA$7) -> -3570016.8 | AD38: =SLOPE(M38:AA38,$M$7:$AA$7) -> 1782.4693 | AE38: =RSQ(M38:AA38,$M$7:$AA$7) -> 0.91870327
B39: D52: Warehousing and support activities for transportation | D39: 2176.8 | E39: 2479.8 | F39: 2384.4 | G39: 1057.4 | H39: 1586.2 | I39: 1717.1 | J39: 1667.1 | K39: 2037.5 | L39: 2449.4 | M39: 2671.1 | N39: 2970.3 | O39: 3777.1 | P39: 4478.7 | Q39: 5285.2 | R39: 5565.7 | S39: 7315.6 | T39: 8546.5 | U39: 8796 | V39: 8652.9 | W39: 8403.1 | X39: 8041.1 | Y39: 8563.4 | Z39: 9282.9 | AA39: 9510.5 | AC39: =INTERCEPT(M39:AA39,$M$7:$AA$7) -> -1005467.7 | AD39: =SLOPE(M39:AA39,$M$7:$AA$7) -> 503.36071 | AE39: =RSQ(M39:AA39,$M$7:$AA$7) -> 0.87024147
B40: D53: Postal and courier activities | D40: 408.2 | E40: 459 | F40: 441.5 | G40: 195.8 | H40: 293.7 | I40: 317.3 | J40: 312.6 | K40: 382.2 | L40: 459.9 | M40: 500.9 | N40: 557.2 | O40: 704.9 | P40: 836 | Q40: 982.3 | R40: 1040.5 | S40: 1371.9 | T40: 2115.9 | U40: 2179.2 | V40: 2145.7 | W40: 2085.4 | X40: 1995.6 | Y40: 2123.2 | Z40: 2299.4 | AA40: 2356 | AC40: =INTERCEPT(M40:AA40,$M$7:$AA$7) -> -296475.82 | AD40: =SLOPE(M40:AA40,$M$7:$AA$7) -> 148.19929 | AE40: =RSQ(M40:AA40,$M$7:$AA$7) -> 0.87605351
A41: ISIC 55T56 | B41: D55T56: Accommodation and food service activities | D41: 14355.2 | E41: 16348.2 | F41: 15719.9 | G41: 6971.3 | H41: 10457 | I41: 11319.9 | J41: 10993.5 | K41: 13436.2 | L41: 16153.5 | M41: 17614.7 | N41: 19587.7 | O41: 24905.8 | P41: 29532.1 | Q41: 34846.8 | R41: 36700.8 | S41: 48242.9 | T41: 56769.7 | U41: 58427.9 | V41: 57478.7 | W41: 55820.8 | X41: 53416.4 | Y41: 56884.3 | Z41: 61662.1 | AA41: 63174.1 | AC41: =INTERCEPT(M41:AA41,$M$7:$AA$7) -> -6716657.8 | AD41: =SLOPE(M41:AA41,$M$7:$AA$7) -> 3362.3382 | AE41: =RSQ(M41:AA41,$M$7:$AA$7) -> 0.87134171
A42: ISIC 58T60 | B42: D58T60: Publishing, audiovisual and broadcasting activities | D42: 3756 | E42: 4461.6 | F42: 4288.5 | G42: 1901.6 | H42: 2852.6 | I42: 3093.6 | J42: 2719.5 | K42: 3320.1 | L42: 3983.8 | M42: 4247 | N42: 4840.1 | O42: 5778.5 | P42: 6854.2 | Q42: 8096.6 | R42: 8528.9 | S42: 11191.4 | T42: 12738.5 | U42: 13089.1 | V42: 12855.8 | W42: 12477.4 | X42: 11940.1 | Y42: 12772.5 | Z42: 13839.9 | AA42: 14179.9 | AC42: =INTERCEPT(M42:AA42,$M$7:$AA$7) -> -1444418.1 | AD42: =SLOPE(M42:AA42,$M$7:$AA$7) -> 723.345 | AE42: =RSQ(M42:AA42,$M$7:$AA$7) -> 0.8675895
A43: ISIC 61 | B43: D61: Telecommunications | D43: 7189.8 | E43: 8429.5 | F43: 8106 | G43: 3676 | H43: 5391.9 | I43: 5835.9 | J43: 6074.6 | K43: 7928.7 | L43: 9142.6 | M43: 11030.7 | N43: 11236.1 | O43: 14687.7 | P43: 17414 | Q43: 20540.4 | R43: 21631.9 | S43: 28451.7 | T43: 32086.2 | U43: 33052.3 | V43: 32541.7 | W43: 31609.1 | X43: 30247.5 | Y43: 32125.7 | Z43: 34841 | AA43: 35693.6 | AC43: =INTERCEPT(M43:AA43,$M$7:$AA$7) -> -3654461 | AD43: =SLOPE(M43:AA43,$M$7:$AA$7) -> 1830.0714 | AE43: =RSQ(M43:AA43,$M$7:$AA$7) -> 0.86283708
A44: ISIC 62T63 | B44: D62T63: IT and other information services | D44: 2384.3 | E44: 2289.6 | F44: 2202.8 | G44: 978.2 | H44: 1465.8 | I44: 1582 | J44: 1414.3 | K44: 1729.3 | L44: 2080.4 | M44: 2213.3 | N44: 2521 | O44: 2661 | P44: 3155 | Q44: 3721.4 | R44: 3919.1 | S44: 5154.7 | T44: 7890.9 | U44: 8114.1 | V44: 7976.6 | W44: 7748 | X44: 7414.2 | Y44: 7923.9 | Z44: 8577.7 | AA44: 8789.2 | AC44: =INTERCEPT(M44:AA44,$M$7:$AA$7) -> -1063403.9 | AD44: =SLOPE(M44:AA44,$M$7:$AA$7) -> 531.70357 | AE44: =RSQ(M44:AA44,$M$7:$AA$7) -> 0.8724947
A45: ISIC 64T66 | B45: D64T66: Financial and insurance activities | D45: 10787.7 | E45: 12285.3 | F45: 11813.2 | G45: 5238.8 | H45: 7858.3 | I45: 8506.7 | J45: 8261.4 | K45: 10097.1 | L45: 12139 | M45: 13237.1 | N45: 14719.8 | O45: 18716.3 | P45: 22192.9 | Q45: 26186.8 | R45: 27580 | S45: 36253.7 | T45: 42661.4 | U45: 43907.5 | V45: 43194.2 | W45: 41948.3 | X45: 40141.5 | Y45: 44824.9 | Z45: 48982.1 | AA45: 48486.4 | AC45: =INTERCEPT(M45:AA45,$M$7:$AA$7) -> -5286494.4 | AD45: =SLOPE(M45:AA45,$M$7:$AA$7) -> 2645.7964 | AE45: =RSQ(M45:AA45,$M$7:$AA$7) -> 0.8939242
A46: ISIC 68 | B46: D68: Real estate activities | D46: 8410.1 | E46: 9798.9 | F46: 9271.8 | G46: 4062.8 | H46: 5995.1 | I46: 6425.3 | J46: 6238.4 | K46: 8040.8 | L46: 9343.8 | M46: 9987.7 | N46: 10950.2 | O46: 13745 | P46: 16082.2 | Q46: 18976.4 | R46: 19986 | S46: 26271.5 | T46: 30914.9 | U46: 31817.9 | V46: 31301 | W46: 30398.1 | X46: 29088.8 | Y46: 30977.3 | Z46: 33579.1 | AA46: 34402.5 | AC46: =INTERCEPT(M46:AA46,$M$7:$AA$7) -> -3618981.8 | AD46: =SLOPE(M46:AA46,$M$7:$AA$7) -> 1811.8086 | AE46: =RSQ(M46:AA46,$M$7:$AA$7) -> 0.87210105
A47: ISIC 69T82 | B47: COMBINED: 69T82 | D47: =SUM(D48:D49) -> 5443.1 | E47: =SUM(E48:E49) -> 6195 | F47: =SUM(F48:F49) -> 5957 | G47: =SUM(G48:G49) -> 2641.8 | H47: =SUM(H48:H49) -> 3962.7 | I47: =SUM(I48:I49) -> 4289.6 | J47: =SUM(J48:J49) -> 4166 | K47: =SUM(K48:K49) -> 5091.6 | ... AA47: =SUM(AA48:AA49) -> 24467.5 | AC47: =INTERCEPT(M47:AA47,$M$7:$AA$7) -> -2615636.8 | AD47: =SLOPE(M47:AA47,$M$7:$AA$7) -> 1309.2471 | AE47: =RSQ(M47:AA47,$M$7:$AA$7) -> 0.87109964
B48: D69T75: Professional, scientific and technical activities | D48: 983 | E48: 1781.7 | F48: 1713.3 | G48: 759.8 | H48: 1139.7 | I48: 1233.7 | J48: 1193.9 | K48: 1459.4 | L48: 1755 | M48: 1913.5 | N48: 2127.5 | O48: 2169.1 | P48: 2574.2 | Q48: 3090.3 | R48: 3307.8 | S48: 4256.9 | T48: 4180.4 | U48: 4571.7 | V48: 4302.5 | W48: 4015.2 | X48: 3808.2 | Y48: 4053.5 | Z48: 4342 | AA48: 4483.7 | AC48: =INTERCEPT(M48:AA48,$M$7:$AA$7) -> -360698.1 | AD48: =SLOPE(M48:AA48,$M$7:$AA$7) -> 181.12607 | AE48: =RSQ(M48:AA48,$M$7:$AA$7) -> 0.74238842
B49: D77T82: Administrative and support services | D49: 4460.1 | E49: 4413.3 | F49: 4243.7 | G49: 1882 | H49: 2823 | I49: 3055.9 | J49: 2972.1 | K49: 3632.2 | L49: 4367.6 | M49: 4761.5 | N49: 5295.2 | O49: 7268.9 | P49: 8619.1 | Q49: 10170.3 | R49: 10711.3 | S49: 14080 | T49: 17625.3 | U49: 18140.1 | V49: 17845.4 | W49: 17330.7 | X49: 16618 | Y49: 17824.8 | Z49: 19417.4 | AA49: 19983.8 | AC49: =INTERCEPT(M49:AA49,$M$7:$AA$7) -> -2254938.7 | AD49: =SLOPE(M49:AA49,$M$7:$AA$7) -> 1128.1211 | AE49: =RSQ(M49:AA49,$M$7:$AA$7) -> 0.88546445
A50: ISIC 84 | B50: D84: Public administration and defence; compulsory social security | D50: 13646.2 | E50: 15540.7 | F50: 14943.5 | G50: 6626.9 | H50: 9940.5 | I50: 10760.8 | J50: 10450.5 | K50: 12772.6 | L50: 15355.6 | M50: 16744.6 | N50: 18620.2 | O50: 23675.7 | P50: 28073.5 | Q50: 33125.6 | R50: 34888 | S50: 45860.1 | T50: 53965.6 | U50: 55542 | V50: 54639.6 | W50: 53063.6 | X50: 50778 | Y50: 54074.6 | Z50: 58616.4 | AA50: 60053.7 | AC50: =INTERCEPT(M50:AA50,$M$7:$AA$7) -> -6384895.3 | AD50: =SLOPE(M50:AA50,$M$7:$AA$7) -> 3196.2589 | AE50: =RSQ(M50:AA50,$M$7:$AA$7) -> 0.87134158
A51: ISIC 85 | B51: D85: Education | D51: 10147.7 | E51: 11556.5 | F51: 11112.4 | G51: 4928 | H51: 7392.1 | I51: 8002 | J51: 7771.3 | K51: 9498.1 | L51: 11418.9 | M51: 12451.8 | N51: 13846.6 | O51: 17605.9 | P51: 20876.3 | Q51: 24633.2 | R51: 25943.8 | S51: 34102.9 | T51: 40130.5 | U51: 41302.7 | V51: 40631.7 | W51: 39459.7 | X51: 37760.1 | Y51: 40211.5 | Z51: 43588.9 | AA51: 44657.8 | AC51: =INTERCEPT(M51:AA51,$M$7:$AA$7) -> -4748003.8 | AD51: =SLOPE(M51:AA51,$M$7:$AA$7) -> 2376.8361 | AE51: =RSQ(M51:AA51,$M$7:$AA$7) -> 0.87134184
A52: ISIC 86T88 | B52: D86T88: Human health and social work activities | D52: 4864.7 | E52: 5540.1 | F52: 5327.2 | G52: 2362.4 | H52: 3543.7 | I52: 3836.1 | J52: 3725.5 | K52: 4553.3 | L52: 5474.1 | M52: 5969.3 | N52: 6637.9 | O52: 8440.1 | P52: 10007.9 | Q52: 11808.9 | R52: 12437.2 | S52: 16348.6 | T52: 19238.1 | U52: 19800.1 | V52: 19478.4 | W52: 18916.5 | X52: 18101.8 | Y52: 19277 | Z52: 20896 | AA52: 21408.4 | AC52: =INTERCEPT(M52:AA52,$M$7:$AA$7) -> -2276133.3 | AD52: =SLOPE(M52:AA52,$M$7:$AA$7) -> 1139.4254 | AE52: =RSQ(M52:AA52,$M$7:$AA$7) -> 0.87134075
A53: ISIC 90T96 | B53: COMBINED: 90T96 | D53: =SUM(D54:D55) -> 4726.2 | E53: =SUM(E54:E55) -> 5438.2 | F53: =SUM(F54:F55) -> 5236.6 | G53: =SUM(G54:G55) -> 2325.4 | H53: =SUM(H54:H55) -> 3492.9 | I53: =SUM(I54:I55) -> 3785.3 | J53: =SUM(J54:J55) -> 3634.6 | K53: =SUM(K54:K55) -> 4441.6 | ... AA53: =SUM(AA54:AA55) -> 21047.5 | AC53: =INTERCEPT(M53:AA53,$M$7:$AA$7) -> -2284620.1 | AD53: =SLOPE(M53:AA53,$M$7:$AA$7) -> 1143.4486 | AE53: =RSQ(M53:AA53,$M$7:$AA$7) -> 0.87506163
B54: D90T93: Arts, entertainment and recreation | D54: 1230.6 | E54: 1712.4 | F54: 1649.5 | G54: 733.3 | H54: 1100.5 | I54: 1190.3 | J54: 896.7 | K54: 1096.7 | L54: 1320.2 | M54: 1438 | N54: 1597.8 | O54: 1951 | P54: 2312.7 | Q54: 2727.9 | R54: 2872 | S54: 3775.4 | T54: 6113.2 | U54: 6291.7 | V54: 6186 | W54: 6005.5 | X54: 5746.8 | Y54: 6115 | Z54: 6628.1 | AA54: 6790.7 | AC54: =INTERCEPT(M54:AA54,$M$7:$AA$7) -> -865925.45 | AD54: =SLOPE(M54:AA54,$M$7:$AA$7) -> 432.80071 | AE54: =RSQ(M54:AA54,$M$7:$AA$7) -> 0.87128709
B55: D94T96: Other service activities | D55: 3495.6 | E55: 3725.8 | F55: 3587.1 | G55: 1592.1 | H55: 2392.4 | I55: 2595 | J55: 2737.9 | K55: 3344.9 | L55: 4019.2 | M55: 4382.3 | N55: 4873.2 | O55: 6051.1 | P55: 7172.9 | Q55: 8460.7 | R55: 8907.7 | S55: 11709.6 | T55: 12834.4 | U55: 13209.1 | V55: 12987.3 | W55: 12608.4 | X55: 12065.1 | Y55: 12838.2 | Z55: 13915.5 | AA55: 14256.8 | AC55: =INTERCEPT(M55:AA55,$M$7:$AA$7) -> -1418694.7 | AD55: =SLOPE(M55:AA55,$M$7:$AA$7) -> 710.64786 | AE55: =RSQ(M55:AA55,$M$7:$AA$7) -> 0.85636687
A56: ISIC 97T98 | B56: D97T98: Activities of households as employers; undifferentiated goods- and services-producing activities of households for own use | D56: 678.3 | E56: 637.6 | F56: 605.1 | G56: 267.6 | H56: 392.5 | I56: 421.6 | J56: 493.8 | K56: 662.8 | L56: 843.1 | M56: 969.6 | N56: 1123.2 | O56: 1697.8 | P56: 1918.1 | Q56: 2068 | R56: 2160.5 | S56: 2935.9 | T56: 2570.2 | U56: 2604.3 | V56: 2675.2 | W56: 2749.2 | X56: 2838.9 | Y56: 3168.6 | Z56: 3566.3 | AA56: 3763.2 | AC56: =INTERCEPT(M56:AA56,$M$7:$AA$7) -> -342234.34 | AD56: =SLOPE(M56:AA56,$M$7:$AA$7) -> 171.40143 | AE56: =RSQ(M56:AA56,$M$7:$AA$7) -> 0.90563946
B57: HFCE: Final consumption expenditure of households | D57: 0 | E57: 0 | F57: 0 | G57: 0 | H57: 0 | I57: 0 | J57: 0 | K57: 0 | L57: 0 | M57: 0 | N57: 0 | O57: 0 | P57: 0 | Q57: 0 | R57: 0 | S57: 0 | T57: 0 | U57: 0 | V57: 0 | W57: 0 | X57: 0 | Y57: 0 | Z57: 0 | AA57: 0
B58: NPISH: Final consumption expenditure of non-profit institutions serving households | D58: 0 | E58: 0 | F58: 0 | G58: 0 | H58: 0 | I58: 0 | J58: 0 | K58: 0 | L58: 0 | M58: 0 | N58: 0 | O58: 0 | P58: 0 | Q58: 0 | R58: 0 | S58: 0 | T58: 0 | U58: 0 | V58: 0 | W58: 0 | X58: 0 | Y58: 0 | Z58: 0 | AA58: 0
B59: GGFC: Final consumption expenditure of general government | D59: 0 | E59: 0 | F59: 0 | G59: 0 | H59: 0 | I59: 0 | J59: 0 | K59: 0 | L59: 0 | M59: 0 | N59: 0 | O59: 0 | P59: 0 | Q59: 0 | R59: 0 | S59: 0 | T59: 0 | U59: 0 | V59: 0 | W59: 0 | X59: 0 | Y59: 0 | Z59: 0 | AA59: 0
B60: GFCF: Gross Fixed Capital Formation | D60: 0 | E60: 0 | F60: 0 | G60: 0 | H60: 0 | I60: 0 | J60: 0 | K60: 0 | L60: 0 | M60: 0 | N60: 0 | O60: 0 | P60: 0 | Q60: 0 | R60: 0 | S60: 0 | T60: 0 | U60: 0 | V60: 0 | W60: 0 | X60: 0 | Y60: 0 | Z60: 0 | AA60: 0
B61: INVNT: Changes in inventories | D61: 0 | E61: 0 | F61: 0 | G61: 0 | H61: 0 | I61: 0 | J61: 0 | K61: 0 | L61: 0 | M61: 0 | N61: 0 | O61: 0 | P61: 0 | Q61: 0 | R61: 0 | S61: 0 | T61: 0 | U61: 0 | V61: 0 | W61: 0 | X61: 0 | Y61: 0 | Z61: 0 | AA61: 0
B62: CONS_ABR: Direct purchases abroad by residents (imports) | D62: 0 | E62: 0 | F62: 0 | G62: 0 | H62: 0 | I62: 0 | J62: 0 | K62: 0 | L62: 0 | M62: 0 | N62: 0 | O62: 0 | P62: 0 | Q62: 0 | R62: 0 | S62: 0 | T62: 0 | U62: 0 | V62: 0 | W62: 0 | X62: 0 | Y62: 0 | Z62: 0 | AA62: 0
B63: CONS_NONRES: Direct purchases by non-residents (exports) | D63: 0 | E63: 0 | F63: 0 | G63: 0 | H63: 0 | I63: 0 | J63: 0 | K63: 0 | L63: 0 | M63: 0 | N63: 0 | O63: 0 | P63: 0 | Q63: 0 | R63: 0 | S63: 0 | T63: 0 | U63: 0 | V63: 0 | W63: 0 | X63: 0 | Y63: 0 | Z63: 0 | AA63: 0
B64: EXPO: Exports (cross border) | D64: 0 | E64: 0 | F64: 0 | G64: 0 | H64: 0 | I64: 0 | J64: 0 | K64: 0 | L64: 0 | M64: 0 | N64: 0 | O64: 0 | P64: 0 | Q64: 0 | R64: 0 | S64: 0 | T64: 0 | U64: 0 | V64: 0 | W64: 0 | X64: 0 | Y64: 0 | Z64: 0 | AA64: 0
B65: IMPO: Imports (cross border) | D65: 0 | E65: 0 | F65: 0 | G65: 0 | H65: 0 | I65: 0 | J65: 0 | K65: 0 | L65: 0 | M65: 0 | N65: 0 | O65: 0 | P65: 0 | Q65: 0 | R65: 0 | S65: 0 | T65: 0 | U65: 0 | V65: 0 | W65: 0 | X65: 0 | Y65: 0 | Z65: 0 | AA65: 0
B66: Data extracted on 28 Mar 2023 19:43 UTC (GMT) from OECD.Stat

Sheet isic groups
A1: ISIC used | B1: ISIC Group | E1: bifubc sector used | F1: bifubc sector grouped
A2: ISIC 01T03 | E2: agriculture and forestry 01T03
A3: ISIC 239 | B3: ISIC 231 | E3: cement and other nonmetallic minerals 239 | F3: glass and glass products 231
A4: ISIC 20 | E4: chemicals 20
A5: ISIC 05 | E5: coal mining 05
A6: ISIC 41T43 | E6: construction 41T43
A7: ISIC 352T353 | E7: energy pipelines and gas processing 352T353
A8: ISIC 10T12 | E8: food beverage and tobacco 10T12
A9: ISIC 241 | E9: iron and steel 241
A10: ISIC 25 | B10: ISIC 26 | C10: ISIC 27 | D10: ISIC 28 | E10: metal products except machinery and vehicles 25 | F10: computers and electronics 26 | G10: appliances and electrical equipment 27 | H10: other machinery 28
A11: ISIC 06 | E11: oil and gas extraction 06
A12: ISIC 31T33 | B12: ISIC 22 | E12: other manufacturing 31T33 | F12: rubber and plastic products 22
A13: ISIC 242 | E13: other metals 242
A14: ISIC 07T08 | E14: other mining and quarrying 07T08
A15: ISIC 17T18 | E15: pulp paper and printing 17T18
A16: ISIC 19 | E16: refined petroleum and coke 19
A17: ISIC 29 | B17: ISIC 30 | E17: road vehicles 29 | F17: nonroad vehicles 30
A18: ISIC 13T15 | E18: textiles apparel and leather 13T15
A19: ISIC 16 | E19: wood products 16

Sheet calcs
A1: Preconsolidation
A2: original | B2: consolidated | C2: Intercept | D2: Slope | E2: 2018 | F2: 2020 | G2: 2021 | H2: 2022 | I2: 2023 | J2: 2024 | K2: 2025 | L2: 2026 | M2: 2027 | N2: 2028 | O2: 2029 | P2: 2030 | Q2: 2031 | R2: 2032 | S2: 2033 | T2: 2034 | U2: 2035 | V2: 2036 | W2: 2037 | X2: 2038 | Y2: 2039 | Z2: 2040 | AA2: 2041 | AB2: 2042 | AC2: 2043 | AD2: 2044 | AE2: 2045 | AF2: 2046 | AG2: 2047 | AH2: 2048 | AI2: 2049 | AJ2: 2050 | AL2: TOTAL
A3: ISIC 01T03 | B3: ISIC 01T03 | C3: {=INDEX('OECD 2018'!AC:AC,MATCH($A3,'OECD 2018'!$A:$A,0))} -> -15047330 | D3: {=INDEX('OECD 2018'!AD:AD,MATCH($A3,'OECD 2018'!$A:$A,0))} -> 7533.3021 | E3: =SUMIFS('OECD 2018'!$AA$9:$AA$65,'OECD 2018'!$A$9:$A$65,calcs!A3) -> 142726.1 | F3: =F$2*$D3+$C3 -> 169940.38 | G3: =G$2*$D3+$C3 -> 177473.68 | H3: =H$2*$D3+$C3 -> 185006.98 | I3: =I$2*$D3+$C3 -> 192540.29 | J3: =J$2*$D3+$C3 -> 200073.59 | K3: =K$2*$D3+$C3 -> 207606.89 | L3: =L$2*$D3+$C3 -> 215140.19 | M3: =M$2*$D3+$C3 -> 222673.49 | ... AJ3: =AJ$2*$D3+$C3 -> 395939.44 | AL3: =(AJ3-E3)/E3 -> 1.7741208
A4: ISIC 05 | B4: ISIC 05 | C4: {=INDEX('OECD 2018'!AC:AC,MATCH($A4,'OECD 2018'!$A:$A,0))} -> -10638070 | D4: {=INDEX('OECD 2018'!AD:AD,MATCH($A4,'OECD 2018'!$A:$A,0))} -> 5325.6586 | E4: =SUMIFS('OECD 2018'!$AA$9:$AA$65,'OECD 2018'!$A$9:$A$65,calcs!A4) -> 100140.2 | F4: =F$2*$D4+$C4 -> 119760.55 | G4: =G$2*$D4+$C4 -> 125086.21 | H4: =H$2*$D4+$C4 -> 130411.87 | I4: =I$2*$D4+$C4 -> 135737.53 | J4: =J$2*$D4+$C4 -> 141063.19 | K4: =K$2*$D4+$C4 -> 146388.85 | L4: =L$2*$D4+$C4 -> 151714.51 | M4: =M$2*$D4+$C4 -> 157040.16 | ... AJ4: =AJ$2*$D4+$C4 -> 279530.31 | AL4: =(AJ4-E4)/E4 -> 1.7913896
A5: ISIC 07T08 | B5: ISIC 07T08 | C5: {=INDEX('OECD 2018'!AC:AC,MATCH($A5,'OECD 2018'!$A:$A,0))} -> -4114458.6 | D5: {=INDEX('OECD 2018'!AD:AD,MATCH($A5,'OECD 2018'!$A:$A,0))} -> 2059.95 | E5: =SUMIFS('OECD 2018'!$AA$9:$AA$65,'OECD 2018'!$A$9:$A$65,calcs!A5) -> 38835.3 | F5: =F$2*$D5+$C5 -> 46640.39 | G5: =G$2*$D5+$C5 -> 48700.34 | H5: =H$2*$D5+$C5 -> 50760.29 | I5: =I$2*$D5+$C5 -> 52820.24 | J5: =J$2*$D5+$C5 -> 54880.19 | K5: =K$2*$D5+$C5 -> 56940.14 | L5: =L$2*$D5+$C5 -> 59000.09 | M5: =M$2*$D5+$C5 -> 61060.04 | ... AJ5: =AJ$2*$D5+$C5 -> 108438.89 | AL5: =(AJ5-E5)/E5 -> 1.7922764
A6: ISIC 09 | B6: ISIC 09 | C6: {=INDEX('OECD 2018'!AC:AC,MATCH($A6,'OECD 2018'!$A:$A,0))} -> -721846.43 | D6: {=INDEX('OECD 2018'!AD:AD,MATCH($A6,'OECD 2018'!$A:$A,0))} -> 361.16893 | E6: =SUMIFS('OECD 2018'!$AA$9:$AA$65,'OECD 2018'!$A$9:$A$65,calcs!A6) -> 6417.9 | F6: =F$2*$D6+$C6 -> 7714.807 | G6: =G$2*$D6+$C6 -> 8075.976 | H6: =H$2*$D6+$C6 -> 8437.1449 | I6: =I$2*$D6+$C6 -> 8798.3138 | J6: =J$2*$D6+$C6 -> 9159.4827 | K6: =K$2*$D6+$C6 -> 9520.6517 | L6: =L$2*$D6+$C6 -> 9881.8206 | M6: =M$2*$D6+$C6 -> 10242.99 | ... AJ6: =AJ$2*$D6+$C6 -> 18549.875 | AL6: =(AJ6-E6)/E6 -> 1.890334
A7: ISIC 10T12 | B7: ISIC 10T12 | C7: {=INDEX('OECD 2018'!AC:AC,MATCH($A7,'OECD 2018'!$A:$A,0))} -> -17228765 | D7: {=INDEX('OECD 2018'!AD:AD,MATCH($A7,'OECD 2018'!$A:$A,0))} -> 8624.2393 | E7: =SUMIFS('OECD 2018'!$AA$9:$AA$65,'OECD 2018'!$A$9:$A$65,calcs!A7) -> 160201.6 | F7: =F$2*$D7+$C7 -> 192198.17 | G7: =G$2*$D7+$C7 -> 200822.41 | H7: =H$2*$D7+$C7 -> 209446.65 | I7: =I$2*$D7+$C7 -> 218070.89 | J7: =J$2*$D7+$C7 -> 226695.13 | K7: =K$2*$D7+$C7 -> 235319.37 | L7: =L$2*$D7+$C7 -> 243943.61 | M7: =M$2*$D7+$C7 -> 252567.85 | ... AJ7: =AJ$2*$D7+$C7 -> 450925.35 | AL7: =(AJ7-E7)/E7 -> 1.8147369
A8: ISIC 13T15 | B8: ISIC 13T15 | C8: {=INDEX('OECD 2018'!AC:AC,MATCH($A8,'OECD 2018'!$A:$A,0))} -> -5361753.6 | D8: {=INDEX('OECD 2018'!AD:AD,MATCH($A8,'OECD 2018'!$A:$A,0))} -> 2684.6614 | E8: =SUMIFS('OECD 2018'!$AA$9:$AA$65,'OECD 2018'!$A$9:$A$65,calcs!A8) -> 52239.5 | F8: =F$2*$D8+$C8 -> 61262.513 | G8: =G$2*$D8+$C8 -> 63947.174 | H8: =H$2*$D8+$C8 -> 66631.836 | I8: =I$2*$D8+$C8 -> 69316.497 | J8: =J$2*$D8+$C8 -> 72001.159 | K8: =K$2*$D8+$C8 -> 74685.82 | L8: =L$2*$D8+$C8 -> 77370.481 | M8: =M$2*$D8+$C8 -> 80055.143 | ... AJ8: =AJ$2*$D8+$C8 -> 141802.36 | AL8: =(AJ8-E8)/E8 -> 1.7144662
A9: ISIC 16 | B9: ISIC 16 | C9: {=INDEX('OECD 2018'!AC:AC,MATCH($A9,'OECD 2018'!$A:$A,0))} -> -1710885.4 | D9: {=INDEX('OECD 2018'!AD:AD,MATCH($A9,'OECD 2018'!$A:$A,0))} -> 856.41286 | E9: =SUMIFS('OECD 2018'!$AA$9:$AA$65,'OECD 2018'!$A$9:$A$65,calcs!A9) -> 15897.5 | F9: =F$2*$D9+$C9 -> 19068.569 | G9: =G$2*$D9+$C9 -> 19924.982 | H9: =H$2*$D9+$C9 -> 20781.395 | I9: =I$2*$D9+$C9 -> 21637.808 | J9: =J$2*$D9+$C9 -> 22494.22 | K9: =K$2*$D9+$C9 -> 23350.633 | L9: =L$2*$D9+$C9 -> 24207.046 | M9: =M$2*$D9+$C9 -> 25063.459 | ... AJ9: =AJ$2*$D9+$C9 -> 44760.955 | AL9: =(AJ9-E9)/E9 -> 1.8155971
A10: ISIC 17T18 | B10: ISIC 17T18 | C10: {=INDEX('OECD 2018'!AC:AC,MATCH($A10,'OECD 2018'!$A:$A,0))} -> -2793795.9 | D10: {=INDEX('OECD 2018'!AD:AD,MATCH($A10,'OECD 2018'!$A:$A,0))} -> 1398.3104 | E10: =SUMIFS('OECD 2018'!$AA$9:$AA$65,'OECD 2018'!$A$9:$A$65,calcs!A10) -> 25618.8 | F10: =F$2*$D10+$C10 -> 30791.007 | G10: =G$2*$D10+$C10 -> 32189.317 | H10: =H$2*$D10+$C10 -> 33587.627 | I10: =I$2*$D10+$C10 -> 34985.938 | J10: =J$2*$D10+$C10 -> 36384.248 | K10: =K$2*$D10+$C10 -> 37782.558 | L10: =L$2*$D10+$C10 -> 39180.869 | M10: =M$2*$D10+$C10 -> 40579.179 | ... AJ10: =AJ$2*$D10+$C10 -> 72740.317 | AL10: =(AJ10-E10)/E10 -> 1.8393335
A11: ISIC 19 | B11: ISIC 19 | C11: {=INDEX('OECD 2018'!AC:AC,MATCH($A11,'OECD 2018'!$A:$A,0))} -> -9626379.6 | D11: {=INDEX('OECD 2018'!AD:AD,MATCH($A11,'OECD 2018'!$A:$A,0))} -> 4818.4857 | E11: =SUMIFS('OECD 2018'!$AA$9:$AA$65,'OECD 2018'!$A$9:$A$65,calcs!A11) -> 92056.9 | F11: =F$2*$D11+$C11 -> 106961.57 | G11: =G$2*$D11+$C11 -> 111780.06 | H11: =H$2*$D11+$C11 -> 116598.54 | I11: =I$2*$D11+$C11 -> 121417.03 | J11: =J$2*$D11+$C11 -> 126235.51 | K11: =K$2*$D11+$C11 -> 131054 | L11: =L$2*$D11+$C11 -> 135872.49 | M11: =M$2*$D11+$C11 -> 140690.97 | ... AJ11: =AJ$2*$D11+$C11 -> 251516.14 | AL11: =(AJ11-E11)/E11 -> 1.7321813
A12: ISIC 20 | B12: ISIC 20 | C12: {=INDEX('OECD 2018'!AC:AC,MATCH($A12,'OECD 2018'!$A:$A,0))} -> -4285129.5 | D12: {=INDEX('OECD 2018'!AD:AD,MATCH($A12,'OECD 2018'!$A:$A,0))} -> 2144.9946 | E12: =SUMIFS('OECD 2018'!$AA$9:$AA$65,'OECD 2018'!$A$9:$A$65,calcs!A12) -> 39817.2 | F12: =F$2*$D12+$C12 -> 47759.652 | G12: =G$2*$D12+$C12 -> 49904.646 | H12: =H$2*$D12+$C12 -> 52049.641 | I12: =I$2*$D12+$C12 -> 54194.636 | J12: =J$2*$D12+$C12 -> 56339.63 | K12: =K$2*$D12+$C12 -> 58484.625 | L12: =L$2*$D12+$C12 -> 60629.62 | M12: =M$2*$D12+$C12 -> 62774.614 | ... AJ12: =AJ$2*$D12+$C12 -> 112109.49 | AL12: =(AJ12-E12)/E12 -> 1.8156046
A13: ISIC 21 | B13: ISIC 21 | C13: {=INDEX('OECD 2018'!AC:AC,MATCH($A13,'OECD 2018'!$A:$A,0))} -> -401621.97 | D13: {=INDEX('OECD 2018'!AD:AD,MATCH($A13,'OECD 2018'!$A:$A,0))} -> 201.49143 | E13: =SUMIFS('OECD 2018'!$AA$9:$AA$65,'OECD 2018'!$A$9:$A$65,calcs!A13) -> 4573.2 | F13: =F$2*$D13+$C13 -> 5390.7162 | G13: =G$2*$D13+$C13 -> 5592.2076 | H13: =H$2*$D13+$C13 -> 5793.699 | I13: =I$2*$D13+$C13 -> 5995.1905 | J13: =J$2*$D13+$C13 -> 6196.6819 | K13: =K$2*$D13+$C13 -> 6398.1733 | L13: =L$2*$D13+$C13 -> 6599.6648 | M13: =M$2*$D13+$C13 -> 6801.1562 | ... AJ13: =AJ$2*$D13+$C13 -> 11435.459 | AL13: =(AJ13-E13)/E13 -> 1.5005377
A14: ISIC 22 | B14: ISIC 31T33 | C14: {=INDEX('OECD 2018'!AC:AC,MATCH($A14,'OECD 2018'!$A:$A,0))} -> -3168213.4 | D14: {=INDEX('OECD 2018'!AD:AD,MATCH($A14,'OECD 2018'!$A:$A,0))} -> 1585.9032 | E14: =SUMIFS('OECD 2018'!$AA$9:$AA$65,'OECD 2018'!$A$9:$A$65,calcs!A14) -> 29438.8 | F14: =F$2*$D14+$C14 -> 35311.076 | G14: =G$2*$D14+$C14 -> 36896.979 | H14: =H$2*$D14+$C14 -> 38482.882 | I14: =I$2*$D14+$C14 -> 40068.785 | J14: =J$2*$D14+$C14 -> 41654.688 | K14: =K$2*$D14+$C14 -> 43240.592 | L14: =L$2*$D14+$C14 -> 44826.495 | M14: =M$2*$D14+$C14 -> 46412.398 | ... AJ14: =AJ$2*$D14+$C14 -> 82888.172 | AL14: =(AJ14-E14)/E14 -> 1.8156097
... A40: ISIC 97T98 | B40: ISIC 97T98 | C40: {=INDEX('OECD 2018'!AC:AC,MATCH($A40,'OECD 2018'!$A:$A,0))} -> -342234.34 | D40: {=INDEX('OECD 2018'!AD:AD,MATCH($A40,'OECD 2018'!$A:$A,0))} -> 171.40143 | E40: =SUMIFS('OECD 2018'!$AA$9:$AA$65,'OECD 2018'!$A$9:$A$65,calcs!A40) -> 3763.2 | F40: =F$2*$D40+$C40 -> 3996.5462 | G40: =G$2*$D40+$C40 -> 4167.9476 | H40: =H$2*$D40+$C40 -> 4339.349 | I40: =I$2*$D40+$C40 -> 4510.7505 | J40: =J$2*$D40+$C40 -> 4682.1519 | K40: =K$2*$D40+$C40 -> 4853.5533 | L40: =L$2*$D40+$C40 -> 5024.9548 | M40: =M$2*$D40+$C40 -> 5196.3562 | ... AJ40: =AJ$2*$D40+$C40 -> 9138.589 | AL40: =(AJ40-E40)/E40 -> 1.4284091
A42: consolidation
A43: =SUM(F44:AJ81)=SUM(F3:AJ40) -> TRUE | F43: 2020 | G43: 2021 | H43: 2022 | I43: 2023 | J43: 2024 | K43: 2025 | L43: 2026 | M43: 2027 | N43: 2028 | O43: 2029 | P43: 2030 | Q43: 2031 | R43: 2032 | S43: 2033 | T43: 2034 | U43: 2035 | V43: 2036 | W43: 2037 | X43: 2038 | Y43: 2039 | Z43: 2040 | AA43: 2041 | AB43: 2042 | AC43: 2043 | AD43: 2044 | AE43: 2045 | AF43: 2046 | AG43: 2047 | AH43: 2048 | AI43: 2049 | AJ43: 2050 | AL43: TOTAL
A44: ISIC 01T03 | F44: =SUMIFS(F$3:F$40,$B$3:$B$40,$A44) -> 169940.38 | G44: =SUMIFS(G$3:G$40,$B$3:$B$40,$A44) -> 177473.68 | H44: =SUMIFS(H$3:H$40,$B$3:$B$40,$A44) -> 185006.98 | I44: =SUMIFS(I$3:I$40,$B$3:$B$40,$A44) -> 192540.29 | J44: =SUMIFS(J$3:J$40,$B$3:$B$40,$A44) -> 200073.59 | K44: =SUMIFS(K$3:K$40,$B$3:$B$40,$A44) -> 207606.89 | L44: =SUMIFS(L$3:L$40,$B$3:$B$40,$A44) -> 215140.19 | M44: =SUMIFS(M$3:M$40,$B$3:$B$40,$A44) -> 222673.49 | ... AJ44: =SUMIFS(AJ$3:AJ$40,$B$3:$B$40,$A44) -> 395939.44 | AL44: =(AJ44-E44)/E44 -> #DIV/0!
A45: ISIC 05 | F45: =SUMIFS(F$3:F$40,$B$3:$B$40,$A45) -> 119760.55 | G45: =SUMIFS(G$3:G$40,$B$3:$B$40,$A45) -> 125086.21 | H45: =SUMIFS(H$3:H$40,$B$3:$B$40,$A45) -> 130411.87 | I45: =SUMIFS(I$3:I$40,$B$3:$B$40,$A45) -> 135737.53 | J45: =SUMIFS(J$3:J$40,$B$3:$B$40,$A45) -> 141063.19 | K45: =SUMIFS(K$3:K$40,$B$3:$B$40,$A45) -> 146388.85 | L45: =SUMIFS(L$3:L$40,$B$3:$B$40,$A45) -> 151714.51 | M45: =SUMIFS(M$3:M$40,$B$3:$B$40,$A45) -> 157040.16 | ... AJ45: =SUMIFS(AJ$3:AJ$40,$B$3:$B$40,$A45) -> 279530.31 | AL45: =(AJ45-E45)/E45 -> #DIV/0!
A46: ISIC 07T08 | F46: =SUMIFS(F$3:F$40,$B$3:$B$40,$A46) -> 46640.39 | G46: =SUMIFS(G$3:G$40,$B$3:$B$40,$A46) -> 48700.34 | H46: =SUMIFS(H$3:H$40,$B$3:$B$40,$A46) -> 50760.29 | I46: =SUMIFS(I$3:I$40,$B$3:$B$40,$A46) -> 52820.24 | J46: =SUMIFS(J$3:J$40,$B$3:$B$40,$A46) -> 54880.19 | K46: =SUMIFS(K$3:K$40,$B$3:$B$40,$A46) -> 56940.14 | L46: =SUMIFS(L$3:L$40,$B$3:$B$40,$A46) -> 59000.09 | M46: =SUMIFS(M$3:M$40,$B$3:$B$40,$A46) -> 61060.04 | ... AJ46: =SUMIFS(AJ$3:AJ$40,$B$3:$B$40,$A46) -> 108438.89 | AL46: =(AJ46-E46)/E46 -> #DIV/0!
A47: ISIC 09 | F47: =SUMIFS(F$3:F$40,$B$3:$B$40,$A47) -> 7714.807 | G47: =SUMIFS(G$3:G$40,$B$3:$B$40,$A47) -> 8075.976 | H47: =SUMIFS(H$3:H$40,$B$3:$B$40,$A47) -> 8437.1449 | I47: =SUMIFS(I$3:I$40,$B$3:$B$40,$A47) -> 8798.3138 | J47: =SUMIFS(J$3:J$40,$B$3:$B$40,$A47) -> 9159.4827 | K47: =SUMIFS(K$3:K$40,$B$3:$B$40,$A47) -> 9520.6517 | L47: =SUMIFS(L$3:L$40,$B$3:$B$40,$A47) -> 9881.8206 | M47: =SUMIFS(M$3:M$40,$B$3:$B$40,$A47) -> 10242.99 | ... AJ47: =SUMIFS(AJ$3:AJ$40,$B$3:$B$40,$A47) -> 18549.875 | AL47: =(AJ47-E47)/E47 -> #DIV/0!
A48: ISIC 10T12 | F48: =SUMIFS(F$3:F$40,$B$3:$B$40,$A48) -> 192198.17 | G48: =SUMIFS(G$3:G$40,$B$3:$B$40,$A48) -> 200822.41 | H48: =SUMIFS(H$3:H$40,$B$3:$B$40,$A48) -> 209446.65 | I48: =SUMIFS(I$3:I$40,$B$3:$B$40,$A48) -> 218070.89 | J48: =SUMIFS(J$3:J$40,$B$3:$B$40,$A48) -> 226695.13 | K48: =SUMIFS(K$3:K$40,$B$3:$B$40,$A48) -> 235319.37 | L48: =SUMIFS(L$3:L$40,$B$3:$B$40,$A48) -> 243943.61 | M48: =SUMIFS(M$3:M$40,$B$3:$B$40,$A48) -> 252567.85 | ... AJ48: =SUMIFS(AJ$3:AJ$40,$B$3:$B$40,$A48) -> 450925.35 | AL48: =(AJ48-E48)/E48 -> #DIV/0!
A49: ISIC 13T15 | F49: =SUMIFS(F$3:F$40,$B$3:$B$40,$A49) -> 61262.513 | G49: =SUMIFS(G$3:G$40,$B$3:$B$40,$A49) -> 63947.174 | H49: =SUMIFS(H$3:H$40,$B$3:$B$40,$A49) -> 66631.836 | I49: =SUMIFS(I$3:I$40,$B$3:$B$40,$A49) -> 69316.497 | J49: =SUMIFS(J$3:J$40,$B$3:$B$40,$A49) -> 72001.159 | K49: =SUMIFS(K$3:K$40,$B$3:$B$40,$A49) -> 74685.82 | L49: =SUMIFS(L$3:L$40,$B$3:$B$40,$A49) -> 77370.481 | M49: =SUMIFS(M$3:M$40,$B$3:$B$40,$A49) -> 80055.143 | ... AJ49: =SUMIFS(AJ$3:AJ$40,$B$3:$B$40,$A49) -> 141802.36 | AL49: =(AJ49-E49)/E49 -> #DIV/0!
A50: ISIC 16 | F50: =SUMIFS(F$3:F$40,$B$3:$B$40,$A50) -> 19068.569 | G50: =SUMIFS(G$3:G$40,$B$3:$B$40,$A50) -> 19924.982 | H50: =SUMIFS(H$3:H$40,$B$3:$B$40,$A50) -> 20781.395 | I50: =SUMIFS(I$3:I$40,$B$3:$B$40,$A50) -> 21637.808 | J50: =SUMIFS(J$3:J$40,$B$3:$B$40,$A50) -> 22494.22 | K50: =SUMIFS(K$3:K$40,$B$3:$B$40,$A50) -> 23350.633 | L50: =SUMIFS(L$3:L$40,$B$3:$B$40,$A50) -> 24207.046 | M50: =SUMIFS(M$3:M$40,$B$3:$B$40,$A50) -> 25063.459 | ... AJ50: =SUMIFS(AJ$3:AJ$40,$B$3:$B$40,$A50) -> 44760.955 | AL50: =(AJ50-E50)/E50 -> #DIV/0!
A51: ISIC 17T18 | F51: =SUMIFS(F$3:F$40,$B$3:$B$40,$A51) -> 30791.007 | G51: =SUMIFS(G$3:G$40,$B$3:$B$40,$A51) -> 32189.317 | H51: =SUMIFS(H$3:H$40,$B$3:$B$40,$A51) -> 33587.627 | I51: =SUMIFS(I$3:I$40,$B$3:$B$40,$A51) -> 34985.938 | J51: =SUMIFS(J$3:J$40,$B$3:$B$40,$A51) -> 36384.248 | K51: =SUMIFS(K$3:K$40,$B$3:$B$40,$A51) -> 37782.558 | L51: =SUMIFS(L$3:L$40,$B$3:$B$40,$A51) -> 39180.869 | M51: =SUMIFS(M$3:M$40,$B$3:$B$40,$A51) -> 40579.179 | ... AJ51: =SUMIFS(AJ$3:AJ$40,$B$3:$B$40,$A51) -> 72740.317 | AL51: =(AJ51-E51)/E51 -> #DIV/0!
A52: ISIC 19 | F52: =SUMIFS(F$3:F$40,$B$3:$B$40,$A52) -> 106961.57 | G52: =SUMIFS(G$3:G$40,$B$3:$B$40,$A52) -> 111780.06 | H52: =SUMIFS(H$3:H$40,$B$3:$B$40,$A52) -> 116598.54 | I52: =SUMIFS(I$3:I$40,$B$3:$B$40,$A52) -> 121417.03 | J52: =SUMIFS(J$3:J$40,$B$3:$B$40,$A52) -> 126235.51 | K52: =SUMIFS(K$3:K$40,$B$3:$B$40,$A52) -> 131054 | L52: =SUMIFS(L$3:L$40,$B$3:$B$40,$A52) -> 135872.49 | M52: =SUMIFS(M$3:M$40,$B$3:$B$40,$A52) -> 140690.97 | ... AJ52: =SUMIFS(AJ$3:AJ$40,$B$3:$B$40,$A52) -> 251516.14 | AL52: =(AJ52-E52)/E52 -> #DIV/0!
A53: ISIC 20 | F53: =SUMIFS(F$3:F$40,$B$3:$B$40,$A53) -> 47759.652 | G53: =SUMIFS(G$3:G$40,$B$3:$B$40,$A53) -> 49904.646 | H53: =SUMIFS(H$3:H$40,$B$3:$B$40,$A53) -> 52049.641 | I53: =SUMIFS(I$3:I$40,$B$3:$B$40,$A53) -> 54194.636 | J53: =SUMIFS(J$3:J$40,$B$3:$B$40,$A53) -> 56339.63 | K53: =SUMIFS(K$3:K$40,$B$3:$B$40,$A53) -> 58484.625 | L53: =SUMIFS(L$3:L$40,$B$3:$B$40,$A53) -> 60629.62 | M53: =SUMIFS(M$3:M$40,$B$3:$B$40,$A53) -> 62774.614 | ... AJ53: =SUMIFS(AJ$3:AJ$40,$B$3:$B$40,$A53) -> 112109.49 | AL53: =(AJ53-E53)/E53 -> #DIV/0!
A54: ISIC 21 | F54: =SUMIFS(F$3:F$40,$B$3:$B$40,$A54) -> 5390.7162 | G54: =SUMIFS(G$3:G$40,$B$3:$B$40,$A54) -> 5592.2076 | H54: =SUMIFS(H$3:H$40,$B$3:$B$40,$A54) -> 5793.699 | I54: =SUMIFS(I$3:I$40,$B$3:$B$40,$A54) -> 5995.1905 | J54: =SUMIFS(J$3:J$40,$B$3:$B$40,$A54) -> 6196.6819 | K54: =SUMIFS(K$3:K$40,$B$3:$B$40,$A54) -> 6398.1733 | L54: =SUMIFS(L$3:L$40,$B$3:$B$40,$A54) -> 6599.6648 | M54: =SUMIFS(M$3:M$40,$B$3:$B$40,$A54) -> 6801.1562 | ... AJ54: =SUMIFS(AJ$3:AJ$40,$B$3:$B$40,$A54) -> 11435.459 | AL54: =(AJ54-E54)/E54 -> #DIV/0!
A55: ISIC 22 | F55: =SUMIFS(F$3:F$40,$B$3:$B$40,$A55) -> 0 | G55: =SUMIFS(G$3:G$40,$B$3:$B$40,$A55) -> 0 | H55: =SUMIFS(H$3:H$40,$B$3:$B$40,$A55) -> 0 | I55: =SUMIFS(I$3:I$40,$B$3:$B$40,$A55) -> 0 | J55: =SUMIFS(J$3:J$40,$B$3:$B$40,$A55) -> 0 | K55: =SUMIFS(K$3:K$40,$B$3:$B$40,$A55) -> 0 | L55: =SUMIFS(L$3:L$40,$B$3:$B$40,$A55) -> 0 | M55: =SUMIFS(M$3:M$40,$B$3:$B$40,$A55) -> 0 | ... AJ55: =SUMIFS(AJ$3:AJ$40,$B$3:$B$40,$A55) -> 0 | AL55: =(AJ55-E55)/E55 -> #DIV/0!
... A81: ISIC 97T98 | F81: =SUMIFS(F$3:F$40,$B$3:$B$40,$A81) -> 3996.5462 | G81: =SUMIFS(G$3:G$40,$B$3:$B$40,$A81) -> 4167.9476 | H81: =SUMIFS(H$3:H$40,$B$3:$B$40,$A81) -> 4339.349 | I81: =SUMIFS(I$3:I$40,$B$3:$B$40,$A81) -> 4510.7505 | J81: =SUMIFS(J$3:J$40,$B$3:$B$40,$A81) -> 4682.1519 | K81: =SUMIFS(K$3:K$40,$B$3:$B$40,$A81) -> 4853.5533 | L81: =SUMIFS(L$3:L$40,$B$3:$B$40,$A81) -> 5024.9548 | M81: =SUMIFS(M$3:M$40,$B$3:$B$40,$A81) -> 5196.3562 | ... AJ81: =SUMIFS(AJ$3:AJ$40,$B$3:$B$40,$A81) -> 9138.589 | AL81: =(AJ81-E81)/E81 -> #DIV/0!
D84: ISIC CODE | F84: 2020 | G84: 2021 | H84: 2022 | I84: 2023 | J84: 2024 | K84: 2025 | L84: 2026 | M84: 2027 | N84: 2028 | O84: 2029 | P84: 2030 | Q84: 2031 | R84: 2032 | S84: 2033 | T84: 2034 | U84: 2035 | V84: 2036 | W84: 2037 | X84: 2038 | Y84: 2039 | Z84: 2040 | AA84: 2041 | AB84: 2042 | AC84: 2043 | AD84: 2044 | AE84: 2045 | AF84: 2046 | AG84: 2047 | AH84: 2048 | AI84: 2049 | AJ84: 2050
D85: ISIC 01T03 | F85: 0 | G85: =IFERROR((SUMIFS(G$44:G$81,$A$44:$A$81,$D85)-SUMIFS(F$44:F$81,$A$44:$A$81,$D85))/SUMIFS(F$44:F$81,$A$44:$A$81,$D85),0) -> 0.044329089 | H85: =IFERROR((SUMIFS(H$44:H$81,$A$44:$A$81,$D85)-SUMIFS(G$44:G$81,$A$44:$A$81,$D85))/SUMIFS(G$44:G$81,$A$44:$A$81,$D85),0) -> 0.042447433 | I85: =IFERROR((SUMIFS(I$44:I$81,$A$44:$A$81,$D85)-SUMIFS(H$44:H$81,$A$44:$A$81,$D85))/SUMIFS(H$44:H$81,$A$44:$A$81,$D85),0) -> 0.040719015 | J85: =IFERROR((SUMIFS(J$44:J$81,$A$44:$A$81,$D85)-SUMIFS(I$44:I$81,$A$44:$A$81,$D85))/SUMIFS(I$44:I$81,$A$44:$A$81,$D85),0) -> 0.039125849 | K85: =IFERROR((SUMIFS(K$44:K$81,$A$44:$A$81,$D85)-SUMIFS(J$44:J$81,$A$44:$A$81,$D85))/SUMIFS(J$44:J$81,$A$44:$A$81,$D85),0) -> 0.037652657 | L85: =IFERROR((SUMIFS(L$44:L$81,$A$44:$A$81,$D85)-SUMIFS(K$44:K$81,$A$44:$A$81,$D85))/SUMIFS(K$44:K$81,$A$44:$A$81,$D85),0) -> 0.036286378 | M85: =IFERROR((SUMIFS(M$44:M$81,$A$44:$A$81,$D85)-SUMIFS(L$44:L$81,$A$44:$A$81,$D85))/SUMIFS(L$44:L$81,$A$44:$A$81,$D85),0) -> 0.035015782 | N85: =IFERROR((SUMIFS(N$44:N$81,$A$44:$A$81,$D85)-SUMIFS(M$44:M$81,$A$44:$A$81,$D85))/SUMIFS(M$44:M$81,$A$44:$A$81,$D85),0) -> 0.033831158 | ... AJ85: =IFERROR((SUMIFS(AJ$44:AJ$81,$A$44:$A$81,$D85)-SUMIFS(AI$44:AI$81,$A$44:$A$81,$D85))/SUMIFS(AI$44:AI$81,$A$44:$A$81,$D85),0) -> 0.019395425
D86: ISIC 05 | F86: 0 | G86: =IFERROR((SUMIFS(G$44:G$81,$A$44:$A$81,$D86)-SUMIFS(F$44:F$81,$A$44:$A$81,$D86))/SUMIFS(F$44:F$81,$A$44:$A$81,$D86),0) -> 0.044469221 | H86: =IFERROR((SUMIFS(H$44:H$81,$A$44:$A$81,$D86)-SUMIFS(G$44:G$81,$A$44:$A$81,$D86))/SUMIFS(G$44:G$81,$A$44:$A$81,$D86),0) -> 0.042575904 | I86: =IFERROR((SUMIFS(I$44:I$81,$A$44:$A$81,$D86)-SUMIFS(H$44:H$81,$A$44:$A$81,$D86))/SUMIFS(H$44:H$81,$A$44:$A$81,$D86),0) -> 0.040837222 | J86: =IFERROR((SUMIFS(J$44:J$81,$A$44:$A$81,$D86)-SUMIFS(I$44:I$81,$A$44:$A$81,$D86))/SUMIFS(I$44:I$81,$A$44:$A$81,$D86),0) -> 0.039234975 | K86: =IFERROR((SUMIFS(K$44:K$81,$A$44:$A$81,$D86)-SUMIFS(J$44:J$81,$A$44:$A$81,$D86))/SUMIFS(J$44:J$81,$A$44:$A$81,$D86),0) -> 0.037753709 | L86: =IFERROR((SUMIFS(L$44:L$81,$A$44:$A$81,$D86)-SUMIFS(K$44:K$81,$A$44:$A$81,$D86))/SUMIFS(K$44:K$81,$A$44:$A$81,$D86),0) -> 0.036380221 | M86: =IFERROR((SUMIFS(M$44:M$81,$A$44:$A$81,$D86)-SUMIFS(L$44:L$81,$A$44:$A$81,$D86))/SUMIFS(L$44:L$81,$A$44:$A$81,$D86),0) -> 0.03510316 | N86: =IFERROR((SUMIFS(N$44:N$81,$A$44:$A$81,$D86)-SUMIFS(M$44:M$81,$A$44:$A$81,$D86))/SUMIFS(M$44:M$81,$A$44:$A$81,$D86),0) -> 0.033912717 | ... AJ86: =IFERROR((SUMIFS(AJ$44:AJ$81,$A$44:$A$81,$D86)-SUMIFS(AI$44:AI$81,$A$44:$A$81,$D86))/SUMIFS(AI$44:AI$81,$A$44:$A$81,$D86),0) -> 0.019422204
D87: ISIC 06 | F87: =F86 -> 0 | G87: =IFERROR((SUMIFS(G$44:G$81,$A$44:$A$81,$D87)-SUMIFS(F$44:F$81,$A$44:$A$81,$D87))/SUMIFS(F$44:F$81,$A$44:$A$81,$D87),0) -> 0 | H87: =IFERROR((SUMIFS(H$44:H$81,$A$44:$A$81,$D87)-SUMIFS(G$44:G$81,$A$44:$A$81,$D87))/SUMIFS(G$44:G$81,$A$44:$A$81,$D87),0) -> 0 | I87: =IFERROR((SUMIFS(I$44:I$81,$A$44:$A$81,$D87)-SUMIFS(H$44:H$81,$A$44:$A$81,$D87))/SUMIFS(H$44:H$81,$A$44:$A$81,$D87),0) -> 0 | J87: =IFERROR((SUMIFS(J$44:J$81,$A$44:$A$81,$D87)-SUMIFS(I$44:I$81,$A$44:$A$81,$D87))/SUMIFS(I$44:I$81,$A$44:$A$81,$D87),0) -> 0 | K87: =IFERROR((SUMIFS(K$44:K$81,$A$44:$A$81,$D87)-SUMIFS(J$44:J$81,$A$44:$A$81,$D87))/SUMIFS(J$44:J$81,$A$44:$A$81,$D87),0) -> 0 | L87: =IFERROR((SUMIFS(L$44:L$81,$A$44:$A$81,$D87)-SUMIFS(K$44:K$81,$A$44:$A$81,$D87))/SUMIFS(K$44:K$81,$A$44:$A$81,$D87),0) -> 0 | M87: =IFERROR((SUMIFS(M$44:M$81,$A$44:$A$81,$D87)-SUMIFS(L$44:L$81,$A$44:$A$81,$D87))/SUMIFS(L$44:L$81,$A$44:$A$81,$D87),0) -> 0 | N87: =IFERROR((SUMIFS(N$44:N$81,$A$44:$A$81,$D87)-SUMIFS(M$44:M$81,$A$44:$A$81,$D87))/SUMIFS(M$44:M$81,$A$44:$A$81,$D87),0) -> 0 | ... AJ87: =IFERROR((SUMIFS(AJ$44:AJ$81,$A$44:$A$81,$D87)-SUMIFS(AI$44:AI$81,$A$44:$A$81,$D87))/SUMIFS(AI$44:AI$81,$A$44:$A$81,$D87),0) -> 0
D88: ISIC 07T08 | F88: 0 | G88: =IFERROR((SUMIFS(G$44:G$81,$A$44:$A$81,$D88)-SUMIFS(F$44:F$81,$A$44:$A$81,$D88))/SUMIFS(F$44:F$81,$A$44:$A$81,$D88),0) -> 0.044166655 | H88: =IFERROR((SUMIFS(H$44:H$81,$A$44:$A$81,$D88)-SUMIFS(G$44:G$81,$A$44:$A$81,$D88))/SUMIFS(G$44:G$81,$A$44:$A$81,$D88),0) -> 0.042298473 | I88: =IFERROR((SUMIFS(I$44:I$81,$A$44:$A$81,$D88)-SUMIFS(H$44:H$81,$A$44:$A$81,$D88))/SUMIFS(H$44:H$81,$A$44:$A$81,$D88),0) -> 0.040581919 | J88: =IFERROR((SUMIFS(J$44:J$81,$A$44:$A$81,$D88)-SUMIFS(I$44:I$81,$A$44:$A$81,$D88))/SUMIFS(I$44:I$81,$A$44:$A$81,$D88),0) -> 0.038999255 | K88: =IFERROR((SUMIFS(K$44:K$81,$A$44:$A$81,$D88)-SUMIFS(J$44:J$81,$A$44:$A$81,$D88))/SUMIFS(J$44:J$81,$A$44:$A$81,$D88),0) -> 0.037535402 | L88: =IFERROR((SUMIFS(L$44:L$81,$A$44:$A$81,$D88)-SUMIFS(K$44:K$81,$A$44:$A$81,$D88))/SUMIFS(K$44:K$81,$A$44:$A$81,$D88),0) -> 0.036177466 | M88: =IFERROR((SUMIFS(M$44:M$81,$A$44:$A$81,$D88)-SUMIFS(L$44:L$81,$A$44:$A$81,$D88))/SUMIFS(L$44:L$81,$A$44:$A$81,$D88),0) -> 0.034914354 | N88: =IFERROR((SUMIFS(N$44:N$81,$A$44:$A$81,$D88)-SUMIFS(M$44:M$81,$A$44:$A$81,$D88))/SUMIFS(M$44:M$81,$A$44:$A$81,$D88),0) -> 0.033736467 | ... AJ88: =IFERROR((SUMIFS(AJ$44:AJ$81,$A$44:$A$81,$D88)-SUMIFS(AI$44:AI$81,$A$44:$A$81,$D88))/SUMIFS(AI$44:AI$81,$A$44:$A$81,$D88),0) -> 0.019364265
D89: ISIC 09 | F89: 0 | G89: =IFERROR((SUMIFS(G$44:G$81,$A$44:$A$81,$D89)-SUMIFS(F$44:F$81,$A$44:$A$81,$D89))/SUMIFS(F$44:F$81,$A$44:$A$81,$D89),0) -> 0.046815031 | H89: =IFERROR((SUMIFS(H$44:H$81,$A$44:$A$81,$D89)-SUMIFS(G$44:G$81,$A$44:$A$81,$D89))/SUMIFS(G$44:G$81,$A$44:$A$81,$D89),0) -> 0.044721397 | I89: =IFERROR((SUMIFS(I$44:I$81,$A$44:$A$81,$D89)-SUMIFS(H$44:H$81,$A$44:$A$81,$D89))/SUMIFS(H$44:H$81,$A$44:$A$81,$D89),0) -> 0.042807008 | J89: =IFERROR((SUMIFS(J$44:J$81,$A$44:$A$81,$D89)-SUMIFS(I$44:I$81,$A$44:$A$81,$D89))/SUMIFS(I$44:I$81,$A$44:$A$81,$D89),0) -> 0.041049789 | K89: =IFERROR((SUMIFS(K$44:K$81,$A$44:$A$81,$D89)-SUMIFS(J$44:J$81,$A$44:$A$81,$D89))/SUMIFS(J$44:J$81,$A$44:$A$81,$D89),0) -> 0.039431149 | L89: =IFERROR((SUMIFS(L$44:L$81,$A$44:$A$81,$D89)-SUMIFS(K$44:K$81,$A$44:$A$81,$D89))/SUMIFS(K$44:K$81,$A$44:$A$81,$D89),0) -> 0.037935316 | M89: =IFERROR((SUMIFS(M$44:M$81,$A$44:$A$81,$D89)-SUMIFS(L$44:L$81,$A$44:$A$81,$D89))/SUMIFS(L$44:L$81,$A$44:$A$81,$D89),0) -> 0.036548825 | N89: =IFERROR((SUMIFS(N$44:N$81,$A$44:$A$81,$D89)-SUMIFS(M$44:M$81,$A$44:$A$81,$D89))/SUMIFS(M$44:M$81,$A$44:$A$81,$D89),0) -> 0.035260109 | ... AJ89: =IFERROR((SUMIFS(AJ$44:AJ$81,$A$44:$A$81,$D89)-SUMIFS(AI$44:AI$81,$A$44:$A$81,$D89))/SUMIFS(AI$44:AI$81,$A$44:$A$81,$D89),0) -> 0.019856769
D90: ISIC 10T12 | F90: 0 | G90: =IFERROR((SUMIFS(G$44:G$81,$A$44:$A$81,$D90)-SUMIFS(F$44:F$81,$A$44:$A$81,$D90))/SUMIFS(F$44:F$81,$A$44:$A$81,$D90),0) -> 0.044871599 | H90: =IFERROR((SUMIFS(H$44:H$81,$A$44:$A$81,$D90)-SUMIFS(G$44:G$81,$A$44:$A$81,$D90))/SUMIFS(G$44:G$81,$A$44:$A$81,$D90),0) -> 0.042944605 | I90: =IFERROR((SUMIFS(I$44:I$81,$A$44:$A$81,$D90)-SUMIFS(H$44:H$81,$A$44:$A$81,$D90))/SUMIFS(H$44:H$81,$A$44:$A$81,$D90),0) -> 0.041176305 | J90: =IFERROR((SUMIFS(J$44:J$81,$A$44:$A$81,$D90)-SUMIFS(I$44:I$81,$A$44:$A$81,$D90))/SUMIFS(I$44:I$81,$A$44:$A$81,$D90),0) -> 0.03954787 | K90: =IFERROR((SUMIFS(K$44:K$81,$A$44:$A$81,$D90)-SUMIFS(J$44:J$81,$A$44:$A$81,$D90))/SUMIFS(J$44:J$81,$A$44:$A$81,$D90),0) -> 0.038043337 | L90: =IFERROR((SUMIFS(L$44:L$81,$A$44:$A$81,$D90)-SUMIFS(K$44:K$81,$A$44:$A$81,$D90))/SUMIFS(K$44:K$81,$A$44:$A$81,$D90),0) -> 0.036649084 | M90: =IFERROR((SUMIFS(M$44:M$81,$A$44:$A$81,$D90)-SUMIFS(L$44:L$81,$A$44:$A$81,$D90))/SUMIFS(L$44:L$81,$A$44:$A$81,$D90),0) -> 0.035353413 | N90: =IFERROR((SUMIFS(N$44:N$81,$A$44:$A$81,$D90)-SUMIFS(M$44:M$81,$A$44:$A$81,$D90))/SUMIFS(M$44:M$81,$A$44:$A$81,$D90),0) -> 0.034146228 | ... AJ90: =IFERROR((SUMIFS(AJ$44:AJ$81,$A$44:$A$81,$D90)-SUMIFS(AI$44:AI$81,$A$44:$A$81,$D90))/SUMIFS(AI$44:AI$81,$A$44:$A$81,$D90),0) -> 0.01949857
D91: ISIC 13T15 | F91: 0 | G91: =IFERROR((SUMIFS(G$44:G$81,$A$44:$A$81,$D91)-SUMIFS(F$44:F$81,$A$44:$A$81,$D91))/SUMIFS(F$44:F$81,$A$44:$A$81,$D91),0) -> 0.043822254 | H91: =IFERROR((SUMIFS(H$44:H$81,$A$44:$A$81,$D91)-SUMIFS(G$44:G$81,$A$44:$A$81,$D91))/SUMIFS(G$44:G$81,$A$44:$A$81,$D91),0) -> 0.041982487 | I91: =IFERROR((SUMIFS(I$44:I$81,$A$44:$A$81,$D91)-SUMIFS(H$44:H$81,$A$44:$A$81,$D91))/SUMIFS(H$44:H$81,$A$44:$A$81,$D91),0) -> 0.040290972 | J91: =IFERROR((SUMIFS(J$44:J$81,$A$44:$A$81,$D91)-SUMIFS(I$44:I$81,$A$44:$A$81,$D91))/SUMIFS(I$44:I$81,$A$44:$A$81,$D91),0) -> 0.038730483 | K91: =IFERROR((SUMIFS(K$44:K$81,$A$44:$A$81,$D91)-SUMIFS(J$44:J$81,$A$44:$A$81,$D91))/SUMIFS(J$44:J$81,$A$44:$A$81,$D91),0) -> 0.037286364 | L91: =IFERROR((SUMIFS(L$44:L$81,$A$44:$A$81,$D91)-SUMIFS(K$44:K$81,$A$44:$A$81,$D91))/SUMIFS(K$44:K$81,$A$44:$A$81,$D91),0) -> 0.035946066 | M91: =IFERROR((SUMIFS(M$44:M$81,$A$44:$A$81,$D91)-SUMIFS(L$44:L$81,$A$44:$A$81,$D91))/SUMIFS(L$44:L$81,$A$44:$A$81,$D91),0) -> 0.034698781 | N91: =IFERROR((SUMIFS(N$44:N$81,$A$44:$A$81,$D91)-SUMIFS(M$44:M$81,$A$44:$A$81,$D91))/SUMIFS(M$44:M$81,$A$44:$A$81,$D91),0) -> 0.033535153 | ... AJ91: =IFERROR((SUMIFS(AJ$44:AJ$81,$A$44:$A$81,$D91)-SUMIFS(AI$44:AI$81,$A$44:$A$81,$D91))/SUMIFS(AI$44:AI$81,$A$44:$A$81,$D91),0) -> 0.019297771
D92: ISIC 16 | F92: 0 | G92: =IFERROR((SUMIFS(G$44:G$81,$A$44:$A$81,$D92)-SUMIFS(F$44:F$81,$A$44:$A$81,$D92))/SUMIFS(F$44:F$81,$A$44:$A$81,$D92),0) -> 0.044912277 | H92: =IFERROR((SUMIFS(H$44:H$81,$A$44:$A$81,$D92)-SUMIFS(G$44:G$81,$A$44:$A$81,$D92))/SUMIFS(G$44:G$81,$A$44:$A$81,$D92),0) -> 0.042981864 | I92: =IFERROR((SUMIFS(I$44:I$81,$A$44:$A$81,$D92)-SUMIFS(H$44:H$81,$A$44:$A$81,$D92))/SUMIFS(H$44:H$81,$A$44:$A$81,$D92),0) -> 0.041210557 | J92: =IFERROR((SUMIFS(J$44:J$81,$A$44:$A$81,$D92)-SUMIFS(I$44:I$81,$A$44:$A$81,$D92))/SUMIFS(I$44:I$81,$A$44:$A$81,$D92),0) -> 0.039579465 | K92: =IFERROR((SUMIFS(K$44:K$81,$A$44:$A$81,$D92)-SUMIFS(J$44:J$81,$A$44:$A$81,$D92))/SUMIFS(J$44:J$81,$A$44:$A$81,$D92),0) -> 0.038072573 | L92: =IFERROR((SUMIFS(L$44:L$81,$A$44:$A$81,$D92)-SUMIFS(K$44:K$81,$A$44:$A$81,$D92))/SUMIFS(K$44:K$81,$A$44:$A$81,$D92),0) -> 0.036676215 | M92: =IFERROR((SUMIFS(M$44:M$81,$A$44:$A$81,$D92)-SUMIFS(L$44:L$81,$A$44:$A$81,$D92))/SUMIFS(L$44:L$81,$A$44:$A$81,$D92),0) -> 0.03537866 | N92: =IFERROR((SUMIFS(N$44:N$81,$A$44:$A$81,$D92)-SUMIFS(M$44:M$81,$A$44:$A$81,$D92))/SUMIFS(M$44:M$81,$A$44:$A$81,$D92),0) -> 0.034169779 | ... AJ92: =IFERROR((SUMIFS(AJ$44:AJ$81,$A$44:$A$81,$D92)-SUMIFS(AI$44:AI$81,$A$44:$A$81,$D92))/SUMIFS(AI$44:AI$81,$A$44:$A$81,$D92),0) -> 0.019506247
D93: ISIC 17T18 | F93: 0 | G93: =IFERROR((SUMIFS(G$44:G$81,$A$44:$A$81,$D93)-SUMIFS(F$44:F$81,$A$44:$A$81,$D93))/SUMIFS(F$44:F$81,$A$44:$A$81,$D93),0) -> 0.045412947 | H93: =IFERROR((SUMIFS(H$44:H$81,$A$44:$A$81,$D93)-SUMIFS(G$44:G$81,$A$44:$A$81,$D93))/SUMIFS(G$44:G$81,$A$44:$A$81,$D93),0) -> 0.0434402 | I93: =IFERROR((SUMIFS(I$44:I$81,$A$44:$A$81,$D93)-SUMIFS(H$44:H$81,$A$44:$A$81,$D93))/SUMIFS(H$44:H$81,$A$44:$A$81,$D93),0) -> 0.04163171 | J93: =IFERROR((SUMIFS(J$44:J$81,$A$44:$A$81,$D93)-SUMIFS(I$44:I$81,$A$44:$A$81,$D93))/SUMIFS(I$44:I$81,$A$44:$A$81,$D93),0) -> 0.039967783 | K93: =IFERROR((SUMIFS(K$44:K$81,$A$44:$A$81,$D93)-SUMIFS(J$44:J$81,$A$44:$A$81,$D93))/SUMIFS(J$44:J$81,$A$44:$A$81,$D93),0) -> 0.038431751 | L93: =IFERROR((SUMIFS(L$44:L$81,$A$44:$A$81,$D93)-SUMIFS(K$44:K$81,$A$44:$A$81,$D93))/SUMIFS(K$44:K$81,$A$44:$A$81,$D93),0) -> 0.037009414 | M93: =IFERROR((SUMIFS(M$44:M$81,$A$44:$A$81,$D93)-SUMIFS(L$44:L$81,$A$44:$A$81,$D93))/SUMIFS(L$44:L$81,$A$44:$A$81,$D93),0) -> 0.0356886 | N93: =IFERROR((SUMIFS(N$44:N$81,$A$44:$A$81,$D93)-SUMIFS(M$44:M$81,$A$44:$A$81,$D93))/SUMIFS(M$44:M$81,$A$44:$A$81,$D93),0) -> 0.034458813 | ... AJ93: =IFERROR((SUMIFS(AJ$44:AJ$81,$A$44:$A$81,$D93)-SUMIFS(AI$44:AI$81,$A$44:$A$81,$D93))/SUMIFS(AI$44:AI$81,$A$44:$A$81,$D93),0) -> 0.019600098
D94: ISIC 19 | F94: 0 | G94: =IFERROR((SUMIFS(G$44:G$81,$A$44:$A$81,$D94)-SUMIFS(F$44:F$81,$A$44:$A$81,$D94))/SUMIFS(F$44:F$81,$A$44:$A$81,$D94),0) -> 0.045048756 | H94: =IFERROR((SUMIFS(H$44:H$81,$A$44:$A$81,$D94)-SUMIFS(G$44:G$81,$A$44:$A$81,$D94))/SUMIFS(G$44:G$81,$A$44:$A$81,$D94),0) -> 0.043106846 | I94: =IFERROR((SUMIFS(I$44:I$81,$A$44:$A$81,$D94)-SUMIFS(H$44:H$81,$A$44:$A$81,$D94))/SUMIFS(H$44:H$81,$A$44:$A$81,$D94),0) -> 0.041325437 | J94: =IFERROR((SUMIFS(J$44:J$81,$A$44:$A$81,$D94)-SUMIFS(I$44:I$81,$A$44:$A$81,$D94))/SUMIFS(I$44:I$81,$A$44:$A$81,$D94),0) -> 0.03968542 | K94: =IFERROR((SUMIFS(K$44:K$81,$A$44:$A$81,$D94)-SUMIFS(J$44:J$81,$A$44:$A$81,$D94))/SUMIFS(J$44:J$81,$A$44:$A$81,$D94),0) -> 0.038170603 | L94: =IFERROR((SUMIFS(L$44:L$81,$A$44:$A$81,$D94)-SUMIFS(K$44:K$81,$A$44:$A$81,$D94))/SUMIFS(K$44:K$81,$A$44:$A$81,$D94),0) -> 0.036767178 | M94: =IFERROR((SUMIFS(M$44:M$81,$A$44:$A$81,$D94)-SUMIFS(L$44:L$81,$A$44:$A$81,$D94))/SUMIFS(L$44:L$81,$A$44:$A$81,$D94),0) -> 0.035463293 | N94: =IFERROR((SUMIFS(N$44:N$81,$A$44:$A$81,$D94)-SUMIFS(M$44:M$81,$A$44:$A$81,$D94))/SUMIFS(M$44:M$81,$A$44:$A$81,$D94),0) -> 0.03424872 | ... AJ94: =IFERROR((SUMIFS(AJ$44:AJ$81,$A$44:$A$81,$D94)-SUMIFS(AI$44:AI$81,$A$44:$A$81,$D94))/SUMIFS(AI$44:AI$81,$A$44:$A$81,$D94),0) -> 0.019531948
D95: ISIC 20 | F95: 0 | G95: =IFERROR((SUMIFS(G$44:G$81,$A$44:$A$81,$D95)-SUMIFS(F$44:F$81,$A$44:$A$81,$D95))/SUMIFS(F$44:F$81,$A$44:$A$81,$D95),0) -> 0.044912276 | H95: =IFERROR((SUMIFS(H$44:H$81,$A$44:$A$81,$D95)-SUMIFS(G$44:G$81,$A$44:$A$81,$D95))/SUMIFS(G$44:G$81,$A$44:$A$81,$D95),0) -> 0.042981862 | I95: =IFERROR((SUMIFS(I$44:I$81,$A$44:$A$81,$D95)-SUMIFS(H$44:H$81,$A$44:$A$81,$D95))/SUMIFS(H$44:H$81,$A$44:$A$81,$D95),0) -> 0.041210556 | J95: =IFERROR((SUMIFS(J$44:J$81,$A$44:$A$81,$D95)-SUMIFS(I$44:I$81,$A$44:$A$81,$D95))/SUMIFS(I$44:I$81,$A$44:$A$81,$D95),0) -> 0.039579464 | K95: =IFERROR((SUMIFS(K$44:K$81,$A$44:$A$81,$D95)-SUMIFS(J$44:J$81,$A$44:$A$81,$D95))/SUMIFS(J$44:J$81,$A$44:$A$81,$D95),0) -> 0.038072572 | L95: =IFERROR((SUMIFS(L$44:L$81,$A$44:$A$81,$D95)-SUMIFS(K$44:K$81,$A$44:$A$81,$D95))/SUMIFS(K$44:K$81,$A$44:$A$81,$D95),0) -> 0.036676214 | M95: =IFERROR((SUMIFS(M$44:M$81,$A$44:$A$81,$D95)-SUMIFS(L$44:L$81,$A$44:$A$81,$D95))/SUMIFS(L$44:L$81,$A$44:$A$81,$D95),0) -> 0.035378659 | N95: =IFERROR((SUMIFS(N$44:N$81,$A$44:$A$81,$D95)-SUMIFS(M$44:M$81,$A$44:$A$81,$D95))/SUMIFS(M$44:M$81,$A$44:$A$81,$D95),0) -> 0.034169778 | ... AJ95: =IFERROR((SUMIFS(AJ$44:AJ$81,$A$44:$A$81,$D95)-SUMIFS(AI$44:AI$81,$A$44:$A$81,$D95))/SUMIFS(AI$44:AI$81,$A$44:$A$81,$D95),0) -> 0.019506247
D96: ISIC 21 | F96: 0 | G96: =IFERROR((SUMIFS(G$44:G$81,$A$44:$A$81,$D96)-SUMIFS(F$44:F$81,$A$44:$A$81,$D96))/SUMIFS(F$44:F$81,$A$44:$A$81,$D96),0) -> 0.037377488 | H96: =IFERROR((SUMIFS(H$44:H$81,$A$44:$A$81,$D96)-SUMIFS(G$44:G$81,$A$44:$A$81,$D96))/SUMIFS(G$44:G$81,$A$44:$A$81,$D96),0) -> 0.036030749 | I96: =IFERROR((SUMIFS(I$44:I$81,$A$44:$A$81,$D96)-SUMIFS(H$44:H$81,$A$44:$A$81,$D96))/SUMIFS(H$44:H$81,$A$44:$A$81,$D96),0) -> 0.034777683 | J96: =IFERROR((SUMIFS(J$44:J$81,$A$44:$A$81,$D96)-SUMIFS(I$44:I$81,$A$44:$A$81,$D96))/SUMIFS(I$44:I$81,$A$44:$A$81,$D96),0) -> 0.033608845 | K96: =IFERROR((SUMIFS(K$44:K$81,$A$44:$A$81,$D96)-SUMIFS(J$44:J$81,$A$44:$A$81,$D96))/SUMIFS(J$44:J$81,$A$44:$A$81,$D96),0) -> 0.032516019 | L96: =IFERROR((SUMIFS(L$44:L$81,$A$44:$A$81,$D96)-SUMIFS(K$44:K$81,$A$44:$A$81,$D96))/SUMIFS(K$44:K$81,$A$44:$A$81,$D96),0) -> 0.031492024 | M96: =IFERROR((SUMIFS(M$44:M$81,$A$44:$A$81,$D96)-SUMIFS(L$44:L$81,$A$44:$A$81,$D96))/SUMIFS(L$44:L$81,$A$44:$A$81,$D96),0) -> 0.030530555 | N96: =IFERROR((SUMIFS(N$44:N$81,$A$44:$A$81,$D96)-SUMIFS(M$44:M$81,$A$44:$A$81,$D96))/SUMIFS(M$44:M$81,$A$44:$A$81,$D96),0) -> 0.029626055 | ... AJ96: =IFERROR((SUMIFS(AJ$44:AJ$81,$A$44:$A$81,$D96)-SUMIFS(AI$44:AI$81,$A$44:$A$81,$D96))/SUMIFS(AI$44:AI$81,$A$44:$A$81,$D96),0) -> 0.01793591
D97: ISIC 22 | F97: 0 | G97: =IFERROR((SUMIFS(G$44:G$81,$A$44:$A$81,$D97)-SUMIFS(F$44:F$81,$A$44:$A$81,$D97))/SUMIFS(F$44:F$81,$A$44:$A$81,$D97),0) -> 0 | H97: =IFERROR((SUMIFS(H$44:H$81,$A$44:$A$81,$D97)-SUMIFS(G$44:G$81,$A$44:$A$81,$D97))/SUMIFS(G$44:G$81,$A$44:$A$81,$D97),0) -> 0 | I97: =IFERROR((SUMIFS(I$44:I$81,$A$44:$A$81,$D97)-SUMIFS(H$44:H$81,$A$44:$A$81,$D97))/SUMIFS(H$44:H$81,$A$44:$A$81,$D97),0) -> 0 | J97: =IFERROR((SUMIFS(J$44:J$81,$A$44:$A$81,$D97)-SUMIFS(I$44:I$81,$A$44:$A$81,$D97))/SUMIFS(I$44:I$81,$A$44:$A$81,$D97),0) -> 0 | K97: =IFERROR((SUMIFS(K$44:K$81,$A$44:$A$81,$D97)-SUMIFS(J$44:J$81,$A$44:$A$81,$D97))/SUMIFS(J$44:J$81,$A$44:$A$81,$D97),0) -> 0 | L97: =IFERROR((SUMIFS(L$44:L$81,$A$44:$A$81,$D97)-SUMIFS(K$44:K$81,$A$44:$A$81,$D97))/SUMIFS(K$44:K$81,$A$44:$A$81,$D97),0) -> 0 | M97: =IFERROR((SUMIFS(M$44:M$81,$A$44:$A$81,$D97)-SUMIFS(L$44:L$81,$A$44:$A$81,$D97))/SUMIFS(L$44:L$81,$A$44:$A$81,$D97),0) -> 0 | N97: =IFERROR((SUMIFS(N$44:N$81,$A$44:$A$81,$D97)-SUMIFS(M$44:M$81,$A$44:$A$81,$D97))/SUMIFS(M$44:M$81,$A$44:$A$81,$D97),0) -> 0 | ... AJ97: =IFERROR((SUMIFS(AJ$44:AJ$81,$A$44:$A$81,$D97)-SUMIFS(AI$44:AI$81,$A$44:$A$81,$D97))/SUMIFS(AI$44:AI$81,$A$44:$A$81,$D97),0) -> 0
D98: ISIC 231 | F98: 0 | G98: =IFERROR((SUMIFS(G$44:G$81,$A$44:$A$81,$D98)-SUMIFS(F$44:F$81,$A$44:$A$81,$D98))/SUMIFS(F$44:F$81,$A$44:$A$81,$D98),0) -> 0 | H98: =IFERROR((SUMIFS(H$44:H$81,$A$44:$A$81,$D98)-SUMIFS(G$44:G$81,$A$44:$A$81,$D98))/SUMIFS(G$44:G$81,$A$44:$A$81,$D98),0) -> 0 | I98: =IFERROR((SUMIFS(I$44:I$81,$A$44:$A$81,$D98)-SUMIFS(H$44:H$81,$A$44:$A$81,$D98))/SUMIFS(H$44:H$81,$A$44:$A$81,$D98),0) -> 0 | J98: =IFERROR((SUMIFS(J$44:J$81,$A$44:$A$81,$D98)-SUMIFS(I$44:I$81,$A$44:$A$81,$D98))/SUMIFS(I$44:I$81,$A$44:$A$81,$D98),0) -> 0 | K98: =IFERROR((SUMIFS(K$44:K$81,$A$44:$A$81,$D98)-SUMIFS(J$44:J$81,$A$44:$A$81,$D98))/SUMIFS(J$44:J$81,$A$44:$A$81,$D98),0) -> 0 | L98: =IFERROR((SUMIFS(L$44:L$81,$A$44:$A$81,$D98)-SUMIFS(K$44:K$81,$A$44:$A$81,$D98))/SUMIFS(K$44:K$81,$A$44:$A$81,$D98),0) -> 0 | M98: =IFERROR((SUMIFS(M$44:M$81,$A$44:$A$81,$D98)-SUMIFS(L$44:L$81,$A$44:$A$81,$D98))/SUMIFS(L$44:L$81,$A$44:$A$81,$D98),0) -> 0 | N98: =IFERROR((SUMIFS(N$44:N$81,$A$44:$A$81,$D98)-SUMIFS(M$44:M$81,$A$44:$A$81,$D98))/SUMIFS(M$44:M$81,$A$44:$A$81,$D98),0) -> 0 | ... AJ98: =IFERROR((SUMIFS(AJ$44:AJ$81,$A$44:$A$81,$D98)-SUMIFS(AI$44:AI$81,$A$44:$A$81,$D98))/SUMIFS(AI$44:AI$81,$A$44:$A$81,$D98),0) -> 0
D99: ISIC 239 | F99: =F98 -> 0 | G99: =IFERROR((SUMIFS(G$44:G$81,$A$44:$A$81,$D99)-SUMIFS(F$44:F$81,$A$44:$A$81,$D99))/SUMIFS(F$44:F$81,$A$44:$A$81,$D99),0) -> 0 | H99: =IFERROR((SUMIFS(H$44:H$81,$A$44:$A$81,$D99)-SUMIFS(G$44:G$81,$A$44:$A$81,$D99))/SUMIFS(G$44:G$81,$A$44:$A$81,$D99),0) -> 0 | I99: =IFERROR((SUMIFS(I$44:I$81,$A$44:$A$81,$D99)-SUMIFS(H$44:H$81,$A$44:$A$81,$D99))/SUMIFS(H$44:H$81,$A$44:$A$81,$D99),0) -> 0 | J99: =IFERROR((SUMIFS(J$44:J$81,$A$44:$A$81,$D99)-SUMIFS(I$44:I$81,$A$44:$A$81,$D99))/SUMIFS(I$44:I$81,$A$44:$A$81,$D99),0) -> 0 | K99: =IFERROR((SUMIFS(K$44:K$81,$A$44:$A$81,$D99)-SUMIFS(J$44:J$81,$A$44:$A$81,$D99))/SUMIFS(J$44:J$81,$A$44:$A$81,$D99),0) -> 0 | L99: =IFERROR((SUMIFS(L$44:L$81,$A$44:$A$81,$D99)-SUMIFS(K$44:K$81,$A$44:$A$81,$D99))/SUMIFS(K$44:K$81,$A$44:$A$81,$D99),0) -> 0 | M99: =IFERROR((SUMIFS(M$44:M$81,$A$44:$A$81,$D99)-SUMIFS(L$44:L$81,$A$44:$A$81,$D99))/SUMIFS(L$44:L$81,$A$44:$A$81,$D99),0) -> 0 | N99: =IFERROR((SUMIFS(N$44:N$81,$A$44:$A$81,$D99)-SUMIFS(M$44:M$81,$A$44:$A$81,$D99))/SUMIFS(M$44:M$81,$A$44:$A$81,$D99),0) -> 0 | ... AJ99: =IFERROR((SUMIFS(AJ$44:AJ$81,$A$44:$A$81,$D99)-SUMIFS(AI$44:AI$81,$A$44:$A$81,$D99))/SUMIFS(AI$44:AI$81,$A$44:$A$81,$D99),0) -> 0
D100: ISIC 241 | F100: 0 | G100: =IFERROR((SUMIFS(G$44:G$81,$A$44:$A$81,$D100)-SUMIFS(F$44:F$81,$A$44:$A$81,$D100))/SUMIFS(F$44:F$81,$A$44:$A$81,$D100),0) -> 0 | H100: =IFERROR((SUMIFS(H$44:H$81,$A$44:$A$81,$D100)-SUMIFS(G$44:G$81,$A$44:$A$81,$D100))/SUMIFS(G$44:G$81,$A$44:$A$81,$D100),0) -> 0 | I100: =IFERROR((SUMIFS(I$44:I$81,$A$44:$A$81,$D100)-SUMIFS(H$44:H$81,$A$44:$A$81,$D100))/SUMIFS(H$44:H$81,$A$44:$A$81,$D100),0) -> 0 | J100: =IFERROR((SUMIFS(J$44:J$81,$A$44:$A$81,$D100)-SUMIFS(I$44:I$81,$A$44:$A$81,$D100))/SUMIFS(I$44:I$81,$A$44:$A$81,$D100),0) -> 0 | K100: =IFERROR((SUMIFS(K$44:K$81,$A$44:$A$81,$D100)-SUMIFS(J$44:J$81,$A$44:$A$81,$D100))/SUMIFS(J$44:J$81,$A$44:$A$81,$D100),0) -> 0 | L100: =IFERROR((SUMIFS(L$44:L$81,$A$44:$A$81,$D100)-SUMIFS(K$44:K$81,$A$44:$A$81,$D100))/SUMIFS(K$44:K$81,$A$44:$A$81,$D100),0) -> 0 | M100: =IFERROR((SUMIFS(M$44:M$81,$A$44:$A$81,$D100)-SUMIFS(L$44:L$81,$A$44:$A$81,$D100))/SUMIFS(L$44:L$81,$A$44:$A$81,$D100),0) -> 0 | N100: =IFERROR((SUMIFS(N$44:N$81,$A$44:$A$81,$D100)-SUMIFS(M$44:M$81,$A$44:$A$81,$D100))/SUMIFS(M$44:M$81,$A$44:$A$81,$D100),0) -> 0 | ... AJ100: =IFERROR((SUMIFS(AJ$44:AJ$81,$A$44:$A$81,$D100)-SUMIFS(AI$44:AI$81,$A$44:$A$81,$D100))/SUMIFS(AI$44:AI$81,$A$44:$A$81,$D100),0) -> 0
D101: ISIC 242 | F101: =F100 -> 0 | G101: =IFERROR((SUMIFS(G$44:G$81,$A$44:$A$81,$D101)-SUMIFS(F$44:F$81,$A$44:$A$81,$D101))/SUMIFS(F$44:F$81,$A$44:$A$81,$D101),0) -> 0 | H101: =IFERROR((SUMIFS(H$44:H$81,$A$44:$A$81,$D101)-SUMIFS(G$44:G$81,$A$44:$A$81,$D101))/SUMIFS(G$44:G$81,$A$44:$A$81,$D101),0) -> 0 | I101: =IFERROR((SUMIFS(I$44:I$81,$A$44:$A$81,$D101)-SUMIFS(H$44:H$81,$A$44:$A$81,$D101))/SUMIFS(H$44:H$81,$A$44:$A$81,$D101),0) -> 0 | J101: =IFERROR((SUMIFS(J$44:J$81,$A$44:$A$81,$D101)-SUMIFS(I$44:I$81,$A$44:$A$81,$D101))/SUMIFS(I$44:I$81,$A$44:$A$81,$D101),0) -> 0 | K101: =IFERROR((SUMIFS(K$44:K$81,$A$44:$A$81,$D101)-SUMIFS(J$44:J$81,$A$44:$A$81,$D101))/SUMIFS(J$44:J$81,$A$44:$A$81,$D101),0) -> 0 | L101: =IFERROR((SUMIFS(L$44:L$81,$A$44:$A$81,$D101)-SUMIFS(K$44:K$81,$A$44:$A$81,$D101))/SUMIFS(K$44:K$81,$A$44:$A$81,$D101),0) -> 0 | M101: =IFERROR((SUMIFS(M$44:M$81,$A$44:$A$81,$D101)-SUMIFS(L$44:L$81,$A$44:$A$81,$D101))/SUMIFS(L$44:L$81,$A$44:$A$81,$D101),0) -> 0 | N101: =IFERROR((SUMIFS(N$44:N$81,$A$44:$A$81,$D101)-SUMIFS(M$44:M$81,$A$44:$A$81,$D101))/SUMIFS(M$44:M$81,$A$44:$A$81,$D101),0) -> 0 | ... AJ101: =IFERROR((SUMIFS(AJ$44:AJ$81,$A$44:$A$81,$D101)-SUMIFS(AI$44:AI$81,$A$44:$A$81,$D101))/SUMIFS(AI$44:AI$81,$A$44:$A$81,$D101),0) -> 0
D102: ISIC 25 | F102: 0 | G102: =IFERROR((SUMIFS(G$44:G$81,$A$44:$A$81,$D102)-SUMIFS(F$44:F$81,$A$44:$A$81,$D102))/SUMIFS(F$44:F$81,$A$44:$A$81,$D102),0) -> 0.04428513 | H102: =IFERROR((SUMIFS(H$44:H$81,$A$44:$A$81,$D102)-SUMIFS(G$44:G$81,$A$44:$A$81,$D102))/SUMIFS(G$44:G$81,$A$44:$A$81,$D102),0) -> 0.042407125 | I102: =IFERROR((SUMIFS(I$44:I$81,$A$44:$A$81,$D102)-SUMIFS(H$44:H$81,$A$44:$A$81,$D102))/SUMIFS(H$44:H$81,$A$44:$A$81,$D102),0) -> 0.040681922 | J102: =IFERROR((SUMIFS(J$44:J$81,$A$44:$A$81,$D102)-SUMIFS(I$44:I$81,$A$44:$A$81,$D102))/SUMIFS(I$44:I$81,$A$44:$A$81,$D102),0) -> 0.0390916 | K102: =IFERROR((SUMIFS(K$44:K$81,$A$44:$A$81,$D102)-SUMIFS(J$44:J$81,$A$44:$A$81,$D102))/SUMIFS(J$44:J$81,$A$44:$A$81,$D102),0) -> 0.037620938 | L102: =IFERROR((SUMIFS(L$44:L$81,$A$44:$A$81,$D102)-SUMIFS(K$44:K$81,$A$44:$A$81,$D102))/SUMIFS(K$44:K$81,$A$44:$A$81,$D102),0) -> 0.036256919 | M102: =IFERROR((SUMIFS(M$44:M$81,$A$44:$A$81,$D102)-SUMIFS(L$44:L$81,$A$44:$A$81,$D102))/SUMIFS(L$44:L$81,$A$44:$A$81,$D102),0) -> 0.034988349 | N102: =IFERROR((SUMIFS(N$44:N$81,$A$44:$A$81,$D102)-SUMIFS(M$44:M$81,$A$44:$A$81,$D102))/SUMIFS(M$44:M$81,$A$44:$A$81,$D102),0) -> 0.033805549 | ... AJ102: =IFERROR((SUMIFS(AJ$44:AJ$81,$A$44:$A$81,$D102)-SUMIFS(AI$44:AI$81,$A$44:$A$81,$D102))/SUMIFS(AI$44:AI$81,$A$44:$A$81,$D102),0) -> 0.019387005
D103: ISIC 26 | F103: 0 | G103: =IFERROR((SUMIFS(G$44:G$81,$A$44:$A$81,$D103)-SUMIFS(F$44:F$81,$A$44:$A$81,$D103))/SUMIFS(F$44:F$81,$A$44:$A$81,$D103),0) -> 0 | H103: =IFERROR((SUMIFS(H$44:H$81,$A$44:$A$81,$D103)-SUMIFS(G$44:G$81,$A$44:$A$81,$D103))/SUMIFS(G$44:G$81,$A$44:$A$81,$D103),0) -> 0 | I103: =IFERROR((SUMIFS(I$44:I$81,$A$44:$A$81,$D103)-SUMIFS(H$44:H$81,$A$44:$A$81,$D103))/SUMIFS(H$44:H$81,$A$44:$A$81,$D103),0) -> 0 | J103: =IFERROR((SUMIFS(J$44:J$81,$A$44:$A$81,$D103)-SUMIFS(I$44:I$81,$A$44:$A$81,$D103))/SUMIFS(I$44:I$81,$A$44:$A$81,$D103),0) -> 0 | K103: =IFERROR((SUMIFS(K$44:K$81,$A$44:$A$81,$D103)-SUMIFS(J$44:J$81,$A$44:$A$81,$D103))/SUMIFS(J$44:J$81,$A$44:$A$81,$D103),0) -> 0 | L103: =IFERROR((SUMIFS(L$44:L$81,$A$44:$A$81,$D103)-SUMIFS(K$44:K$81,$A$44:$A$81,$D103))/SUMIFS(K$44:K$81,$A$44:$A$81,$D103),0) -> 0 | M103: =IFERROR((SUMIFS(M$44:M$81,$A$44:$A$81,$D103)-SUMIFS(L$44:L$81,$A$44:$A$81,$D103))/SUMIFS(L$44:L$81,$A$44:$A$81,$D103),0) -> 0 | N103: =IFERROR((SUMIFS(N$44:N$81,$A$44:$A$81,$D103)-SUMIFS(M$44:M$81,$A$44:$A$81,$D103))/SUMIFS(M$44:M$81,$A$44:$A$81,$D103),0) -> 0 | ... AJ103: =IFERROR((SUMIFS(AJ$44:AJ$81,$A$44:$A$81,$D103)-SUMIFS(AI$44:AI$81,$A$44:$A$81,$D103))/SUMIFS(AI$44:AI$81,$A$44:$A$81,$D103),0) -> 0
D104: ISIC 27 | F104: 0 | G104: =IFERROR((SUMIFS(G$44:G$81,$A$44:$A$81,$D104)-SUMIFS(F$44:F$81,$A$44:$A$81,$D104))/SUMIFS(F$44:F$81,$A$44:$A$81,$D104),0) -> 0 | H104: =IFERROR((SUMIFS(H$44:H$81,$A$44:$A$81,$D104)-SUMIFS(G$44:G$81,$A$44:$A$81,$D104))/SUMIFS(G$44:G$81,$A$44:$A$81,$D104),0) -> 0 | I104: =IFERROR((SUMIFS(I$44:I$81,$A$44:$A$81,$D104)-SUMIFS(H$44:H$81,$A$44:$A$81,$D104))/SUMIFS(H$44:H$81,$A$44:$A$81,$D104),0) -> 0 | J104: =IFERROR((SUMIFS(J$44:J$81,$A$44:$A$81,$D104)-SUMIFS(I$44:I$81,$A$44:$A$81,$D104))/SUMIFS(I$44:I$81,$A$44:$A$81,$D104),0) -> 0 | K104: =IFERROR((SUMIFS(K$44:K$81,$A$44:$A$81,$D104)-SUMIFS(J$44:J$81,$A$44:$A$81,$D104))/SUMIFS(J$44:J$81,$A$44:$A$81,$D104),0) -> 0 | L104: =IFERROR((SUMIFS(L$44:L$81,$A$44:$A$81,$D104)-SUMIFS(K$44:K$81,$A$44:$A$81,$D104))/SUMIFS(K$44:K$81,$A$44:$A$81,$D104),0) -> 0 | M104: =IFERROR((SUMIFS(M$44:M$81,$A$44:$A$81,$D104)-SUMIFS(L$44:L$81,$A$44:$A$81,$D104))/SUMIFS(L$44:L$81,$A$44:$A$81,$D104),0) -> 0 | N104: =IFERROR((SUMIFS(N$44:N$81,$A$44:$A$81,$D104)-SUMIFS(M$44:M$81,$A$44:$A$81,$D104))/SUMIFS(M$44:M$81,$A$44:$A$81,$D104),0) -> 0 | ... AJ104: =IFERROR((SUMIFS(AJ$44:AJ$81,$A$44:$A$81,$D104)-SUMIFS(AI$44:AI$81,$A$44:$A$81,$D104))/SUMIFS(AI$44:AI$81,$A$44:$A$81,$D104),0) -> 0
D105: ISIC 28 | F105: 0 | G105: =IFERROR((SUMIFS(G$44:G$81,$A$44:$A$81,$D105)-SUMIFS(F$44:F$81,$A$44:$A$81,$D105))/SUMIFS(F$44:F$81,$A$44:$A$81,$D105),0) -> 0 | H105: =IFERROR((SUMIFS(H$44:H$81,$A$44:$A$81,$D105)-SUMIFS(G$44:G$81,$A$44:$A$81,$D105))/SUMIFS(G$44:G$81,$A$44:$A$81,$D105),0) -> 0 | I105: =IFERROR((SUMIFS(I$44:I$81,$A$44:$A$81,$D105)-SUMIFS(H$44:H$81,$A$44:$A$81,$D105))/SUMIFS(H$44:H$81,$A$44:$A$81,$D105),0) -> 0 | J105: =IFERROR((SUMIFS(J$44:J$81,$A$44:$A$81,$D105)-SUMIFS(I$44:I$81,$A$44:$A$81,$D105))/SUMIFS(I$44:I$81,$A$44:$A$81,$D105),0) -> 0 | K105: =IFERROR((SUMIFS(K$44:K$81,$A$44:$A$81,$D105)-SUMIFS(J$44:J$81,$A$44:$A$81,$D105))/SUMIFS(J$44:J$81,$A$44:$A$81,$D105),0) -> 0 | L105: =IFERROR((SUMIFS(L$44:L$81,$A$44:$A$81,$D105)-SUMIFS(K$44:K$81,$A$44:$A$81,$D105))/SUMIFS(K$44:K$81,$A$44:$A$81,$D105),0) -> 0 | M105: =IFERROR((SUMIFS(M$44:M$81,$A$44:$A$81,$D105)-SUMIFS(L$44:L$81,$A$44:$A$81,$D105))/SUMIFS(L$44:L$81,$A$44:$A$81,$D105),0) -> 0 | N105: =IFERROR((SUMIFS(N$44:N$81,$A$44:$A$81,$D105)-SUMIFS(M$44:M$81,$A$44:$A$81,$D105))/SUMIFS(M$44:M$81,$A$44:$A$81,$D105),0) -> 0 | ... AJ105: =IFERROR((SUMIFS(AJ$44:AJ$81,$A$44:$A$81,$D105)-SUMIFS(AI$44:AI$81,$A$44:$A$81,$D105))/SUMIFS(AI$44:AI$81,$A$44:$A$81,$D105),0) -> 0
D106: ISIC 29 | F106: 0 | G106: =IFERROR((SUMIFS(G$44:G$81,$A$44:$A$81,$D106)-SUMIFS(F$44:F$81,$A$44:$A$81,$D106))/SUMIFS(F$44:F$81,$A$44:$A$81,$D106),0) -> 0.044226811 | H106: =IFERROR((SUMIFS(H$44:H$81,$A$44:$A$81,$D106)-SUMIFS(G$44:G$81,$A$44:$A$81,$D106))/SUMIFS(G$44:G$81,$A$44:$A$81,$D106),0) -> 0.042353644 | I106: =IFERROR((SUMIFS(I$44:I$81,$A$44:$A$81,$D106)-SUMIFS(H$44:H$81,$A$44:$A$81,$D106))/SUMIFS(H$44:H$81,$A$44:$A$81,$D106),0) -> 0.040632701 | J106: =IFERROR((SUMIFS(J$44:J$81,$A$44:$A$81,$D106)-SUMIFS(I$44:I$81,$A$44:$A$81,$D106))/SUMIFS(I$44:I$81,$A$44:$A$81,$D106),0) -> 0.039046151 | K106: =IFERROR((SUMIFS(K$44:K$81,$A$44:$A$81,$D106)-SUMIFS(J$44:J$81,$A$44:$A$81,$D106))/SUMIFS(J$44:J$81,$A$44:$A$81,$D106),0) -> 0.037578842 | L106: =IFERROR((SUMIFS(L$44:L$81,$A$44:$A$81,$D106)-SUMIFS(K$44:K$81,$A$44:$A$81,$D106))/SUMIFS(K$44:K$81,$A$44:$A$81,$D106),0) -> 0.036217818 | M106: =IFERROR((SUMIFS(M$44:M$81,$A$44:$A$81,$D106)-SUMIFS(L$44:L$81,$A$44:$A$81,$D106))/SUMIFS(L$44:L$81,$A$44:$A$81,$D106),0) -> 0.034951935 | N106: =IFERROR((SUMIFS(N$44:N$81,$A$44:$A$81,$D106)-SUMIFS(M$44:M$81,$A$44:$A$81,$D106))/SUMIFS(M$44:M$81,$A$44:$A$81,$D106),0) -> 0.033771554 | ... AJ106: =IFERROR((SUMIFS(AJ$44:AJ$81,$A$44:$A$81,$D106)-SUMIFS(AI$44:AI$81,$A$44:$A$81,$D106))/SUMIFS(AI$44:AI$81,$A$44:$A$81,$D106),0) -> 0.01937582
D107: ISIC 30 | F107: 0 | G107: =IFERROR((SUMIFS(G$44:G$81,$A$44:$A$81,$D107)-SUMIFS(F$44:F$81,$A$44:$A$81,$D107))/SUMIFS(F$44:F$81,$A$44:$A$81,$D107),0) -> 0 | H107: =IFERROR((SUMIFS(H$44:H$81,$A$44:$A$81,$D107)-SUMIFS(G$44:G$81,$A$44:$A$81,$D107))/SUMIFS(G$44:G$81,$A$44:$A$81,$D107),0) -> 0 | I107: =IFERROR((SUMIFS(I$44:I$81,$A$44:$A$81,$D107)-SUMIFS(H$44:H$81,$A$44:$A$81,$D107))/SUMIFS(H$44:H$81,$A$44:$A$81,$D107),0) -> 0 | J107: =IFERROR((SUMIFS(J$44:J$81,$A$44:$A$81,$D107)-SUMIFS(I$44:I$81,$A$44:$A$81,$D107))/SUMIFS(I$44:I$81,$A$44:$A$81,$D107),0) -> 0 | K107: =IFERROR((SUMIFS(K$44:K$81,$A$44:$A$81,$D107)-SUMIFS(J$44:J$81,$A$44:$A$81,$D107))/SUMIFS(J$44:J$81,$A$44:$A$81,$D107),0) -> 0 | L107: =IFERROR((SUMIFS(L$44:L$81,$A$44:$A$81,$D107)-SUMIFS(K$44:K$81,$A$44:$A$81,$D107))/SUMIFS(K$44:K$81,$A$44:$A$81,$D107),0) -> 0 | M107: =IFERROR((SUMIFS(M$44:M$81,$A$44:$A$81,$D107)-SUMIFS(L$44:L$81,$A$44:$A$81,$D107))/SUMIFS(L$44:L$81,$A$44:$A$81,$D107),0) -> 0 | N107: =IFERROR((SUMIFS(N$44:N$81,$A$44:$A$81,$D107)-SUMIFS(M$44:M$81,$A$44:$A$81,$D107))/SUMIFS(M$44:M$81,$A$44:$A$81,$D107),0) -> 0 | ... AJ107: =IFERROR((SUMIFS(AJ$44:AJ$81,$A$44:$A$81,$D107)-SUMIFS(AI$44:AI$81,$A$44:$A$81,$D107))/SUMIFS(AI$44:AI$81,$A$44:$A$81,$D107),0) -> 0
D108: ISIC 31T33 | F108: 0 | G108: =IFERROR((SUMIFS(G$44:G$81,$A$44:$A$81,$D108)-SUMIFS(F$44:F$81,$A$44:$A$81,$D108))/SUMIFS(F$44:F$81,$A$44:$A$81,$D108),0) -> 0.045119544 | H108: =IFERROR((SUMIFS(H$44:H$81,$A$44:$A$81,$D108)-SUMIFS(G$44:G$81,$A$44:$A$81,$D108))/SUMIFS(G$44:G$81,$A$44:$A$81,$D108),0) -> 0.043171658 | I108: =IFERROR((SUMIFS(I$44:I$81,$A$44:$A$81,$D108)-SUMIFS(H$44:H$81,$A$44:$A$81,$D108))/SUMIFS(H$44:H$81,$A$44:$A$81,$D108),0) -> 0.041384999 | J108: =IFERROR((SUMIFS(J$44:J$81,$A$44:$A$81,$D108)-SUMIFS(I$44:I$81,$A$44:$A$81,$D108))/SUMIFS(I$44:I$81,$A$44:$A$81,$D108),0) -> 0.039740345 | K108: =IFERROR((SUMIFS(K$44:K$81,$A$44:$A$81,$D108)-SUMIFS(J$44:J$81,$A$44:$A$81,$D108))/SUMIFS(J$44:J$81,$A$44:$A$81,$D108),0) -> 0.038221413 | L108: =IFERROR((SUMIFS(L$44:L$81,$A$44:$A$81,$D108)-SUMIFS(K$44:K$81,$A$44:$A$81,$D108))/SUMIFS(K$44:K$81,$A$44:$A$81,$D108),0) -> 0.036814318 | M108: =IFERROR((SUMIFS(M$44:M$81,$A$44:$A$81,$D108)-SUMIFS(L$44:L$81,$A$44:$A$81,$D108))/SUMIFS(L$44:L$81,$A$44:$A$81,$D108),0) -> 0.035507146 | N108: =IFERROR((SUMIFS(N$44:N$81,$A$44:$A$81,$D108)-SUMIFS(M$44:M$81,$A$44:$A$81,$D108))/SUMIFS(M$44:M$81,$A$44:$A$81,$D108),0) -> 0.03428962 | ... AJ108: =IFERROR((SUMIFS(AJ$44:AJ$81,$A$44:$A$81,$D108)-SUMIFS(AI$44:AI$81,$A$44:$A$81,$D108))/SUMIFS(AI$44:AI$81,$A$44:$A$81,$D108),0) -> 0.019545243
D109: ISIC 351 | F109: 0 | G109: =IFERROR((SUMIFS(G$44:G$81,$A$44:$A$81,$D109)-SUMIFS(F$44:F$81,$A$44:$A$81,$D109))/SUMIFS(F$44:F$81,$A$44:$A$81,$D109),0) -> 0.044673121 | H109: =IFERROR((SUMIFS(H$44:H$81,$A$44:$A$81,$D109)-SUMIFS(G$44:G$81,$A$44:$A$81,$D109))/SUMIFS(G$44:G$81,$A$44:$A$81,$D109),0) -> 0.042762775 | I109: =IFERROR((SUMIFS(I$44:I$81,$A$44:$A$81,$D109)-SUMIFS(H$44:H$81,$A$44:$A$81,$D109))/SUMIFS(H$44:H$81,$A$44:$A$81,$D109),0) -> 0.041009111 | J109: =IFERROR((SUMIFS(J$44:J$81,$A$44:$A$81,$D109)-SUMIFS(I$44:I$81,$A$44:$A$81,$D109))/SUMIFS(I$44:I$81,$A$44:$A$81,$D109),0) -> 0.039393614 | K109: =IFERROR((SUMIFS(K$44:K$81,$A$44:$A$81,$D109)-SUMIFS(J$44:J$81,$A$44:$A$81,$D109))/SUMIFS(J$44:J$81,$A$44:$A$81,$D109),0) -> 0.037900574 | L109: =IFERROR((SUMIFS(L$44:L$81,$A$44:$A$81,$D109)-SUMIFS(K$44:K$81,$A$44:$A$81,$D109))/SUMIFS(K$44:K$81,$A$44:$A$81,$D109),0) -> 0.036516575 | M109: =IFERROR((SUMIFS(M$44:M$81,$A$44:$A$81,$D109)-SUMIFS(L$44:L$81,$A$44:$A$81,$D109))/SUMIFS(L$44:L$81,$A$44:$A$81,$D109),0) -> 0.035230092 | N109: =IFERROR((SUMIFS(N$44:N$81,$A$44:$A$81,$D109)-SUMIFS(M$44:M$81,$A$44:$A$81,$D109))/SUMIFS(M$44:M$81,$A$44:$A$81,$D109),0) -> 0.034031171 | ... AJ109: =IFERROR((SUMIFS(AJ$44:AJ$81,$A$44:$A$81,$D109)-SUMIFS(AI$44:AI$81,$A$44:$A$81,$D109))/SUMIFS(AI$44:AI$81,$A$44:$A$81,$D109),0) -> 0.019460999
D110: ISIC 352T353 | F110: =F109 -> 0 | G110: =IFERROR((SUMIFS(G$44:G$81,$A$44:$A$81,$D110)-SUMIFS(F$44:F$81,$A$44:$A$81,$D110))/SUMIFS(F$44:F$81,$A$44:$A$81,$D110),0) -> 0 | H110: =IFERROR((SUMIFS(H$44:H$81,$A$44:$A$81,$D110)-SUMIFS(G$44:G$81,$A$44:$A$81,$D110))/SUMIFS(G$44:G$81,$A$44:$A$81,$D110),0) -> 0 | I110: =IFERROR((SUMIFS(I$44:I$81,$A$44:$A$81,$D110)-SUMIFS(H$44:H$81,$A$44:$A$81,$D110))/SUMIFS(H$44:H$81,$A$44:$A$81,$D110),0) -> 0 | J110: =IFERROR((SUMIFS(J$44:J$81,$A$44:$A$81,$D110)-SUMIFS(I$44:I$81,$A$44:$A$81,$D110))/SUMIFS(I$44:I$81,$A$44:$A$81,$D110),0) -> 0 | K110: =IFERROR((SUMIFS(K$44:K$81,$A$44:$A$81,$D110)-SUMIFS(J$44:J$81,$A$44:$A$81,$D110))/SUMIFS(J$44:J$81,$A$44:$A$81,$D110),0) -> 0 | L110: =IFERROR((SUMIFS(L$44:L$81,$A$44:$A$81,$D110)-SUMIFS(K$44:K$81,$A$44:$A$81,$D110))/SUMIFS(K$44:K$81,$A$44:$A$81,$D110),0) -> 0 | M110: =IFERROR((SUMIFS(M$44:M$81,$A$44:$A$81,$D110)-SUMIFS(L$44:L$81,$A$44:$A$81,$D110))/SUMIFS(L$44:L$81,$A$44:$A$81,$D110),0) -> 0 | N110: =IFERROR((SUMIFS(N$44:N$81,$A$44:$A$81,$D110)-SUMIFS(M$44:M$81,$A$44:$A$81,$D110))/SUMIFS(M$44:M$81,$A$44:$A$81,$D110),0) -> 0 | ... AJ110: =IFERROR((SUMIFS(AJ$44:AJ$81,$A$44:$A$81,$D110)-SUMIFS(AI$44:AI$81,$A$44:$A$81,$D110))/SUMIFS(AI$44:AI$81,$A$44:$A$81,$D110),0) -> 0
D111: ISIC 36T39 | F111: 0 | G111: =IFERROR((SUMIFS(G$44:G$81,$A$44:$A$81,$D111)-SUMIFS(F$44:F$81,$A$44:$A$81,$D111))/SUMIFS(F$44:F$81,$A$44:$A$81,$D111),0) -> 0.044074053 | H111: =IFERROR((SUMIFS(H$44:H$81,$A$44:$A$81,$D111)-SUMIFS(G$44:G$81,$A$44:$A$81,$D111))/SUMIFS(G$44:G$81,$A$44:$A$81,$D111),0) -> 0.042213532 | I111: =IFERROR((SUMIFS(I$44:I$81,$A$44:$A$81,$D111)-SUMIFS(H$44:H$81,$A$44:$A$81,$D111))/SUMIFS(H$44:H$81,$A$44:$A$81,$D111),0) -> 0.040503727 | J111: =IFERROR((SUMIFS(J$44:J$81,$A$44:$A$81,$D111)-SUMIFS(I$44:I$81,$A$44:$A$81,$D111))/SUMIFS(I$44:I$81,$A$44:$A$81,$D111),0) -> 0.038927037 | K111: =IFERROR((SUMIFS(K$44:K$81,$A$44:$A$81,$D111)-SUMIFS(J$44:J$81,$A$44:$A$81,$D111))/SUMIFS(J$44:J$81,$A$44:$A$81,$D111),0) -> 0.037468499 | L111: =IFERROR((SUMIFS(L$44:L$81,$A$44:$A$81,$D111)-SUMIFS(K$44:K$81,$A$44:$A$81,$D111))/SUMIFS(K$44:K$81,$A$44:$A$81,$D111),0) -> 0.036115312 | M111: =IFERROR((SUMIFS(M$44:M$81,$A$44:$A$81,$D111)-SUMIFS(L$44:L$81,$A$44:$A$81,$D111))/SUMIFS(L$44:L$81,$A$44:$A$81,$D111),0) -> 0.03485646 | N111: =IFERROR((SUMIFS(N$44:N$81,$A$44:$A$81,$D111)-SUMIFS(M$44:M$81,$A$44:$A$81,$D111))/SUMIFS(M$44:M$81,$A$44:$A$81,$D111),0) -> 0.033682411 | ... AJ111: =IFERROR((SUMIFS(AJ$44:AJ$81,$A$44:$A$81,$D111)-SUMIFS(AI$44:AI$81,$A$44:$A$81,$D111))/SUMIFS(AI$44:AI$81,$A$44:$A$81,$D111),0) -> 0.019346444
D112: ISIC 41T43 | F112: 0 | G112: =IFERROR((SUMIFS(G$44:G$81,$A$44:$A$81,$D112)-SUMIFS(F$44:F$81,$A$44:$A$81,$D112))/SUMIFS(F$44:F$81,$A$44:$A$81,$D112),0) -> 0.0446731 | H112: =IFERROR((SUMIFS(H$44:H$81,$A$44:$A$81,$D112)-SUMIFS(G$44:G$81,$A$44:$A$81,$D112))/SUMIFS(G$44:G$81,$A$44:$A$81,$D112),0) -> 0.042762755 | I112: =IFERROR((SUMIFS(I$44:I$81,$A$44:$A$81,$D112)-SUMIFS(H$44:H$81,$A$44:$A$81,$D112))/SUMIFS(H$44:H$81,$A$44:$A$81,$D112),0) -> 0.041009093 | J112: =IFERROR((SUMIFS(J$44:J$81,$A$44:$A$81,$D112)-SUMIFS(I$44:I$81,$A$44:$A$81,$D112))/SUMIFS(I$44:I$81,$A$44:$A$81,$D112),0) -> 0.039393598 | K112: =IFERROR((SUMIFS(K$44:K$81,$A$44:$A$81,$D112)-SUMIFS(J$44:J$81,$A$44:$A$81,$D112))/SUMIFS(J$44:J$81,$A$44:$A$81,$D112),0) -> 0.037900558 | L112: =IFERROR((SUMIFS(L$44:L$81,$A$44:$A$81,$D112)-SUMIFS(K$44:K$81,$A$44:$A$81,$D112))/SUMIFS(K$44:K$81,$A$44:$A$81,$D112),0) -> 0.03651656 | M112: =IFERROR((SUMIFS(M$44:M$81,$A$44:$A$81,$D112)-SUMIFS(L$44:L$81,$A$44:$A$81,$D112))/SUMIFS(L$44:L$81,$A$44:$A$81,$D112),0) -> 0.035230079 | N112: =IFERROR((SUMIFS(N$44:N$81,$A$44:$A$81,$D112)-SUMIFS(M$44:M$81,$A$44:$A$81,$D112))/SUMIFS(M$44:M$81,$A$44:$A$81,$D112),0) -> 0.034031159 | ... AJ112: =IFERROR((SUMIFS(AJ$44:AJ$81,$A$44:$A$81,$D112)-SUMIFS(AI$44:AI$81,$A$44:$A$81,$D112))/SUMIFS(AI$44:AI$81,$A$44:$A$81,$D112),0) -> 0.019460994
D113: ISIC 45T47 | F113: 0 | G113: =IFERROR((SUMIFS(G$44:G$81,$A$44:$A$81,$D113)-SUMIFS(F$44:F$81,$A$44:$A$81,$D113))/SUMIFS(F$44:F$81,$A$44:$A$81,$D113),0) -> 0.044673101 | H113: =IFERROR((SUMIFS(H$44:H$81,$A$44:$A$81,$D113)-SUMIFS(G$44:G$81,$A$44:$A$81,$D113))/SUMIFS(G$44:G$81,$A$44:$A$81,$D113),0) -> 0.042762756 | I113: =IFERROR((SUMIFS(I$44:I$81,$A$44:$A$81,$D113)-SUMIFS(H$44:H$81,$A$44:$A$81,$D113))/SUMIFS(H$44:H$81,$A$44:$A$81,$D113),0) -> 0.041009095 | J113: =IFERROR((SUMIFS(J$44:J$81,$A$44:$A$81,$D113)-SUMIFS(I$44:I$81,$A$44:$A$81,$D113))/SUMIFS(I$44:I$81,$A$44:$A$81,$D113),0) -> 0.039393599 | K113: =IFERROR((SUMIFS(K$44:K$81,$A$44:$A$81,$D113)-SUMIFS(J$44:J$81,$A$44:$A$81,$D113))/SUMIFS(J$44:J$81,$A$44:$A$81,$D113),0) -> 0.037900559 | L113: =IFERROR((SUMIFS(L$44:L$81,$A$44:$A$81,$D113)-SUMIFS(K$44:K$81,$A$44:$A$81,$D113))/SUMIFS(K$44:K$81,$A$44:$A$81,$D113),0) -> 0.036516561 | M113: =IFERROR((SUMIFS(M$44:M$81,$A$44:$A$81,$D113)-SUMIFS(L$44:L$81,$A$44:$A$81,$D113))/SUMIFS(L$44:L$81,$A$44:$A$81,$D113),0) -> 0.03523008 | N113: =IFERROR((SUMIFS(N$44:N$81,$A$44:$A$81,$D113)-SUMIFS(M$44:M$81,$A$44:$A$81,$D113))/SUMIFS(M$44:M$81,$A$44:$A$81,$D113),0) -> 0.034031159 | ... AJ113: =IFERROR((SUMIFS(AJ$44:AJ$81,$A$44:$A$81,$D113)-SUMIFS(AI$44:AI$81,$A$44:$A$81,$D113))/SUMIFS(AI$44:AI$81,$A$44:$A$81,$D113),0) -> 0.019460995
D114: ISIC 49T53 | F114: 0 | G114: =IFERROR((SUMIFS(G$44:G$81,$A$44:$A$81,$D114)-SUMIFS(F$44:F$81,$A$44:$A$81,$D114))/SUMIFS(F$44:F$81,$A$44:$A$81,$D114),0) -> 0.04864907 | H114: =IFERROR((SUMIFS(H$44:H$81,$A$44:$A$81,$D114)-SUMIFS(G$44:G$81,$A$44:$A$81,$D114))/SUMIFS(G$44:G$81,$A$44:$A$81,$D114),0) -> 0.046392136 | I114: =IFERROR((SUMIFS(I$44:I$81,$A$44:$A$81,$D114)-SUMIFS(H$44:H$81,$A$44:$A$81,$D114))/SUMIFS(H$44:H$81,$A$44:$A$81,$D114),0) -> 0.044335326 | J114: =IFERROR((SUMIFS(J$44:J$81,$A$44:$A$81,$D114)-SUMIFS(I$44:I$81,$A$44:$A$81,$D114))/SUMIFS(I$44:I$81,$A$44:$A$81,$D114),0) -> 0.042453151 | K114: =IFERROR((SUMIFS(K$44:K$81,$A$44:$A$81,$D114)-SUMIFS(J$44:J$81,$A$44:$A$81,$D114))/SUMIFS(J$44:J$81,$A$44:$A$81,$D114),0) -> 0.040724277 | L114: =IFERROR((SUMIFS(L$44:L$81,$A$44:$A$81,$D114)-SUMIFS(K$44:K$81,$A$44:$A$81,$D114))/SUMIFS(K$44:K$81,$A$44:$A$81,$D114),0) -> 0.039130708 | M114: =IFERROR((SUMIFS(M$44:M$81,$A$44:$A$81,$D114)-SUMIFS(L$44:L$81,$A$44:$A$81,$D114))/SUMIFS(L$44:L$81,$A$44:$A$81,$D114),0) -> 0.037657156 | N114: =IFERROR((SUMIFS(N$44:N$81,$A$44:$A$81,$D114)-SUMIFS(M$44:M$81,$A$44:$A$81,$D114))/SUMIFS(M$44:M$81,$A$44:$A$81,$D114),0) -> 0.036290557 | ... AJ114: =IFERROR((SUMIFS(AJ$44:AJ$81,$A$44:$A$81,$D114)-SUMIFS(AI$44:AI$81,$A$44:$A$81,$D114))/SUMIFS(AI$44:AI$81,$A$44:$A$81,$D114),0) -> 0.020179445
D115: ISIC 55T56 | F115: 0 | G115: =IFERROR((SUMIFS(G$44:G$81,$A$44:$A$81,$D115)-SUMIFS(F$44:F$81,$A$44:$A$81,$D115))/SUMIFS(F$44:F$81,$A$44:$A$81,$D115),0) -> 0.044673114 | H115: =IFERROR((SUMIFS(H$44:H$81,$A$44:$A$81,$D115)-SUMIFS(G$44:G$81,$A$44:$A$81,$D115))/SUMIFS(G$44:G$81,$A$44:$A$81,$D115),0) -> 0.042762768 | I115: =IFERROR((SUMIFS(I$44:I$81,$A$44:$A$81,$D115)-SUMIFS(H$44:H$81,$A$44:$A$81,$D115))/SUMIFS(H$44:H$81,$A$44:$A$81,$D115),0) -> 0.041009105 | J115: =IFERROR((SUMIFS(J$44:J$81,$A$44:$A$81,$D115)-SUMIFS(I$44:I$81,$A$44:$A$81,$D115))/SUMIFS(I$44:I$81,$A$44:$A$81,$D115),0) -> 0.039393609 | K115: =IFERROR((SUMIFS(K$44:K$81,$A$44:$A$81,$D115)-SUMIFS(J$44:J$81,$A$44:$A$81,$D115))/SUMIFS(J$44:J$81,$A$44:$A$81,$D115),0) -> 0.037900569 | L115: =IFERROR((SUMIFS(L$44:L$81,$A$44:$A$81,$D115)-SUMIFS(K$44:K$81,$A$44:$A$81,$D115))/SUMIFS(K$44:K$81,$A$44:$A$81,$D115),0) -> 0.03651657 | M115: =IFERROR((SUMIFS(M$44:M$81,$A$44:$A$81,$D115)-SUMIFS(L$44:L$81,$A$44:$A$81,$D115))/SUMIFS(L$44:L$81,$A$44:$A$81,$D115),0) -> 0.035230088 | N115: =IFERROR((SUMIFS(N$44:N$81,$A$44:$A$81,$D115)-SUMIFS(M$44:M$81,$A$44:$A$81,$D115))/SUMIFS(M$44:M$81,$A$44:$A$81,$D115),0) -> 0.034031167 | ... AJ115: =IFERROR((SUMIFS(AJ$44:AJ$81,$A$44:$A$81,$D115)-SUMIFS(AI$44:AI$81,$A$44:$A$81,$D115))/SUMIFS(AI$44:AI$81,$A$44:$A$81,$D115),0) -> 0.019460997
D116: ISIC 58T60 | F116: 0 | G116: =IFERROR((SUMIFS(G$44:G$81,$A$44:$A$81,$D116)-SUMIFS(F$44:F$81,$A$44:$A$81,$D116))/SUMIFS(F$44:F$81,$A$44:$A$81,$D116),0) -> 0.043213762 | H116: =IFERROR((SUMIFS(H$44:H$81,$A$44:$A$81,$D116)-SUMIFS(G$44:G$81,$A$44:$A$81,$D116))/SUMIFS(G$44:G$81,$A$44:$A$81,$D116),0) -> 0.041423688 | I116: =IFERROR((SUMIFS(I$44:I$81,$A$44:$A$81,$D116)-SUMIFS(H$44:H$81,$A$44:$A$81,$D116))/SUMIFS(H$44:H$81,$A$44:$A$81,$D116),0) -> 0.039776019 | J116: =IFERROR((SUMIFS(J$44:J$81,$A$44:$A$81,$D116)-SUMIFS(I$44:I$81,$A$44:$A$81,$D116))/SUMIFS(I$44:I$81,$A$44:$A$81,$D116),0) -> 0.038254411 | K116: =IFERROR((SUMIFS(K$44:K$81,$A$44:$A$81,$D116)-SUMIFS(J$44:J$81,$A$44:$A$81,$D116))/SUMIFS(J$44:J$81,$A$44:$A$81,$D116),0) -> 0.03684493 | L116: =IFERROR((SUMIFS(L$44:L$81,$A$44:$A$81,$D116)-SUMIFS(K$44:K$81,$A$44:$A$81,$D116))/SUMIFS(K$44:K$81,$A$44:$A$81,$D116),0) -> 0.035535622 | M116: =IFERROR((SUMIFS(M$44:M$81,$A$44:$A$81,$D116)-SUMIFS(L$44:L$81,$A$44:$A$81,$D116))/SUMIFS(L$44:L$81,$A$44:$A$81,$D116),0) -> 0.034316175 | N116: =IFERROR((SUMIFS(N$44:N$81,$A$44:$A$81,$D116)-SUMIFS(M$44:M$81,$A$44:$A$81,$D116))/SUMIFS(M$44:M$81,$A$44:$A$81,$D116),0) -> 0.033177646 | ... AJ116: =IFERROR((SUMIFS(AJ$44:AJ$81,$A$44:$A$81,$D116)-SUMIFS(AI$44:AI$81,$A$44:$A$81,$D116))/SUMIFS(AI$44:AI$81,$A$44:$A$81,$D116),0) -> 0.019178847
D117: ISIC 61 | F117: 0 | G117: =IFERROR((SUMIFS(G$44:G$81,$A$44:$A$81,$D117)-SUMIFS(F$44:F$81,$A$44:$A$81,$D117))/SUMIFS(F$44:F$81,$A$44:$A$81,$D117),0) -> 0.043281205 | H117: =IFERROR((SUMIFS(H$44:H$81,$A$44:$A$81,$D117)-SUMIFS(G$44:G$81,$A$44:$A$81,$D117))/SUMIFS(G$44:G$81,$A$44:$A$81,$D117),0) -> 0.041485656 | I117: =IFERROR((SUMIFS(I$44:I$81,$A$44:$A$81,$D117)-SUMIFS(H$44:H$81,$A$44:$A$81,$D117))/SUMIFS(H$44:H$81,$A$44:$A$81,$D117),0) -> 0.039833151 | J117: =IFERROR((SUMIFS(J$44:J$81,$A$44:$A$81,$D117)-SUMIFS(I$44:I$81,$A$44:$A$81,$D117))/SUMIFS(I$44:I$81,$A$44:$A$81,$D117),0) -> 0.038307253 | K117: =IFERROR((SUMIFS(K$44:K$81,$A$44:$A$81,$D117)-SUMIFS(J$44:J$81,$A$44:$A$81,$D117))/SUMIFS(J$44:J$81,$A$44:$A$81,$D117),0) -> 0.036893947 | L117: =IFERROR((SUMIFS(L$44:L$81,$A$44:$A$81,$D117)-SUMIFS(K$44:K$81,$A$44:$A$81,$D117))/SUMIFS(K$44:K$81,$A$44:$A$81,$D117),0) -> 0.035581215 | M117: =IFERROR((SUMIFS(M$44:M$81,$A$44:$A$81,$D117)-SUMIFS(L$44:L$81,$A$44:$A$81,$D117))/SUMIFS(L$44:L$81,$A$44:$A$81,$D117),0) -> 0.034358691 | N117: =IFERROR((SUMIFS(N$44:N$81,$A$44:$A$81,$D117)-SUMIFS(M$44:M$81,$A$44:$A$81,$D117))/SUMIFS(M$44:M$81,$A$44:$A$81,$D117),0) -> 0.033217386 | ... AJ117: =IFERROR((SUMIFS(AJ$44:AJ$81,$A$44:$A$81,$D117)-SUMIFS(AI$44:AI$81,$A$44:$A$81,$D117))/SUMIFS(AI$44:AI$81,$A$44:$A$81,$D117),0) -> 0.01919212
D118: ISIC 62T63 | F118: 0 | G118: =IFERROR((SUMIFS(G$44:G$81,$A$44:$A$81,$D118)-SUMIFS(F$44:F$81,$A$44:$A$81,$D118))/SUMIFS(F$44:F$81,$A$44:$A$81,$D118),0) -> 0.049984642 | H118: =IFERROR((SUMIFS(H$44:H$81,$A$44:$A$81,$D118)-SUMIFS(G$44:G$81,$A$44:$A$81,$D118))/SUMIFS(G$44:G$81,$A$44:$A$81,$D118),0) -> 0.047605117 | I118: =IFERROR((SUMIFS(I$44:I$81,$A$44:$A$81,$D118)-SUMIFS(H$44:H$81,$A$44:$A$81,$D118))/SUMIFS(H$44:H$81,$A$44:$A$81,$D118),0) -> 0.045441852 | J118: =IFERROR((SUMIFS(J$44:J$81,$A$44:$A$81,$D118)-SUMIFS(I$44:I$81,$A$44:$A$81,$D118))/SUMIFS(I$44:I$81,$A$44:$A$81,$D118),0) -> 0.043466647 | K118: =IFERROR((SUMIFS(K$44:K$81,$A$44:$A$81,$D118)-SUMIFS(J$44:J$81,$A$44:$A$81,$D118))/SUMIFS(J$44:J$81,$A$44:$A$81,$D118),0) -> 0.041656001 | L118: =IFERROR((SUMIFS(L$44:L$81,$A$44:$A$81,$D118)-SUMIFS(K$44:K$81,$A$44:$A$81,$D118))/SUMIFS(K$44:K$81,$A$44:$A$81,$D118),0) -> 0.03999017 | M118: =IFERROR((SUMIFS(M$44:M$81,$A$44:$A$81,$D118)-SUMIFS(L$44:L$81,$A$44:$A$81,$D118))/SUMIFS(L$44:L$81,$A$44:$A$81,$D118),0) -> 0.03845245 | N118: =IFERROR((SUMIFS(N$44:N$81,$A$44:$A$81,$D118)-SUMIFS(M$44:M$81,$A$44:$A$81,$D118))/SUMIFS(M$44:M$81,$A$44:$A$81,$D118),0) -> 0.037028609 | ... AJ118: =IFERROR((SUMIFS(AJ$44:AJ$81,$A$44:$A$81,$D118)-SUMIFS(AI$44:AI$81,$A$44:$A$81,$D118))/SUMIFS(AI$44:AI$81,$A$44:$A$81,$D118),0) -> 0.020405604
D119: ISIC 64T66 | F119: 0 | G119: =IFERROR((SUMIFS(G$44:G$81,$A$44:$A$81,$D119)-SUMIFS(F$44:F$81,$A$44:$A$81,$D119))/SUMIFS(F$44:F$81,$A$44:$A$81,$D119),0) -> 0.045605887 | H119: =IFERROR((SUMIFS(H$44:H$81,$A$44:$A$81,$D119)-SUMIFS(G$44:G$81,$A$44:$A$81,$D119))/SUMIFS(G$44:G$81,$A$44:$A$81,$D119),0) -> 0.043616709 | I119: =IFERROR((SUMIFS(I$44:I$81,$A$44:$A$81,$D119)-SUMIFS(H$44:H$81,$A$44:$A$81,$D119))/SUMIFS(H$44:H$81,$A$44:$A$81,$D119),0) -> 0.041793801 | J119: =IFERROR((SUMIFS(J$44:J$81,$A$44:$A$81,$D119)-SUMIFS(I$44:I$81,$A$44:$A$81,$D119))/SUMIFS(I$44:I$81,$A$44:$A$81,$D119),0) -> 0.040117152 | K119: =IFERROR((SUMIFS(K$44:K$81,$A$44:$A$81,$D119)-SUMIFS(J$44:J$81,$A$44:$A$81,$D119))/SUMIFS(J$44:J$81,$A$44:$A$81,$D119),0) -> 0.03856984 | L119: =IFERROR((SUMIFS(L$44:L$81,$A$44:$A$81,$D119)-SUMIFS(K$44:K$81,$A$44:$A$81,$D119))/SUMIFS(K$44:K$81,$A$44:$A$81,$D119),0) -> 0.037137455 | M119: =IFERROR((SUMIFS(M$44:M$81,$A$44:$A$81,$D119)-SUMIFS(L$44:L$81,$A$44:$A$81,$D119))/SUMIFS(L$44:L$81,$A$44:$A$81,$D119),0) -> 0.03580765 | N119: =IFERROR((SUMIFS(N$44:N$81,$A$44:$A$81,$D119)-SUMIFS(M$44:M$81,$A$44:$A$81,$D119))/SUMIFS(M$44:M$81,$A$44:$A$81,$D119),0) -> 0.034569787 | ... AJ119: =IFERROR((SUMIFS(AJ$44:AJ$81,$A$44:$A$81,$D119)-SUMIFS(AI$44:AI$81,$A$44:$A$81,$D119))/SUMIFS(AI$44:AI$81,$A$44:$A$81,$D119),0) -> 0.019635952
D120: ISIC 68 | F120: 0 | G120: =IFERROR((SUMIFS(G$44:G$81,$A$44:$A$81,$D120)-SUMIFS(F$44:F$81,$A$44:$A$81,$D120))/SUMIFS(F$44:F$81,$A$44:$A$81,$D120),0) -> 0.044329369 | H120: =IFERROR((SUMIFS(H$44:H$81,$A$44:$A$81,$D120)-SUMIFS(G$44:G$81,$A$44:$A$81,$D120))/SUMIFS(G$44:G$81,$A$44:$A$81,$D120),0) -> 0.04244769 | I120: =IFERROR((SUMIFS(I$44:I$81,$A$44:$A$81,$D120)-SUMIFS(H$44:H$81,$A$44:$A$81,$D120))/SUMIFS(H$44:H$81,$A$44:$A$81,$D120),0) -> 0.040719252 | J120: =IFERROR((SUMIFS(J$44:J$81,$A$44:$A$81,$D120)-SUMIFS(I$44:I$81,$A$44:$A$81,$D120))/SUMIFS(I$44:I$81,$A$44:$A$81,$D120),0) -> 0.039126067 | K120: =IFERROR((SUMIFS(K$44:K$81,$A$44:$A$81,$D120)-SUMIFS(J$44:J$81,$A$44:$A$81,$D120))/SUMIFS(J$44:J$81,$A$44:$A$81,$D120),0) -> 0.037652859 | L120: =IFERROR((SUMIFS(L$44:L$81,$A$44:$A$81,$D120)-SUMIFS(K$44:K$81,$A$44:$A$81,$D120))/SUMIFS(K$44:K$81,$A$44:$A$81,$D120),0) -> 0.036286566 | M120: =IFERROR((SUMIFS(M$44:M$81,$A$44:$A$81,$D120)-SUMIFS(L$44:L$81,$A$44:$A$81,$D120))/SUMIFS(L$44:L$81,$A$44:$A$81,$D120),0) -> 0.035015957 | N120: =IFERROR((SUMIFS(N$44:N$81,$A$44:$A$81,$D120)-SUMIFS(M$44:M$81,$A$44:$A$81,$D120))/SUMIFS(M$44:M$81,$A$44:$A$81,$D120),0) -> 0.033831321 | ... AJ120: =IFERROR((SUMIFS(AJ$44:AJ$81,$A$44:$A$81,$D120)-SUMIFS(AI$44:AI$81,$A$44:$A$81,$D120))/SUMIFS(AI$44:AI$81,$A$44:$A$81,$D120),0) -> 0.019395479
D121: ISIC 69T82 | F121: 0 | G121: =IFERROR((SUMIFS(G$44:G$81,$A$44:$A$81,$D121)-SUMIFS(F$44:F$81,$A$44:$A$81,$D121))/SUMIFS(F$44:F$81,$A$44:$A$81,$D121),0) -> 0.045080474 | H121: =IFERROR((SUMIFS(H$44:H$81,$A$44:$A$81,$D121)-SUMIFS(G$44:G$81,$A$44:$A$81,$D121))/SUMIFS(G$44:G$81,$A$44:$A$81,$D121),0) -> 0.043135887 | I121: =IFERROR((SUMIFS(I$44:I$81,$A$44:$A$81,$D121)-SUMIFS(H$44:H$81,$A$44:$A$81,$D121))/SUMIFS(H$44:H$81,$A$44:$A$81,$D121),0) -> 0.041352127 | J121: =IFERROR((SUMIFS(J$44:J$81,$A$44:$A$81,$D121)-SUMIFS(I$44:I$81,$A$44:$A$81,$D121))/SUMIFS(I$44:I$81,$A$44:$A$81,$D121),0) -> 0.039710032 | K121: =IFERROR((SUMIFS(K$44:K$81,$A$44:$A$81,$D121)-SUMIFS(J$44:J$81,$A$44:$A$81,$D121))/SUMIFS(J$44:J$81,$A$44:$A$81,$D121),0) -> 0.038193372 | L121: =IFERROR((SUMIFS(L$44:L$81,$A$44:$A$81,$D121)-SUMIFS(K$44:K$81,$A$44:$A$81,$D121))/SUMIFS(K$44:K$81,$A$44:$A$81,$D121),0) -> 0.036788303 | M121: =IFERROR((SUMIFS(M$44:M$81,$A$44:$A$81,$D121)-SUMIFS(L$44:L$81,$A$44:$A$81,$D121))/SUMIFS(L$44:L$81,$A$44:$A$81,$D121),0) -> 0.035482946 | N121: =IFERROR((SUMIFS(N$44:N$81,$A$44:$A$81,$D121)-SUMIFS(M$44:M$81,$A$44:$A$81,$D121))/SUMIFS(M$44:M$81,$A$44:$A$81,$D121),0) -> 0.03426705 | ... AJ121: =IFERROR((SUMIFS(AJ$44:AJ$81,$A$44:$A$81,$D121)-SUMIFS(AI$44:AI$81,$A$44:$A$81,$D121))/SUMIFS(AI$44:AI$81,$A$44:$A$81,$D121),0) -> 0.019537908
D122: ISIC 84 | F122: 0 | G122: =IFERROR((SUMIFS(G$44:G$81,$A$44:$A$81,$D122)-SUMIFS(F$44:F$81,$A$44:$A$81,$D122))/SUMIFS(F$44:F$81,$A$44:$A$81,$D122),0) -> 0.044673092 | H122: =IFERROR((SUMIFS(H$44:H$81,$A$44:$A$81,$D122)-SUMIFS(G$44:G$81,$A$44:$A$81,$D122))/SUMIFS(G$44:G$81,$A$44:$A$81,$D122),0) -> 0.042762748 | I122: =IFERROR((SUMIFS(I$44:I$81,$A$44:$A$81,$D122)-SUMIFS(H$44:H$81,$A$44:$A$81,$D122))/SUMIFS(H$44:H$81,$A$44:$A$81,$D122),0) -> 0.041009087 | J122: =IFERROR((SUMIFS(J$44:J$81,$A$44:$A$81,$D122)-SUMIFS(I$44:I$81,$A$44:$A$81,$D122))/SUMIFS(I$44:I$81,$A$44:$A$81,$D122),0) -> 0.039393591 | K122: =IFERROR((SUMIFS(K$44:K$81,$A$44:$A$81,$D122)-SUMIFS(J$44:J$81,$A$44:$A$81,$D122))/SUMIFS(J$44:J$81,$A$44:$A$81,$D122),0) -> 0.037900552 | L122: =IFERROR((SUMIFS(L$44:L$81,$A$44:$A$81,$D122)-SUMIFS(K$44:K$81,$A$44:$A$81,$D122))/SUMIFS(K$44:K$81,$A$44:$A$81,$D122),0) -> 0.036516555 | M122: =IFERROR((SUMIFS(M$44:M$81,$A$44:$A$81,$D122)-SUMIFS(L$44:L$81,$A$44:$A$81,$D122))/SUMIFS(L$44:L$81,$A$44:$A$81,$D122),0) -> 0.035230074 | N122: =IFERROR((SUMIFS(N$44:N$81,$A$44:$A$81,$D122)-SUMIFS(M$44:M$81,$A$44:$A$81,$D122))/SUMIFS(M$44:M$81,$A$44:$A$81,$D122),0) -> 0.034031154 | ... AJ122: =IFERROR((SUMIFS(AJ$44:AJ$81,$A$44:$A$81,$D122)-SUMIFS(AI$44:AI$81,$A$44:$A$81,$D122))/SUMIFS(AI$44:AI$81,$A$44:$A$81,$D122),0) -> 0.019460993
... D126: ISIC 97T98 | F126: 0 | G126: =IFERROR((SUMIFS(G$44:G$81,$A$44:$A$81,$D126)-SUMIFS(F$44:F$81,$A$44:$A$81,$D126))/SUMIFS(F$44:F$81,$A$44:$A$81,$D126),0) -> 0.042887388 | H126: =IFERROR((SUMIFS(H$44:H$81,$A$44:$A$81,$D126)-SUMIFS(G$44:G$81,$A$44:$A$81,$D126))/SUMIFS(G$44:G$81,$A$44:$A$81,$D126),0) -> 0.0411237 | I126: =IFERROR((SUMIFS(I$44:I$81,$A$44:$A$81,$D126)-SUMIFS(H$44:H$81,$A$44:$A$81,$D126))/SUMIFS(H$44:H$81,$A$44:$A$81,$D126),0) -> 0.039499341 | J126: =IFERROR((SUMIFS(J$44:J$81,$A$44:$A$81,$D126)-SUMIFS(I$44:I$81,$A$44:$A$81,$D126))/SUMIFS(I$44:I$81,$A$44:$A$81,$D126),0) -> 0.037998428 | K126: =IFERROR((SUMIFS(K$44:K$81,$A$44:$A$81,$D126)-SUMIFS(J$44:J$81,$A$44:$A$81,$D126))/SUMIFS(J$44:J$81,$A$44:$A$81,$D126),0) -> 0.036607404 | L126: =IFERROR((SUMIFS(L$44:L$81,$A$44:$A$81,$D126)-SUMIFS(K$44:K$81,$A$44:$A$81,$D126))/SUMIFS(K$44:K$81,$A$44:$A$81,$D126),0) -> 0.035314628 | M126: =IFERROR((SUMIFS(M$44:M$81,$A$44:$A$81,$D126)-SUMIFS(L$44:L$81,$A$44:$A$81,$D126))/SUMIFS(L$44:L$81,$A$44:$A$81,$D126),0) -> 0.034110044 | N126: =IFERROR((SUMIFS(N$44:N$81,$A$44:$A$81,$D126)-SUMIFS(M$44:M$81,$A$44:$A$81,$D126))/SUMIFS(M$44:M$81,$A$44:$A$81,$D126),0) -> 0.032984927 | ... AJ126: =IFERROR((SUMIFS(AJ$44:AJ$81,$A$44:$A$81,$D126)-SUMIFS(AI$44:AI$81,$A$44:$A$81,$D126))/SUMIFS(AI$44:AI$81,$A$44:$A$81,$D126),0) -> 0.01911429

Sheet GDP growth by Industry
A1: Unit: dimensionless (% change) | B1: 2019 | C1: 2020 | D1: 2021 | E1: 2022 | F1: 2023 | G1: 2024 | H1: 2025 | I1: 2026 | J1: 2027 | K1: 2028 | L1: 2029 | M1: 2030 | N1: 2031 | O1: 2032 | P1: 2033 | Q1: 2034 | R1: 2035 | S1: 2036 | T1: 2037 | U1: 2038 | V1: 2039 | W1: 2040 | X1: 2041 | Y1: 2042 | Z1: 2043 | AA1: 2044 | AB1: 2045 | AC1: 2046 | AD1: 2047 | AE1: 2048 | AF1: 2049 | AG1: 2050 | AH1: 2051 | AI1: 2052 | AJ1: 2053 | AK1: 2054 | AL1: 2055 | AM1: 2056 | AN1: 2057 | AO1: 2058 | AP1: 2059 | AQ1: 2060 | AR1: 2061 | AS1: 2062 | AT1: 2063 | AU1: 2064 | AV1: 2065 | AW1: 2066 | AX1: 2067 | AY1: 2068 | AZ1: 2069 | BA1: 2070
A2: ISIC 01T03 | B2: =B47 -> 0.0285 | C2: =C47 -> 0.0437 | D2: =D47 -> 0.0321 | E2: =E47 -> 0.0463 | F2: =F47 -> 0.0418 | G2: =G47 -> 0.0825 | H2: =H47 -> 0.073666667 | I2: =I47 -> 0.08162381 | ... BA2: =BA47 -> 0.4317381
A3: ISIC 05 | B3: =B48 -> 0.0251 | C3: =C48 -> 0.1247 | D3: =D48 -> 0.2718 | E3: =E48 -> 0.3371 | F3: =F48 -> 0.0329 | G3: =G48 -> 0.0177 | H3: =H48 -> 0.0177 | I3: =I48 -> 0.22316571 | ... BA3: =BA48 -> 0.84469714
A4: ISIC 06 | B4: =B48 -> 0.0251 | C4: =C48 -> 0.1247 | D4: =D48 -> 0.2718 | E4: =E48 -> 0.3371 | F4: =F48 -> 0.0329 | G4: =G48 -> 0.0177 | H4: =H48 -> 0.0177 | I4: =I48 -> 0.22316571 | ... BA4: =BA48 -> 0.84469714
A5: ISIC 07T08 | B5: =B4 -> 0.0251 | C5: =C4 -> 0.1247 | D5: =D4 -> 0.2718 | E5: =E4 -> 0.3371 | F5: =F4 -> 0.0329 | G5: =G4 -> 0.0177 | H5: =H4 -> 0.0177 | I5: =I4 -> 0.22316571 | ... BA5: =BA4 -> 0.84469714
A6: ISIC 09 | B6: =B5 -> 0.0251 | C6: =C5 -> 0.1247 | D6: =D5 -> 0.2718 | E6: =E5 -> 0.3371 | F6: =F5 -> 0.0329 | G6: =G5 -> 0.0177 | H6: =H5 -> 0.0177 | I6: =I5 -> 0.22316571 | ... BA6: =BA5 -> 0.84469714
A7: ISIC 10T12 | B7: =B49 -> 0.0357 | C7: =C49 -> 0.0124 | D7: =D49 -> 0.0129 | E7: =E49 -> 0.0129 | F7: =F49 -> 0.0211 | G7: =G49 -> 0.0076 | H7: =H49 -> 0.00566 | I7: =I49 -> 0.0023914286 | ... BA7: =BA49 -> 0.0023914286
A8: ISIC 13T15 | B8: =B7 -> 0.0357 | C8: =C7 -> 0.0124 | D8: =D7 -> 0.0129 | E8: =E7 -> 0.0129 | F8: =F7 -> 0.0211 | G8: =G7 -> 0.0076 | H8: =H7 -> 0.00566 | I8: =I7 -> 0.0023914286 | ... BA8: =BA7 -> 0.0023914286
A9: ISIC 16 | B9: =B49 -> 0.0357 | C9: =C49 -> 0.0124 | D9: =D49 -> 0.0129 | E9: =E49 -> 0.0129 | F9: =F49 -> 0.0211 | G9: =G49 -> 0.0076 | H9: =H49 -> 0.00566 | I9: =I49 -> 0.0023914286 | ... BA9: =BA49 -> 0.0023914286
A10: ISIC 17T18 | B10: =B9 -> 0.0357 | C10: =C9 -> 0.0124 | D10: =D9 -> 0.0129 | E10: =E9 -> 0.0129 | F10: =F9 -> 0.0211 | G10: =G9 -> 0.0076 | H10: =H9 -> 0.00566 | I10: =I9 -> 0.0023914286 | ... BA10: =BA9 -> 0.0023914286
A11: ISIC 19 | B11: =B9 -> 0.0357 | C11: =C9 -> 0.0124 | D11: =D9 -> 0.0129 | E11: =E9 -> 0.0129 | F11: =F9 -> 0.0211 | G11: =G9 -> 0.0076 | H11: =H9 -> 0.00566 | I11: =I9 -> 0.0023914286 | ... BA11: =BA9 -> 0.0023914286
A12: ISIC 20 | B12: =B9 -> 0.0357 | C12: =C9 -> 0.0124 | D12: =D9 -> 0.0129 | E12: =E9 -> 0.0129 | F12: =F9 -> 0.0211 | G12: =G9 -> 0.0076 | H12: =H9 -> 0.00566 | I12: =I9 -> 0.0023914286 | ... BA12: =BA9 -> 0.0023914286
A13: ISIC 21 | B13: =B9 -> 0.0357 | C13: =C9 -> 0.0124 | D13: =D9 -> 0.0129 | E13: =E9 -> 0.0129 | F13: =F9 -> 0.0211 | G13: =G9 -> 0.0076 | H13: =H9 -> 0.00566 | I13: =I9 -> 0.0023914286 | ... BA13: =BA9 -> 0.0023914286
A14: ISIC 22 | B14: =B9 -> 0.0357 | C14: =C9 -> 0.0124 | D14: =D9 -> 0.0129 | E14: =E9 -> 0.0129 | F14: =F9 -> 0.0211 | G14: =G9 -> 0.0076 | H14: =H9 -> 0.00566 | I14: =I9 -> 0.0023914286 | ... BA14: =BA9 -> 0.0023914286
A15: ISIC 231 | B15: =B9 -> 0.0357 | C15: =C9 -> 0.0124 | D15: =D9 -> 0.0129 | E15: =E9 -> 0.0129 | F15: =F9 -> 0.0211 | G15: =G9 -> 0.0076 | H15: =H9 -> 0.00566 | I15: =I9 -> 0.0023914286 | ... BA15: =BA9 -> 0.0023914286
A16: ISIC 239 | B16: =B9 -> 0.0357 | C16: =C9 -> 0.0124 | D16: =D9 -> 0.0129 | E16: =E9 -> 0.0129 | F16: =F9 -> 0.0211 | G16: =G9 -> 0.0076 | H16: =H9 -> 0.00566 | I16: =I9 -> 0.0023914286 | ... BA16: =BA9 -> 0.0023914286
A17: ISIC 241 | B17: =B9 -> 0.0357 | C17: =C9 -> 0.0124 | D17: =D9 -> 0.0129 | E17: =E9 -> 0.0129 | F17: =F9 -> 0.0211 | G17: =G9 -> 0.0076 | H17: =H9 -> 0.00566 | I17: =I9 -> 0.0023914286 | ... BA17: =BA9 -> 0.0023914286
A18: ISIC 242 | B18: =B9 -> 0.0357 | C18: =C9 -> 0.0124 | D18: =D9 -> 0.0129 | E18: =E9 -> 0.0129 | F18: =F9 -> 0.0211 | G18: =G9 -> 0.0076 | H18: =H9 -> 0.00566 | I18: =I9 -> 0.0023914286 | ... BA18: =BA9 -> 0.0023914286
A19: ISIC 25 | B19: =B9 -> 0.0357 | C19: =C9 -> 0.0124 | D19: =D9 -> 0.0129 | E19: =E9 -> 0.0129 | F19: =F9 -> 0.0211 | G19: =G9 -> 0.0076 | H19: =H9 -> 0.00566 | I19: =I9 -> 0.0023914286 | ... BA19: =BA9 -> 0.0023914286
A20: ISIC 26 | B20: =B9 -> 0.0357 | C20: =C9 -> 0.0124 | D20: =D9 -> 0.0129 | E20: =E9 -> 0.0129 | F20: =F9 -> 0.0211 | G20: =G9 -> 0.0076 | H20: =H9 -> 0.00566 | I20: =I9 -> 0.0023914286 | ... BA20: =BA9 -> 0.0023914286
A21: ISIC 27 | B21: =B9 -> 0.0357 | C21: =C9 -> 0.0124 | D21: =D9 -> 0.0129 | E21: =E9 -> 0.0129 | F21: =F9 -> 0.0211 | G21: =G9 -> 0.0076 | H21: =H9 -> 0.00566 | I21: =I9 -> 0.0023914286 | ... BA21: =BA9 -> 0.0023914286
A22: ISIC 28 | B22: =B9 -> 0.0357 | C22: =C9 -> 0.0124 | D22: =D9 -> 0.0129 | E22: =E9 -> 0.0129 | F22: =F9 -> 0.0211 | G22: =G9 -> 0.0076 | H22: =H9 -> 0.00566 | I22: =I9 -> 0.0023914286 | ... BA22: =BA9 -> 0.0023914286
A23: ISIC 29 | B23: =B9 -> 0.0357 | C23: =C9 -> 0.0124 | D23: =D9 -> 0.0129 | E23: =E9 -> 0.0129 | F23: =F9 -> 0.0211 | G23: =G9 -> 0.0076 | H23: =H9 -> 0.00566 | I23: =I9 -> 0.0023914286 | ... BA23: =BA9 -> 0.0023914286
A24: ISIC 30 | B24: =B9 -> 0.0357 | C24: =C9 -> 0.0124 | D24: =D9 -> 0.0129 | E24: =E9 -> 0.0129 | F24: =F9 -> 0.0211 | G24: =G9 -> 0.0076 | H24: =H9 -> 0.00566 | I24: =I9 -> 0.0023914286 | ... BA24: =BA9 -> 0.0023914286
A25: ISIC 31T33 | B25: =B9 -> 0.0357 | C25: =C9 -> 0.0124 | D25: =D9 -> 0.0129 | E25: =E9 -> 0.0129 | F25: =F9 -> 0.0211 | G25: =G9 -> 0.0076 | H25: =H9 -> 0.00566 | I25: =I9 -> 0.0023914286 | ... BA25: =BA9 -> 0.0023914286
A26: ISIC 351 | B26: =B50 -> 0.0058 | C26: =C50 -> 0.0006 | D26: =D50 -> 0.0096 | E26: =E50 -> 0.0154 | F26: =F50 -> 0.0076 | G26: =G50 -> 0.003 | H26: =H50 -> 0.00828 | I26: =I50 -> 0.0086457143 | ... BA26: =BA50 -> 0.024737143
A27: ISIC 352T353 | B27: =B50 -> 0.0058 | C27: =C50 -> 0.0006 | D27: =D50 -> 0.0096 | E27: =E50 -> 0.0154 | F27: =F50 -> 0.0076 | G27: =G50 -> 0.003 | H27: =H50 -> 0.00828 | I27: =I50 -> 0.0086457143 | ... BA27: =BA50 -> 0.024737143
A28: ISIC 41T43 | B28: =B52 -> 0.03 | C28: =C52 -> 0.0038 | D28: =D52 -> 0.0427 | E28: =E52 -> 0.0584 | F28: =F52 -> 0.0326 | G28: =G52 -> 0.0071 | H28: =H52 -> 0.02786 | I28: =I52 -> 0.027505714 | ... BA28: =BA52 -> 0.011917143
A29: ISIC 49T53 | B29: =B54 -> 0.0576 | C29: =C54 -> 0.0434 | D29: =D54 -> 0.0238 | E29: =E54 -> 0.0484 | F29: =F54 -> 0.0409 | G29: =G54 -> 0.0106 | H29: =H54 -> 0.01566 | I29: =I54 -> 0.0094342857 | ... BA29: =BA54 -> 0.0032085714
A30: ISIC 55T56 | B30: =B55 -> 0.0091 | C30: =C55 -> 0.006 | D30: =D55 -> 0.0073 | E30: =E55 -> 0.018 | F30: =F55 -> 0.012 | G30: =G55 -> 0.0227 | H30: =H55 -> 0.022186667 | I30: =I55 -> 0.024949524 | ... BA30: =BA55 -> 0.14651524
A31: ISIC 58T60 | B31: =B56 -> 0.0244 | C31: =C56 -> 0.0043 | D31: =D56 -> 0.0073 | E31: =E56 -> 0.0075 | F31: =F56 -> 0.0105 | G31: =G56 -> 0.01 | H31: =H56 -> 0.0053466667 | I31: =I56 -> 0.0038266667 | ... BA31: =BA56 -> 0.00078666667
A32: ISIC 61 | B32: =B56 -> 0.0244 | C32: =C56 -> 0.0043 | D32: =D56 -> 0.0073 | E32: =E56 -> 0.0075 | F32: =F56 -> 0.0105 | G32: =G56 -> 0.01 | H32: =H56 -> 0.0053466667 | I32: =I56 -> 0.0038266667 | ... BA32: =BA56 -> 0.00078666667
A33: ISIC 62T63 | B33: =B56 -> 0.0244 | C33: =C56 -> 0.0043 | D33: =D56 -> 0.0073 | E33: =E56 -> 0.0075 | F33: =F56 -> 0.0105 | G33: =G56 -> 0.01 | H33: =H56 -> 0.0053466667 | I33: =I56 -> 0.0038266667 | ... BA33: =BA56 -> 0.00078666667
A34: ISIC 64T66 | B34: =B57 -> 0.0257 | C34: =C57 -> 0.0041 | D34: =D57 -> 0.0414 | E34: =E57 -> 0.0422 | F34: =F57 -> 0.0368 | G34: =G57 -> 0.0217 | H34: =H57 -> 0.03654 | I34: =I57 -> 0.038794286 | ... BA34: =BA57 -> 0.13798286
A35: ISIC 68 | B35: =B58 -> 0.0234 | C35: =C58 -> 0.0092 | D35: =D58 -> 0.0039 | E35: =E58 -> 0.0253 | F35: =F58 -> 0.0205 | G35: =G58 -> 0.0051 | H35: =H58 -> 0.010946667 | I35: =I58 -> 0.009912381 | ... BA35: =BA58 -> 0.00060380952
A36: ISIC 69T82 | B36: =B59 -> 0.0333 | C36: =C59 -> 0.0227 | D36: =D59 -> 0.0158 | E36: =E59 -> 0.0425 | F36: =F59 -> 0.0366 | G36: =G59 -> 0.0216 | H36: =H59 -> 0.02974 | I36: =I59 -> 0.030022857 | ... BA36: =BA59 -> 0.042468571
A37: ISIC 84 | B37: =B60 -> 0.0083 | C37: =C60 -> 0.0254 | D37: =D60 -> 0.0047 | E37: =E60 -> 0.0063 | F37: =F60 -> 0.0032 | G37: =G60 -> 0.0272 | H37: =H60 -> 0.015466667 | I37: =I60 -> 0.016309524 | ... BA37: =BA60 -> 0.053395238
A38: ISIC 85 | B38: =B61 -> 0.0201 | C38: =C61 -> 0.0284 | D38: =D61 -> 0.0106 | E38: =E61 -> 0.0101 | F38: =F61 -> 0.0121 | G38: =G61 -> 0.0267 | H38: =H61 -> 0.01636 | I38: =I61 -> 0.015891429 | ... BA38: =BA61 -> 0.00042857143
A39: ISIC 86T88 | B39: =B62 -> 0.017 | C39: =C62 -> 0.0338 | D39: =D62 -> 0.0211 | E39: =E62 -> 0.0117 | F39: =F62 -> 0.0193 | G39: =G62 -> 0.0212 | H39: =H62 -> 0.017493333 | I39: =I62 -> 0.016581905 | ... BA39: =BA62 -> 0.00017619048
A40: ISIC 90T96 | B40: =B63 -> 0.0405 | C40: =C63 -> 0.0211 | D40: =D63 -> 0.0103 | E40: =E63 -> 0.0364 | F40: =F63 -> 0.0352 | G40: =G63 -> 0.0212 | H40: =H63 -> 0.02464 | I40: =I63 -> 0.023837143 | ... BA40: =BA63 -> 0.00055428571
A41: ISIC 97T98 | B41: =B63 -> 0.0405 | C41: =C63 -> 0.0211 | D41: =D63 -> 0.0103 | E41: =E63 -> 0.0364 | F41: =F63 -> 0.0352 | G41: =G63 -> 0.0212 | H41: =H63 -> 0.02464 | I41: =I63 -> 0.023837143 | ... BA41: =BA63 -> 0.00055428571
A44: Historical data
A46: GDP Growth by industry (Percent) | B46: 2019 | C46: 2020 | D46: 2021 | E46: 2022 | F46: 2023 | G46: 2024 | H46: 2025 | I46: 2026 | J46: 2027 | K46: 2028 | L46: 2029 | M46: 2030 | N46: 2031 | O46: 2032 | P46: 2033 | Q46: 2034 | R46: 2035 | S46: 2036 | T46: 2037 | U46: 2038 | V46: 2039 | W46: 2040 | X46: 2041 | Y46: 2042 | Z46: 2043 | AA46: 2044 | AB46: 2045 | AC46: 2046 | AD46: 2047 | AE46: 2048 | AF46: 2049 | AG46: 2050 | AH46: 2051 | AI46: 2052 | AJ46: 2053 | AK46: 2054 | AL46: 2055 | AM46: 2056 | AN46: 2057 | AO46: 2058 | AP46: 2059 | AQ46: 2060 | AR46: 2061 | AS46: 2062 | AT46: 2063 | AU46: 2064 | AV46: 2065 | AW46: 2066 | AX46: 2067 | AY46: 2068 | AZ46: 2069 | BA46: 2070
A47: Agriculture, Forestry and Fishing | B47: 0.0285 | C47: 0.0437 | D47: 0.0321 | E47: 0.0463 | F47: 0.0418 | G47: 0.0825 | H47: 0.073666667 | I47: 0.08162381 | J47: 0.089580952 | K47: 0.097538095 | L47: 0.10549524 | M47: 0.11345238 | N47: 0.12140952 | O47: 0.12936667 | P47: 0.13732381 | Q47: 0.14528095 | R47: 0.1532381 | S47: 0.16119524 | T47: 0.16915238 | U47: 0.17710952 | V47: 0.18506667 | W47: 0.19302381 | X47: 0.20098095 | Y47: 0.2089381 | Z47: 0.21689524 | AA47: 0.22485238 | AB47: 0.23280952 | AC47: 0.24076667 | AD47: 0.24872381 | AE47: 0.25668095 | AF47: 0.2646381 | AG47: 0.27259524 | AH47: 0.28055238 | AI47: 0.28850952 | AJ47: 0.29646667 | AK47: 0.30442381 | AL47: 0.31238095 | AM47: 0.3203381 | AN47: 0.32829524 | AO47: 0.33625238 | AP47: 0.34420952 | AQ47: 0.35216667 | AR47: 0.36012381 | AS47: 0.36808095 | AT47: 0.3760381 | AU47: 0.38399524 | AV47: 0.39195238 | AW47: 0.39990952 | AX47: 0.40786667 | AY47: 0.41582381 | AZ47: 0.42378095 | BA47: 0.4317381
A48: Mining and Quarrying | B48: 0.0251 | C48: 0.1247 | D48: 0.2718 | E48: 0.3371 | F48: 0.0329 | G48: 0.0177 | H48: =G48 -> 0.0177 | I48: 0.22316571 | J48: 0.23729143 | K48: 0.25141714 | L48: 0.26554286 | M48: 0.27966857 | N48: 0.29379429 | O48: 0.30792 | P48: 0.32204571 | Q48: 0.33617143 | R48: 0.35029714 | S48: 0.36442286 | T48: 0.37854857 | U48: 0.39267429 | V48: 0.4068 | W48: 0.42092571 | X48: 0.43505143 | Y48: 0.44917714 | Z48: 0.46330286 | AA48: 0.47742857 | AB48: 0.49155429 | AC48: 0.50568 | AD48: 0.51980571 | AE48: 0.53393143 | AF48: 0.54805714 | AG48: 0.56218286 | AH48: 0.57630857 | AI48: 0.59043429 | AJ48: 0.60456 | AK48: 0.61868571 | AL48: 0.63281143 | AM48: 0.64693714 | AN48: 0.66106286 | AO48: 0.67518857 | AP48: 0.68931429 | AQ48: 0.70344 | AR48: 0.71756571 | AS48: 0.73169143 | AT48: 0.74581714 | AU48: 0.75994286 | AV48: 0.77406857 | AW48: 0.78819429 | AX48: 0.80232 | AY48: 0.81644571 | AZ48: 0.83057143 | BA48: 0.84469714
A49: Manufacturing | B49: 0.0357 | C49: 0.0124 | D49: 0.0129 | E49: 0.0129 | F49: 0.0211 | G49: 0.0076 | H49: 0.00566 | I49: 0.0023914286 | J49: 0.0023914286 | K49: 0.0023914286 | L49: 0.0023914286 | M49: 0.0023914286 | N49: 0.0023914286 | O49: 0.0023914286 | P49: 0.0023914286 | Q49: 0.0023914286 | R49: 0.0023914286 | S49: 0.0023914286 | T49: 0.0023914286 | U49: 0.0023914286 | V49: 0.0023914286 | W49: 0.0023914286 | X49: 0.0023914286 | Y49: 0.0023914286 | Z49: 0.0023914286 | AA49: 0.0023914286 | AB49: 0.0023914286 | AC49: 0.0023914286 | AD49: 0.0023914286 | AE49: 0.0023914286 | AF49: 0.0023914286 | AG49: 0.0023914286 | AH49: 0.0023914286 | AI49: 0.0023914286 | AJ49: 0.0023914286 | AK49: 0.0023914286 | AL49: 0.0023914286 | AM49: 0.0023914286 | AN49: 0.0023914286 | AO49: 0.0023914286 | AP49: 0.0023914286 | AQ49: 0.0023914286 | AR49: 0.0023914286 | AS49: 0.0023914286 | AT49: 0.0023914286 | AU49: 0.0023914286 | AV49: 0.0023914286 | AW49: 0.0023914286 | AX49: 0.0023914286 | AY49: 0.0023914286 | AZ49: 0.0023914286 | BA49: 0.0023914286
A50: Electricity and Gas | B50: 0.0058 | C50: 0.0006 | D50: 0.0096 | E50: 0.0154 | F50: 0.0076 | G50: 0.003 | H50: 0.00828 | I50: 0.0086457143 | J50: 0.0090114286 | K50: 0.0093771429 | L50: 0.0097428571 | M50: 0.010108571 | N50: 0.010474286 | O50: 0.01084 | P50: 0.011205714 | Q50: 0.011571429 | R50: 0.011937143 | S50: 0.012302857 | T50: 0.012668571 | U50: 0.013034286 | V50: 0.0134 | W50: 0.013765714 | X50: 0.014131429 | Y50: 0.014497143 | Z50: 0.014862857 | AA50: 0.015228571 | AB50: 0.015594286 | AC50: 0.01596 | AD50: 0.016325714 | AE50: 0.016691429 | AF50: 0.017057143 | AG50: 0.017422857 | AH50: 0.017788571 | AI50: 0.018154286 | AJ50: 0.01852 | AK50: 0.018885714 | AL50: 0.019251429 | AM50: 0.019617143 | AN50: 0.019982857 | AO50: 0.020348571 | AP50: 0.020714286 | AQ50: 0.02108 | AR50: 0.021445714 | AS50: 0.021811429 | AT50: 0.022177143 | AU50: 0.022542857 | AV50: 0.022908571 | AW50: 0.023274286 | AX50: 0.02364 | AY50: 0.024005714 | AZ50: 0.024371429 | BA50: 0.024737143
A51: Water supply, Sewerage, Waste Management and Remediation Activities | B51: 0.0026 | C51: 0.0035 | D51: 0.0134 | E51: 0.0098 | F51: 0.0102 | G51: 0.0568 | H51: 0.0448 | I51: 0.053014286 | J51: 0.061228571 | K51: 0.069442857 | L51: 0.077657143 | M51: 0.085871429 | N51: 0.094085714 | O51: 0.1023 | P51: 0.11051429 | Q51: 0.11872857 | R51: 0.12694286 | S51: 0.13515714 | T51: 0.14337143 | U51: 0.15158571 | V51: 0.1598 | W51: 0.16801429 | X51: 0.17622857 | Y51: 0.18444286 | Z51: 0.19265714 | AA51: 0.20087143 | AB51: 0.20908571 | AC51: 0.2173 | AD51: 0.22551429 | AE51: 0.23372857 | AF51: 0.24194286 | AG51: 0.25015714 | AH51: 0.25837143 | AI51: 0.26658571 | AJ51: 0.2748 | AK51: 0.28301429 | AL51: 0.29122857 | AM51: 0.29944286 | AN51: 0.30765714 | AO51: 0.31587143 | AP51: 0.32408571 | AQ51: 0.3323 | AR51: 0.34051429 | AS51: 0.34872857 | AT51: 0.35694286 | AU51: 0.36515714 | AV51: 0.37337143 | AW51: 0.38158571 | AX51: 0.3898 | AY51: 0.39801429 | AZ51: 0.40622857 | BA51: 0.41444286
A52: Construction | B52: 0.03 | C52: 0.0038 | D52: 0.0427 | E52: 0.0584 | F52: 0.0326 | G52: 0.0071 | H52: 0.02786 | I52: 0.027505714 | J52: 0.027151429 | K52: 0.026797143 | L52: 0.026442857 | M52: 0.026088571 | N52: 0.025734286 | O52: 0.02538 | P52: 0.025025714 | Q52: 0.024671429 | R52: 0.024317143 | S52: 0.023962857 | T52: 0.023608571 | U52: 0.023254286 | V52: 0.0229 | W52: 0.022545714 | X52: 0.022191429 | Y52: 0.021837143 | Z52: 0.021482857 | AA52: 0.021128571 | AB52: 0.020774286 | AC52: 0.02042 | AD52: 0.020065714 | AE52: 0.019711429 | AF52: 0.019357143 | AG52: 0.019002857 | AH52: 0.018648571 | AI52: 0.018294286 | AJ52: 0.01794 | AK52: 0.017585714 | AL52: 0.017231429 | AM52: 0.016877143 | AN52: 0.016522857 | AO52: 0.016168571 | AP52: 0.015814286 | AQ52: 0.01546 | AR52: 0.015105714 | AS52: 0.014751429 | AT52: 0.014397143 | AU52: 0.014042857 | AV52: 0.013688571 | AW52: 0.013334286 | AX52: 0.01298 | AY52: 0.012625714 | AZ52: 0.012271429 | BA52: 0.011917143
A53: Wholesale and Retail Trade; Repair of Motor Vehicles and Motorcycles | B53: 0.0196 | C53: 0.0059 | D53: 0.0636 | E53: 0.0995 | F53: 0.0255 | G53: 0.0205 | H53: 0.04902 | I53: 0.051854286 | J53: 0.054688571 | K53: 0.057522857 | L53: 0.060357143 | M53: 0.063191429 | N53: 0.066025714 | O53: 0.06886 | P53: 0.071694286 | Q53: 0.074528571 | R53: 0.077362857 | S53: 0.080197143 | T53: 0.083031429 | U53: 0.085865714 | V53: 0.0887 | W53: 0.091534286 | X53: 0.094368571 | Y53: 0.097202857 | Z53: 0.10003714 | AA53: 0.10287143 | AB53: 0.10570571 | AC53: 0.10854 | AD53: 0.11137429 | AE53: 0.11420857 | AF53: 0.11704286 | AG53: 0.11987714 | AH53: 0.12271143 | AI53: 0.12554571 | AJ53: 0.12838 | AK53: 0.13121429 | AL53: 0.13404857 | AM53: 0.13688286 | AN53: 0.13971714 | AO53: 0.14255143 | AP53: 0.14538571 | AQ53: 0.14822 | AR53: 0.15105429 | AS53: 0.15388857 | AT53: 0.15672286 | AU53: 0.15955714 | AV53: 0.16239143 | AW53: 0.16522571 | AX53: 0.16806 | AY53: 0.17089429 | AZ53: 0.17372857 | BA53: 0.17656286
A54: Transportation and Storage | B54: 0.0576 | C54: 0.0434 | D54: 0.0238 | E54: 0.0484 | F54: 0.0409 | G54: 0.0106 | H54: 0.01566 | I54: 0.0094342857 | J54: 0.0032085714 | K54: 0.0032085714 | L54: 0.0032085714 | M54: 0.0032085714 | N54: 0.0032085714 | O54: 0.0032085714 | P54: 0.0032085714 | Q54: 0.0032085714 | R54: 0.0032085714 | S54: 0.0032085714 | T54: 0.0032085714 | U54: 0.0032085714 | V54: 0.0032085714 | W54: 0.0032085714 | X54: 0.0032085714 | Y54: 0.0032085714 | Z54: 0.0032085714 | AA54: 0.0032085714 | AB54: 0.0032085714 | AC54: 0.0032085714 | AD54: 0.0032085714 | AE54: 0.0032085714 | AF54: 0.0032085714 | AG54: 0.0032085714 | AH54: 0.0032085714 | AI54: 0.0032085714 | AJ54: 0.0032085714 | AK54: 0.0032085714 | AL54: 0.0032085714 | AM54: 0.0032085714 | AN54: 0.0032085714 | AO54: 0.0032085714 | AP54: 0.0032085714 | AQ54: 0.0032085714 | AR54: 0.0032085714 | AS54: 0.0032085714 | AT54: 0.0032085714 | AU54: 0.0032085714 | AV54: 0.0032085714 | AW54: 0.0032085714 | AX54: 0.0032085714 | AY54: 0.0032085714 | AZ54: 0.0032085714 | BA54: 0.0032085714
A55: Accommodation and Food Service Activities | B55: 0.0091 | C55: 0.006 | D55: 0.0073 | E55: 0.018 | F55: 0.012 | G55: 0.0227 | H55: 0.022186667 | I55: 0.024949524 | J55: 0.027712381 | K55: 0.030475238 | L55: 0.033238095 | M55: 0.036000952 | N55: 0.03876381 | O55: 0.041526667 | P55: 0.044289524 | Q55: 0.047052381 | R55: 0.049815238 | S55: 0.052578095 | T55: 0.055340952 | U55: 0.05810381 | V55: 0.060866667 | W55: 0.063629524 | X55: 0.066392381 | Y55: 0.069155238 | Z55: 0.071918095 | AA55: 0.074680952 | AB55: 0.07744381 | AC55: 0.080206667 | AD55: 0.082969524 | AE55: 0.085732381 | AF55: 0.088495238 | AG55: 0.091258095 | AH55: 0.094020952 | AI55: 0.09678381 | AJ55: 0.099546667 | AK55: 0.10230952 | AL55: 0.10507238 | AM55: 0.10783524 | AN55: 0.1105981 | AO55: 0.11336095 | AP55: 0.11612381 | AQ55: 0.11888667 | AR55: 0.12164952 | AS55: 0.12441238 | AT55: 0.12717524 | AU55: 0.1299381 | AV55: 0.13270095 | AW55: 0.13546381 | AX55: 0.13822667 | AY55: 0.14098952 | AZ55: 0.14375238 | BA55: 0.14651524
A56: Information and Communication | B56: 0.0244 | C56: 0.0043 | D56: 0.0073 | E56: 0.0075 | F56: 0.0105 | G56: 0.01 | H56: 0.0053466667 | I56: 0.0038266667 | J56: 0.0023066667 | K56: 0.00078666667 | L56: 0.00078666667 | M56: 0.00078666667 | N56: 0.00078666667 | O56: 0.00078666667 | P56: 0.00078666667 | Q56: 0.00078666667 | R56: 0.00078666667 | S56: 0.00078666667 | T56: 0.00078666667 | U56: 0.00078666667 | V56: 0.00078666667 | W56: 0.00078666667 | X56: 0.00078666667 | Y56: 0.00078666667 | Z56: 0.00078666667 | AA56: 0.00078666667 | AB56: 0.00078666667 | AC56: 0.00078666667 | AD56: 0.00078666667 | AE56: 0.00078666667 | AF56: 0.00078666667 | AG56: 0.00078666667 | AH56: 0.00078666667 | AI56: 0.00078666667 | AJ56: 0.00078666667 | AK56: 0.00078666667 | AL56: 0.00078666667 | AM56: 0.00078666667 | AN56: 0.00078666667 | AO56: 0.00078666667 | AP56: 0.00078666667 | AQ56: 0.00078666667 | AR56: 0.00078666667 | AS56: 0.00078666667 | AT56: 0.00078666667 | AU56: 0.00078666667 | AV56: 0.00078666667 | AW56: 0.00078666667 | AX56: 0.00078666667 | AY56: 0.00078666667 | AZ56: 0.00078666667 | BA56: 0.00078666667
A57: Financial and Insurance Activities | B57: 0.0257 | C57: 0.0041 | D57: 0.0414 | E57: 0.0422 | F57: 0.0368 | G57: 0.0217 | H57: 0.03654 | I57: 0.038794286 | J57: 0.041048571 | K57: 0.043302857 | L57: 0.045557143 | M57: 0.047811429 | N57: 0.050065714 | O57: 0.05232 | P57: 0.054574286 | Q57: 0.056828571 | R57: 0.059082857 | S57: 0.061337143 | T57: 0.063591429 | U57: 0.065845714 | V57: 0.0681 | W57: 0.070354286 | X57: 0.072608571 | Y57: 0.074862857 | Z57: 0.077117143 | AA57: 0.079371429 | AB57: 0.081625714 | AC57: 0.08388 | AD57: 0.086134286 | AE57: 0.088388571 | AF57: 0.090642857 | AG57: 0.092897143 | AH57: 0.095151429 | AI57: 0.097405714 | AJ57: 0.09966 | AK57: 0.10191429 | AL57: 0.10416857 | AM57: 0.10642286 | AN57: 0.10867714 | AO57: 0.11093143 | AP57: 0.11318571 | AQ57: 0.11544 | AR57: 0.11769429 | AS57: 0.11994857 | AT57: 0.12220286 | AU57: 0.12445714 | AV57: 0.12671143 | AW57: 0.12896571 | AX57: 0.13122 | AY57: 0.13347429 | AZ57: 0.13572857 | BA57: 0.13798286
A58: Real Estate Activities | B58: 0.0234 | C58: 0.0092 | D58: 0.0039 | E58: 0.0253 | F58: 0.0205 | G58: 0.0051 | H58: 0.010946667 | I58: 0.009912381 | J58: 0.0088780952 | K58: 0.0078438095 | L58: 0.0068095238 | M58: 0.0057752381 | N58: 0.0047409524 | O58: 0.0037066667 | P58: 0.002672381 | Q58: 0.0016380952 | R58: 0.00060380952 | S58: 0.00060380952 | T58: 0.00060380952 | U58: 0.00060380952 | V58: 0.00060380952 | W58: 0.00060380952 | X58: 0.00060380952 | Y58: 0.00060380952 | Z58: 0.00060380952 | AA58: 0.00060380952 | AB58: 0.00060380952 | AC58: 0.00060380952 | AD58: 0.00060380952 | AE58: 0.00060380952 | AF58: 0.00060380952 | AG58: 0.00060380952 | AH58: 0.00060380952 | AI58: 0.00060380952 | AJ58: 0.00060380952 | AK58: 0.00060380952 | AL58: 0.00060380952 | AM58: 0.00060380952 | AN58: 0.00060380952 | AO58: 0.00060380952 | AP58: 0.00060380952 | AQ58: 0.00060380952 | AR58: 0.00060380952 | AS58: 0.00060380952 | AT58: 0.00060380952 | AU58: 0.00060380952 | AV58: 0.00060380952 | AW58: 0.00060380952 | AX58: 0.00060380952 | AY58: 0.00060380952 | AZ58: 0.00060380952 | BA58: 0.00060380952
A59: Business Activities | B59: 0.0333 | C59: 0.0227 | D59: 0.0158 | E59: 0.0425 | F59: 0.0366 | G59: 0.0216 | H59: 0.02974 | I59: 0.030022857 | J59: 0.030305714 | K59: 0.030588571 | L59: 0.030871429 | M59: 0.031154286 | N59: 0.031437143 | O59: 0.03172 | P59: 0.032002857 | Q59: 0.032285714 | R59: 0.032568571 | S59: 0.032851429 | T59: 0.033134286 | U59: 0.033417143 | V59: 0.0337 | W59: 0.033982857 | X59: 0.034265714 | Y59: 0.034548571 | Z59: 0.034831429 | AA59: 0.035114286 | AB59: 0.035397143 | AC59: 0.03568 | AD59: 0.035962857 | AE59: 0.036245714 | AF59: 0.036528571 | AG59: 0.036811429 | AH59: 0.037094286 | AI59: 0.037377143 | AJ59: 0.03766 | AK59: 0.037942857 | AL59: 0.038225714 | AM59: 0.038508571 | AN59: 0.038791429 | AO59: 0.039074286 | AP59: 0.039357143 | AQ59: 0.03964 | AR59: 0.039922857 | AS59: 0.040205714 | AT59: 0.040488571 | AU59: 0.040771429 | AV59: 0.041054286 | AW59: 0.041337143 | AX59: 0.04162 | AY59: 0.041902857 | AZ59: 0.042185714 | BA59: 0.042468571
A60: Public Administration and Defence; Compulsory Social Security | B60: 0.0083 | C60: 0.0254 | D60: 0.0047 | E60: 0.0063 | F60: 0.0032 | G60: 0.0272 | H60: 0.015466667 | I60: 0.016309524 | J60: 0.017152381 | K60: 0.017995238 | L60: 0.018838095 | M60: 0.019680952 | N60: 0.02052381 | O60: 0.021366667 | P60: 0.022209524 | Q60: 0.023052381 | R60: 0.023895238 | S60: 0.024738095 | T60: 0.025580952 | U60: 0.02642381 | V60: 0.027266667 | W60: 0.028109524 | X60: 0.028952381 | Y60: 0.029795238 | Z60: 0.030638095 | AA60: 0.031480952 | AB60: 0.03232381 | AC60: 0.033166667 | AD60: 0.034009524 | AE60: 0.034852381 | AF60: 0.035695238 | AG60: 0.036538095 | AH60: 0.037380952 | AI60: 0.03822381 | AJ60: 0.039066667 | AK60: 0.039909524 | AL60: 0.040752381 | AM60: 0.041595238 | AN60: 0.042438095 | AO60: 0.043280952 | AP60: 0.04412381 | AQ60: 0.044966667 | AR60: 0.045809524 | AS60: 0.046652381 | AT60: 0.047495238 | AU60: 0.048338095 | AV60: 0.049180952 | AW60: 0.05002381 | AX60: 0.050866667 | AY60: 0.051709524 | AZ60: 0.052552381 | BA60: 0.053395238
... A63: Other Services Activities | B63: 0.0405 | C63: 0.0211 | D63: 0.0103 | E63: 0.0364 | F63: 0.0352 | G63: 0.0212 | H63: 0.02464 | I63: 0.023837143 | J63: 0.023034286 | K63: 0.022231429 | L63: 0.021428571 | M63: 0.020625714 | N63: 0.019822857 | O63: 0.01902 | P63: 0.018217143 | Q63: 0.017414286 | R63: 0.016611429 | S63: 0.015808571 | T63: 0.015005714 | U63: 0.014202857 | V63: 0.0134 | W63: 0.012597143 | X63: 0.011794286 | Y63: 0.010991429 | Z63: 0.010188571 | AA63: 0.0093857143 | AB63: 0.0085828571 | AC63: 0.00778 | AD63: 0.0069771429 | AE63: 0.0061742857 | AF63: 0.0053714286 | AG63: 0.0045685714 | AH63: 0.0037657143 | AI63: 0.0029628571 | AJ63: 0.00216 | AK63: 0.0013571429 | AL63: 0.00055428571 | AM63: 0.00055428571 | AN63: 0.00055428571 | AO63: 0.00055428571 | AP63: 0.00055428571 | AQ63: 0.00055428571 | AR63: 0.00055428571 | AS63: 0.00055428571 | AT63: 0.00055428571 | AU63: 0.00055428571 | AV63: 0.00055428571 | AW63: 0.00055428571 | AX63: 0.00055428571 | AY63: 0.00055428571 | AZ63: 0.00055428571 | BA63: 0.00055428571
A66: Updated values below (July 17, 2026)
A67: GDP by Industrial Origin (2010 Series): Google Translate of Column 'B' | B67: 2019 | C67: 2020 | D67: 2021 | E67: 2022 | F67: 2023 | G67: 2024 | H67: 2025 | I67: 2026 | J67: 2027 | K67: 2028 | L67: 2029 | M67: 2030 | N67: 2031 | O67: 2032 | P67: 2033 | Q67: 2034 | R67: 2035 | S67: 2036 | T67: 2037 | U67: 2038 | V67: 2039 | W67: 2040 | X67: 2041 | Y67: 2042 | Z67: 2043 | AA67: 2044 | AB67: 2045 | AC67: 2046 | AD67: 2047 | AE67: 2048 | AF67: 2049 | AG67: 2050 | AH67: 2051 | AI67: 2052 | AJ67: 2053 | AK67: 2054 | AL67: 2055 | AM67: 2056 | AN67: 2057 | AO67: 2058 | AP67: 2059 | AQ67: 2060 | AR67: 2061 | AS67: 2062 | AT67: 2063 | AU67: 2064 | AV67: 2065 | AW67: 2066 | AX67: 2067 | AY67: 2068 | AZ67: 2069 | BA67: 2070
A68: A. Agriculture, Forestry, and Fisheries | B68: 0.0361 | C68: 0.0177 | D68: 0.0187 | E68: 0.0225 | F68: 0.0131 | G68: 0.0068 | H68: 0.0533 | I68: {=TREND(B68:H68,$B$67:$H$67,$I$67:$BA$67)} -> 0.027485714 | J68: 0.02835 | K68: 0.029214286 | L68: 0.030078571 | M68: 0.030942857 | N68: 0.031807143 | O68: 0.032671429 | P68: 0.033535714 | Q68: 0.0344 | R68: 0.035264286 | S68: 0.036128571 | T68: 0.036992857 | U68: 0.037857143 | V68: 0.038721429 | W68: 0.039585714 | X68: 0.04045 | Y68: 0.041314286 | Z68: 0.042178571 | AA68: 0.043042857 | AB68: 0.043907143 | AC68: 0.044771429 | AD68: 0.045635714 | AE68: 0.0465 | AF68: 0.047364286 | AG68: 0.048228571 | AH68: 0.049092857 | AI68: 0.049957143 | AJ68: 0.050821429 | AK68: 0.051685714 | AL68: 0.05255 | AM68: 0.053414286 | AN68: 0.054278571 | AO68: 0.055142857 | AP68: 0.056007143 | AQ68: 0.056871429 | AR68: 0.057735714 | AS68: 0.0586 | AT68: 0.059464286 | AU68: 0.060328571 | AV68: 0.061192857 | AW68: 0.062057143 | AX68: 0.062921429 | AY68: 0.063785714 | AZ68: 0.06465 | BA68: 0.065514286
A69: B. Mining and Quarrying | B69: 0.0122 | C69: -0.0195 | D69: 0.04 | E69: 0.0438 | F69: 0.0612 | G69: 0.049 | H69: -0.0066 | I69: {=TREND(B69:H69,$B$67:$H$67,$I$67:$BA$67)} -> 0.040271429 | J69: 0.043907143 | K69: 0.047542857 | L69: 0.051178571 | M69: 0.054814286 | N69: 0.05845 | O69: 0.062085714 | P69: 0.065721429 | Q69: 0.069357143 | R69: 0.072992857 | S69: 0.076628571 | T69: 0.080264286 | U69: 0.0839 | V69: 0.087535714 | W69: 0.091171429 | X69: 0.094807143 | Y69: 0.098442857 | Z69: 0.10207857 | AA69: 0.10571429 | AB69: 0.10935 | AC69: 0.11298571 | AD69: 0.11662143 | AE69: 0.12025714 | AF69: 0.12389286 | AG69: 0.12752857 | AH69: 0.13116429 | AI69: 0.1348 | AJ69: 0.13843571 | AK69: 0.14207143 | AL69: 0.14570714 | AM69: 0.14934286 | AN69: 0.15297857 | AO69: 0.15661429 | AP69: 0.16025 | AQ69: 0.16388571 | AR69: 0.16752143 | AS69: 0.17115714 | AT69: 0.17479286 | AU69: 0.17842857 | AV69: 0.18206429 | AW69: 0.1857 | AX69: 0.18933571 | AY69: 0.19297143 | AZ69: 0.19660714 | BA69: 0.20024286
A70: C. Manufacturing Industry | B70: 0.038 | C70: -0.0293 | D70: 0.0339 | E70: 0.0489 | F70: 0.0464 | G70: 0.0443 | H70: 0.053 | I70: {=TREND(B70:H70,$B$67:$H$67,$I$67:$BA$67)} -> 0.062842857 | J70: 0.070153571 | K70: 0.077464286 | L70: 0.084775 | M70: 0.092085714 | N70: 0.099396429 | O70: 0.10670714 | P70: 0.11401786 | Q70: 0.12132857 | R70: 0.12863929 | S70: 0.13595 | T70: 0.14326071 | U70: 0.15057143 | V70: 0.15788214 | W70: 0.16519286 | X70: 0.17250357 | Y70: 0.17981429 | Z70: 0.187125 | AA70: 0.19443571 | AB70: 0.20174643 | AC70: 0.20905714 | AD70: 0.21636786 | AE70: 0.22367857 | AF70: 0.23098929 | AG70: 0.2383 | AH70: 0.24561071 | AI70: 0.25292143 | AJ70: 0.26023214 | AK70: 0.26754286 | AL70: 0.27485357 | AM70: 0.28216429 | AN70: 0.289475 | AO70: 0.29678571 | AP70: 0.30409643 | AQ70: 0.31140714 | AR70: 0.31871786 | AS70: 0.32602857 | AT70: 0.33333929 | AU70: 0.34065 | AV70: 0.34796071 | AW70: 0.35527143 | AX70: 0.36258214 | AY70: 0.36989286 | AZ70: 0.37720357 | BA70: 0.38451429
A71: D. Electricity and Gas Supply | B71: 0.0404 | C71: -0.0234 | D71: 0.0555 | E71: 0.0661 | F71: 0.0491 | G71: 0.0477 | H71: 0.031 | I71: {=TREND(B71:H71,$B$67:$H$67,$I$67:$BA$67)} -> 0.053428571 | J71: 0.057271429 | K71: 0.061114286 | L71: 0.064957143 | M71: 0.0688 | N71: 0.072642857 | O71: 0.076485714 | P71: 0.080328571 | Q71: 0.084171429 | R71: 0.088014286 | S71: 0.091857143 | T71: 0.0957 | U71: 0.099542857 | V71: 0.10338571 | W71: 0.10722857 | X71: 0.11107143 | Y71: 0.11491429 | Z71: 0.11875714 | AA71: 0.1226 | AB71: 0.12644286 | AC71: 0.13028571 | AD71: 0.13412857 | AE71: 0.13797143 | AF71: 0.14181429 | AG71: 0.14565714 | AH71: 0.1495 | AI71: 0.15334286 | AJ71: 0.15718571 | AK71: 0.16102857 | AL71: 0.16487143 | AM71: 0.16871429 | AN71: 0.17255714 | AO71: 0.1764 | AP71: 0.18024286 | AQ71: 0.18408571 | AR71: 0.18792857 | AS71: 0.19177143 | AT71: 0.19561429 | AU71: 0.19945714 | AV71: 0.2033 | AW71: 0.20714286 | AX71: 0.21098571 | AY71: 0.21482857 | AZ71: 0.21867143 | BA71: 0.22251429
A72: E. Water Supply, Waste Management, Sewerage, and Recycling | B72: 0.0683 | C72: 0.0494 | D72: 0.0497 | E72: 0.0323 | F72: 0.049 | G72: 0.0157 | H72: 0.0094 | I72: {=TREND(B72:H72,$B$67:$H$67,$I$67:$BA$67)} -> 0.0041428571 | J72: -0.0046 | K72: -0.013342857 | L72: -0.022085714 | M72: -0.030828571 | N72: -0.039571429 | O72: -0.048314286 | P72: -0.057057143 | Q72: -0.0658 | R72: -0.074542857 | S72: -0.083285714 | T72: -0.092028571 | U72: -0.10077143 | V72: -0.10951429 | W72: -0.11825714 | X72: -0.127 | Y72: -0.13574286 | Z72: -0.14448571 | AA72: -0.15322857 | AB72: -0.16197143 | AC72: -0.17071429 | AD72: -0.17945714 | AE72: -0.1882 | AF72: -0.19694286 | AG72: -0.20568571 | AH72: -0.21442857 | AI72: -0.22317143 | AJ72: -0.23191429 | AK72: -0.24065714 | AL72: -0.2494 | AM72: -0.25814286 | AN72: -0.26688571 | AO72: -0.27562857 | AP72: -0.28437143 | AQ72: -0.29311429 | AR72: -0.30185714 | AS72: -0.3106 | AT72: -0.31934286 | AU72: -0.32808571 | AV72: -0.33682857 | AW72: -0.34557143 | AX72: -0.35431429 | AY72: -0.36305714 | AZ72: -0.3718 | BA72: -0.38054286
A73: F. Construction | B73: 0.0576 | C73: -0.0326 | D73: 0.0281 | E73: 0.0201 | F73: 0.0491 | G73: 0.0702 | H73: 0.0381 | I73: {=TREND(B73:H73,$B$67:$H$67,$I$67:$BA$67)} -> 0.056957143 | J73: 0.062960714 | K73: 0.068964286 | L73: 0.074967857 | M73: 0.080971429 | N73: 0.086975 | O73: 0.092978571 | P73: 0.098982143 | Q73: 0.10498571 | R73: 0.11098929 | S73: 0.11699286 | T73: 0.12299643 | U73: 0.129 | V73: 0.13500357 | W73: 0.14100714 | X73: 0.14701071 | Y73: 0.15301429 | Z73: 0.15901786 | AA73: 0.16502143 | AB73: 0.171025 | AC73: 0.17702857 | AD73: 0.18303214 | AE73: 0.18903571 | AF73: 0.19503929 | AG73: 0.20104286 | AH73: 0.20704643 | AI73: 0.21305 | AJ73: 0.21905357 | AK73: 0.22505714 | AL73: 0.23106071 | AM73: 0.23706429 | AN73: 0.24306786 | AO73: 0.24907143 | AP73: 0.255075 | AQ73: 0.26107857 | AR73: 0.26708214 | AS73: 0.27308571 | AT73: 0.27908929 | AU73: 0.28509286 | AV73: 0.29109643 | AW73: 0.2971 | AX73: 0.30310357 | AY73: 0.30910714 | AZ73: 0.31511071 | BA73: 0.32111429
A74: G. Wholesale and Retail Trade; Repair of Motor Vehicles and Motorcycles | B74: 0.046 | C74: -0.0379 | D74: 0.0463 | E74: 0.0553 | F74: 0.0485 | G74: 0.0489 | H74: 0.0549 | I74: {=TREND(B74:H74,$B$67:$H$67,$I$67:$BA$67)} -> 0.066357143 | J74: 0.073589286 | K74: 0.080821429 | L74: 0.088053571 | M74: 0.095285714 | N74: 0.10251786 | O74: 0.10975 | P74: 0.11698214 | Q74: 0.12421429 | R74: 0.13144643 | S74: 0.13867857 | T74: 0.14591071 | U74: 0.15314286 | V74: 0.160375 | W74: 0.16760714 | X74: 0.17483929 | Y74: 0.18207143 | Z74: 0.18930357 | AA74: 0.19653571 | AB74: 0.20376786 | AC74: 0.211 | AD74: 0.21823214 | AE74: 0.22546429 | AF74: 0.23269643 | AG74: 0.23992857 | AH74: 0.24716071 | AI74: 0.25439286 | AJ74: 0.261625 | AK74: 0.26885714 | AL74: 0.27608929 | AM74: 0.28332143 | AN74: 0.29055357 | AO74: 0.29778571 | AP74: 0.30501786 | AQ74: 0.31225 | AR74: 0.31948214 | AS74: 0.32671429 | AT74: 0.33394643 | AU74: 0.34117857 | AV74: 0.34841071 | AW74: 0.35564286 | AX74: 0.362875 | AY74: 0.37010714 | AZ74: 0.37733929 | BA74: 0.38457143
A75: H. Transportation and Warehousing | B75: 0.0638 | C75: -0.1505 | D75: 0.0324 | E75: 0.1987 | F75: 0.1396 | G75: 0.0869 | H75: 0.0878 | I75: {=TREND(B75:H75,$B$67:$H$67,$I$67:$BA$67)} -> 0.15895714 | J75: 0.18231429 | K75: 0.20567143 | L75: 0.22902857 | M75: 0.25238571 | N75: 0.27574286 | O75: 0.2991 | P75: 0.32245714 | Q75: 0.34581429 | R75: 0.36917143 | S75: 0.39252857 | T75: 0.41588571 | U75: 0.43924286 | V75: 0.4626 | W75: 0.48595714 | X75: 0.50931429 | Y75: 0.53267143 | Z75: 0.55602857 | AA75: 0.57938571 | AB75: 0.60274286 | AC75: 0.6261 | AD75: 0.64945714 | AE75: 0.67281429 | AF75: 0.69617143 | AG75: 0.71952857 | AH75: 0.74288571 | AI75: 0.76624286 | AJ75: 0.7896 | AK75: 0.81295714 | AL75: 0.83631429 | AM75: 0.85967143 | AN75: 0.88302857 | AO75: 0.90638571 | AP75: 0.92974286 | AQ75: 0.9531 | AR75: 0.97645714 | AS75: 0.99981429 | AT75: 1.0231714 | AU75: 1.0465286 | AV75: 1.0698857 | AW75: 1.0932429 | AX75: 1.1166 | AY75: 1.1399571 | AZ75: 1.1633143 | BA75: 1.1866714
A76: I. Accommodation and Food & Beverage Service Activities | B76: 0.0579 | C76: -0.1026 | D76: 0.0388 | E76: 0.1194 | F76: 0.1 | G76: 0.0846 | H76: 0.0741 | I76: {=TREND(B76:H76,$B$67:$H$67,$I$67:$BA$67)} -> 0.12234286 | J76: 0.13963571 | K76: 0.15692857 | L76: 0.17422143 | M76: 0.19151429 | N76: 0.20880714 | O76: 0.2261 | P76: 0.24339286 | Q76: 0.26068571 | R76: 0.27797857 | S76: 0.29527143 | T76: 0.31256429 | U76: 0.32985714 | V76: 0.34715 | W76: 0.36444286 | X76: 0.38173571 | Y76: 0.39902857 | Z76: 0.41632143 | AA76: 0.43361429 | AB76: 0.45090714 | AC76: 0.4682 | AD76: 0.48549286 | AE76: 0.50278571 | AF76: 0.52007857 | AG76: 0.53737143 | AH76: 0.55466429 | AI76: 0.57195714 | AJ76: 0.58925 | AK76: 0.60654286 | AL76: 0.62383571 | AM76: 0.64112857 | AN76: 0.65842143 | AO76: 0.67571429 | AP76: 0.69300714 | AQ76: 0.7103 | AR76: 0.72759286 | AS76: 0.74488571 | AT76: 0.76217857 | AU76: 0.77947143 | AV76: 0.79676429 | AW76: 0.81405714 | AX76: 0.83135 | AY76: 0.84864286 | AZ76: 0.86593571 | BA76: 0.88322857
A77: J. Information and Communication | B77: 0.0942 | C77: 0.1061 | D77: 0.0682 | E77: 0.0773 | F77: 0.0759 | G77: 0.0757 | H77: 0.0835 | I77: {=TREND(B77:H77,$B$67:$H$67,$I$67:$BA$67)} -> 0.070814286 | J77: 0.067771429 | K77: 0.064728571 | L77: 0.061685714 | M77: 0.058642857 | N77: 0.0556 | O77: 0.052557143 | P77: 0.049514286 | Q77: 0.046471429 | R77: 0.043428571 | S77: 0.040385714 | T77: 0.037342857 | U77: 0.0343 | V77: 0.031257143 | W77: 0.028214286 | X77: 0.025171429 | Y77: 0.022128571 | Z77: 0.019085714 | AA77: 0.016042857 | AB77: 0.013 | AC77: 0.0099571429 | AD77: 0.0069142857 | AE77: 0.0038714286 | AF77: 0.00082857143 | AG77: -0.0022142857 | AH77: -0.0052571429 | AI77: -0.0083 | AJ77: -0.011342857 | AK77: -0.014385714 | AL77: -0.017428571 | AM77: -0.020471429 | AN77: -0.023514286 | AO77: -0.026557143 | AP77: -0.0296 | AQ77: -0.032642857 | AR77: -0.035685714 | AS77: -0.038728571 | AT77: -0.041771429 | AU77: -0.044814286 | AV77: -0.047857143 | AW77: -0.0509 | AX77: -0.053942857 | AY77: -0.056985714 | AZ77: -0.060028571 | BA77: -0.063071429
A78: K. Financial and Insurance Services | B78: 0.0661 | C78: 0.0325 | D78: 0.0156 | E78: 0.0193 | F78: 0.0477 | G78: 0.0474 | H78: 0.0396 | I78: {=TREND(B78:H78,$B$67:$H$67,$I$67:$BA$67)} -> 0.0358 | J78: 0.035171429 | K78: 0.034542857 | L78: 0.033914286 | M78: 0.033285714 | N78: 0.032657143 | O78: 0.032028571 | P78: 0.0314 | Q78: 0.030771429 | R78: 0.030142857 | S78: 0.029514286 | T78: 0.028885714 | U78: 0.028257143 | V78: 0.027628571 | W78: 0.027 | X78: 0.026371429 | Y78: 0.025742857 | Z78: 0.025114286 | AA78: 0.024485714 | AB78: 0.023857143 | AC78: 0.023228571 | AD78: 0.0226 | AE78: 0.021971429 | AF78: 0.021342857 | AG78: 0.020714286 | AH78: 0.020085714 | AI78: 0.019457143 | AJ78: 0.018828571 | AK78: 0.0182 | AL78: 0.017571429 | AM78: 0.016942857 | AN78: 0.016314286 | AO78: 0.015685714 | AP78: 0.015057143 | AQ78: 0.014428571 | AR78: 0.0138 | AS78: 0.013171429 | AT78: 0.012542857 | AU78: 0.011914286 | AV78: 0.011285714 | AW78: 0.010657143 | AX78: 0.010028571 | AY78: 0.0094 | AZ78: 0.0087714286 | BA78: 0.0081428571
A79: L. Real Estate | B79: 0.0576 | C79: 0.0232 | D79: 0.0278 | E79: 0.0172 | F79: 0.0143 | G79: 0.025 | H79: 0.0358 | I79: {=TREND(B79:H79,$B$67:$H$67,$I$67:$BA$67)} -> 0.017942857 | J79: 0.015253571 | K79: 0.012564286 | L79: 0.009875 | M79: 0.0071857143 | N79: 0.0044964286 | O79: 0.0018071429 | P79: -0.00088214286 | Q79: -0.0035714286 | R79: -0.0062607143 | S79: -0.00895 | T79: -0.011639286 | U79: -0.014328571 | V79: -0.017017857 | W79: -0.019707143 | X79: -0.022396429 | Y79: -0.025085714 | Z79: -0.027775 | AA79: -0.030464286 | AB79: -0.033153571 | AC79: -0.035842857 | AD79: -0.038532143 | AE79: -0.041221429 | AF79: -0.043910714 | AG79: -0.0466 | AH79: -0.049289286 | AI79: -0.051978571 | AJ79: -0.054667857 | AK79: -0.057357143 | AL79: -0.060046429 | AM79: -0.062735714 | AN79: -0.065425 | AO79: -0.068114286 | AP79: -0.070803571 | AQ79: -0.073492857 | AR79: -0.076182143 | AS79: -0.078871429 | AT79: -0.081560714 | AU79: -0.08425 | AV79: -0.086939286 | AW79: -0.089628571 | AX79: -0.092317857 | AY79: -0.095007143 | AZ79: -0.097696429 | BA79: -0.10038571
... A83: R,S,T,U. Other Services | B83: 0.1057 | C83: -0.041 | D83: 0.0212 | E83: 0.0947 | F83: 0.1052 | G83: 0.098 | H83: 0.0993 | I83: {=TREND(B83:H83,$B$67:$H$67,$I$67:$BA$67)} -> 0.11798571 | J83: 0.13022857 | K83: 0.14247143 | L83: 0.15471429 | M83: 0.16695714 | N83: 0.1792 | O83: 0.19144286 | P83: 0.20368571 | Q83: 0.21592857 | R83: 0.22817143 | S83: 0.24041429 | T83: 0.25265714 | U83: 0.2649 | V83: 0.27714286 | W83: 0.28938571 | X83: 0.30162857 | Y83: 0.31387143 | Z83: 0.32611429 | AA83: 0.33835714 | AB83: 0.3506 | AC83: 0.36284286 | AD83: 0.37508571 | AE83: 0.38732857 | AF83: 0.39957143 | AG83: 0.41181429 | AH83: 0.42405714 | AI83: 0.4363 | AJ83: 0.44854286 | AK83: 0.46078571 | AL83: 0.47302857 | AM83: 0.48527143 | AN83: 0.49751429 | AO83: 0.50975714 | AP83: 0.522 | AQ83: 0.53424286 | AR83: 0.54648571 | AS83: 0.55872857 | AT83: 0.57097143 | AU83: 0.58321429 | AV83: 0.59545714 | AW83: 0.6077 | AX83: 0.61994286 | AY83: 0.63218571 | AZ83: 0.64442857 | BA83: 0.65667143
A85: Differences between original data and the updated data below
A86: A. Agriculture, Forestry, and Fisheries | B86: =B68-B47 -> 0.0076 | C86: =C68-C47 -> -0.026 | D86: =D68-D47 -> -0.0134 | E86: =E68-E47 -> -0.0238 | F86: =F68-F47 -> -0.0287 | G86: =G68-G47 -> -0.0757 | H86: =H68-H47 -> -0.020366667
A87: B. Mining and Quarrying | B87: =B69-B48 -> -0.0129 | C87: =C69-C48 -> -0.1442 | D87: =D69-D48 -> -0.2318 | E87: =E69-E48 -> -0.2933 | F87: =F69-F48 -> 0.0283 | G87: =G69-G48 -> 0.0313 | H87: =H69-H48 -> -0.0243
A88: C. Manufacturing Industry | B88: =B70-B49 -> 0.0023 | C88: =C70-C49 -> -0.0417 | D88: =D70-D49 -> 0.021 | E88: =E70-E49 -> 0.036 | F88: =F70-F49 -> 0.0253 | G88: =G70-G49 -> 0.0367 | H88: =H70-H49 -> 0.04734
A89: D. Electricity and Gas Supply | B89: =B71-B50 -> 0.0346 | C89: =C71-C50 -> -0.024 | D89: =D71-D50 -> 0.0459 | E89: =E71-E50 -> 0.0507 | F89: =F71-F50 -> 0.0415 | G89: =G71-G50 -> 0.0447 | H89: =H71-H50 -> 0.02272
A90: E. Water Supply, Waste Management, Sewerage, and Recycling | B90: =B72-B51 -> 0.0657 | C90: =C72-C51 -> 0.0459 | D90: =D72-D51 -> 0.0363 | E90: =E72-E51 -> 0.0225 | F90: =F72-F51 -> 0.0388 | G90: =G72-G51 -> -0.0411 | H90: =H72-H51 -> -0.0354
A91: F. Construction | B91: =B73-B52 -> 0.0276 | C91: =C73-C52 -> -0.0364 | D91: =D73-D52 -> -0.0146 | E91: =E73-E52 -> -0.0383 | F91: =F73-F52 -> 0.0165 | G91: =G73-G52 -> 0.0631 | H91: =H73-H52 -> 0.01024
A92: G. Wholesale and Retail Trade; Repair of Motor Vehicles and Motorcycles | B92: =B74-B53 -> 0.0264 | C92: =C74-C53 -> -0.0438 | D92: =D74-D53 -> -0.0173 | E92: =E74-E53 -> -0.0442 | F92: =F74-F53 -> 0.023 | G92: =G74-G53 -> 0.0284 | H92: =H74-H53 -> 0.00588
A93: H. Transportation and Warehousing | B93: =B75-B54 -> 0.0062 | C93: =C75-C54 -> -0.1939 | D93: =D75-D54 -> 0.0086 | E93: =E75-E54 -> 0.1503 | F93: =F75-F54 -> 0.0987 | G93: =G75-G54 -> 0.0763 | H93: =H75-H54 -> 0.07214
A94: I. Accommodation and Food & Beverage Service Activities | B94: =B76-B55 -> 0.0488 | C94: =C76-C55 -> -0.1086 | D94: =D76-D55 -> 0.0315 | E94: =E76-E55 -> 0.1014 | F94: =F76-F55 -> 0.088 | G94: =G76-G55 -> 0.0619 | H94: =H76-H55 -> 0.051913333
A95: J. Information and Communication | B95: =B77-B56 -> 0.0698 | C95: =C77-C56 -> 0.1018 | D95: =D77-D56 -> 0.0609 | E95: =E77-E56 -> 0.0698 | F95: =F77-F56 -> 0.0654 | G95: =G77-G56 -> 0.0657 | H95: =H77-H56 -> 0.078153333
A96: K. Financial and Insurance Services | B96: =B78-B57 -> 0.0404 | C96: =C78-C57 -> 0.0284 | D96: =D78-D57 -> -0.0258 | E96: =E78-E57 -> -0.0229 | F96: =F78-F57 -> 0.0109 | G96: =G78-G57 -> 0.0257 | H96: =H78-H57 -> 0.00306
A97: L. Real Estate | B97: =B79-B58 -> 0.0342 | C97: =C79-C58 -> 0.014 | D97: =D79-D58 -> 0.0239 | E97: =E79-E58 -> -0.0081 | F97: =F79-F58 -> -0.0062 | G97: =G79-G58 -> 0.0199 | H97: =H79-H58 -> 0.024853333
... A101: R,S,T,U. Other Services | B101: =B83-B62 -> 0.0887 | C101: =C83-C62 -> -0.0748 | D101: =D83-D62 -> 0.0001 | E101: =E83-E62 -> 0.083 | F101: =F83-F62 -> 0.0859 | G101: =G83-G62 -> 0.0768 | H101: =H83-H62 -> 0.081806667

Sheet BPS-Statistics summary
A1: GDP by Industrial Origin (2010 Version) | C1: PDB Lapangan Usaha (Seri 2010) | D1: GDP by Industrial Origin (2010 Series): Google Translate of Column 'B' | E1: 2019 | F1: 2020 | G1: 2021 | H1: 2022 | I1: 2023 | J1: 2024 | K1: 2025 | L1: 2026 | M1: 2027 | N1: 2028 | O1: 2029 | P1: 2030 | Q1: 2031 | R1: 2032 | S1: 2033 | T1: 2034 | U1: 2035 | V1: 2036 | W1: 2037 | X1: 2038 | Y1: 2039 | Z1: 2040 | AA1: 2041 | AB1: 2042 | AC1: 2043 | AD1: 2044 | AE1: 2045 | AF1: 2046 | AG1: 2047 | AH1: 2048 | AI1: 2049 | AJ1: 2050 | AK1: 2051 | AL1: 2052 | AM1: 2053 | AN1: 2054 | AO1: 2055 | AP1: 2056 | AQ1: 2057 | AR1: 2058 | AS1: 2059 | AT1: 2060 | AU1: 2061 | AV1: 2062 | AW1: 2063 | AX1: 2064 | AY1: 2065 | AZ1: 2066 | BA1: 2067 | BB1: 2068 | BC1: 2069 | BD1: 2070
A2: A. Agriculture, Forestry and Fishing | B2: A | C2: A. Pertanian, Kehutanan, dan Perikanan | D2: A. Agriculture, Forestry, and Fisheries | E2: ='BPS 2019'!P6/100 -> 0.0361 | F2: ='BPS 2020'!F6/100 -> 0.0177 | G2: ='BPS 2021'!F6/100 -> 0.0187 | H2: ='BPS 2022'!F6/100 -> 0.0225 | I2: ='BPS 2023'!F6/100 -> 0.0131 | J2: ='BPS 2024'!F6/100 -> 0.0068 | K2: ='BPS 2025'!F6/100 -> 0.0533 | L2: =AVERAGE(H2:K2) -> 0.023925 | M2: =AVERAGE(I2:L2) -> 0.02428125 | N2: =AVERAGE(J2:M2) -> 0.027076563 | O2: =AVERAGE(K2:N2) -> 0.032145703 | P2: =AVERAGE(L2:O2) -> 0.026857129 | Q2: =AVERAGE(M2:P2) -> 0.027590161 | R2: =AVERAGE(N2:Q2) -> 0.028417389 | S2: =AVERAGE(O2:R2) -> 0.028752596 | ... BD2: =AVERAGE(AZ2:BC2) -> 0.02823
A3: - | B3: A-1 | C3: 1. Pertanian, Peternakan, Perburuan dan Jasa Pertanian | D3: 1. Agriculture, Livestock, Hunting, and Agricultural Services | E3: ='BPS 2019'!P7/100 -> 0.0331 | F3: ='BPS 2020'!F7/100 -> 0.0214 | G3: ='BPS 2021'!F7/100 -> 0.0112 | H3: ='BPS 2022'!F7/100 -> 0.0233 | I3: ='BPS 2023'!F7/100 -> 0.0018 | J3: ='BPS 2024'!F7/100 -> 0.0083 | K3: ='BPS 2025'!F7/100 -> 0.0574 | L3: =AVERAGE(H3:K3) -> 0.0227 | M3: =AVERAGE(I3:L3) -> 0.02255 | N3: =AVERAGE(J3:M3) -> 0.0277375 | O3: =AVERAGE(K3:N3) -> 0.032596875 | P3: =AVERAGE(L3:O3) -> 0.026396094 | Q3: =AVERAGE(M3:P3) -> 0.027320117 | R3: =AVERAGE(N3:Q3) -> 0.028512646 | S3: =AVERAGE(O3:R3) -> 0.028706433 | ... BD3: =AVERAGE(AZ3:BC3) -> 0.02814
A4: - | B4: A-1-a | C4: a. Tanaman Pangan | D4: a. Food Crops | E4: ='BPS 2019'!P8/100 -> -0.0173 | F4: ='BPS 2020'!F8/100 -> 0.0361 | G4: ='BPS 2021'!F8/100 -> -0.014 | H4: ='BPS 2022'!F8/100 -> 0.0008 | I4: ='BPS 2023'!F8/100 -> -0.0386 | J4: ='BPS 2024'!F8/100 -> -0.0019 | K4: ='BPS 2025'!F8/100 -> 0.0994 | L4: =AVERAGE(H4:K4) -> 0.014925 | M4: =AVERAGE(I4:L4) -> 0.01845625 | N4: =AVERAGE(J4:M4) -> 0.032720312 | O4: =AVERAGE(K4:N4) -> 0.041375391 | P4: =AVERAGE(L4:O4) -> 0.026869238 | Q4: =AVERAGE(M4:P4) -> 0.029855298 | R4: =AVERAGE(N4:Q4) -> 0.03270506 | S4: =AVERAGE(O4:R4) -> 0.032701247 | ... BD4: =AVERAGE(AZ4:BC4) -> 0.03155
A5: - | B5: A-1-b | C5: b. Tanaman Hortikultura | D5: b. Horticultural Crops | E5: ='BPS 2019'!P9/100 -> 0.0553 | F5: ='BPS 2020'!F9/100 -> 0.0417 | G5: ='BPS 2021'!F9/100 -> 0.0053 | H5: ='BPS 2022'!F9/100 -> 0.0422 | I5: ='BPS 2023'!F9/100 -> -0.0032 | J5: ='BPS 2024'!F9/100 -> 0.0086 | K5: ='BPS 2025'!F9/100 -> 0.0357 | L5: =AVERAGE(H5:K5) -> 0.020825 | M5: =AVERAGE(I5:L5) -> 0.01548125 | N5: =AVERAGE(J5:M5) -> 0.020151562 | O5: =AVERAGE(K5:N5) -> 0.023039453 | P5: =AVERAGE(L5:O5) -> 0.019874316 | Q5: =AVERAGE(M5:P5) -> 0.019636646 | R5: =AVERAGE(N5:Q5) -> 0.020675494 | S5: =AVERAGE(O5:R5) -> 0.020806477 | ... BD5: =AVERAGE(AZ5:BC5) -> 0.02044
A6: - | B6: A-1-c | C6: c. Tanaman Perkebunan | D6: c. Plantation Crops | E6: ='BPS 2019'!P10/100 -> 0.0456 | F6: ='BPS 2020'!F10/100 -> 0.0134 | G6: ='BPS 2021'!F10/100 -> 0.0352 | H6: ='BPS 2022'!F10/100 -> 0.0164 | I6: ='BPS 2023'!F10/100 -> 0.0172 | J6: ='BPS 2024'!F10/100 -> 0.0068 | K6: ='BPS 2025'!F10/100 -> 0.0295 | L6: =AVERAGE(H6:K6) -> 0.017475 | M6: =AVERAGE(I6:L6) -> 0.01774375 | N6: =AVERAGE(J6:M6) -> 0.017879688 | O6: =AVERAGE(K6:N6) -> 0.020649609 | P6: =AVERAGE(L6:O6) -> 0.018437012 | Q6: =AVERAGE(M6:P6) -> 0.018677515 | R6: =AVERAGE(N6:Q6) -> 0.018910956 | S6: =AVERAGE(O6:R6) -> 0.019168773 | ... BD6: =AVERAGE(AZ6:BC6) -> 0.01892
A7: - | B7: A-1-d | C7: d. Peternakan | D7: d. Livestock | E7: ='BPS 2019'!P11/100 -> 0.0778 | F7: ='BPS 2020'!F11/100 -> -0.0031 | G7: ='BPS 2021'!F11/100 -> 0.0032 | H7: ='BPS 2022'!F11/100 -> 0.0624 | I7: ='BPS 2023'!F11/100 -> 0.0371 | J7: ='BPS 2024'!F11/100 -> 0.0278 | K7: ='BPS 2025'!F11/100 -> 0.0778 | L7: =AVERAGE(H7:K7) -> 0.051275 | M7: =AVERAGE(I7:L7) -> 0.04849375 | N7: =AVERAGE(J7:M7) -> 0.051342187 | O7: =AVERAGE(K7:N7) -> 0.057227734 | P7: =AVERAGE(L7:O7) -> 0.052084668 | Q7: =AVERAGE(M7:P7) -> 0.052287085 | R7: =AVERAGE(N7:Q7) -> 0.053235419 | S7: =AVERAGE(O7:R7) -> 0.053708727 | ... BD7: =AVERAGE(AZ7:BC7) -> 0.05312
A8: - | B8: A-1-e | C8: e. Jasa Pertanian dan Perburuan | D8: e. Agricultural and Hunting Services | E8: ='BPS 2019'!P12/100 -> 0.0317 | F8: ='BPS 2020'!F12/100 -> 0.0165 | G8: ='BPS 2021'!F12/100 -> 0.0143 | H8: ='BPS 2022'!F12/100 -> 0.0265 | I8: ='BPS 2023'!F12/100 -> 0.0017 | J8: ='BPS 2024'!F12/100 -> 0.0087 | K8: ='BPS 2025'!F12/100 -> 0.0613 | L8: =AVERAGE(H8:K8) -> 0.02455 | M8: =AVERAGE(I8:L8) -> 0.0240625 | N8: =AVERAGE(J8:M8) -> 0.029653125 | O8: =AVERAGE(K8:N8) -> 0.034891406 | P8: =AVERAGE(L8:O8) -> 0.028289258 | Q8: =AVERAGE(M8:P8) -> 0.029224072 | R8: =AVERAGE(N8:Q8) -> 0.030514465 | S8: =AVERAGE(O8:R8) -> 0.0307298 | ... BD8: =AVERAGE(AZ8:BC8) -> 0.03012
A9: - | B9: A-2 | C9: 2. Kehutanan dan Penebangan Kayu | D9: 2. Forestry and Logging | E9: ='BPS 2019'!P13/100 -> 0.0037 | F9: ='BPS 2020'!F13/100 -> -0.0003 | G9: ='BPS 2021'!F13/100 -> 0.0007 | H9: ='BPS 2022'!F13/100 -> -0.0126 | I9: ='BPS 2023'!F13/100 -> 0.0261 | J9: ='BPS 2024'!F13/100 -> -0.0206 | K9: ='BPS 2025'!F13/100 -> -0.0029 | L9: =AVERAGE(H9:K9) -> -0.0025 | M9: =AVERAGE(I9:L9) -> 2.5e-05 | N9: =AVERAGE(J9:M9) -> -0.00649375 | O9: =AVERAGE(K9:N9) -> -0.0029671875 | P9: =AVERAGE(L9:O9) -> -0.0029839844 | Q9: =AVERAGE(M9:P9) -> -0.0031049805 | R9: =AVERAGE(N9:Q9) -> -0.0038874756 | S9: =AVERAGE(O9:R9) -> -0.003235907 | ... BD9: =AVERAGE(AZ9:BC9) -> -0.00338
A10: - | B10: A-3 | C10: 3. Perikanan | D10: 3. Fisheries | E10: ='BPS 2019'!P14/100 -> 0.0573 | F10: ='BPS 2020'!F14/100 -> 0.0073 | G10: ='BPS 2021'!F14/100 -> 0.0545 | H10: ='BPS 2022'!F14/100 -> 0.0279 | I10: ='BPS 2023'!F14/100 -> 0.0549 | J10: ='BPS 2024'!F14/100 -> 0.0068 | K10: ='BPS 2025'!F14/100 -> 0.0495 | L10: =AVERAGE(H10:K10) -> 0.034775 | M10: =AVERAGE(I10:L10) -> 0.03649375 | N10: =AVERAGE(J10:M10) -> 0.031892188 | O10: =AVERAGE(K10:N10) -> 0.038165234 | P10: =AVERAGE(L10:O10) -> 0.035331543 | Q10: =AVERAGE(M10:P10) -> 0.035470679 | R10: =AVERAGE(N10:Q10) -> 0.035214911 | S10: =AVERAGE(O10:R10) -> 0.036045592 | ... BD10: =AVERAGE(AZ10:BC10) -> 0.03561
A11: B. Mining and Quarrying | B11: B | C11: B. Pertambangan dan Penggalian | D11: B. Mining and Quarrying | E11: ='BPS 2019'!P15/100 -> 0.0122 | F11: ='BPS 2020'!F15/100 -> -0.0195 | G11: ='BPS 2021'!F15/100 -> 0.04 | H11: ='BPS 2022'!F15/100 -> 0.0438 | I11: ='BPS 2023'!F15/100 -> 0.0612 | J11: ='BPS 2024'!F15/100 -> 0.049 | K11: ='BPS 2025'!F15/100 -> -0.0066 | L11: =AVERAGE(H11:K11) -> 0.03685 | M11: =AVERAGE(I11:L11) -> 0.0351125 | N11: =AVERAGE(J11:M11) -> 0.028590625 | O11: =AVERAGE(K11:N11) -> 0.023488281 | P11: =AVERAGE(L11:O11) -> 0.031010352 | Q11: =AVERAGE(M11:P11) -> 0.029550439 | R11: =AVERAGE(N11:Q11) -> 0.028159924 | S11: =AVERAGE(O11:R11) -> 0.028052249 | ... BD11: =AVERAGE(AZ11:BC11) -> 0.02868
A12: - | B12: B-1 | C12: 1. Pertambangan Minyak, Gas dan Panas Bumi | D12: 1. Oil, Gas, and Geothermal Mining | E12: ='BPS 2019'!P16/100 -> -0.0283 | F12: ='BPS 2020'!F16/100 -> -0.06 | G12: ='BPS 2021'!F16/100 -> -0.0442 | H12: ='BPS 2022'!F16/100 -> -0.0482 | I12: ='BPS 2023'!F16/100 -> 0.0073 | J12: ='BPS 2024'!F16/100 -> -0.0078 | K12: ='BPS 2025'!F16/100 -> 0.0114 | L12: =AVERAGE(H12:K12) -> -0.009325 | M12: =AVERAGE(I12:L12) -> 0.00039375 | N12: =AVERAGE(J12:M12) -> -0.0013328125 | O12: =AVERAGE(K12:N12) -> 0.00028398437 | P12: =AVERAGE(L12:O12) -> -0.0024950195 | Q12: =AVERAGE(M12:P12) -> -0.00078752441 | R12: =AVERAGE(N12:Q12) -> -0.001082843 | S12: =AVERAGE(O12:R12) -> -0.0010203506 | ... BD12: =AVERAGE(AZ12:BC12) -> -0.00114
A13: - | B13: B-2 | C13: 2. Pertambangan Batubara dan Lignit | D13: 2. Coal and Lignite Mining | E13: ='BPS 2019'!P17/100 -> 0.102 | F13: ='BPS 2020'!F17/100 -> -0.0543 | G13: ='BPS 2021'!F17/100 -> 0.066 | H13: ='BPS 2022'!F17/100 -> 0.0811 | I13: ='BPS 2023'!F17/100 -> 0.1002 | J13: ='BPS 2024'!F17/100 -> 0.0682 | K13: ='BPS 2025'!F17/100 -> -0.0126 | L13: =AVERAGE(H13:K13) -> 0.059225 | M13: =AVERAGE(I13:L13) -> 0.05375625 | N13: =AVERAGE(J13:M13) -> 0.042145312 | O13: =AVERAGE(K13:N13) -> 0.035631641 | P13: =AVERAGE(L13:O13) -> 0.047689551 | Q13: =AVERAGE(M13:P13) -> 0.044805688 | R13: =AVERAGE(N13:Q13) -> 0.042568048 | S13: =AVERAGE(O13:R13) -> 0.042673732 | ... BD13: =AVERAGE(AZ13:BC13) -> 0.04357
... A63: R,S,T,U. Other Services Activities | B63: R,S,T,U | C63: R,S,T,U. Jasa lainnya | D63: R,S,T,U. Other Services | E63: ='BPS 2019'!P67/100 -> 0.1057 | F63: ='BPS 2020'!F67/100 -> -0.041 | G63: ='BPS 2021'!F67/100 -> 0.0212 | H63: ='BPS 2022'!F67/100 -> 0.0947 | I63: ='BPS 2023'!F67/100 -> 0.1052 | J63: ='BPS 2024'!F67/100 -> 0.098 | K63: ='BPS 2025'!F67/100 -> 0.0993 | L63: =AVERAGE(H63:K63) -> 0.0993 | M63: =AVERAGE(I63:L63) -> 0.10045 | N63: =AVERAGE(J63:M63) -> 0.0992625 | O63: =AVERAGE(K63:N63) -> 0.099578125 | P63: =AVERAGE(L63:O63) -> 0.099647656 | Q63: =AVERAGE(M63:P63) -> 0.09973457 | R63: =AVERAGE(N63:Q63) -> 0.099555713 | S63: =AVERAGE(O63:R63) -> 0.099629016 | ... BD63: =AVERAGE(AZ63:BC63) -> 0.09963
L64: =AVERAGE(H64:K64) -> #DIV/0! | M64: =AVERAGE(I64:L64) -> #DIV/0! | N64: =AVERAGE(J64:M64) -> #DIV/0! | O64: =AVERAGE(K64:N64) -> #DIV/0! | P64: =AVERAGE(L64:O64) -> #DIV/0! | Q64: =AVERAGE(M64:P64) -> #DIV/0! | R64: =AVERAGE(N64:Q64) -> #DIV/0! | S64: =AVERAGE(O64:R64) -> #DIV/0! | ... BD64: =AVERAGE(AZ64:BC64) -> #DIV/0!
A65: A. GROSS VALUE ADDED AT BASIC PRICE | C65: A. NILAI TAMBAH BRUTO ATAS HARGA DASAR | D65: A. GROSS VALUE ADDED AT BASIC PRICES | E65: ='BPS 2019'!P68/100 -> 0.0496 | F65: ='BPS 2020'!F68/100 -> -0.0159 | G65: ='BPS 2021'!F68/100 -> 0.0327 | H65: ='BPS 2022'!F68/100 -> 0.0495 | I65: ='BPS 2023'!F68/100 -> 0.0505 | J65: ='BPS 2024'!F68/100 -> 0.0511 | K65: ='BPS 2025'!F68/100 -> 0.0516 | L65: =AVERAGE(H65:K65) -> 0.050675 | M65: =AVERAGE(I65:L65) -> 0.05096875 | N65: =AVERAGE(J65:M65) -> 0.051085938 | O65: =AVERAGE(K65:N65) -> 0.051082422 | P65: =AVERAGE(L65:O65) -> 0.050953027 | Q65: =AVERAGE(M65:P65) -> 0.051022534 | R65: =AVERAGE(N65:Q65) -> 0.05103598 | S65: =AVERAGE(O65:R65) -> 0.051023491 | ... BD65: =AVERAGE(AZ65:BC65) -> 0.05102
A66: B. TAXES LESS SUBSIDIES ON PRUDUCTS | C66: B. PAJAK DIKURANG SUBSIDI ATAS PRODUK | D66: B. TAXES LESS SUBSIDIES ON PRODUCTS | E66: ='BPS 2019'!P69/100 -> 0.0652 | F66: ='BPS 2020'!F69/100 -> -0.1313 | G66: ='BPS 2021'!F69/100 -> 0.1514 | H66: ='BPS 2022'!F69/100 -> 0.1383 | I66: ='BPS 2023'!F69/100 -> 0.0494 | J66: ='BPS 2024'!F69/100 -> 0.0324 | K66: ='BPS 2025'!F69/100 -> 0.0389 | L66: =AVERAGE(H66:K66) -> 0.06475 | M66: =AVERAGE(I66:L66) -> 0.0463625 | N66: =AVERAGE(J66:M66) -> 0.045603125 | O66: =AVERAGE(K66:N66) -> 0.048903906 | P66: =AVERAGE(L66:O66) -> 0.051404883 | Q66: =AVERAGE(M66:P66) -> 0.048068604 | R66: =AVERAGE(N66:Q66) -> 0.048495129 | S66: =AVERAGE(O66:R66) -> 0.04921813 | ... BD66: =AVERAGE(AZ66:BC66) -> 0.04899
A67: C. GROSS DOMESTIC PRODUCT | C67: C. PRODUK DOMESTIK BRUTO | D67: C. GROSS DOMESTIC PRODUCT | E67: ='BPS 2019'!P70/100 -> 0.0502 | F67: ='BPS 2020'!F70/100 -> -0.0207 | G67: ='BPS 2021'!F70/100 -> 0.037 | H67: ='BPS 2022'!F70/100 -> 0.0531 | I67: ='BPS 2023'!F70/100 -> 0.0505 | J67: ='BPS 2024'!F70/100 -> 0.0503 | K67: ='BPS 2025'!F70/100 -> 0.0511 | L67: =AVERAGE(H67:K67) -> 0.05125 | M67: =AVERAGE(I67:L67) -> 0.0507875 | N67: =AVERAGE(J67:M67) -> 0.050859375 | O67: =AVERAGE(K67:N67) -> 0.050999219 | P67: =AVERAGE(L67:O67) -> 0.050974023 | Q67: =AVERAGE(M67:P67) -> 0.050905029 | R67: =AVERAGE(N67:Q67) -> 0.050934412 | S67: =AVERAGE(O67:R67) -> 0.050953171 | ... BD67: =AVERAGE(AZ67:BC67) -> 0.05094

Sheet BPS 2019
A1: PDB Lapangan Usaha (Seri 2010)
B2: [Seri 2010] Laju Pertumbuhan PDB Seri 2010 (Persen)
B3: Laju Pertumbuhan Kumulatif (c-to-c) | G3: Laju Pertumbuhan Triwulanan Berantai (q-to-q) | L3: Laju Pertumbuhan Triwulanan terhadap Triwulan yang Sama Tahun Sebelumnya (y-on-y)
B4: 2019 | G4: 2019 | L4: 2019
B5: Triwulan I | C5: Triwulan II | D5: Triwulan III | E5: Triwulan IV | F5: Tahunan | G5: Triwulan I | H5: Triwulan II | I5: Triwulan III | J5: Triwulan IV | K5: Tahunan | L5: Triwulan I | M5: Triwulan II | N5: Triwulan III | O5: Triwulan IV | P5: Tahunan
A6: A. Pertanian, Kehutanan, dan Perikanan | B6: 1.79 | C6: 3.62 | D6: 3.43 | E6: 3.61 | F6: 3.61 | G6: 14.07 | H6: 13.75 | I6: 1.04 | J6: -20.48 | K6: 3.61 | L6: 1.79 | M6: 5.28 | N6: 3.07 | O6: 4.25 | P6: 3.61
A7: 1. Pertanian, Peternakan, Perburuan dan Jasa Pertanian | B7: 1.14 | C7: 3.39 | D7: 3.07 | E7: 3.31 | F7: 3.31 | G7: 19.61 | H7: 17.43 | I7: 0.59 | J7: -26.23 | K7: 3.31 | L7: 1.14 | M7: 5.39 | N7: 2.49 | O7: 4.23 | P7: 3.31
A8: a. Tanaman Pangan | B8: -5.98 | C8: -0.48 | D8: -1.85 | E8: -1.73 | F8: -1.73 | G8: 73.54 | H8: 10.7 | I8: -11.27 | J8: -41.95 | K8: -1.73 | L8: -5.98 | M8: 5.08 | N8: -4.67 | O8: -1.05 | P8: -1.73
A9: b. Tanaman Hortikultura | B9: 6.18 | C9: 6.11 | D9: 5.71 | E9: 5.53 | F9: 5.53 | G9: 7.06 | H9: 23.79 | I9: -0.09 | J9: -20.77 | K9: 5.53 | L9: 6.18 | M9: 6.06 | N9: 4.98 | O9: 4.92 | P9: 5.53
A10: c. Tanaman Perkebunan | B10: 3.36 | C10: 3.99 | D10: 4.36 | E10: 4.56 | F10: 4.56 | G10: -0.03 | H10: 28.14 | I10: 10.41 | J10: -25.6 | K10: 4.56 | L10: 3.36 | M10: 4.5 | N10: 4.96 | O10: 5.23 | P10: 4.56
A11: d. Peternakan | B11: 7.87 | C11: 7.78 | D11: 7.75 | E11: 7.78 | F11: 7.78 | G11: 8.84 | H11: 4.22 | I11: 0.49 | J11: -5.38 | K11: 7.78 | L11: 7.87 | M11: 7.7 | N11: 7.69 | O11: 7.86 | P11: 7.78
A12: e. Jasa Pertanian dan Perburuan | B12: 1.82 | C12: 3.65 | D12: 3.04 | E12: 3.17 | F12: 3.17 | G12: 19.27 | H12: 7.15 | I12: 2.25 | J12: -20.67 | K12: 3.17 | L12: 1.82 | M12: 5.43 | N12: 1.89 | O12: 3.65 | P12: 3.17
A13: 2. Kehutanan dan Penebangan Kayu | B13: -2.84 | C13: -1.04 | D13: 0.58 | E13: 0.37 | F13: 0.37 | G13: -10.53 | H13: 11.62 | I13: 5.79 | J13: -5.56 | K13: 0.37 | L13: -2.84 | M13: 0.63 | N13: 3.63 | O13: -0.23 | P13: 0.37
A14: 3. Perikanan | B14: 5.66 | C14: 5.87 | D14: 5.8 | E14: 5.73 | F14: 5.73 | G14: 1.88 | H14: -0.26 | I14: 1.9 | J14: 1.88 | K14: 5.73 | L14: 5.66 | M14: 6.07 | N14: 5.68 | O14: 5.5 | P14: 5.73
A15: B. Pertambangan dan Penggalian | B15: 2.32 | C15: 0.79 | D15: 1.31 | E15: 1.22 | F15: 1.22 | G15: -0.24 | H15: -0.61 | I15: 3.38 | J15: -1.52 | K15: 1.22 | L15: 2.32 | M15: -0.71 | N15: 2.34 | O15: 0.94 | P15: 1.22
A16: 1. Pertambangan Minyak, Gas dan Panas Bumi | B16: -1.36 | C16: -2.75 | D16: -3.01 | E16: -2.83 | F16: -2.83 | G16: -1.82 | H16: -0.35 | I16: -0.09 | J16: -0.04 | K16: -2.83 | L16: -1.36 | M16: -4.11 | N16: -3.52 | O16: -2.28 | P16: -2.83
A17: 2. Pertambangan Batubara dan Lignit | B17: 14.77 | C17: 13.33 | D17: 13.29 | E17: 10.2 | F17: 10.2 | G17: 2.12 | H17: -2.52 | I17: 2.42 | J17: -0.02 | K17: 10.2 | L17: 14.77 | M17: 11.9 | N17: 13.21 | O17: 1.92 | P17: 10.2
... A70: C. PRODUK DOMESTIK BRUTO | B70: 5.06 | C70: 5.06 | D70: 5.04 | E70: 5.02 | F70: 5.02 | G70: -0.52 | H70: 4.2 | I70: 3.05 | J70: -1.74 | K70: 5.02 | L70: 5.06 | M70: 5.05 | N70: 5.01 | O70: 4.96 | P70: 5.02

Sheet BPS 2020
A1: PDB Lapangan Usaha (Seri 2010)
B2: [Seri 2010] Laju Pertumbuhan PDB Seri 2010 (Persen)
B3: Laju Pertumbuhan Kumulatif (c-to-c) | G3: Laju Pertumbuhan Triwulanan Berantai (q-to-q) | L3: Laju Pertumbuhan Triwulanan terhadap Triwulan yang Sama Tahun Sebelumnya (y-on-y)
B4: 2020 | G4: 2020 | L4: 2020
B5: Triwulan I | C5: Triwulan II | D5: Triwulan III | E5: Triwulan IV | F5: Tahunan | G5: Triwulan I | H5: Triwulan II | I5: Triwulan III | J5: Triwulan IV | K5: Tahunan | L5: Triwulan I | M5: Triwulan II | N5: Triwulan III | O5: Triwulan IV | P5: Tahunan
A6: A. Pertanian, Kehutanan, dan Perikanan | B6: 0.03 | C6: 1.18 | D6: 1.53 | E6: 1.77 | F6: 1.77 | G6: 9.45 | H6: 16.23 | I6: 1.01 | J6: -20.13 | K6: 1.77 | L6: 0.03 | M6: 2.2 | N6: 2.18 | O6: 2.64 | P6: 1.77
A7: 1. Pertanian, Peternakan, Perburuan dan Jasa Pertanian | B7: -1.17 | C7: 0.98 | D7: 1.73 | E7: 2.14 | F7: 2.14 | G7: 13.42 | H7: 22.15 | I7: 0.87 | J7: -25.79 | K7: 2.14 | L7: -1.17 | M7: 2.81 | N7: 3.1 | O7: 3.71 | P7: 2.14
A8: a. Tanaman Pangan | B8: -10.25 | C8: -0.01 | D8: 2.3 | E8: 3.61 | F8: 3.61 | G8: 57.4 | H8: 34.74 | I8: -12.89 | J8: -40.06 | K8: 3.61 | L8: -10.25 | M8: 9.24 | N8: 7.24 | O8: 10.73 | P8: 3.61
A9: b. Tanaman Hortikultura | B9: 2.61 | C9: 1.69 | D9: 3.13 | E9: 4.17 | F9: 4.17 | G9: 4.71 | H9: 21.78 | I9: 4.66 | J9: -19.18 | K9: 4.17 | L9: 2.61 | M9: 0.94 | N9: 5.74 | O9: 7.85 | P9: 4.17
A10: c. Tanaman Perkebunan | B10: 3.97 | C10: 1.84 | D10: 1.4 | E10: 1.34 | F10: 1.34 | G10: -1.22 | H10: 23.46 | I10: 10.97 | J10: -25.26 | K10: 1.34 | L10: 3.97 | M10: 0.18 | N10: 0.68 | O10: 1.14 | P10: 1.34
A11: d. Peternakan | B11: 2.72 | C11: 0.38 | D11: 0.18 | E11: -0.31 | F11: -0.31 | G11: 3.66 | H11: -0.44 | I11: 2.2 | J11: -6.94 | K11: -0.31 | L11: 2.72 | M11: -1.87 | N11: -0.2 | O11: -1.85 | P11: -0.31
A12: e. Jasa Pertanian dan Perburuan | B12: -1.41 | C12: 0.54 | D12: 1.21 | E12: 1.65 | F12: 1.65 | G12: 13.44 | H12: 11.25 | I12: 2.35 | J12: -20.08 | K12: 1.65 | L12: -1.41 | M12: 2.37 | N12: 2.48 | O12: 3.24 | P12: 1.65
A13: 2. Kehutanan dan Penebangan Kayu | B13: 5.32 | C13: 3.7 | D13: 1.79 | E13: -0.03 | F13: -0.03 | G13: -5.55 | H13: 8.34 | I13: 1.8 | J13: -9.2 | K13: -0.03 | L13: 5.32 | M13: 2.24 | N13: -1.62 | O13: -5.41 | P13: -0.03
A14: 3. Perikanan | B14: 3.52 | C14: 1.45 | D14: 0.61 | E14: 0.73 | F14: 0.73 | G14: -0.03 | H14: -4.26 | I14: 1.5 | J14: 4.03 | K14: 0.73 | L14: 3.52 | M14: -0.63 | N14: -1.03 | O14: 1.06 | P14: 0.73
A15: B. Pertambangan dan Penggalian | B15: 0.45 | C15: -1.13 | D15: -2.2 | E15: -1.95 | F15: -1.95 | G15: -0.73 | H15: -3.75 | I15: 1.72 | J15: 1.65 | K15: -1.95 | L15: 0.45 | M15: -2.72 | N15: -4.28 | O15: -1.2 | P15: -1.95
A16: 1. Pertambangan Minyak, Gas dan Panas Bumi | B16: -2.99 | C16: -5.03 | D16: -5.73 | E16: -6 | F16: -6 | G16: -2.53 | H16: -4.54 | I16: -0.17 | J16: 0.32 | K16: -6 | L16: -2.99 | M16: -7.07 | N16: -7.14 | O16: -6.81 | P16: -6
A17: 2. Pertambangan Batubara dan Lignit | B17: 0.13 | C17: -4.04 | D17: -5.28 | E17: -5.43 | F17: -5.43 | G17: 0.32 | H17: -10.75 | I17: 3.05 | J17: 2.01 | K17: -5.43 | L17: 0.13 | M17: -8.32 | N17: -7.75 | O17: -5.87 | P17: -5.43
... A70: C. PRODUK DOMESTIK BRUTO | B70: 2.97 | C70: -1.26 | D70: -2.03 | E70: -2.07 | F70: -2.07 | G70: -2.41 | H70: -4.19 | I70: 5.05 | J70: -0.4 | K70: -2.07 | L70: 2.97 | M70: -5.32 | N70: -3.49 | O70: -2.17 | P70: -2.07

Sheet BPS 2021
A1: PDB Lapangan Usaha (Seri 2010)
B2: [Seri 2010] Laju Pertumbuhan PDB Seri 2010 (Persen)
B3: Laju Pertumbuhan Kumulatif (c-to-c) | G3: Laju Pertumbuhan Triwulanan Berantai (q-to-q) | L3: Laju Pertumbuhan Triwulanan terhadap Triwulan yang Sama Tahun Sebelumnya (y-on-y)
B4: 2021 | G4: 2021 | L4: 2021
B5: Triwulan I | C5: Triwulan II | D5: Triwulan III | E5: Triwulan IV | F5: Tahunan | G5: Triwulan I | H5: Triwulan II | I5: Triwulan III | J5: Triwulan IV | K5: Tahunan | L5: Triwulan I | M5: Triwulan II | N5: Triwulan III | O5: Triwulan IV | P5: Tahunan
A6: A. Pertanian, Kehutanan, dan Perikanan | B6: 3.48 | C6: 1.91 | D6: 1.74 | E6: 1.87 | F6: 1.87 | G6: 10.35 | H6: 12.94 | I6: 1.9 | J6: -19.42 | K6: 1.87 | L6: 3.48 | M6: 0.56 | N6: 1.44 | O6: 2.33 | P6: 1.87
A7: 1. Pertanian, Peternakan, Perburuan dan Jasa Pertanian | B7: 5.37 | C7: 1.74 | D7: 1.36 | E7: 1.12 | F7: 1.12 | G7: 15.24 | H7: 14.49 | I7: 2.82 | J7: -26.14 | K7: 1.12 | L7: 5.37 | M7: -1.23 | N7: 0.68 | O7: 0.21 | P7: 1.12
A8: a. Tanaman Pangan | B8: 12.42 | C8: 0.83 | D8: -1.3 | E8: -1.4 | F8: -1.4 | G8: 59.81 | H8: 10.54 | I8: -10.8 | J8: -37.76 | K8: -1.4 | L8: 12.42 | M8: -7.77 | N8: -5.55 | O8: -1.92 | P8: -1.4
A9: b. Tanaman Hortikultura | B9: 3.01 | C9: 2.28 | D9: -0.51 | E9: 0.53 | F9: 0.53 | G9: 0.01 | H9: 20.21 | I9: -2.58 | J9: -11.16 | K9: 0.53 | L9: 3.01 | M9: 1.68 | N9: -5.35 | O9: 4.04 | P9: 0.53
A10: c. Tanaman Perkebunan | B10: 2.17 | C10: 1.15 | D10: 3.88 | E10: 3.52 | F10: 3.52 | G10: -0.22 | H10: 21.23 | I10: 19.83 | J10: -29.44 | K10: 3.52 | L10: 2.17 | M10: 0.32 | N10: 8.33 | O10: 2.28 | P10: 3.52
A11: d. Peternakan | B11: 2.09 | C11: 4.4 | D11: 2.07 | E11: 0.32 | F11: 0.32 | G11: 7.82 | H11: 4.07 | I11: -6.61 | J11: -9.59 | K11: 0.32 | L11: 2.09 | M11: 6.71 | N11: -2.49 | O11: -5.26 | P11: 0.32
A12: e. Jasa Pertanian dan Perburuan | B12: 5.43 | C12: 2.26 | D12: 1.85 | E12: 1.43 | F12: 1.43 | G12: 15.85 | H12: 4.9 | I12: 4.08 | J12: -21 | K12: 1.43 | L12: 5.43 | M12: -0.59 | N12: 1.09 | O12: -0.08 | P12: 1.43
A13: 2. Kehutanan dan Penebangan Kayu | B13: -6.58 | C13: -3.91 | D13: -1.41 | E13: 0.07 | F13: 0.07 | G13: -6.72 | H13: 14.29 | I13: 6.73 | J13: -7.9 | K13: 0.07 | L13: -6.58 | M13: -1.45 | N13: 3.32 | O13: 4.8 | P13: 0.07
A14: 3. Perikanan | B14: -1.31 | C14: 4.07 | D14: 4.23 | E14: 5.45 | F14: 5.45 | G14: -2.37 | H14: 6.41 | I14: -3.25 | J14: 8.44 | K14: 5.45 | L14: -1.31 | M14: 9.69 | N14: 4.55 | O14: 8.99 | P14: 5.45
A15: B. Pertambangan dan Penggalian | B15: -2.02 | C15: 1.53 | D15: 3.61 | E15: 4 | F15: 4 | G15: -1.56 | H15: 3.37 | I15: 4.2 | J15: -0.83 | K15: 4 | L15: -2.02 | M15: 5.22 | N15: 7.78 | O15: 5.15 | P15: 4
A16: 1. Pertambangan Minyak, Gas dan Panas Bumi | B16: -6.87 | C16: -5.99 | D16: -4.76 | E16: -4.42 | F16: -4.42 | G16: -2.6 | H16: -2.68 | I16: 2.81 | J16: -0.86 | K16: -4.42 | L16: -6.87 | M16: -5.06 | N16: -2.23 | O16: -3.38 | P16: -4.42
A17: 2. Pertambangan Batubara dan Lignit | B17: -7.05 | C17: 2.53 | D17: 6.59 | E17: 6.6 | F17: 6.6 | G17: -0.93 | H17: 8.76 | I17: 4.58 | J17: -5.37 | K17: 6.6 | L17: -7.05 | M17: 13.27 | N17: 14.95 | O17: 6.63 | P17: 6.6
... A70: C. PRODUK DOMESTIK BRUTO | B70: -0.69 | C70: 3.11 | D70: 3.25 | E70: 3.7 | F70: 3.7 | G70: -0.93 | H70: 3.3 | I70: 1.57 | J70: 1.05 | K70: 3.7 | L70: -0.69 | M70: 7.08 | N70: 3.53 | O70: 5.03 | P70: 3.7

Sheet BPS 2022
A1: PDB Lapangan Usaha (Seri 2010)
B2: [Seri 2010] Laju Pertumbuhan PDB Seri 2010 (Persen)
B3: Laju Pertumbuhan Kumulatif (c-to-c) | G3: Laju Pertumbuhan Triwulanan Berantai (q-to-q) | L3: Laju Pertumbuhan Triwulanan terhadap Triwulan yang Sama Tahun Sebelumnya (y-on-y)
B4: 2022 | G4: 2022 | L4: 2022
B5: Triwulan I | C5: Triwulan II | D5: Triwulan III | E5: Triwulan IV | F5: Tahunan | G5: Triwulan I | H5: Triwulan II | I5: Triwulan III | J5: Triwulan IV | K5: Tahunan | L5: Triwulan I | M5: Triwulan II | N5: Triwulan III | O5: Triwulan IV | P5: Tahunan
A6: A. Pertanian, Kehutanan, dan Perikanan | B6: 1.16 | C6: 1.43 | D6: 1.62 | E6: 2.25 | F6: 2.25 | G6: 9.08 | H6: 13.52 | I6: 2.18 | J6: -17.4 | K6: 2.25 | L6: 1.16 | M6: 1.68 | N6: 1.95 | O6: 4.51 | P6: 2.25
A7: 1. Pertanian, Peternakan, Perburuan dan Jasa Pertanian | B7: 1.56 | C7: 1.57 | D7: 1.48 | E7: 2.33 | F7: 2.33 | G7: 16.79 | H7: 14.53 | I7: 2.55 | J7: -23.05 | K7: 2.33 | L7: 1.56 | M7: 1.59 | N7: 1.32 | O7: 5.56 | P7: 2.33
A8: a. Tanaman Pangan | B8: -0.08 | C8: 1.3 | D8: -0.84 | E8: 0.08 | F8: 0.08 | G8: 62.81 | H8: 13.45 | I8: -17.73 | J8: -31.1 | K8: 0.08 | L8: -0.08 | M8: 2.55 | N8: -5.41 | O8: 4.7 | P8: 0.08
A9: b. Tanaman Hortikultura | B9: 3.67 | C9: 2.52 | D9: 3.7 | E9: 4.22 | F9: 4.22 | G9: -0.35 | H9: 17.77 | I9: 1.59 | J9: -11.17 | K9: 4.22 | L9: 3.67 | M9: 1.56 | N9: 5.92 | O9: 5.91 | P9: 4.22
A10: c. Tanaman Perkebunan | B10: -0.34 | C10: 0 | D10: 0.93 | E10: 1.64 | F10: 1.64 | G10: -2.77 | H10: 21.97 | I10: 22.32 | J10: -28.17 | K10: 1.64 | L10: -0.34 | M10: 0.27 | N10: 2.35 | O10: 4.18 | P10: 1.64
A11: d. Peternakan | B11: 6.82 | C11: 4.81 | D11: 5.25 | E11: 6.24 | F11: 6.24 | G11: 21.57 | H11: 0.23 | I11: -3.61 | J11: -6.68 | K11: 6.24 | L11: 6.82 | M11: 2.88 | N11: 6.19 | O11: 9.61 | P11: 6.24
A12: e. Jasa Pertanian dan Perburuan | B12: 1.58 | C12: 1.71 | D12: 1.63 | E12: 2.65 | F12: 2.65 | G12: 17.77 | H12: 5.17 | I12: 3.72 | J12: -17.2 | K12: 2.65 | L12: 1.58 | M12: 1.84 | N12: 1.48 | O12: 6.37 | P12: 2.65
A13: 2. Kehutanan dan Penebangan Kayu | B13: 2.07 | C13: 0.4 | D13: -1.11 | E13: -1.26 | F13: -1.26 | G13: -9.14 | H13: 10.79 | I13: 3.8 | J13: -5.93 | K13: -1.26 | L13: 2.07 | M13: -1.06 | N13: -3.77 | O13: -1.71 | P13: -1.26
A14: 3. Perikanan | B14: -0.64 | C14: 1.1 | D14: 2.86 | E14: 2.79 | F14: 2.79 | G14: -11 | H14: 10.01 | I14: 0.19 | J14: 4.61 | K14: 2.79 | L14: -0.64 | M14: 2.73 | N14: 6.38 | O14: 2.62 | P14: 2.79
A15: B. Pertambangan dan Penggalian | B15: 3.82 | C15: 3.91 | D15: 3.67 | E15: 4.38 | F15: 4.38 | G15: -2.81 | H15: 3.56 | I15: 3.4 | J15: 2.28 | K15: 4.38 | L15: 3.82 | M15: 4.01 | N15: 3.22 | O15: 6.46 | P15: 4.38
A16: 1. Pertambangan Minyak, Gas dan Panas Bumi | B16: -6.26 | C16: -5.04 | D16: -5.11 | E16: -4.82 | F16: -4.82 | G16: -5.49 | H16: -0.13 | I16: 1.27 | J16: 0.49 | K16: -4.82 | L16: -6.26 | M16: -3.8 | N16: -5.24 | O16: -3.95 | P16: -4.82
A17: 2. Pertambangan Batubara dan Lignit | B17: 3.64 | C17: 3.96 | D17: 5.88 | E17: 8.11 | F17: 8.11 | G17: -3.7 | H17: 9.39 | I17: 9.76 | J17: -0.72 | K17: 8.11 | L17: 3.64 | M17: 4.25 | N17: 9.41 | O17: 14.8 | P17: 8.11
... A70: C. PRODUK DOMESTIK BRUTO | B70: 5.02 | C70: 5.25 | D70: 5.41 | E70: 5.31 | F70: 5.31 | G70: -0.94 | H70: 3.73 | I70: 1.83 | J70: 0.36 | K70: 5.31 | L70: 5.02 | M70: 5.46 | N70: 5.73 | O70: 5.01 | P70: 5.31

Sheet BPS 2023
A1: PDB Lapangan Usaha (Seri 2010)
B2: [Seri 2010] Laju Pertumbuhan PDB Seri 2010 (Persen)
B3: Laju Pertumbuhan Kumulatif (c-to-c) | G3: Laju Pertumbuhan Triwulanan Berantai (q-to-q) | L3: Laju Pertumbuhan Triwulanan terhadap Triwulan yang Sama Tahun Sebelumnya (y-on-y)
B4: 2023 | G4: 2023 | L4: 2023
B5: Triwulan I | C5: Triwulan II | D5: Triwulan III | E5: Triwulan IV | F5: Tahunan | G5: Triwulan I | H5: Triwulan II | I5: Triwulan III | J5: Triwulan IV | K5: Tahunan | L5: Triwulan I | M5: Triwulan II | N5: Triwulan III | O5: Triwulan IV | P5: Tahunan
A6: A. Pertanian, Kehutanan, dan Perikanan | B6: 0.44 | C6: 1.29 | D6: 1.36 | E6: 1.31 | F6: 1.31 | G6: 4.84 | H6: 15.32 | I6: 1.64 | J6: -17.7 | K6: 1.31 | L6: 0.44 | M6: 2.03 | N6: 1.49 | O6: 1.13 | P6: 1.31
A7: 1. Pertanian, Peternakan, Perburuan dan Jasa Pertanian | B7: 0.47 | C7: 0.35 | D7: 0.25 | E7: 0.18 | F7: 0.18 | G7: 11.16 | H7: 14.27 | I7: 2.38 | J7: -23.16 | K7: 0.18 | L7: 0.47 | M7: 0.24 | N7: 0.07 | O7: -0.07 | P7: 0.18
A8: a. Tanaman Pangan | B8: -3 | C8: -3.14 | D8: -2.58 | E8: -3.86 | F8: -3.86 | G8: 50.83 | H8: 13.14 | I8: -16.04 | J8: -37.15 | K8: -3.86 | L8: -3 | M8: -3.27 | N8: -1.29 | O8: -9.96 | P8: -3.86
A9: b. Tanaman Hortikultura | B9: -2.65 | C9: -1.67 | D9: 0.11 | E9: -0.32 | F9: -0.32 | G9: -8.4 | H9: 19.96 | I9: 5.91 | J9: -15.52 | K9: -0.32 | L9: -2.65 | M9: -0.84 | N9: 3.37 | O9: -1.7 | P9: -0.32
A10: c. Tanaman Perkebunan | B10: 4.67 | C10: 3.73 | D10: 1.79 | E10: 1.72 | F10: 1.72 | G10: -2.32 | H10: 19.97 | I10: 17.5 | J10: -26.29 | K10: 1.72 | L10: 4.67 | M10: 2.96 | N10: -1.1 | O10: 1.5 | P10: 1.72
A11: d. Peternakan | B11: 0.81 | C11: 1.29 | D11: 1.73 | E11: 3.71 | F11: 3.71 | G11: 11.82 | H11: 1.17 | I11: -2.75 | J11: 0.18 | K11: 3.71 | L11: 0.81 | M11: 1.76 | N11: 2.66 | O11: 10.21 | P11: 3.71
A12: e. Jasa Pertanian dan Perburuan | B12: 0.86 | C12: 0.59 | D12: 0.25 | E12: 0.17 | F12: 0.17 | G12: 11.67 | H12: 4.62 | I12: 2.95 | J12: -16.94 | K12: 0.17 | L12: 0.86 | M12: 0.34 | N12: -0.4 | O12: -0.1 | P12: 0.17
A13: 2. Kehutanan dan Penebangan Kayu | B13: 1.81 | C13: 1.37 | D13: 2.76 | E13: 2.61 | F13: 2.61 | G13: -5.89 | H13: 9.88 | I13: 8.25 | J13: -8.76 | K13: 2.61 | L13: 1.81 | M13: 0.98 | N13: 5.31 | O13: 2.14 | P13: 2.61
A14: 3. Perikanan | B14: 0.03 | C14: 5.21 | D14: 5.75 | E14: 5.49 | F14: 5.49 | G14: -13.25 | H14: 20.9 | I14: -2.68 | J14: 2.63 | K14: 5.49 | L14: 0.03 | M14: 9.93 | N14: 6.78 | O14: 4.76 | P14: 5.49
A15: B. Pertambangan dan Penggalian | B15: 4.92 | C15: 4.97 | D15: 5.65 | E15: 6.12 | F15: 6.12 | G15: -4.21 | H15: 3.65 | I15: 5.31 | J15: 2.76 | K15: 6.12 | L15: 4.92 | M15: 5.01 | N15: 6.95 | O15: 7.46 | P15: 6.12
A16: 1. Pertambangan Minyak, Gas dan Panas Bumi | B16: 0.96 | C16: 0.92 | D16: 0.99 | E16: 0.73 | F16: 0.73 | G16: -0.66 | H16: -0.21 | I16: 1.53 | J16: -0.67 | K16: 0.73 | L16: 0.96 | M16: 0.88 | N16: 1.13 | O16: -0.04 | P16: 0.73
A17: 2. Pertambangan Batubara dan Lignit | B17: 17.36 | C17: 13.71 | D17: 11.06 | E17: 10.02 | F17: 10.02 | G17: -1.55 | H17: 2.88 | I17: 5.87 | J17: -0.09 | K17: 10.02 | L17: 17.36 | M17: 10.37 | N17: 6.45 | O17: 7.13 | P17: 10.02
... A70: C. PRODUK DOMESTIK BRUTO | B70: 5.04 | C70: 5.11 | D70: 5.05 | E70: 5.05 | F70: 5.05 | G70: -0.9 | H70: 3.86 | I70: 1.6 | J70: 0.45 | K70: 5.05 | L70: 5.04 | M70: 5.17 | N70: 4.94 | O70: 5.04 | P70: 5.05

Sheet BPS 2024
A1: PDB Lapangan Usaha (Seri 2010)
B2: [Seri 2010] Laju Pertumbuhan PDB Seri 2010 (Persen)
B3: Laju Pertumbuhan Kumulatif (c-to-c) | G3: Laju Pertumbuhan Triwulanan Berantai (q-to-q) | L3: Laju Pertumbuhan Triwulanan terhadap Triwulan yang Sama Tahun Sebelumnya (y-on-y)
B4: 2024 | G4: 2024 | L4: 2024
B5: Triwulan I | C5: Triwulan II | D5: Triwulan III | E5: Triwulan IV | F5: Tahunan | G5: Triwulan I | H5: Triwulan II | I5: Triwulan III | J5: Triwulan IV | K5: Tahunan | L5: Triwulan I | M5: Triwulan II | N5: Triwulan III | O5: Triwulan IV | P5: Tahunan
A6: A. Pertanian, Kehutanan, dan Perikanan | B6: -3.54 | C6: 0.1 | D6: 0.66 | E6: 0.68 | F6: 0.68 | G6: 0 | H6: 23.43 | I6: 0.11 | J6: -18.49 | K6: 0.68 | L6: -3.54 | M6: 3.25 | N6: 1.7 | O6: 0.72 | P6: 0.68
A7: 1. Pertanian, Peternakan, Perburuan dan Jasa Pertanian | B7: -5.51 | C7: 0.19 | D7: 0.79 | E7: 0.83 | F7: 0.83 | G7: 5.11 | H7: 27.2 | I7: -0.83 | J7: -23.84 | K7: 0.83 | L7: -5.51 | M7: 5.19 | N7: 1.89 | O7: 0.99 | P7: 0.83
A8: a. Tanaman Pangan | B8: -24.72 | C8: -4.95 | D8: -2.03 | E8: -0.19 | F8: -0.19 | G8: 26.1 | H8: 69.11 | I8: -22 | J8: -34.29 | K8: -0.19 | L8: -24.72 | M8: 12.52 | N8: 4.53 | O8: 9.28 | P8: -0.19
A9: b. Tanaman Hortikultura | B9: -0.31 | C9: 0.47 | D9: 0.22 | E9: 0.86 | F9: 0.86 | G9: -7.12 | H9: 21.69 | I9: 4.52 | J9: -12.89 | K9: 0.86 | L9: -0.31 | M9: 1.12 | N9: -0.2 | O9: 2.91 | P9: 0.86
A10: c. Tanaman Perkebunan | B10: 3.05 | C10: 2.02 | D10: 1.41 | E10: 0.68 | F10: 0.68 | G10: -0.82 | H10: 17.76 | I10: 16.72 | J10: -28.02 | K10: 0.68 | L10: 3.05 | M10: 1.15 | N10: 0.48 | O10: -1.88 | P10: 0.68
A11: d. Peternakan | B11: 5.22 | C11: 5.07 | D11: 4.66 | E11: 2.78 | F11: 2.78 | G11: 6.75 | H11: 0.89 | I11: -3.77 | J11: -6.33 | K11: 2.78 | L11: 5.22 | M11: 4.93 | N11: 3.83 | O11: -2.92 | P11: 2.78
A12: e. Jasa Pertanian dan Perburuan | B12: -4.29 | C12: 0.45 | D12: 0.97 | E12: 0.87 | F12: 0.87 | G12: 6.98 | H12: 14.77 | I12: 0 | J12: -18.13 | K12: 0.87 | L12: -4.29 | M12: 4.99 | N12: 1.97 | O12: 0.52 | P12: 0.87
A13: 2. Kehutanan dan Penebangan Kayu | B13: 1.19 | C13: -0.85 | D13: -1.34 | E13: -2.06 | F13: -2.06 | G13: -6.76 | H13: 5.64 | I13: 8.85 | J13: -10.68 | K13: -2.06 | L13: 1.19 | M13: -2.72 | N13: -2.19 | O13: -4.24 | P13: -2.06
A14: 3. Perikanan | B14: 3.49 | C14: -0.09 | D14: 0.59 | E14: 0.68 | F14: 0.68 | G14: -14.3 | H14: 13.26 | I14: 2.25 | J14: 1.72 | K14: 0.68 | L14: 3.49 | M14: -3.05 | N14: 1.86 | O14: 0.95 | P14: 0.68
A15: B. Pertambangan dan Penggalian | B15: 9.31 | C15: 6.18 | D15: 5.23 | E15: 4.9 | F15: 4.9 | G15: -2.56 | H15: -2.17 | I15: 5.62 | J15: 3.25 | K15: 4.9 | L15: 9.31 | M15: 3.17 | N15: 3.46 | O15: 3.95 | P15: 4.9
A16: 1. Pertambangan Minyak, Gas dan Panas Bumi | B16: -3.52 | C16: -1.85 | D16: -0.93 | E16: -0.78 | F16: -0.78 | G16: -4.12 | H16: 3.25 | I16: 2.59 | J16: -1.85 | K16: -0.78 | L16: -3.52 | M16: -0.18 | N16: 0.87 | O16: -0.32 | P16: -0.78
A17: 2. Pertambangan Batubara dan Lignit | B17: 9.72 | C17: 4.69 | D17: 4.24 | E17: 6.82 | F17: 6.82 | G17: 0.83 | H17: -6.41 | I17: 9.69 | J17: 10.34 | K17: 6.82 | L17: 9.72 | M17: -0.19 | N17: 3.41 | O17: 14.21 | P17: 6.82
... A70: C. PRODUK DOMESTIK BRUTO | B70: 5.11 | C70: 5.08 | D70: 5.04 | E70: 5.03 | F70: 5.03 | G70: -0.83 | H70: 3.79 | I70: 1.5 | J70: 0.52 | K70: 5.03 | L70: 5.11 | M70: 5.05 | N70: 4.95 | O70: 5.02 | P70: 5.03

Sheet BPS 2025
A1: PDB Lapangan Usaha (Seri 2010)
B2: [Seri 2010] Laju Pertumbuhan PDB Seri 2010 (Persen)
B3: Laju Pertumbuhan Kumulatif (c-to-c) | G3: Laju Pertumbuhan Triwulanan Berantai (q-to-q) | L3: Laju Pertumbuhan Triwulanan terhadap Triwulan yang Sama Tahun Sebelumnya (y-on-y)
B4: 2025 | G4: 2025 | L4: 2025
B5: Triwulan I | C5: Triwulan II | D5: Triwulan III | E5: Triwulan IV | F5: Tahunan | G5: Triwulan I | H5: Triwulan II | I5: Triwulan III | J5: Triwulan IV | K5: Tahunan | L5: Triwulan I | M5: Triwulan II | N5: Triwulan III | O5: Triwulan IV | P5: Tahunan
A6: A. Pertanian, Kehutanan, dan Perikanan | B6: 10.53 | C6: 5.63 | D6: 5.38 | E6: 5.33 | F6: 5.33 | G6: 9.74 | H6: 13.53 | I6: 3.33 | J6: -18.33 | K6: 5.33 | L6: 10.53 | M6: 1.66 | N6: 4.93 | O6: 5.14 | P6: 5.33
A7: 1. Pertanian, Peternakan, Perburuan dan Jasa Pertanian | B7: 13.6 | C7: 6.88 | D7: 6.52 | E7: 5.74 | F7: 5.74 | G7: 18.25 | H7: 13.76 | I7: 3.35 | J7: -26 | K7: 5.74 | L7: 13.6 | M7: 1.6 | N7: 5.88 | O7: 2.87 | P7: 5.74
A8: a. Tanaman Pangan | B8: 42.25 | C8: 11.92 | D8: 11.27 | E8: 9.94 | F8: 9.94 | G8: 64.14 | H8: 11.74 | I8: -8.78 | J8: -37.95 | K8: 9.94 | L8: 42.25 | M8: -6.01 | N8: 9.92 | O8: 3.81 | P8: 9.94
A9: b. Tanaman Hortikultura | B9: 1.83 | C9: 4.22 | D9: 3.48 | E9: 3.57 | F9: 3.57 | G9: -8.09 | H9: 26.89 | I9: 0.6 | J9: -11.48 | K9: 3.57 | L9: 1.83 | M9: 6.18 | N9: 2.19 | O9: 3.85 | P9: 3.57
A10: c. Tanaman Perkebunan | B10: 3.14 | C10: 3.21 | D10: 3.74 | E10: 2.95 | F10: 2.95 | G10: 4.26 | H10: 17.89 | I10: 18.19 | J10: -31.07 | K10: 2.95 | L10: 3.14 | M10: 3.26 | N10: 4.57 | O10: 0.14 | P10: 2.95
A11: d. Peternakan | B11: 8.83 | C11: 8.87 | D11: 8.1 | E11: 7.78 | F11: 7.78 | G11: 19.67 | H11: 0.97 | I11: -5.9 | J11: -6.14 | K11: 7.78 | L11: 8.83 | M11: 8.92 | N11: 6.51 | O11: 6.72 | P11: 7.78
A12: e. Jasa Pertanian dan Perburuan | B12: 12.64 | C12: 6.99 | D12: 6.73 | E12: 6.13 | F12: 6.13 | G12: 19.87 | H12: 4.01 | I12: 4.08 | J12: -19.83 | K12: 6.13 | L12: 12.64 | M12: 2.08 | N12: 6.24 | O12: 4.03 | P12: 6.13
A13: 2. Kehutanan dan Penebangan Kayu | B13: -4.29 | C13: -2.21 | D13: -1.64 | E13: -0.29 | F13: -0.29 | G13: -6.8 | H13: 10.09 | I13: 8.46 | J13: -6.62 | K13: -0.29 | L13: -4.29 | M13: -0.25 | N13: -0.6 | O13: 3.92 | P13: -0.29
A14: 3. Perikanan | B14: 2.3 | C14: 2.31 | D14: 2.3 | E14: 4.95 | F14: 4.95 | G14: -13.16 | H14: 13.3 | I14: 2.2 | J14: 11.73 | K14: 4.95 | L14: 2.3 | M14: 2.33 | N14: 2.27 | O14: 12.34 | P14: 4.95
A15: B. Pertambangan dan Penggalian | B15: -1.23 | C15: 0.38 | D15: -0.43 | E15: -0.66 | F15: -0.66 | G15: -7.42 | H15: 1.06 | I15: 1.47 | J15: 3.96 | K15: -0.66 | L15: -1.23 | M15: 2.03 | N15: -1.98 | O15: -1.31 | P15: -0.66
A16: 1. Pertambangan Minyak, Gas dan Panas Bumi | B16: 2.59 | C16: 1.75 | D16: 0.98 | E16: 1.14 | F16: 1.14 | G16: -1.32 | H16: 1.57 | I16: 1.15 | J16: 0.23 | K16: 1.14 | L16: 2.59 | M16: 0.93 | N16: -0.49 | O16: 1.61 | P16: 1.14
A17: 2. Pertambangan Batubara dan Lignit | B17: -0.91 | C17: -0.52 | D17: -2.87 | E17: -1.26 | F17: -1.26 | G17: -12.52 | H17: -5.64 | I17: 1.79 | J17: 22.54 | K17: -1.26 | L17: -0.91 | M17: -0.1 | N17: -7.29 | O17: 2.96 | P17: -1.26
... A70: C. PRODUK DOMESTIK BRUTO | B70: 4.87 | C70: 5 | D70: 5.01 | E70: 5.11 | F70: 5.11 | G70: -0.98 | H70: 4.04 | I70: 1.42 | J70: 0.86 | K70: 5.11 | L70: 4.87 | M70: 5.12 | N70: 5.04 | O70: 5.39 | P70: 5.11

Sheet BPS 2026
A1: PDB Lapangan Usaha (Seri 2010)
B2: [Seri 2010] Laju Pertumbuhan PDB Seri 2010 (Persen)
B3: Laju Pertumbuhan Kumulatif (c-to-c) | G3: Laju Pertumbuhan Triwulanan Berantai (q-to-q) | L3: Laju Pertumbuhan Triwulanan terhadap Triwulan yang Sama Tahun Sebelumnya (y-on-y)
B4: 2026 | G4: 2026 | L4: 2026
B5: Triwulan I | C5: Triwulan II | D5: Triwulan III | E5: Triwulan IV | F5: Tahunan | G5: Triwulan I | H5: Triwulan II | I5: Triwulan III | J5: Triwulan IV | K5: Tahunan | L5: Triwulan I | M5: Triwulan II | N5: Triwulan III | O5: Triwulan IV | P5: Tahunan
A6: A. Pertanian, Kehutanan, dan Perikanan | B6: 4.97 | C6: - | D6: - | E6: - | F6: - | G6: 9.56 | H6: - | I6: - | J6: - | K6: - | L6: 4.97 | M6: - | N6: - | O6: - | P6: -
A7: 1. Pertanian, Peternakan, Perburuan dan Jasa Pertanian | B7: 5.78 | C7: - | D7: - | E7: - | F7: - | G7: 21.58 | H7: - | I7: - | J7: - | K7: - | L7: 5.78 | M7: - | N7: - | O7: - | P7: -
A8: a. Tanaman Pangan | B8: 7.58 | C8: - | D8: - | E8: - | F8: - | G8: 70.1 | H8: - | I8: - | J8: - | K8: - | L8: 7.58 | M8: - | N8: - | O8: - | P8: -
A9: b. Tanaman Hortikultura | B9: 2.4 | C9: - | D9: - | E9: - | F9: - | G9: -9.37 | H9: - | I9: - | J9: - | K9: - | L9: 2.4 | M9: - | N9: - | O9: - | P9: -
A10: c. Tanaman Perkebunan | B10: 2.28 | C10: - | D10: - | E10: - | F10: - | G10: 6.49 | H10: - | I10: - | J10: - | K10: - | L10: 2.28 | M10: - | N10: - | O10: - | P10: -
A11: d. Peternakan | B11: 11.84 | C11: - | D11: - | E11: - | F11: - | G11: 25.41 | H11: - | I11: - | J11: - | K11: - | L11: 11.84 | M11: - | N11: - | O11: - | P11: -
A12: e. Jasa Pertanian dan Perburuan | B12: 6.41 | C12: - | D12: - | E12: - | F12: - | G12: 22.62 | H12: - | I12: - | J12: - | K12: - | L12: 6.41 | M12: - | N12: - | O12: - | P12: -
A13: 2. Kehutanan dan Penebangan Kayu | B13: -0.65 | C13: - | D13: - | E13: - | F13: - | G13: -10.9 | H13: - | I13: - | J13: - | K13: - | L13: -0.65 | M13: - | N13: - | O13: - | P13: -
A14: 3. Perikanan | B14: 2.78 | C14: - | D14: - | E14: - | F14: - | G14: -20.55 | H14: - | I14: - | J14: - | K14: - | L14: 2.78 | M14: - | N14: - | O14: - | P14: -
A15: B. Pertambangan dan Penggalian | B15: -2.14 | C15: - | D15: - | E15: - | F15: - | G15: -8.2 | H15: - | I15: - | J15: - | K15: - | L15: -2.14 | M15: - | N15: - | O15: - | P15: -
A16: 1. Pertambangan Minyak, Gas dan Panas Bumi | B16: -3.11 | C16: - | D16: - | E16: - | F16: - | G16: -5.9 | H16: - | I16: - | J16: - | K16: - | L16: -3.11 | M16: - | N16: - | O16: - | P16: -
A17: 2. Pertambangan Batubara dan Lignit | B17: -1.16 | C17: - | D17: - | E17: - | F17: - | G17: -16.02 | H17: - | I17: - | J17: - | K17: - | L17: -1.16 | M17: - | N17: - | O17: - | P17: -
... A70: C. PRODUK DOMESTIK BRUTO | B70: 5.61 | C70: - | D70: - | E70: - | F70: - | G70: -0.77 | H70: - | I70: - | J70: - | K70: - | L70: 5.61 | M70: - | N70: - | O70: - | P70: -

Sheet BPCiObIC
A1: Unit: dimensionless (% change) | B1: 2019 | C1: 2020 | D1: 2021 | E1: 2022 | F1: 2023 | G1: 2024 | H1: 2025 | I1: 2026 | J1: 2027 | K1: 2028 | L1: 2029 | M1: 2030 | N1: 2031 | O1: 2032 | P1: 2033 | Q1: 2034 | R1: 2035 | S1: 2036 | T1: 2037 | U1: 2038 | V1: 2039 | W1: 2040 | X1: 2041 | Y1: 2042 | Z1: 2043 | AA1: 2044 | AB1: 2045 | AC1: 2046 | AD1: 2047 | AE1: 2048 | AF1: 2049 | AG1: 2050 | AH1: 2051 | AI1: 2052 | AJ1: 2053 | AK1: 2054 | AL1: 2055 | AM1: 2056 | AN1: 2057 | AO1: 2058 | AP1: 2059 | AQ1: 2060 | AR1: 2061 | AS1: 2062 | AT1: 2063 | AU1: 2064 | AV1: 2065 | AW1: 2066 | AX1: 2067 | AY1: 2068 | AZ1: 2069 | BA1: 2070
A2: ISIC 01T03 | B2: ='BPS-Statistics summary'!E3 -> 0.0331 | C2: ='BPS-Statistics summary'!F3 -> 0.0214 | D2: ='BPS-Statistics summary'!G3 -> 0.0112 | E2: ='BPS-Statistics summary'!H3 -> 0.0233 | F2: ='BPS-Statistics summary'!I3 -> 0.0018 | G2: ='BPS-Statistics summary'!J3 -> 0.0083 | H2: ='BPS-Statistics summary'!K3 -> 0.0574 | I2: ='BPS-Statistics summary'!L3 -> 0.0227 | ... BA2: ='BPS-Statistics summary'!BD3 -> 0.02814
A3: ISIC 05 | B3: ='BPS-Statistics summary'!E13 -> 0.102 | C3: ='BPS-Statistics summary'!F13 -> -0.0543 | D3: ='BPS-Statistics summary'!G13 -> 0.066 | E3: ='BPS-Statistics summary'!H13 -> 0.0811 | F3: ='BPS-Statistics summary'!I13 -> 0.1002 | G3: ='BPS-Statistics summary'!J13 -> 0.0682 | H3: ='BPS-Statistics summary'!K13 -> -0.0126 | I3: ='BPS-Statistics summary'!L13 -> 0.059225 | ... BA3: ='BPS-Statistics summary'!BD13 -> 0.04357
A4: ISIC 06 | B4: ='BPS-Statistics summary'!E12 -> -0.0283 | C4: ='BPS-Statistics summary'!F12 -> -0.06 | D4: ='BPS-Statistics summary'!G12 -> -0.0442 | E4: ='BPS-Statistics summary'!H12 -> -0.0482 | F4: ='BPS-Statistics summary'!I12 -> 0.0073 | G4: ='BPS-Statistics summary'!J12 -> -0.0078 | H4: ='BPS-Statistics summary'!K12 -> 0.0114 | I4: ='BPS-Statistics summary'!L12 -> -0.009325 | ... BA4: ='BPS-Statistics summary'!BD12 -> -0.00114
A5: ISIC 07T08 | B5: ='BPS-Statistics summary'!E14 -> -0.1515 | C5: ='BPS-Statistics summary'!F14 -> 0.2026 | D5: ='BPS-Statistics summary'!G14 -> 0.2284 | E5: ='BPS-Statistics summary'!H14 -> 0.1801 | F5: ='BPS-Statistics summary'!I14 -> 0.085 | G5: ='BPS-Statistics summary'!J14 -> 0.083 | H5: ='BPS-Statistics summary'!K14 -> -0.0792 | I5: ='BPS-Statistics summary'!L14 -> 0.067225 | ... BA5: ='BPS-Statistics summary'!BD14 -> 0.02823
A6: ISIC 09 | B6: ='BPS-Statistics summary'!E15 -> 0.0618 | C6: ='BPS-Statistics summary'!F15 -> -0.0122 | D6: ='BPS-Statistics summary'!G15 -> 0.0197 | E6: ='BPS-Statistics summary'!H15 -> 0.0233 | F6: ='BPS-Statistics summary'!I15 -> 0.0537 | G6: ='BPS-Statistics summary'!J15 -> 0.0627 | H6: ='BPS-Statistics summary'!K15 -> 0.0479 | I6: ='BPS-Statistics summary'!L15 -> 0.0469 | ... BA6: ='BPS-Statistics summary'!BD15 -> 0.05104
A7: ISIC 10T12 | B7: =AVERAGE('BPS-Statistics summary'!E19,'BPS-Statistics summary'!E20) -> 0.0557 | C7: =AVERAGE('BPS-Statistics summary'!F19,'BPS-Statistics summary'!F20) -> -0.021 | D7: =AVERAGE('BPS-Statistics summary'!G19,'BPS-Statistics summary'!G20) -> 0.0061 | E7: =AVERAGE('BPS-Statistics summary'!H19,'BPS-Statistics summary'!H20) -> 0.0128 | F7: =AVERAGE('BPS-Statistics summary'!I19,'BPS-Statistics summary'!I20) -> 0.04635 | G7: =AVERAGE('BPS-Statistics summary'!J19,'BPS-Statistics summary'!J20) -> 0.04695 | H7: =AVERAGE('BPS-Statistics summary'!K19,'BPS-Statistics summary'!K20) -> 0.02505 | I7: =AVERAGE('BPS-Statistics summary'!L19,'BPS-Statistics summary'!L20) -> 0.0327875 | ... BA7: =AVERAGE('BPS-Statistics summary'!BD19,'BPS-Statistics summary'!BD20) -> 0.034655
A8: ISIC 13T15 | B8: =AVERAGE('BPS-Statistics summary'!E21,'BPS-Statistics summary'!E22) -> 0.0718 | C8: =AVERAGE('BPS-Statistics summary'!F21,'BPS-Statistics summary'!F22) -> -0.0882 | D8: =AVERAGE('BPS-Statistics summary'!G21,'BPS-Statistics summary'!G22) -> 0.01835 | E8: =AVERAGE('BPS-Statistics summary'!H21,'BPS-Statistics summary'!H22) -> 0.0935 | F8: =AVERAGE('BPS-Statistics summary'!I21,'BPS-Statistics summary'!I22) -> -0.0116 | G8: =AVERAGE('BPS-Statistics summary'!J21,'BPS-Statistics summary'!J22) -> 0.05545 | H8: =AVERAGE('BPS-Statistics summary'!K21,'BPS-Statistics summary'!K22) -> 0.0343 | I8: =AVERAGE('BPS-Statistics summary'!L21,'BPS-Statistics summary'!L22) -> 0.0429125 | ... BA8: =AVERAGE('BPS-Statistics summary'!BD21,'BPS-Statistics summary'!BD22) -> 0.037385
A9: ISIC 16 | B9: ='BPS-Statistics summary'!E23 -> -0.0455 | C9: ='BPS-Statistics summary'!F23 -> -0.0216 | D9: ='BPS-Statistics summary'!G23 -> -0.0371 | E9: ='BPS-Statistics summary'!H23 -> 0.0059 | F9: ='BPS-Statistics summary'!I23 -> 0.012 | G9: ='BPS-Statistics summary'!J23 -> 0.0279 | H9: ='BPS-Statistics summary'!K23 -> -0.0329 | I9: ='BPS-Statistics summary'!L23 -> 0.003225 | ... BA9: ='BPS-Statistics summary'!BD23 -> -0.0018
A10: ISIC 17T18 | B10: ='BPS-Statistics summary'!E24 -> 0.0886 | C10: ='BPS-Statistics summary'!F24 -> 0.0022 | D10: ='BPS-Statistics summary'!G24 -> -0.0289 | E10: ='BPS-Statistics summary'!H24 -> 0.0373 | F10: ='BPS-Statistics summary'!I24 -> 0.0452 | G10: ='BPS-Statistics summary'!J24 -> 0.0261 | H10: ='BPS-Statistics summary'!K24 -> 0.0336 | I10: ='BPS-Statistics summary'!L24 -> 0.03555 | ... BA10: ='BPS-Statistics summary'!BD24 -> 0.03404
A11: ISIC 19 | B11: ='BPS-Statistics summary'!E17 -> -0.0111 | C11: ='BPS-Statistics summary'!F17 -> -0.0681 | D11: ='BPS-Statistics summary'!G17 -> 0.0057 | E11: ='BPS-Statistics summary'!H17 -> 0.0372 | F11: ='BPS-Statistics summary'!I17 -> 0.0416 | G11: ='BPS-Statistics summary'!J17 -> 0.0104 | H11: ='BPS-Statistics summary'!K17 -> 0.0692 | I11: ='BPS-Statistics summary'!L17 -> 0.0396 | ... BA11: ='BPS-Statistics summary'!BD17 -> 0.04284
A12: ISIC 20 | B12: ='BPS-Statistics summary'!E25 -> 0.0848 | C12: ='BPS-Statistics summary'!F25 -> 0.0939 | D12: ='BPS-Statistics summary'!G25 -> 0.0961 | E12: ='BPS-Statistics summary'!H25 -> 0.0069 | F12: ='BPS-Statistics summary'!I25 -> 0.0011 | G12: ='BPS-Statistics summary'!J25 -> 0.0586 | H12: ='BPS-Statistics summary'!K25 -> 0.0835 | I12: ='BPS-Statistics summary'!L25 -> 0.037525 | ... BA12: ='BPS-Statistics summary'!BD25 -> 0.05189
A13: ISIC 21 | B13: ='BPS-Statistics summary'!E25 -> 0.0848 | C13: ='BPS-Statistics summary'!F25 -> 0.0939 | D13: ='BPS-Statistics summary'!G25 -> 0.0961 | E13: ='BPS-Statistics summary'!H25 -> 0.0069 | F13: ='BPS-Statistics summary'!I25 -> 0.0011 | G13: ='BPS-Statistics summary'!J25 -> 0.0586 | H13: ='BPS-Statistics summary'!K25 -> 0.0835 | I13: ='BPS-Statistics summary'!L25 -> 0.037525 | ... BA13: ='BPS-Statistics summary'!BD25 -> 0.05189
A14: ISIC 22 | B14: ='BPS-Statistics summary'!E26 -> -0.0552 | C14: ='BPS-Statistics summary'!F26 -> -0.0561 | D14: ='BPS-Statistics summary'!G26 -> 0.0108 | E14: ='BPS-Statistics summary'!H26 -> -0.041 | F14: ='BPS-Statistics summary'!I26 -> -0.0363 | G14: ='BPS-Statistics summary'!J26 -> 0.0175 | H14: ='BPS-Statistics summary'!K26 -> -0.0407 | I14: ='BPS-Statistics summary'!L26 -> -0.025125 | ... BA14: ='BPS-Statistics summary'!BD26 -> -0.02239
A15: ISIC 231 | B15: ='BPS-Statistics summary'!E33 -> 0.0517 | C15: ='BPS-Statistics summary'!F33 -> -0.0088 | D15: ='BPS-Statistics summary'!G33 -> -0.0164 | E15: ='BPS-Statistics summary'!H33 -> 0.0608 | F15: ='BPS-Statistics summary'!I33 -> -0.021 | G15: ='BPS-Statistics summary'!J33 -> 0.0354 | H15: ='BPS-Statistics summary'!K33 -> 0.0924 | I15: ='BPS-Statistics summary'!L33 -> 0.0419 | ... BA15: ='BPS-Statistics summary'!BD33 -> 0.04946
A16: ISIC 239 | B16: ='BPS-Statistics summary'!E27 -> -0.0103 | C16: ='BPS-Statistics summary'!F27 -> -0.0913 | D16: ='BPS-Statistics summary'!G27 -> 0.0089 | E16: ='BPS-Statistics summary'!H27 -> -0.02 | F16: ='BPS-Statistics summary'!I27 -> 0.0411 | G16: ='BPS-Statistics summary'!J27 -> -0.006 | H16: ='BPS-Statistics summary'!K27 -> 0.0616 | I16: ='BPS-Statistics summary'!L27 -> 0.019175 | ... BA16: ='BPS-Statistics summary'!BD27 -> 0.02906
A17: ISIC 241 | B17: ='BPS-Statistics summary'!E28 -> 0.0283 | C17: ='BPS-Statistics summary'!F28 -> 0.0587 | D17: ='BPS-Statistics summary'!G28 -> 0.115 | E17: ='BPS-Statistics summary'!H28 -> 0.148 | F17: ='BPS-Statistics summary'!I28 -> 0.1417 | G17: ='BPS-Statistics summary'!J28 -> 0.1334 | H17: ='BPS-Statistics summary'!K28 -> 0.1571 | I17: ='BPS-Statistics summary'!L28 -> 0.14505 | ... BA17: ='BPS-Statistics summary'!BD28 -> 0.146
A18: ISIC 242 | B18: ='BPS-Statistics summary'!E28 -> 0.0283 | C18: ='BPS-Statistics summary'!F28 -> 0.0587 | D18: ='BPS-Statistics summary'!G28 -> 0.115 | E18: ='BPS-Statistics summary'!H28 -> 0.148 | F18: ='BPS-Statistics summary'!I28 -> 0.1417 | G18: ='BPS-Statistics summary'!J28 -> 0.1334 | H18: ='BPS-Statistics summary'!K28 -> 0.1571 | I18: ='BPS-Statistics summary'!L28 -> 0.14505 | ... BA18: ='BPS-Statistics summary'!BD28 -> 0.146
A19: ISIC 25 | B19: ='BPS-Statistics summary'!E29 -> -0.0051 | C19: ='BPS-Statistics summary'!F29 -> -0.0546 | D19: ='BPS-Statistics summary'!G29 -> -0.0162 | E19: ='BPS-Statistics summary'!H29 -> 0.0671 | F19: ='BPS-Statistics summary'!I29 -> 0.1367 | G19: ='BPS-Statistics summary'!J29 -> 0.0616 | H19: ='BPS-Statistics summary'!K29 -> 0.0458 | I19: ='BPS-Statistics summary'!L29 -> 0.0778 | ... BA19: ='BPS-Statistics summary'!BD29 -> 0.07085
A20: ISIC 26 | B20: ='BPS-Statistics summary'!E29 -> -0.0051 | C20: ='BPS-Statistics summary'!F29 -> -0.0546 | D20: ='BPS-Statistics summary'!G29 -> -0.0162 | E20: ='BPS-Statistics summary'!H29 -> 0.0671 | F20: ='BPS-Statistics summary'!I29 -> 0.1367 | G20: ='BPS-Statistics summary'!J29 -> 0.0616 | H20: ='BPS-Statistics summary'!K29 -> 0.0458 | I20: ='BPS-Statistics summary'!L29 -> 0.0778 | ... BA20: ='BPS-Statistics summary'!BD29 -> 0.07085
A21: ISIC 27 | B21: ='BPS-Statistics summary'!E30 -> -0.0413 | C21: ='BPS-Statistics summary'!F30 -> -0.1017 | D21: ='BPS-Statistics summary'!G30 -> 0.1143 | E21: ='BPS-Statistics summary'!H30 -> 0.1137 | F21: ='BPS-Statistics summary'!I30 -> -0.0003 | G21: ='BPS-Statistics summary'!J30 -> -0.0042 | H21: ='BPS-Statistics summary'!K30 -> 0.1398 | I21: ='BPS-Statistics summary'!L30 -> 0.06225 | ... BA21: ='BPS-Statistics summary'!BD30 -> 0.06597
A22: ISIC 28 | B22: ='BPS-Statistics summary'!E29 -> -0.0051 | C22: ='BPS-Statistics summary'!F29 -> -0.0546 | D22: ='BPS-Statistics summary'!G29 -> -0.0162 | E22: ='BPS-Statistics summary'!H29 -> 0.0671 | F22: ='BPS-Statistics summary'!I29 -> 0.1367 | G22: ='BPS-Statistics summary'!J29 -> 0.0616 | H22: ='BPS-Statistics summary'!K29 -> 0.0458 | I22: ='BPS-Statistics summary'!L29 -> 0.0778 | ... BA22: ='BPS-Statistics summary'!BD29 -> 0.07085
A23: ISIC 29 | B23: ='BPS-Statistics summary'!E30 -> -0.0413 | C23: ='BPS-Statistics summary'!F30 -> -0.1017 | D23: ='BPS-Statistics summary'!G30 -> 0.1143 | E23: ='BPS-Statistics summary'!H30 -> 0.1137 | F23: ='BPS-Statistics summary'!I30 -> -0.0003 | G23: ='BPS-Statistics summary'!J30 -> -0.0042 | H23: ='BPS-Statistics summary'!K30 -> 0.1398 | I23: ='BPS-Statistics summary'!L30 -> 0.06225 | ... BA23: ='BPS-Statistics summary'!BD30 -> 0.06597
A24: ISIC 30 | B24: ='BPS-Statistics summary'!E31 -> -0.0343 | C24: ='BPS-Statistics summary'!F31 -> -0.1986 | D24: ='BPS-Statistics summary'!G31 -> 0.1782 | E24: ='BPS-Statistics summary'!H31 -> 0.1067 | F24: ='BPS-Statistics summary'!I31 -> 0.0763 | G24: ='BPS-Statistics summary'!J31 -> -0.021 | H24: ='BPS-Statistics summary'!K31 -> -0.0264 | I24: ='BPS-Statistics summary'!L31 -> 0.0339 | ... BA24: ='BPS-Statistics summary'!BD31 -> 0.00907
A25: ISIC 31T33 | B25: ='BPS-Statistics summary'!E32 -> 0.0835 | C25: ='BPS-Statistics summary'!F32 -> -0.0336 | D25: ='BPS-Statistics summary'!G32 -> 0.0816 | E25: ='BPS-Statistics summary'!H32 -> -0.0199 | F25: ='BPS-Statistics summary'!I32 -> -0.0204 | G25: ='BPS-Statistics summary'!J32 -> 0.0207 | H25: ='BPS-Statistics summary'!K32 -> 0.016 | I25: ='BPS-Statistics summary'!L32 -> -0.0009 | ... BA25: ='BPS-Statistics summary'!BD32 -> 0.00654
A26: ISIC 351 | B26: ='BPS-Statistics summary'!E35 -> 0.0461 | C26: ='BPS-Statistics summary'!F35 -> -0.0098 | D26: ='BPS-Statistics summary'!G35 -> 0.0561 | E26: ='BPS-Statistics summary'!H35 -> 0.0706 | F26: ='BPS-Statistics summary'!I35 -> 0.0507 | G26: ='BPS-Statistics summary'!J35 -> 0.0647 | H26: ='BPS-Statistics summary'!K35 -> 0.0344 | I26: ='BPS-Statistics summary'!L35 -> 0.0551 | ... BA26: ='BPS-Statistics summary'!BD35 -> 0.05037
A27: ISIC 352T353 | B27: ='BPS-Statistics summary'!E36 -> 0.0016 | C27: ='BPS-Statistics summary'!F36 -> -0.1194 | D27: ='BPS-Statistics summary'!G36 -> 0.0505 | E27: ='BPS-Statistics summary'!H36 -> 0.0301 | F27: ='BPS-Statistics summary'!I36 -> 0.0354 | G27: ='BPS-Statistics summary'!J36 -> -0.0951 | H27: ='BPS-Statistics summary'!K36 -> -0.0031 | I27: ='BPS-Statistics summary'!L36 -> -0.008175 | ... BA27: ='BPS-Statistics summary'!BD36 -> -0.01968
A28: ISIC 36T39 | B28: ='BPS-Statistics summary'!E37 -> 0.0683 | C28: ='BPS-Statistics summary'!F37 -> 0.0494 | D28: ='BPS-Statistics summary'!G37 -> 0.0497 | E28: ='BPS-Statistics summary'!H37 -> 0.0323 | F28: ='BPS-Statistics summary'!I37 -> 0.049 | G28: ='BPS-Statistics summary'!J37 -> 0.0157 | H28: ='BPS-Statistics summary'!K37 -> 0.0094 | I28: ='BPS-Statistics summary'!L37 -> 0.0266 | ... BA28: ='BPS-Statistics summary'!BD37 -> 0.0215
A29: ISIC 41T43 | B29: ='BPS-Statistics summary'!E38 -> 0.0576 | C29: ='BPS-Statistics summary'!F38 -> -0.0326 | D29: ='BPS-Statistics summary'!G38 -> 0.0281 | E29: ='BPS-Statistics summary'!H38 -> 0.0201 | F29: ='BPS-Statistics summary'!I38 -> 0.0491 | G29: ='BPS-Statistics summary'!J38 -> 0.0702 | H29: ='BPS-Statistics summary'!K38 -> 0.0381 | I29: ='BPS-Statistics summary'!L38 -> 0.044375 | ... BA29: ='BPS-Statistics summary'!BD38 -> 0.04813
A30: ISIC 45T47 | B30: ='BPS-Statistics summary'!E39 -> 0.046 | C30: ='BPS-Statistics summary'!F39 -> -0.0379 | D30: ='BPS-Statistics summary'!G39 -> 0.0463 | E30: ='BPS-Statistics summary'!H39 -> 0.0553 | F30: ='BPS-Statistics summary'!I39 -> 0.0485 | G30: ='BPS-Statistics summary'!J39 -> 0.0489 | H30: ='BPS-Statistics summary'!K39 -> 0.0549 | I30: ='BPS-Statistics summary'!L39 -> 0.0519 | ... BA30: ='BPS-Statistics summary'!BD39 -> 0.05186
A31: ISIC 49T53 | B31: ='BPS-Statistics summary'!E42 -> 0.0638 | C31: ='BPS-Statistics summary'!F42 -> -0.1505 | D31: ='BPS-Statistics summary'!G42 -> 0.0324 | E31: ='BPS-Statistics summary'!H42 -> 0.1987 | F31: ='BPS-Statistics summary'!I42 -> 0.1396 | G31: ='BPS-Statistics summary'!J42 -> 0.0869 | H31: ='BPS-Statistics summary'!K42 -> 0.0878 | I31: ='BPS-Statistics summary'!L42 -> 0.12825 | ... BA31: ='BPS-Statistics summary'!BD42 -> 0.10898
A32: ISIC 55T56 | B32: ='BPS-Statistics summary'!E49 -> 0.0579 | C32: ='BPS-Statistics summary'!F49 -> -0.1026 | D32: ='BPS-Statistics summary'!G49 -> 0.0388 | E32: ='BPS-Statistics summary'!H49 -> 0.1194 | F32: ='BPS-Statistics summary'!I49 -> 0.1 | G32: ='BPS-Statistics summary'!J49 -> 0.0846 | H32: ='BPS-Statistics summary'!K49 -> 0.0741 | I32: ='BPS-Statistics summary'!L49 -> 0.094525 | ... BA32: ='BPS-Statistics summary'!BD49 -> 0.08696
A33: ISIC 58T60 | B33: ='BPS-Statistics summary'!E52 -> 0.0942 | C33: ='BPS-Statistics summary'!F52 -> 0.1061 | D33: ='BPS-Statistics summary'!G52 -> 0.0682 | E33: ='BPS-Statistics summary'!H52 -> 0.0773 | F33: ='BPS-Statistics summary'!I52 -> 0.0759 | G33: ='BPS-Statistics summary'!J52 -> 0.0757 | H33: ='BPS-Statistics summary'!K52 -> 0.0835 | I33: ='BPS-Statistics summary'!L52 -> 0.0781 | ... BA33: ='BPS-Statistics summary'!BD52 -> 0.07902
A34: ISIC 61 | B34: ='BPS-Statistics summary'!E52 -> 0.0942 | C34: ='BPS-Statistics summary'!F52 -> 0.1061 | D34: ='BPS-Statistics summary'!G52 -> 0.0682 | E34: ='BPS-Statistics summary'!H52 -> 0.0773 | F34: ='BPS-Statistics summary'!I52 -> 0.0759 | G34: ='BPS-Statistics summary'!J52 -> 0.0757 | H34: ='BPS-Statistics summary'!K52 -> 0.0835 | I34: ='BPS-Statistics summary'!L52 -> 0.0781 | ... BA34: ='BPS-Statistics summary'!BD52 -> 0.07902
A35: ISIC 62T63 | B35: ='BPS-Statistics summary'!E59 -> 0.1025 | C35: ='BPS-Statistics summary'!F59 -> -0.0544 | D35: ='BPS-Statistics summary'!G59 -> 0.0073 | E35: ='BPS-Statistics summary'!H59 -> 0.0877 | F35: ='BPS-Statistics summary'!I59 -> 0.0824 | G35: ='BPS-Statistics summary'!J59 -> 0.0838 | H35: ='BPS-Statistics summary'!K59 -> 0.091 | I35: ='BPS-Statistics summary'!L59 -> 0.086225 | ... BA35: ='BPS-Statistics summary'!BD59 -> 0.08679
A36: ISIC 64T66 | B36: ='BPS-Statistics summary'!E53 -> 0.0661 | C36: ='BPS-Statistics summary'!F53 -> 0.0325 | D36: ='BPS-Statistics summary'!G53 -> 0.0156 | E36: ='BPS-Statistics summary'!H53 -> 0.0193 | F36: ='BPS-Statistics summary'!I53 -> 0.0477 | G36: ='BPS-Statistics summary'!J53 -> 0.0474 | H36: ='BPS-Statistics summary'!K53 -> 0.0396 | I36: ='BPS-Statistics summary'!L53 -> 0.0385 | ... BA36: ='BPS-Statistics summary'!BD53 -> 0.04153
A37: ISIC 68 | B37: ='BPS-Statistics summary'!E58 -> 0.0576 | C37: ='BPS-Statistics summary'!F58 -> 0.0232 | D37: ='BPS-Statistics summary'!G58 -> 0.0278 | E37: ='BPS-Statistics summary'!H58 -> 0.0172 | F37: ='BPS-Statistics summary'!I58 -> 0.0143 | G37: ='BPS-Statistics summary'!J58 -> 0.025 | H37: ='BPS-Statistics summary'!K58 -> 0.0358 | I37: ='BPS-Statistics summary'!L58 -> 0.023075 | ... BA37: ='BPS-Statistics summary'!BD58 -> 0.0264
A38: ISIC 69T82 | B38: ='BPS-Statistics summary'!E61 -> 0.063 | C38: ='BPS-Statistics summary'!F61 -> 0.0261 | D38: ='BPS-Statistics summary'!G61 -> 0.0011 | E38: ='BPS-Statistics summary'!H61 -> 0.0055 | F38: ='BPS-Statistics summary'!I61 -> 0.0177 | G38: ='BPS-Statistics summary'!J61 -> 0.0376 | H38: ='BPS-Statistics summary'!K61 -> 0.0499 | I38: ='BPS-Statistics summary'!L61 -> 0.027675 | ... BA38: ='BPS-Statistics summary'!BD61 -> 0.03533
A39: ISIC 84 | B39: ='BPS-Statistics summary'!E60 -> 0.0466 | C39: ='BPS-Statistics summary'!F60 -> -0.0003 | D39: ='BPS-Statistics summary'!G60 -> -0.0033 | E39: ='BPS-Statistics summary'!H60 -> 0.0252 | F39: ='BPS-Statistics summary'!I60 -> 0.0151 | G39: ='BPS-Statistics summary'!J60 -> 0.0643 | H39: ='BPS-Statistics summary'!K60 -> 0.0386 | I39: ='BPS-Statistics summary'!L60 -> 0.0358 | ... BA39: ='BPS-Statistics summary'!BD60 -> 0.04027
A40: ISIC 85 | B40: ='BPS-Statistics summary'!E61 -> 0.063 | C40: ='BPS-Statistics summary'!F61 -> 0.0261 | D40: ='BPS-Statistics summary'!G61 -> 0.0011 | E40: ='BPS-Statistics summary'!H61 -> 0.0055 | F40: ='BPS-Statistics summary'!I61 -> 0.0177 | G40: ='BPS-Statistics summary'!J61 -> 0.0376 | H40: ='BPS-Statistics summary'!K61 -> 0.0499 | I40: ='BPS-Statistics summary'!L61 -> 0.027675 | ... BA40: ='BPS-Statistics summary'!BD61 -> 0.03533
A41: ISIC 86T88 | B41: ='BPS-Statistics summary'!E62 -> 0.0866 | C41: ='BPS-Statistics summary'!F62 -> 0.1156 | D41: ='BPS-Statistics summary'!G62 -> 0.1045 | E41: ='BPS-Statistics summary'!H62 -> 0.0275 | F41: ='BPS-Statistics summary'!I62 -> 0.0467 | G41: ='BPS-Statistics summary'!J62 -> 0.0813 | H41: ='BPS-Statistics summary'!K62 -> 0.0559 | I41: ='BPS-Statistics summary'!L62 -> 0.05285 | ... BA41: ='BPS-Statistics summary'!BD62 -> 0.05884
A42: ISIC 90T96 | B42: ='BPS-Statistics summary'!E63 -> 0.1057 | C42: ='BPS-Statistics summary'!F63 -> -0.041 | D42: ='BPS-Statistics summary'!G63 -> 0.0212 | E42: ='BPS-Statistics summary'!H63 -> 0.0947 | F42: ='BPS-Statistics summary'!I63 -> 0.1052 | G42: ='BPS-Statistics summary'!J63 -> 0.098 | H42: ='BPS-Statistics summary'!K63 -> 0.0993 | I42: ='BPS-Statistics summary'!L63 -> 0.0993 | ... BA42: ='BPS-Statistics summary'!BD63 -> 0.09963
A43: ISIC 97T98 | B43: ='BPS-Statistics summary'!E63 -> 0.1057 | C43: ='BPS-Statistics summary'!F63 -> -0.041 | D43: ='BPS-Statistics summary'!G63 -> 0.0212 | E43: ='BPS-Statistics summary'!H63 -> 0.0947 | F43: ='BPS-Statistics summary'!I63 -> 0.1052 | G43: ='BPS-Statistics summary'!J63 -> 0.098 | H43: ='BPS-Statistics summary'!K63 -> 0.0993 | I43: ='BPS-Statistics summary'!L63 -> 0.0993 | ... BA43: ='BPS-Statistics summary'!BD63 -> 0.09963
